Workbook
Name __FDS_HYPERLINK_TOGGLE_STATE__: "ON"
Name _Order1: 0
Name _Order2: 0
Name a: -15987005.5299987
Name ADM: #REF!
Name ADM: #REF!
Name ADM: #REF!
Name ADM: #REF!
Name ADM: #REF!
Name ADM: #REF!
Name ADM: [0]!ADM
Name ALPHA: #REF!
Name ALPHA: #REF!
Name ALPHA: #REF!
Name ALPHA: #REF!
Name ALPHA: #REF!
Name ALPHA: #REF!
Name Amountin2: "Thousands"
Name AnoDoCalendário: #REF!
Name AnoDoCalendário: #REF!
Name AnoDoCalendário: #REF!
Name Ativo: #REF!
Name Ativo: #REF!
Name Ativo: #REF!
Name Ativo: #REF!
Name AV: #REF!
Name Balanço: #REF!
Name Balanço: #REF!
Name Balanço: #REF!
Name Balanço: #REF!
Name BaseYear: #REF!
Name BaseYear: #REF!
Name BaseYear: #REF!
Name BBQ: #REF!
Name BD_Fluxo_Entradas: #REF!
Name BD_Fluxo_Entradas: #REF!
Name BD_Fluxo_Entradas: #REF!
Name BD_Fluxo_Entradas: #REF!
Name BD_Fluxo_Entradas: #REF!
Name BD_Fluxo_Entradas: #REF!
Name BD_Fluxo_Entradas: #REF!
Name BD_Fluxo_Saidas: #REF!
Name BD_Fluxo_Saidas: #REF!
Name BD_Fluxo_Saidas: #REF!
Name BD_Fluxo_Saidas: #REF!
Name BD_Fluxo_Saidas: #REF!
Name BD_Fluxo_Saidas: #REF!
Name BD_Fluxo_Saidas: #REF!
Name BH: #REF!
Name BreakComercial: #REF!
Name BreakComercial: '04 -Base Orçado 2026'!BreakComercial
Name BreakComercial: #REF!
Name BreakComercial: #REF!
Name BreakComercial: 'Base Realizado'!BreakComercial
Name BreakComercial: #REF!
Name BreakComercial: '04 -Base Orçado 2026'!BreakComercial
Name BS: #REF!
Name BS_Deferred_Taxes: #REF!
Name BS_Deferred_Taxes: #REF!
Name BS_Deferred_Taxes: #REF!

Sheet  01-INDIC
B4: INDICADORES DE PERFORMANCE
D7: BD | E7: REAL | G7: BD | H7: REAL | J7: BD | K7: REAL | M7: MEDIA BD | N7: MEDIA REAL | P7: PROJETADO | R7: 2026 X META | T7: GAP 1°TRI | V7: BD | W7: REAL
B8: INDICADORES | D8: BD JAN.26 | E8: REAL JAN.26 | G8: BD FEV.26 | H8: REAL FEV.26 | J8: BD MAR.26 | K8: REAL MAR.26 | M8: JAN-MAR | N8: JAN/MAR | P8: META GLOB | R8: RL x BD_Jan'26 | S8: RL x BD_Fev'26 | T8: =N8 -> JAN/MAR | V8: BD ABR.26 | W8: REAL ABR.26
B9: CMV | D9: =-'03- BD x RE 2026'!BH28 -> 0.32 | E9: =-'03- BD x RE 2026'!BI28 -> 0.44878234 | G9: =-'03- BD x RE 2026'!BJ28 -> 0.32 | H9: =-'03- BD x RE 2026'!BK28 -> 0.3499834 | J9: =-'03- BD x RE 2026'!BL28 -> 0.31896681 | K9: =-'03- BD x RE 2026'!BM28 -> 0.27268283 | M9: =AVERAGE(D9,G9,J9) -> 0.3196556 | N9: =AVERAGE(E9,H9,K9) -> 0.35714953 | P9: =-'03- BD x RE 2026'!BI28 -> 0.44878234 | R9: =E9-D9 -> 0.12878234 | S9: =H9-G9 -> 0.029983403 | T9: =N9-M9 -> 0.037493923 | V9: =-'03- BD x RE 2026'!BN28 -> 0.32 | W9: =-'03- BD x RE 2026'!BO28 -> 0.3900331
B10: PESSOAL | D10: =-'03- BD x RE 2026'!BH44 -> 0.34444628 | E10: =-'03- BD x RE 2026'!BI44 -> 0.26788404 | G10: =-'03- BD x RE 2026'!BJ44 -> 0.27924096 | H10: =-'03- BD x RE 2026'!BK44 -> 0.33623619 | J10: =-'03- BD x RE 2026'!BL44 -> 0.2732448 | K10: =-'03- BD x RE 2026'!BM44 -> 0.25649129 | M10: =AVERAGE(D10,G10,J10) -> 0.29897735 | N10: =AVERAGE(E10,H10,K10) -> 0.2868705 | P10: =-'03- BD x RE 2026'!AT44 -> 0.28475304 | R10: =E10-D10 -> -0.076562237 | S10: =H10-G10 -> 0.056995226 | T10: =N10-M10 -> -0.012106842 | V10: =-'03- BD x RE 2026'!BN44 -> 0.27005862 | W10: =-'03- BD x RE 2026'!BO44 -> 0.25680654
B11: OCUPAÇÃO | D11: =-'03- BD x RE 2026'!BH49 -> 0.039714716 | E11: =-'03- BD x RE 2026'!BI49 -> 0.045645386 | G11: =-'03- BD x RE 2026'!BJ49 -> 0.029151886 | H11: =-'03- BD x RE 2026'!BK49 -> 0.046203079 | J11: =-'03- BD x RE 2026'!BL49 -> 0.028832965 | K11: =-'03- BD x RE 2026'!BM49 -> 0.029023396 | M11: =AVERAGE(D11,G11,J11) -> 0.032566522 | N11: =AVERAGE(E11,H11,K11) -> 0.04029062 | P11: =-'03- BD x RE 2026'!AT49 -> 0.029719036 | R11: =E11-D11 -> 0.0059306699 | S11: =H11-G11 -> 0.017051194 | T11: =N11-M11 -> 0.007724098 | V11: =-'03- BD x RE 2026'!BN49 -> 0.028193278 | W11: =-'03- BD x RE 2026'!BO49 -> 0.030127141
B12: UTILIDADES/ CONSUMO | D12: =-'03- BD x RE 2026'!BH50 -> 0.027 | E12: =-'03- BD x RE 2026'!BI50 -> 0.039432855 | G12: =-'03- BD x RE 2026'!BJ50 -> 0.023893805 | H12: =-'03- BD x RE 2026'!BK50 -> 0.037155091 | J12: =-'03- BD x RE 2026'!BL50 -> 0.023816659 | K12: =-'03- BD x RE 2026'!BM50 -> 0.022394108 | M12: =AVERAGE(D12,G12,J12) -> 0.024903488 | N12: =AVERAGE(E12,H12,K12) -> 0.032994018 | P12: =-'03- BD x RE 2026'!AT50 -> 0.024062252 | R12: =E12-D12 -> 0.012432855 | S12: =H12-G12 -> 0.013261286 | T12: =N12-M12 -> 0.00809053 | V12: =-'03- BD x RE 2026'!BN50 -> 0.023893805 | W12: =-'03- BD x RE 2026'!BO50 -> 0.026359761
B13: OPERAÇÃO | D13: =-'03- BD x RE 2026'!BH51 -> 0.11249162 | E13: =-'03- BD x RE 2026'!BI51 -> 0.1554671 | G13: =-'03- BD x RE 2026'!BJ51 -> 0.079372646 | H13: =-'03- BD x RE 2026'!BK51 -> 0.14694741 | J13: =-'03- BD x RE 2026'!BL51 -> 0.078603017 | K13: =-'03- BD x RE 2026'!BM51 -> 0.099958575 | M13: =AVERAGE(D13,G13,J13) -> 0.090155762 | N13: =AVERAGE(E13,H13,K13) -> 0.13412436 | P13: =-'03- BD x RE 2026'!AT51 -> 0.08181988 | R13: =E13-D13 -> 0.042975478 | S13: =H13-G13 -> 0.067574766 | T13: =N13-M13 -> 0.043968601 | V13: =-'03- BD x RE 2026'!BN51 -> 0.077183524 | W13: =-'03- BD x RE 2026'!BO51 -> 0.11012975
B14: MANUTENÇÃO E CONSERVAS | D14: =-'03- BD x RE 2026'!BH52 -> 0.01 | E14: =-'03- BD x RE 2026'!BI52 -> 0.03744011 | G14: =-'03- BD x RE 2026'!BJ52 -> 0.0088495575 | H14: =-'03- BD x RE 2026'!BK52 -> 0.017819199 | J14: =-'03- BD x RE 2026'!BL52 -> 0.0088209847 | K14: =-'03- BD x RE 2026'!BM52 -> 0.0077245912 | M14: =AVERAGE(D14,G14,J14) -> 0.0092235141 | N14: =AVERAGE(E14,H14,K14) -> 0.020994633 | P14: =-'03- BD x RE 2026'!AT52 -> 0.0089119453 | R14: =E14-D14 -> 0.02744011 | S14: =H14-G14 -> 0.0089696412 | T14: =N14-M14 -> 0.011771119 | V14: =-'03- BD x RE 2026'!BN52 -> 0.0088495575 | W14: =-'03- BD x RE 2026'!BO52 -> 0.0097107564
B15: ADMINISTRATIVA | D15: =-'03- BD x RE 2026'!BH57 -> 0.10775389 | E15: =-'03- BD x RE 2026'!BI57 -> 0.11996838 | G15: =-'03- BD x RE 2026'!BJ57 -> 0.076194079 | H15: =-'03- BD x RE 2026'!BK57 -> 0.095321122 | J15: =-'03- BD x RE 2026'!BL57 -> 0.075493153 | K15: =-'03- BD x RE 2026'!BM57 -> 0.072262988 | M15: =AVERAGE(D15,G15,J15) -> 0.086480376 | N15: =AVERAGE(E15,H15,K15) -> 0.095850829 | P15: =-'03- BD x RE 2026'!AT57 -> 0.078485779 | R15: =E15-D15 -> 0.012214485 | S15: =H15-G15 -> 0.019127042 | T15: =N15-M15 -> 0.0093704539 | V15: =-'03- BD x RE 2026'!BN57 -> 0.074254164 | W15: =-'03- BD x RE 2026'!BO57 -> 0.047794225
B16: MARKETING | D16: =-'03- BD x RE 2026'!BH58 -> 0.02 | E16: =-'03- BD x RE 2026'!BI58 -> 0.055042652 | G16: =-'03- BD x RE 2026'!BJ58 -> 0.02 | H16: =-'03- BD x RE 2026'!BK58 -> 0.028502258 | J16: =-'03- BD x RE 2026'!BL58 -> 0.019935426 | K16: =-'03- BD x RE 2026'!BM58 -> 0.014590393 | M16: =AVERAGE(D16,G16,J16) -> 0.019978475 | N16: =AVERAGE(E16,H16,K16) -> 0.032711768 | P16: =-'03- BD x RE 2026'!AT58 -> 0.019994347 | R16: =E16-D16 -> 0.035042652 | S16: =H16-G16 -> 0.0085022582 | T16: =N16-M16 -> 0.012733293 | V16: =-'03- BD x RE 2026'!BN58 -> 0.02 | W16: =-'03- BD x RE 2026'!BO58 -> 0.028668855
B17: TX CARTÕES | D17: =-'03- BD x RE 2026'!BH59 -> 0.021034109 | E17: =-'03- BD x RE 2026'!BI59 -> 0.013082143 | G17: =-'03- BD x RE 2026'!BJ59 -> 0.02 | H17: =-'03- BD x RE 2026'!BK59 -> 0.012408581 | J17: =-'03- BD x RE 2026'!BL59 -> 0.018554156 | K17: =-'03- BD x RE 2026'!BM59 -> 0.010950112 | M17: =AVERAGE(D17,G17,J17) -> 0.019862755 | N17: =AVERAGE(E17,H17,K17) -> 0.012146945 | P17: =-'03- BD x RE 2026'!AT59 -> 0.031082644 | R17: =E17-D17 -> -0.0079519667 | S17: =H17-G17 -> -0.0075914194 | T17: =N17-M17 -> -0.0077158101 | V17: =-'03- BD x RE 2026'!BN59 -> 0.018614256 | W17: =-'03- BD x RE 2026'!BO59 -> 0.011283126
B19: EBITDA | D19: ='02-Res M'!D30 -> -0.0024406215 | E19: ='02-Res M'!F30 -> -0.18274501 | G19: ='02-Res M'!H30 -> 0.14329707 | H19: ='02-Res M'!J30 -> -0.070576332 | J19: ='02-Res M'!J30 -> -0.070576332 | K19: ='02-Res M'!L30 -> 0.15373203 | M19: =AVERAGE(D19,G19,J19) -> 0.023426704 | N19: =E19 -> -0.18274501 | P19: ='03- BD x RE 2026'!AT62 -> 0.12126151 | R19: =P19-E19 -> 0.30400652 | S19: =P19-H19 -> 0.19183785 | T19: =P19-N19 -> 0.30400652 | V19: ='02-Res M'!V30 -> 0 | W19: ='02-Res M'!X30 -> 0
B20: RESULTADO LÍQUIDO | D20: ='02-Res M'!D41 -> -0.010020481 | E20: ='02-Res M'!F41 -> -0.18446701 | G20: ='02-Res M'!H41 -> 0.13571721 | H20: ='02-Res M'!J41 -> -0.071091259 | J20: ='02-Res M'!J41 -> -0.071091259 | K20: ='02-Res M'!L41 -> 0.14617664 | M20: =AVERAGE(D20,G20,J20) -> 0.018201822 | N20: =AVERAGE(E20,H20,K20) -> -0.036460542 | P20: ='03- BD x RE 2026'!AT72 -> 0.1136838 | R20: =P20-E20 -> 0.29815081 | S20: =P20-H20 -> 0.18477506 | T20: =N20-M20 -> -0.054662364 | V20: ='03- BD x RE 2026'!M73 -> 0.15137294 | W20: ='03- BD x RE 2026'!N73 -> 0.089086739
B22: COMPARATIVOS | D22: BUDGET | E22: REAL | G22: BUDGET | H22: REAL | J22: BUDGET | K22: REAL | M22: Total. BD Tri | N22: Total Real Tri | T22: 1º TRI | V22: BUDGET | W22: REAL
B24: ='[1]02-Res M'!B15 -> Receita Líquida | D24: ='03- BD x RE 2026'!D24 -> 1603133.7 | E24: ='03- BD x RE 2026'!E24 -> 1338861.7 | G24: ='03- BD x RE 2026'!G24 -> 2460755.4 | H24: ='03- BD x RE 2026'!H24 -> 1507127.3 | J24: ='03- BD x RE 2026'!J24 -> 2487973.7 | K24: ='03- BD x RE 2026'!K24 -> 2383612.2 | M24: =SUM(A24,G24,J24) -> 4948729.1 | N24: =SUM(B24,H24,K24) -> 3890739.5 | T24: =M24-L24 -> 4948729.1 | V24: ='03- BD x RE 2026'!M24 -> 2544424.3 | W24: ='03- BD x RE 2026'!N24 -> 2296285.6
B26: Resultado Líquido BD x REAL | D26: ='03- BD x RE 2026'!D72 -> -16064.17 | E26: ='03- BD x RE 2026'!E72 -> -246975.82 | G26: ='03- BD x RE 2026'!G72 -> 333966.85 | H26: ='03- BD x RE 2026'!H72 -> -108396.03 | J26: ='03- BD x RE 2026'!J72 -> 363683.65 | K26: ='03- BD x RE 2026'!K72 -> 508314.52 | M26: =SUM(A26,G26,J26) -> 697650.5 | N26: =SUM(B26,H26,K26) -> 399918.48 | T26: =M26-L26 -> 697650.5 | V26: ='03- BD x RE 2026'!M72 -> 385156.98 | W26: ='03- BD x RE 2026'!N72 -> 204568.6

Sheet 02-Res M
B4: COMPARATIVO REAL VS ORÇAMENTO 2026 | U4: INDICES
U5: PARTICIPAÇÃO | Y5: PARTICIPAÇÃO
D6: BD JAN'26 | F6: REAL JAN'26 | H6: BD FEV'26 | J6: REAL FEV'26 | L6: BD MAR26 | N6: BD MAR26 | P6: V' RE X BD JAN/26 | R6: V' RE X BD JAN/26 | T6: V' RE X BD MAR/26 | U6: BD X MAR'26 | AG6: =U5 -> PARTICIPAÇÃO
B8: Clientes | D8: ='03- BD x RE 2026'!D7/1000 -> 5.7864418 | F8: ='03- BD x RE 2026'!E7/1000 -> 4.761 | H8: ='03- BD x RE 2026'!G7/1000 -> 7.8601684 | J8: ='03- BD x RE 2026'!H7/1000 -> 4.661 | L8: ='03- BD x RE 2026'!J7/1000 -> 7.9214504 | N8: ='03- BD x RE 2026'!K7/1000 -> 6.592 | P8: =IF(ISERROR($F8/D8-1),"-",($F8/D8-1)) -> -0.17721457 | R8: =IF(ISERROR($J8/J8-1),"-",($H8/J8-1)) -> 0.68636953 | T8: =IF(ISERROR($L8/N8-1),"-",($L8/N8-1)) -> 0.20167633
B9: Ticket Médio FB | D9: =IF(ISERROR(D11/D8),0,(D11/D8)) -> 300 | F9: =IF(ISERROR(F11/F8),0,(F11/F8)) -> 292.02877 | H9: =IF(ISERROR(H11/H8),0,(H11/H8)) -> 339 | J9: =IF(ISERROR(J11/J8),0,(J11/J8)) -> 327.94552 | L9: =IF(ISERROR(L11/L8),0,(L11/L8)) -> 340.01408 | N9: =IF(ISERROR(N11/N8),0,(N11/N8)) -> 370.68215 | P9: =IF(ISERROR($F9/D9-1),"-",($F9/D9-1)) -> -0.026570769 | R9: =IF(ISERROR($H9/J9-1),"-",($H9/J9-1)) -> 0.033708288 | T9: =IF(ISERROR($L9/N9-1),"-",($L9/N9-1)) -> -0.082734151
R10: =IF(ISERROR($H10/J10-1),"-",($H10/J10-1)) -> - | T10: =IF(ISERROR($H10/K10-1),"-",($H10/K10-1)) -> -
B11: Faturamento Bruto | D11: ='03- BD x RE 2026'!D10/1000 -> 1735.9325 | F11: ='03- BD x RE 2026'!E10/1000 -> 1390.349 | H11: ='03- BD x RE 2026'!G10/1000 -> 2664.5971 | J11: ='03- BD x RE 2026'!H10/1000 -> 1528.5541 | L11: ='03- BD x RE 2026'!J10/1000 -> 2693.4047 | N11: ='03- BD x RE 2026'!K10/1000 -> 2443.5368 | P11: =IF(ISERROR($F11/D11-1),"-",($F11/D11-1)) -> -0.19907661 | R11: =IF(ISERROR($H11/J11-1),"-",($H11/J11-1)) -> 0.74321416 | T11: =IF(ISERROR($L11/N11-1),"-",($L11/N11-1)) -> 0.10225666 | U11: JAN'26 | Y11: FEV'26 | AC11: Mar'26
R12: =IF(ISERROR($H12/J12-1),"-",($H12/J12-1)) -> -
B13: Impostos (ICMS/PIS/COFINS) | D13: ='03- BD x RE 2026'!D19/1000 -> -132.79884 | F13: ='03- BD x RE 2026'!E19/1000 -> -51.48725 | H13: ='03- BD x RE 2026'!G19/1000 -> -203.84168 | J13: ='03- BD x RE 2026'!H19/1000 -> -21.42681 | L13: ='03- BD x RE 2026'!J19/1000 -> -205.43093 | N13: ='03- BD x RE 2026'!K19/1000 -> -59.92454 | P13: =IF(ISERROR($F13/D13-1),"-",($F13/D13-1)) -> -0.61229142 | R13: =IF(ISERROR($H13/J13-1),"-",($H13/J13-1)) -> 8.5133936 | T13: =IF(ISERROR($L13/N13-1),"-",($L13/N13-1)) -> 2.4281604
R14: =IF(ISERROR($H14/J14-1),"-",($H14/J14-1)) -> -
B15: Receita Líquida | D15: =D11+D13 -> 1603.1337 | F15: =F11+F13 -> 1338.8617 | H15: =H11+H13 -> 2460.7554 | J15: =J11+J13 -> 1507.1273 | L15: =L11+L13 -> 2487.9737 | N15: =N11+N13 -> 2383.6122 | P15: =IF(ISERROR($F15/D15-1),"-",($F15/D15-1)) -> -0.16484713 | R15: =IF(ISERROR($H15/J15-1),"-",($H15/J15-1)) -> 0.63274562 | T15: =IF(ISERROR($L15/N15-1),"-",($L15/N15-1)) -> 0.043782923 | U15: PART% BD | W15: PART% REAL | Y15: PART% BD | AA15: PART% REAL | AC15: PART% BD | AE15: PART% REAL
R16: =IF(ISERROR($H16/J16-1),"-",($H16/J16-1)) -> -
B17: ='[2]2 DRE '!A27 -> CUSTOS/DESPESAS | D17: =SUM(D18:D23) -> -1368.5193 | F17: =SUM(F18:F23) -> -1331.7013 | H17: =SUM(H18:H23) -> -1822.2112 | J17: =SUM(J18:J23) -> -1408.1759 | L17: =SUM(L18:L23) -> -1821.9064 | N17: =SUM(N18:N23) -> -1640.5802 | P17: =IF(ISERROR($F17/D17-1),"-",($F17/D17-1)) -> -0.02690354 | R17: =IF(ISERROR($H17/J17-1),"-",($H17/J17-1)) -> 0.29402244 | T17: =IF(ISERROR($L17/N17-1),"-",($L17/N17-1)) -> 0.11052568 | U17: =IF(ISERROR($D17/$D$15),"-",($D17/$D$15)) -> -0.85365262 | W17: =IF(ISERROR(F17/F$15),"-",(F17/F$15)) -> -0.99465184 | Y17: =IF(ISERROR($H17/$H$15),"-",($H17/$H$15)) -> -0.74050886 | AA17: =IF(ISERROR(J17/J$15),"-",(J17/J$15)) -> -0.93434437 | AC17: =IF(ISERROR($L17/$L$15),"-",($L17/$L$15)) -> -0.73228524 | AE17: =IF(ISERROR(N17/N$15),"-",(N17/N$15)) -> -0.68827479 | AG17: Impacto
B18: CMV | D18: ='03- BD x RE 2026'!D28/1000 -> -513.00279 | F18: ='03- BD x RE 2026'!E28/1000 -> -600.8575 | H18: ='03- BD x RE 2026'!G28/1000 -> -787.44173 | J18: ='03- BD x RE 2026'!H28/1000 -> -527.46952 | L18: ='03- BD x RE 2026'!J28/1000 -> -793.58104 | N18: ='03- BD x RE 2026'!K28/1000 -> -649.97013 | P18: =IF(ISERROR($F18/D18-1),"-",($F18/D18-1)) -> 0.17125582 | R18: =IF(ISERROR($H18/J18-1),"-",($H18/J18-1)) -> 0.49286679 | T18: =IF(ISERROR($L18/N18-1),"-",($L18/N18-1)) -> 0.22095002 | U18: =IF(ISERROR($D18/$D$15),"-",($D18/$D$15)) -> -0.32 | W18: =IF(ISERROR(F18/F$15),"-",(F18/F$15)) -> -0.44878234 | Y18: =IF(ISERROR($H18/$H$15),"-",($H18/$H$15)) -> -0.32 | AA18: =IF(ISERROR(J18/J$15),"-",(J18/J$15)) -> -0.3499834 | AC18: =IF(ISERROR($L18/$L$15),"-",($L18/$L$15)) -> -0.31896681 | AE18: =IF(ISERROR(N18/N$15),"-",(N18/N$15)) -> -0.27268283 | AG18: =-W18*AE18 -> -0.12237524
B19: Pessoal | D19: ='03- BD x RE 2026'!D44/1000 -> -552.19344 | F19: ='03- BD x RE 2026'!E44/1000 -> -358.65969 | H19: ='03- BD x RE 2026'!G44/1000 -> -687.1437 | J19: ='03- BD x RE 2026'!H44/1000 -> -506.75072 | L19: ='03- BD x RE 2026'!J44/1000 -> -679.82589 | N19: ='03- BD x RE 2026'!K44/1000 -> -611.37576 | P19: =IF(ISERROR($F19/D19-1),"-",($F19/D19-1)) -> -0.3504818 | R19: =IF(ISERROR($H19/J19-1),"-",($H19/J19-1)) -> 0.35597973 | T19: =IF(ISERROR($L19/N19-1),"-",($L19/N19-1)) -> 0.11196081 | U19: =IF(ISERROR($D19/$D$15),"-",($D19/$D$15)) -> -0.34444628 | W19: =IF(ISERROR(F19/F$15),"-",(F19/F$15)) -> -0.26788404 | Y19: =IF(ISERROR($H19/$H$15),"-",($H19/$H$15)) -> -0.27924096 | AA19: =IF(ISERROR(J19/J$15),"-",(J19/J$15)) -> -0.33623619 | AC19: =IF(ISERROR($L19/$L$15),"-",($L19/$L$15)) -> -0.2732448 | AE19: =IF(ISERROR(N19/N$15),"-",(N19/N$15)) -> -0.25649129 | AG19: =-W19*AE19 -> -0.068709922
B20: Ocupação | D20: ='03- BD x RE 2026'!D49/1000 -> -63.668 | F20: ='03- BD x RE 2026'!E49/1000 -> -61.11286 | H20: ='03- BD x RE 2026'!G49/1000 -> -71.73566 | J20: ='03- BD x RE 2026'!H49/1000 -> -69.63392 | L20: ='03- BD x RE 2026'!J49/1000 -> -71.73566 | N20: ='03- BD x RE 2026'!K49/1000 -> -69.18052 | P20: =IF(ISERROR($F20/D20-1),"-",($F20/D20-1)) -> -0.040132249 | R20: =IF(ISERROR($H20/J20-1),"-",($H20/J20-1)) -> 0.030182704 | T20: =IF(ISERROR($L20/N20-1),"-",($L20/N20-1)) -> 0.036934386 | U20: =IF(ISERROR($D20/$D$15),"-",($D20/$D$15)) -> -0.039714716 | W20: =IF(ISERROR(F20/F$15),"-",(F20/F$15)) -> -0.045645386 | Y20: =IF(ISERROR($H20/$H$15),"-",($H20/$H$15)) -> -0.029151886 | AA20: =IF(ISERROR(J20/J$15),"-",(J20/J$15)) -> -0.046203079 | AC20: =IF(ISERROR($L20/$L$15),"-",($L20/$L$15)) -> -0.028832965 | AE20: =IF(ISERROR(N20/N$15),"-",(N20/N$15)) -> -0.029023396 | AG20: =-W20*AE20 -> -0.0013247841
B21: Utilidades/ Consumo | D21: ='03- BD x RE 2026'!D50/1000 -> -43.28461 | F21: ='03- BD x RE 2026'!E50/1000 -> -52.79514 | H21: ='03- BD x RE 2026'!G50/1000 -> -58.796811 | J21: ='03- BD x RE 2026'!H50/1000 -> -55.99745 | L21: ='03- BD x RE 2026'!J50/1000 -> -59.255221 | N21: ='03- BD x RE 2026'!K50/1000 -> -53.37887 | P21: =IF(ISERROR($F21/D21-1),"-",($F21/D21-1)) -> 0.21972082 | R21: =IF(ISERROR($H21/J21-1),"-",($H21/J21-1)) -> 0.04999086 | T21: =IF(ISERROR($L21/N21-1),"-",($L21/N21-1)) -> 0.11008759 | U21: =IF(ISERROR($D21/$D$15),"-",($D21/$D$15)) -> -0.027 | W21: =IF(ISERROR(F21/F$15),"-",(F21/F$15)) -> -0.039432855 | Y21: =IF(ISERROR($H21/$H$15),"-",($H21/$H$15)) -> -0.023893805 | AA21: =IF(ISERROR(J21/J$15),"-",(J21/J$15)) -> -0.037155091 | AC21: =IF(ISERROR($L21/$L$15),"-",($L21/$L$15)) -> -0.023816659 | AE21: =IF(ISERROR(N21/N$15),"-",(N21/N$15)) -> -0.022394108 | AG21: =-W21*AE21 -> -0.00088306362
B22: Operação | D22: ='03- BD x RE 2026'!D51/1000 -> -180.33911 | F22: ='03- BD x RE 2026'!E51/1000 -> -208.14895 | H22: ='03- BD x RE 2026'!G51/1000 -> -195.31667 | J22: ='03- BD x RE 2026'!H51/1000 -> -221.46845 | L22: ='03- BD x RE 2026'!J51/1000 -> -195.56224 | N22: ='03- BD x RE 2026'!K51/1000 -> -238.26248 | P22: =IF(ISERROR($F22/D22-1),"-",($F22/D22-1)) -> 0.15420858 | R22: =IF(ISERROR($H22/J22-1),"-",($H22/J22-1)) -> -0.11808355 | T22: =IF(ISERROR($L22/N22-1),"-",($L22/N22-1)) -> -0.17921512 | U22: =IF(ISERROR($D22/$D$15),"-",($D22/$D$15)) -> -0.11249162 | W22: =IF(ISERROR(F22/F$15),"-",(F22/F$15)) -> -0.1554671 | Y22: =IF(ISERROR($H22/$H$15),"-",($H22/$H$15)) -> -0.079372646 | AA22: =IF(ISERROR(J22/J$15),"-",(J22/J$15)) -> -0.14694741 | AC22: =IF(ISERROR($L22/$L$15),"-",($L22/$L$15)) -> -0.078603017 | AE22: =IF(ISERROR(N22/N$15),"-",(N22/N$15)) -> -0.099958575 | AG22: =-W22*AE22 -> -0.01554027
B23: Manutenção e Conservação | D23: ='03- BD x RE 2026'!D52/1000 -> -16.031337 | F23: ='03- BD x RE 2026'!E52/1000 -> -50.12713 | H23: ='03- BD x RE 2026'!G52/1000 -> -21.776597 | J23: ='03- BD x RE 2026'!H52/1000 -> -26.8558 | L23: ='03- BD x RE 2026'!J52/1000 -> -21.946378 | N23: ='03- BD x RE 2026'!K52/1000 -> -18.41243 | P23: =IF(ISERROR($F23/D23-1),"-",($F23/D23-1)) -> 2.1268215 | R23: =IF(ISERROR($H23/J23-1),"-",($H23/J23-1)) -> -0.18912873 | T23: =IF(ISERROR($L23/N23-1),"-",($L23/N23-1)) -> 0.19193274 | U23: =IF(ISERROR($D23/$D$15),"-",($D23/$D$15)) -> -0.01 | W23: =IF(ISERROR(F23/F$15),"-",(F23/F$15)) -> -0.03744011 | Y23: =IF(ISERROR($H23/$H$15),"-",($H23/$H$15)) -> -0.0088495575 | AA23: =IF(ISERROR(J23/J$15),"-",(J23/J$15)) -> -0.017819199 | AC23: =IF(ISERROR($L23/$L$15),"-",($L23/$L$15)) -> -0.0088209847 | AE23: =IF(ISERROR(N23/N$15),"-",(N23/N$15)) -> -0.0077245912 | AG23: =-W23*AE23 -> -0.00028920955
B24: ='[2]2 DRE '!A52 -> DESPESAS ADMINISTRATIVAS | D24: =SUM(D25:D27) -> -238.52706 | F24: =SUM(F25:F27) -> -251.83075 | H24: =SUM(H25:H27) -> -285.92521 | J24: =SUM(J25:J27) -> -205.3189 | L24: =SUM(L25:L27) -> -283.58605 | N24: =SUM(N25:N27) -> -233.1256 | P24: =IF(ISERROR($F24/D24-1),"-",($F24/D24-1)) -> 0.055774327 | R24: =IF(ISERROR($H24/J24-1),"-",($H24/J24-1)) -> 0.39259079 | T24: =IF(ISERROR($L24/N24-1),"-",($L24/N24-1)) -> 0.21645176 | U24: =IF(ISERROR($D24/$D$15),"-",($D24/$D$15)) -> -0.148788 | W24: =IF(ISERROR(F24/F$15),"-",(F24/F$15)) -> -0.18809317 | Y24: =IF(ISERROR($H24/$H$15),"-",($H24/$H$15)) -> -0.11619408 | AA24: =IF(ISERROR(J24/J$15),"-",(J24/J$15)) -> -0.13623196 | AC24: =IF(ISERROR($L24/$L$15),"-",($L24/$L$15)) -> -0.11398273 | AE24: =IF(ISERROR(N24/N$15),"-",(N24/N$15)) -> -0.097803493 | AG24: =AE24-W24 -> 0.090289681
B25: Administrativa | D25: ='03- BD x RE 2026'!D57/1000 -> -172.7439 | F25: ='03- BD x RE 2026'!E57/1000 -> -160.62107 | H25: ='03- BD x RE 2026'!G57/1000 -> -187.49499 | J25: ='03- BD x RE 2026'!H57/1000 -> -143.66106 | L25: ='03- BD x RE 2026'!J57/1000 -> -187.82498 | N25: ='03- BD x RE 2026'!K57/1000 -> -172.24694 | P25: =IF(ISERROR($F25/D25-1),"-",($F25/D25-1)) -> -0.070178048 | R25: =IF(ISERROR($H25/J25-1),"-",($H25/J25-1)) -> 0.30512049 | T25: =IF(ISERROR($L25/N25-1),"-",($L25/N25-1)) -> 0.090440159 | U25: =IF(ISERROR($D25/$D$15),"-",($D25/$D$15)) -> -0.10775389 | W25: =IF(ISERROR(F25/F$15),"-",(F25/F$15)) -> -0.11996838 | Y25: =IF(ISERROR($H25/$H$15),"-",($H25/$H$15)) -> -0.076194079 | AA25: =IF(ISERROR(J25/J$15),"-",(J25/J$15)) -> -0.095321122 | AC25: =IF(ISERROR($L25/$L$15),"-",($L25/$L$15)) -> -0.075493153 | AE25: =IF(ISERROR(N25/N$15),"-",(N25/N$15)) -> -0.072262988 | AG25: =-W25*AE25 -> -0.0086692735
B26: Marketing | D26: ='03- BD x RE 2026'!D58/1000 -> -32.062674 | F26: ='03- BD x RE 2026'!E58/1000 -> -73.6945 | H26: ='03- BD x RE 2026'!G58/1000 -> -49.215108 | J26: ='03- BD x RE 2026'!H58/1000 -> -42.95653 | L26: ='03- BD x RE 2026'!J58/1000 -> -49.598815 | N26: ='03- BD x RE 2026'!K58/1000 -> -34.77784 | P26: =IF(ISERROR($D26/F26-1),"-",($D26/F26-1)) -> -0.56492446 | R26: =IF(ISERROR($H26/J26-1),"-",($H26/J26-1)) -> 0.14569562 | T26: =IF(ISERROR($L26/N26-1),"-",($L26/N26-1)) -> 0.42616145 | U26: =IF(ISERROR($D26/$D$15),"-",($D26/$D$15)) -> -0.02 | W26: =IF(ISERROR(F26/F$15),"-",(F26/F$15)) -> -0.055042652 | Y26: =IF(ISERROR($H26/$H$15),"-",($H26/$H$15)) -> -0.02 | AA26: =IF(ISERROR(J26/J$15),"-",(J26/J$15)) -> -0.028502258 | AC26: =IF(ISERROR($L26/$L$15),"-",($L26/$L$15)) -> -0.019935426 | AE26: =IF(ISERROR(N26/N$15),"-",(N26/N$15)) -> -0.014590393 | AG26: =-W26*AE26 -> -0.00080309395
B27: Taxa Cartão Crédito | D27: ='03- BD x RE 2026'!D59/1000 -> -33.72049 | F27: ='03- BD x RE 2026'!E59/1000 -> -17.51518 | H27: ='03- BD x RE 2026'!G59/1000 -> -49.215108 | J27: ='03- BD x RE 2026'!H59/1000 -> -18.70131 | L27: ='03- BD x RE 2026'!J59/1000 -> -46.162252 | N27: ='03- BD x RE 2026'!K59/1000 -> -26.10082 | P27: =IF(ISERROR($F27/D27-1),"-",($F27/D27-1)) -> -0.48057753 | R27: =IF(ISERROR($H27/J27-1),"-",($H27/J27-1)) -> 1.6316396 | T27: =IF(ISERROR($L27/N27-1),"-",($L27/N27-1)) -> 0.76861309 | U27: =IF(ISERROR($D27/$D$15),"-",($D27/$D$15)) -> -0.021034109 | W27: =IF(ISERROR(F27/F$15),"-",(F27/F$15)) -> -0.013082143 | Y27: =IF(ISERROR($H27/$H$15),"-",($H27/$H$15)) -> -0.02 | AA27: =IF(ISERROR(J27/J$15),"-",(J27/J$15)) -> -0.012408581 | AC27: =IF(ISERROR($L27/$L$15),"-",($L27/$L$15)) -> -0.018554156 | AE27: =IF(ISERROR(N27/N$15),"-",(N27/N$15)) -> -0.010950112 | AG27: =-W27*AE27 -> -0.00014325092
R28: =IF(ISERROR($H28/J28-1),"-",($H28/J28-1)) -> - | T28: =IF(ISERROR($L28/N28-1),"-",($L28/N28-1)) -> - | U28: =IF(ISERROR($D28/$D$15),"-",($D28/$D$15)) -> 0 | Y28: =IF(ISERROR($H28/$H$15),"-",($H28/$H$15)) -> 0 | AC28: =IF(ISERROR($L28/$L$15),"-",($L28/$L$15)) -> 0 | AE28: =IF(ISERROR(N28/N$15),"-",(N28/N$15)) -> 0 | AG28: =-W28*AE28 -> 0
B29: LAJIDA | D29: =D15+D17+D24 -> -3.9126425 | F29: =F15+F17+F24 -> -244.6703 | H29: =H15+H17+H24 -> 352.61903 | J29: =J15+J17+J24 -> -106.36751 | L29: =L15+L17+L24 -> 382.48125 | N29: =N15+N17+N24 -> 509.90643 | P29: =IF(ISERROR($F29/D29-1),"-",($F29/D29-1)) -> 61.533262 | R29: =IF(ISERROR($H29/J29-1),"-",($H29/J29-1)) -> -4.3151008 | T29: =IF(ISERROR($L29/N29-1),"-",($L29/N29-1)) -> -0.24989914 | U29: =IF(ISERROR($D29/$D$15),"-",($D29/$D$15)) -> -0.0024406215 | W29: =IF(ISERROR(F29/F$15),"-",(F29/F$15)) -> -0.18274501 | Y29: =IF(ISERROR($H29/$H$15),"-",($H29/$H$15)) -> 0.14329707 | AA29: =IF(ISERROR(J29/J$15),"-",(J29/J$15)) -> -0.070576332 | AC29: =IF(ISERROR($L29/$L$15),"-",($L29/$L$15)) -> 0.15373203 | AE29: =IF(ISERROR(N29/N$15),"-",(N29/N$15)) -> 0.21392172 | AG29: =AE29-W29 -> 0.39666673
B30: MARGEM EBITDA | D30: =IF(ISERROR(D29/D15),0,(D29/D15)) -> -0.0024406215 | F30: =IF(ISERROR(F29/F15),0,(F29/F15)) -> -0.18274501 | H30: =IF(ISERROR(H29/H15),0,(H29/H15)) -> 0.14329707 | J30: =IF(ISERROR(J29/J15),0,(J29/J15)) -> -0.070576332 | L30: =IF(ISERROR(L29/L15),0,(L29/L15)) -> 0.15373203 | N30: =IF(ISERROR(N29/N15),0,(N29/N15)) -> 0.21392172 | P30: =IF(ISERROR($D30/F30-1),"-",($D30/F30-1)) -> -0.98664466 | R30: =IF(ISERROR($H30/J30-1),"-",($H30/J30-1)) -> -3.0303841 | T30: =IF(ISERROR($L30/N30-1),"-",($L30/N30-1)) -> -0.28136316 | U30: =IF(ISERROR($D30/$D$15),"-",($D30/$D$15)) -> -1.5224067e-06 | Y30: =IF(ISERROR($H30/$H$15),"-",($H30/$H$15)) -> 5.8232957e-05 | AC30: =IF(ISERROR($L30/$L$15),"-",($L30/$L$15)) -> 6.1790054e-05 | AE30: =IF(ISERROR(N30/N$15),"-",(N30/N$15)) -> 8.9746864e-05 | AG30: =-W30*AE30 -> 0
R31: =IF(ISERROR($H31/J31-1),"-",($H31/J31-1)) -> - | T31: =IF(ISERROR($H31/K31-1),"-",($H31/K31-1)) -> - | U31: =IF(ISERROR($D31/$D$15),"-",($D31/$D$15)) -> 0 | Y31: =IF(ISERROR($H31/$H$15),"-",($H31/$H$15)) -> 0 | AC31: =IF(ISERROR($L31/$L$15),"-",($L31/$L$15)) -> 0 | AE31: =IF(ISERROR(N31/N$15),"-",(N31/N$15)) -> 0 | AG31: =-W31*AE31 -> 0
B32: Depreciação & Amortização | P32: =IF(ISERROR($F32/D32-1),"-",($F32/D32-1)) -> - | R32: =IF(ISERROR($H32/J32-1),"-",($H32/J32-1)) -> - | T32: =IF(ISERROR($H32/K32-1),"-",($H32/K32-1)) -> - | U32: =IF(ISERROR($D32/$D$15),"-",($D32/$D$15)) -> 0 | W32: =IF(ISERROR(F32/F$15),"-",(F32/F$15)) -> 0 | Y32: =IF(ISERROR($H32/$H$15),"-",($H32/$H$15)) -> 0 | AA32: =IF(ISERROR(J32/J$15),"-",(J32/J$15)) -> 0 | AC32: =IF(ISERROR($L32/$L$15),"-",($L32/$L$15)) -> 0 | AE32: =IF(ISERROR(N32/N$15),"-",(N32/N$15)) -> 0 | AG32: =-W32*AE32 -> 0
R33: =IF(ISERROR($H33/J33-1),"-",($H33/J33-1)) -> - | T33: =IF(ISERROR($H33/K33-1),"-",($H33/K33-1)) -> - | U33: =IF(ISERROR($D33/$D$15),"-",($D33/$D$15)) -> 0 | Y33: =IF(ISERROR($H33/$H$15),"-",($H33/$H$15)) -> 0 | AC33: =IF(ISERROR($L33/$L$15),"-",($L33/$L$15)) -> 0 | AE33: =IF(ISERROR(N33/N$15),"-",(N33/N$15)) -> 0 | AG33: =-W33*AE33 -> 0
B34: LAIR | D34: =D29+D32 -> -3.9126425 | F34: =F29+F32 -> -244.6703 | H34: =H29+H32 -> 352.61903 | J34: =J29+J32 -> -106.36751 | L34: =L29+L32 -> 382.48125 | N34: =N29+N32 -> 509.90643 | P34: =IF(ISERROR($F34/D34-1),"-",($F34/D34-1)) -> 61.533262 | R34: =IF(ISERROR($H34/J34-1),"-",($H34/J34-1)) -> -4.3151008 | T34: =IF(ISERROR($L34/N34-1),"-",($L34/N34-1)) -> -0.24989914 | U34: =IF(ISERROR($D34/$D$15),"-",($D34/$D$15)) -> -0.0024406215 | W34: =IF(ISERROR(F34/F$15),"-",(F34/F$15)) -> -0.18274501 | Y34: =IF(ISERROR($H34/$H$15),"-",($H34/$H$15)) -> 0.14329707 | AA34: =IF(ISERROR(J34/J$15),"-",(J34/J$15)) -> -0.070576332 | AC34: =IF(ISERROR($L34/$L$15),"-",($L34/$L$15)) -> 0.15373203 | AE34: =IF(ISERROR(N34/N$15),"-",(N34/N$15)) -> 0.21392172 | AG34: =AE34-W34 -> 0.39666673
B35: MARGEM EBIT | D35: =IF(ISERROR(D34/D15),0,(D34/D15)) -> -0.0024406215 | F35: =IF(ISERROR(F34/F15),0,(F34/F15)) -> -0.18274501 | H35: =IF(ISERROR(H34/H15),0,(H34/H15)) -> 0.14329707 | J35: =IF(ISERROR(J34/J15),0,(J34/J15)) -> -0.070576332 | L35: =IF(ISERROR(L34/L15),0,(L34/L15)) -> 0.15373203 | N35: =IF(ISERROR(N34/N15),0,(N34/N15)) -> 0.21392172 | P35: =IF(ISERROR($D35/F35-1),"-",($D35/F35-1)) -> -0.98664466 | R35: =IF(ISERROR($H35/J35-1),"-",($H35/J35-1)) -> -3.0303841 | T35: =IF(ISERROR($L35/N35-1),"-",($L35/N35-1)) -> -0.28136316 | U35: =IF(ISERROR($D35/$D$15),"-",($D35/$D$15)) -> -1.5224067e-06 | Y35: =IF(ISERROR($H35/$H$15),"-",($H35/$H$15)) -> 5.8232957e-05 | AC35: =IF(ISERROR($L35/$L$15),"-",($L35/$L$15)) -> 6.1790054e-05 | AE35: =IF(ISERROR(N35/N$15),"-",(N35/N$15)) -> 8.9746864e-05 | AG35: =-W35*AE35 -> 0
B36: Despesas Financeiras | D36: ='03- BD x RE 2026'!D69/1000 -> -12.151528 | F36: ='03- BD x RE 2026'!E69/1000 -> -2.30552 | H36: ='03- BD x RE 2026'!G69/1000 -> -18.65218 | J36: ='03- BD x RE 2026'!H69/1000 -> -0.77606 | L36: ='03- BD x RE 2026'!J69/1000 -> -18.797602 | N36: ='03- BD x RE 2026'!K69/1000 -> -0.451 | P36: =IF(ISERROR($F36/D36-1),"-",($F36/D36-1)) -> -0.81026913 | R36: =IF(ISERROR($H36/J36-1),"-",($H36/J36-1)) -> 23.034456 | T36: =IF(ISERROR($L36/N36-1),"-",($L36/N36-1)) -> 40.679826 | U36: =IF(ISERROR($D36/$D$15),"-",($D36/$D$15)) -> -0.0075798592 | W36: =IF(ISERROR(F36/F$15),"-",(F36/F$15)) -> -0.0017220001 | Y36: =IF(ISERROR($H36/$H$15),"-",($H36/$H$15)) -> -0.0075798592 | AA36: =IF(ISERROR(J36/J$15),"-",(J36/J$15)) -> -0.00051492666 | AC36: =IF(ISERROR($L36/$L$15),"-",($L36/$L$15)) -> -0.007555386 | AE36: =IF(ISERROR(N36/N$15),"-",(N36/N$15)) -> -0.00018920863 | AG36: =-W36*AE36 -> -3.2581728e-07
B37: Despesas Pré-Operacionais | H37: ='03- BD x RE 2026'!G70/1000 -> 0 | J37: ='[2]9 1 DRE R23'!P68/1000 -> 0 | L37: ='03- BD x RE 2026'!J70/1000 -> 0 | N37: ='03- BD x RE 2026'!K70/1000 -> 0 | P37: =IF(ISERROR(#REF!/D37-1),"-",(#REF!/D37-1)) -> - | R37: =IF(ISERROR($H37/J37-1),"-",($H37/J37-1)) -> - | T37: =IF(ISERROR($H37/K37-1),"-",($H37/K37-1)) -> - | U37: =IF(ISERROR($D37/$D$15),"-",($D37/$D$15)) -> 0 | W37: =IF(ISERROR(F37/F$15),"-",(F37/F$15)) -> 0 | Y37: =IF(ISERROR($H37/$H$15),"-",($H37/$H$15)) -> 0 | AA37: =IF(ISERROR(J37/J$15),"-",(J37/J$15)) -> 0 | AC37: =IF(ISERROR($L37/$L$15),"-",($L37/$L$15)) -> 0 | AE37: =IF(ISERROR(N37/N$15),"-",(N37/N$15)) -> 0 | AG37: =-W37*AE37 -> 0
B38: IRPJ/CSLL | H38: ='03- BD x RE 2026'!G71/1000 -> 0 | L38: ='03- BD x RE 2026'!J71/1000 -> 0 | N38: ='03- BD x RE 2026'!K71/1000 -> 0 | P38: =IF(ISERROR($F38/D38-1),"-",($F38/D38-1)) -> - | R38: =IF(ISERROR($H38/J38-1),"-",($H38/J38-1)) -> - | T38: =IF(ISERROR($H38/K38-1),"-",($H38/K38-1)) -> - | U38: =IF(ISERROR($D38/$D$15),"-",($D38/$D$15)) -> 0 | W38: =IF(ISERROR(F38/F$15),"-",(F38/F$15)) -> 0 | Y38: =IF(ISERROR($H38/$H$15),"-",($H38/$H$15)) -> 0 | AA38: =IF(ISERROR(J38/J$15),"-",(J38/J$15)) -> 0 | AC38: =IF(ISERROR($L38/$L$15),"-",($L38/$L$15)) -> 0 | AE38: =IF(ISERROR(N38/N$15),"-",(N38/N$15)) -> 0 | AG38: =-W38*AE38 -> 0
R39: =IF(ISERROR($H39/J39-1),"-",($H39/J39-1)) -> - | T39: =IF(ISERROR($H39/K39-1),"-",($H39/K39-1)) -> -
B40: RESULTADO OPERACIONAL | D40: =D34+D36+D37+D38 -> -16.06417 | F40: =F34+F36+F37+F38 -> -246.97582 | H40: =H34+H36+H37+H38 -> 333.96685 | J40: =J34+J36+J37+J38 -> -107.14357 | L40: =L34+L36+L37+L38 -> 363.68365 | N40: =N34+N36+N37+N38 -> 509.45543 | P40: =IF(ISERROR($F40/D40-1),"-",($F40/D40-1)) -> 14.374328 | R40: =IF(ISERROR($H40/J40-1),"-",($H40/J40-1)) -> -4.1170031 | T40: =IF(ISERROR($H40/K40-1),"-",($H40/K40-1)) -> - | U40: =IF(ISERROR($D40/$D$15),"-",($D40/$D$15)) -> -0.010020481 | W40: =IF(ISERROR(F40/F$15),"-",(F40/F$15)) -> -0.18446701 | Y40: =IF(ISERROR($H40/$H$15),"-",($H40/$H$15)) -> 0.13571721 | AA40: =IF(ISERROR(J40/J$15),"-",(J40/J$15)) -> -0.071091259 | AC40: =IF(ISERROR($L40/$L$15),"-",($L40/$L$15)) -> 0.14617664 | AE40: =IF(ISERROR(N40/N$15),"-",(N40/N$15)) -> 0.21373251 | AG40: =-W40*AE40 -> 0.039426598
B41: ='[2]2 DRE '!A70 -> Margem líquida | D41: =IF(ISERROR(D40/D15),0,(D40/D15)) -> -0.010020481 | F41: =IF(ISERROR(F40/F15),0,(F40/F15)) -> -0.18446701 | H41: =IF(ISERROR(H40/H15),0,(H40/H15)) -> 0.13571721 | J41: =IF(ISERROR(J40/J15),0,(J40/J15)) -> -0.071091259 | L41: =IF(ISERROR(L40/L15),0,(L40/L15)) -> 0.14617664 | N41: =IF(ISERROR(N40/N15),0,(N40/N15)) -> 0.21373251

Sheet 03- BD x RE 2026
A1: BD(2026)
C5: 2026 | D5: JAN | G5: FEV | J5: MAR | M5: ABR | P5: MAI | S5: JUN | V5: JUL | Y5: AGO | AB5: SET | AE5: OUT | AH5: NOV | AK5: DEZ | AN5: 2026 ACUM. | AQ5: 2026 MÉDIA ANUAL | AT5: 2026 PART% | AV5: JAN | AW5: FEV | AX5: MAR | AY5: ABR | AZ5: MAI | BA5: JUN | BB5: JUL | BC5: AGO | BD5: SET | BE5: OUT | BF5: NOV | BG5: DEZ
D6: PROJETADO | E6: REALIZADO | G6: PROJETADO | H6: REALIZADO | J6: PROJETADO | K6: REALIZADO | M6: PROJETADO | N6: REALIZADO | P6: PROJETADO | Q6: REALIZADO | S6: PROJETADO | T6: REALIZADO | V6: PROJETADO | W6: REALIZADO | Y6: PROJETADO | Z6: REALIZADO | AB6: PROJETADO | AC6: REALIZADO | AE6: PROJETADO | AF6: REALIZADO | AH6: PROJETADO | AI6: REALIZADO | AK6: PROJETADO | AL6: REALIZADO | AN6: PROJETADO | AO6: REALIZADO | AQ6: PROJETADO | AR6: REALIZADO
A7: CLIENTES | C7: =SUM(D7,G7,J7,M7,P7,S7,V7,Y7,AB7,AE7,AH7,AK7) -> 94390.712 | D7: ='04 -Base Orçado 2026'!E7 -> 5786.4418 | E7: ='Base Realizado'!D7 -> 4761 | G7: ='04 -Base Orçado 2026'!F7 -> 7860.1684 | H7: ='Base Realizado'!F7 -> 4661 | J7: ='04 -Base Orçado 2026'!G7 -> 7921.4504 | K7: ='Base Realizado'!H7 -> 6592 | M7: ='04 -Base Orçado 2026'!H7 -> 8127.4243 | N7: ='Base Realizado'!K7 -> 0 | P7: ='04 -Base Orçado 2026'!I7 -> 9134.876 | S7: ='04 -Base Orçado 2026'!J7 -> 7745.6024 | V7: ='04 -Base Orçado 2026'!K7 -> 7474.4325 | Y7: ='04 -Base Orçado 2026'!L7 -> 7645.5461 | AB7: ='04 -Base Orçado 2026'!M7 -> 7551.431 | AE7: ='04 -Base Orçado 2026'!N7 -> 7336.2258 | AH7: ='04 -Base Orçado 2026'!O7 -> 8672.2369 | AK7: ='03- BD x RE 2026'!P7 -> 9134.876 | AN7: =SUM(D7,G7,J7,M7,P7,S7,V7,Y7,AB7,AE7,AH7,AK7) -> 94390.712 | AO7: =SUM(E7,H7,K7,N7,Q7,T7,W7,Z7,AC7,AF7,AI7,AL7) -> 16014 | AQ7: =AN7/12 -> 7865.8926
A8: Ticket Médio - R$M | C8: =SUM(D8,G8,J8,M8,P8,S8,V8,Y8,AB8,AE8,AH8,AK8) -> 3600 | D8: ='04 -Base Orçado 2026'!E8 -> 300 | E8: ='Base Realizado'!D8 -> 289.76034 | G8: ='04 -Base Orçado 2026'!F8 -> 300 | H8: ='Base Realizado'!F8 -> 312.20426 | J8: ='04 -Base Orçado 2026'!G8 -> 300 | K8: ='Base Realizado'!H8 -> 317.16391 | M8: ='04 -Base Orçado 2026'!H8 -> 300 | N8: ='Base Realizado'!K8 -> 0 | P8: ='04 -Base Orçado 2026'!I8 -> 300 | S8: ='04 -Base Orçado 2026'!J8 -> 300 | V8: ='04 -Base Orçado 2026'!K8 -> 300 | Y8: ='04 -Base Orçado 2026'!L8 -> 300 | AB8: ='04 -Base Orçado 2026'!M8 -> 300 | AE8: ='04 -Base Orçado 2026'!N8 -> 300 | AH8: ='04 -Base Orçado 2026'!O8 -> 300 | AK8: ='04 -Base Orçado 2026'!P8 -> 300 | AN8: =IF(ISERROR(AN10/AN7),"0",(AN10/AN7)) -> 326.05316 | AO8: =IF(ISERROR(AO10/AO7),"0",(AO10/AO7)) -> 478.25187 | AQ8: =IF(ISERROR(AQ10/AQ7),"0",(AQ10/AQ7)) -> 326.05316
A10: Faturamento Bruto | C10: =SUM(D10,G10,J10,M10,P10,S10,V10,Y10,AB10,AE10,AH10,AK10) -> 30776390 | D10: =SUM(D11:D17)-D11 -> 1735932.5 | E10: =SUM(E11:E17)-E11 -> 1390349 | G10: =SUM(G11:G17) -> 2664597.1 | H10: =SUM(H11:H17)-H11 -> 1528554.1 | J10: =SUM(J11:J17) -> 2693404.7 | K10: =SUM(K11:K17)-K11 -> 2443536.8 | M10: =SUM(M11:M17) -> 2755196.8 | N10: =SUM(N11:N17)-N11 -> 2296285.6 | P10: =SUM(P11:P17) -> 3096723 | S10: =SUM(S11:S17) -> 2625759.2 | V10: =SUM(V11:V17) -> 2533832.6 | Y10: =SUM(Y11:Y17) -> 2591840.1 | AB10: =SUM(AB11:AB17) -> 2559935.1 | AE10: =SUM(AE11:AE17) -> 2486980.5 | AH10: =SUM(AH11:AH17) -> 2939888.3 | AK10: =SUM(AK11:AK17) -> 2092300.1 | AN10: =SUM(D10,G10,J10,M10,P10,S10,V10,Y10,AB10,AE10,AH10,AK10) -> 30776390 | AO10: =SUM(E10,H10,K10,N10,Q10,T10,W10,Z10,AC10,AF10,AI10,AL10) -> 7658725.4 | AQ10: =AN10/12 -> 2564699.2 | AR10: =AQ10/$AT$12 -> 641174.79
A11: Gorjetas Recebidas | C11: =SUM(D11,G11,J11,M11,P11,S11,V11,Y11,AB11,AE11,AH11,AK11) -> 3573717.7 | D11: ='04 -Base Orçado 2026'!E13 -> 225671.23 | E11: ='Base Realizado'!D12 -> 110797.62 | G11: ='04 -Base Orçado 2026'!F13 -> 306546.57 | H11: ='Base Realizado'!F12 -> 198712 | J11: ='04 -Base Orçado 2026'!H13 -> 316969.55 | K11: ='Base Realizado'!H12 -> 116627.58 | M11: ='04 -Base Orçado 2026'!H13 -> 316969.55 | N11: ='Base Realizado'!N12 -> 0 | P11: ='04 -Base Orçado 2026'!I13 -> 356260.16 | S11: ='04 -Base Orçado 2026'!J13 -> 302078.5 | V11: ='04 -Base Orçado 2026'!K13 -> 291502.87 | Y11: ='04 -Base Orçado 2026'!L13 -> 298176.3 | AB11: ='04 -Base Orçado 2026'!M13 -> 294505.81 | AE11: ='04 -Base Orçado 2026'!N13 -> 286112.81 | AH11: ='04 -Base Orçado 2026'!O13 -> 338217.24 | AK11: ='04 -Base Orçado 2026'!P13 -> 240707.09
A12: Dinheiro | C12: =SUM(D12,G12,J12,M12,P12,S12,V12,Y12,AB12,AE12,AH12,AK12) -> 548566.87 | D12: ='04 -Base Orçado 2026'!E14 -> 34718.651 | E12: ='Base Realizado'!D13 -> 191219.93 | G12: ='04 -Base Orçado 2026'!F14 -> 47161.01 | H12: ='Base Realizado'!F13 -> 232968.95 | J12: ='04 -Base Orçado 2026'!G14 -> 47528.702 | K12: ='Base Realizado'!H13 -> 339893.43 | M12: ='04 -Base Orçado 2026'!H14 -> 48764.546 | N12: ='Base Realizado'!K12 -> 0 | P12: ='04 -Base Orçado 2026'!I14 -> 54809.256 | S12: ='04 -Base Orçado 2026'!J14 -> 46473.615 | V12: ='04 -Base Orçado 2026'!K14 -> 44846.595 | Y12: ='04 -Base Orçado 2026'!L14 -> 45873.276 | AB12: ='04 -Base Orçado 2026'!M14 -> 45308.586 | AE12: ='04 -Base Orçado 2026'!N14 -> 44017.355 | AH12: ='04 -Base Orçado 2026'!O14 -> 52033.422 | AK12: ='04 -Base Orçado 2026'!P14 -> 37031.86 | AN12: =SUM(D12,G12,J12,M12,P12,S12,V12,Y12,AB12,AE12,AH12,AK12) -> 548566.87 | AO12: =SUM(E12,H12,K12,N12,Q12,T12,W12,Z12,AC12,AF12,AI12,AL12) -> 764082.31 | AQ12: =AVERAGE(D12,G12,J12) -> 43136.121 | AR12: =AVERAGE(E12,H12,K12) -> 254694.1 | AT12: =COUNTA(E12,H12,K12,N12,Q12,T12,W12,Z12,AC12,AF12,AI12,AL12) -> 4
A13: Cartão de Débito | C13: =SUM(D13,G13,J13,M13,P13,S13,V13,Y13,AB13,AE13,AH13,AK13) -> 1919984.1 | D13: ='04 -Base Orçado 2026'!E15 -> 121515.28 | E13: ='Base Realizado'!D14 -> 213780.01 | G13: ='04 -Base Orçado 2026'!F15 -> 165063.54 | H13: ='Base Realizado'!F14 -> 988071.98 | J13: ='04 -Base Orçado 2026'!G15 -> 166350.46 | K13: ='Base Realizado'!H14 -> 289846.25 | M13: ='04 -Base Orçado 2026'!H15 -> 170675.91 | N13: ='Base Realizado'!K13 -> 299094.7 | P13: ='04 -Base Orçado 2026'!I15 -> 191832.4 | S13: ='04 -Base Orçado 2026'!J15 -> 162657.65 | V13: ='04 -Base Orçado 2026'!K15 -> 156963.08 | Y13: ='04 -Base Orçado 2026'!L15 -> 160556.47 | AB13: ='04 -Base Orçado 2026'!M15 -> 158580.05 | AE13: ='04 -Base Orçado 2026'!N15 -> 154060.74 | AH13: ='04 -Base Orçado 2026'!O15 -> 182116.98 | AK13: ='04 -Base Orçado 2026'!P15 -> 129611.51 | AN13: =SUM(D13,G13,J13,M13,P13,S13,V13,Y13,AB13,AE13,AH13,AK13) -> 1919984.1 | AO13: =SUM(E13,H13,K13,N13,Q13,T13,W13,Z13,AC13,AF13,AI13,AL13) -> 1790792.9 | AQ13: =AVERAGE(D13,G13,J13) -> 150976.42 | AR13: =AVERAGE(E13,H13,K13) -> 497232.75 | AT13: =COUNTA(E13,H13,K13,N13,Q13,T13,W13,Z13,AC13,AF13,AI13,AL13) -> 4
A14: Cartão de Crédito | C14: =SUM(D14,G14,J14,M14,P14,S14,V14,Y14,AB14,AE14,AH14,AK14) -> 17992993 | D14: ='04 -Base Orçado 2026'!E16 -> 1138771.7 | E14: ='Base Realizado'!D15 -> 963659.96 | G14: ='04 -Base Orçado 2026'!F16 -> 1546881.1 | H14: ='Base Realizado'!F15 -> 223553.48 | J14: ='04 -Base Orçado 2026'!G16 -> 1558941.4 | K14: ='Base Realizado'!H15 -> 1455192.1 | M14: ='04 -Base Orçado 2026'!H16 -> 1599477.1 | N14: ='Base Realizado'!K14 -> 313558.29 | P14: ='04 -Base Orçado 2026'!I16 -> 1797743.6 | S14: ='04 -Base Orçado 2026'!J16 -> 1524334.6 | V14: ='04 -Base Orçado 2026'!K16 -> 1470968.3 | Y14: ='04 -Base Orçado 2026'!L16 -> 1504643.5 | AB14: ='04 -Base Orçado 2026'!M16 -> 1486121.6 | AE14: ='04 -Base Orçado 2026'!N16 -> 1443769.2 | AH14: ='04 -Base Orçado 2026'!O16 -> 1706696.2 | AK14: ='04 -Base Orçado 2026'!P16 -> 1214645 | AN14: =SUM(D14,G14,J14,M14,P14,S14,V14,Y14,AB14,AE14,AH14,AK14) -> 17992993 | AO14: =SUM(E14,H14,K14,N14,Q14,T14,W14,Z14,AC14,AF14,AI14,AL14) -> 2955963.8 | AQ14: =AVERAGE(D14,G14,J14) -> 1414864.8 | AR14: =AVERAGE(E14,H14,K14) -> 880801.84 | AT14: =COUNTA(E14,H14,K14,N14,Q14,T14,W14,Z14,AC14,AF14,AI14,AL14) -> 4
A15: Evento Faturado | C15: =SUM(D15,G15,J15,M15,P15,S15,V15,Y15,AB15,AE15,AH15,AK15) -> 2742834.4 | D15: ='04 -Base Orçado 2026'!E17 -> 173593.25 | E15: ='Base Realizado'!D16 -> 10800 | G15: ='04 -Base Orçado 2026'!F17 -> 235805.05 | H15: ='Base Realizado'!F16 -> 73370 | J15: ='04 -Base Orçado 2026'!G17 -> 237643.51 | K15: ='Base Realizado'!H16 -> 352792.26 | M15: ='04 -Base Orçado 2026'!H17 -> 243822.73 | N15: ='Base Realizado'!K15 -> 1524543.3 | P15: ='04 -Base Orçado 2026'!I17 -> 274046.28 | S15: ='04 -Base Orçado 2026'!J17 -> 232368.07 | V15: ='04 -Base Orçado 2026'!K17 -> 224232.98 | Y15: ='04 -Base Orçado 2026'!L17 -> 229366.38 | AB15: ='04 -Base Orçado 2026'!M17 -> 226542.93 | AE15: ='04 -Base Orçado 2026'!N17 -> 220086.77 | AH15: ='04 -Base Orçado 2026'!O17 -> 260167.11 | AK15: ='04 -Base Orçado 2026'!P17 -> 185159.3 | AN15: =SUM(D15,G15,J15,M15,P15,S15,V15,Y15,AB15,AE15,AH15,AK15) -> 2742834.4 | AO15: =SUM(E15,H15,K15,N15,Q15,T15,W15,Z15,AC15,AF15,AI15,AL15) -> 1961505.6 | AQ15: =AVERAGE(D15,G15,J15) -> 215680.61 | AR15: =AVERAGE(E15,H15,K15) -> 145654.09 | AT15: =COUNTA(E15,H15,K15,N15,Q15,T15,W15,Z15,AC15,AF15,AI15,AL15) -> 4
A16: Delivery | C16: =SUM(D16,G16,J16,M16,P16,S16,V16,Y16,AB16,AE16,AH16,AK16) -> 4114251.5 | D16: ='04 -Base Orçado 2026'!E18 -> 260389.88 | G16: ='04 -Base Orçado 2026'!F18 -> 353707.58 | H16: ='Base Realizado'!F17 -> 0 | J16: ='04 -Base Orçado 2026'!G18 -> 356465.27 | K16: ='Base Realizado'!H17 -> 0 | M16: ='04 -Base Orçado 2026'!H18 -> 365734.09 | N16: ='Base Realizado'!K16 -> 159089.31 | P16: ='04 -Base Orçado 2026'!I18 -> 411069.42 | S16: ='04 -Base Orçado 2026'!J18 -> 348552.11 | V16: ='04 -Base Orçado 2026'!K18 -> 336349.46 | Y16: ='04 -Base Orçado 2026'!L18 -> 344049.57 | AB16: ='04 -Base Orçado 2026'!M18 -> 339814.4 | AE16: ='04 -Base Orçado 2026'!N18 -> 330130.16 | AH16: ='04 -Base Orçado 2026'!O18 -> 390250.66 | AK16: ='04 -Base Orçado 2026'!P18 -> 277738.95 | AN16: =SUM(D16,G16,J16,M16,P16,S16,V16,Y16,AB16,AE16,AH16,AK16) -> 4114251.5 | AO16: =SUM(E16,H16,K16,N16,Q16,T16,W16,Z16,AC16,AF16,AI16,AL16) -> 159089.31 | AQ16: =AVERAGE(D16,G16,J16) -> 323520.91 | AR16: =AVERAGE(E16,H16,K16) -> 0 | AT16: =COUNTA(E16,H16,K16,N16,Q16,T16,W16,Z16,AC16,AF16,AI16,AL16) -> 3
A17: Voucher | C17: =SUM(D17,G17,J17,M17,P17,S17,V17,Y17,AB17,AE17,AH17,AK17) -> 109713.37 | D17: ='04 -Base Orçado 2026'!E19 -> 6943.7302 | E17: ='Base Realizado'!D18 -> 10889.07 | G17: ='04 -Base Orçado 2026'!F19 -> 9432.2021 | H17: ='Base Realizado'!F18 -> 10589.65 | J17: ='04 -Base Orçado 2026'!G19 -> 9505.7404 | K17: ='Base Realizado'!H18 -> 5812.74 | M17: ='04 -Base Orçado 2026'!H19 -> 9752.9091 | N17: ='Base Realizado'!K17 -> 0 | P17: ='04 -Base Orçado 2026'!I19 -> 10961.851 | S17: ='04 -Base Orçado 2026'!J19 -> 9294.7229 | V17: ='04 -Base Orçado 2026'!K19 -> 8969.319 | Y17: ='04 -Base Orçado 2026'!L19 -> 9174.6553 | AB17: ='04 -Base Orçado 2026'!M19 -> 9061.7172 | AE17: ='04 -Base Orçado 2026'!N19 -> 8803.471 | AH17: ='04 -Base Orçado 2026'!O19 -> 10406.684 | AK17: ='04 -Base Orçado 2026'!P19 -> 7406.3719 | AN17: =SUM(D17,G17,J17,M17,P17,S17,V17,Y17,AB17,AE17,AH17,AK17) -> 109713.37 | AQ17: =AVERAGE(D17,G17,J17) -> 8627.2242 | AR17: =AVERAGE(E17,H17,K17) -> 9097.1533 | AT17: =COUNTA(E17,H17,K17,N17,Q17,T17,W17,Z17,AC17,AF17,AI17,AL17) -> 4
A19: Impostos sobre Vendas | C19: =SUM(D19,G19,J19,M19,P19,S19,V19,Y19,AB19,AE19,AH19,AK19) -> -2353779.3 | D19: =SUM(D20:D23) -> -132798.84 | E19: =SUM(E20:E23) -> -51487.25 | G19: =SUM(G20:G23) -> -203841.68 | H19: =SUM(H20:H23) -> -21426.81 | J19: =SUM(J20:J23) -> -205430.93 | K19: =SUM(K20:K23) -> -59924.54 | M19: =SUM(M20:M23) -> -210772.56 | N19: =SUM(N20:N23) -> 0 | P19: =SUM(P20:P23) -> -236899.31 | S19: =SUM(S20:S23) -> -200870.58 | V19: =SUM(V20:V23) -> -193838.2 | Y19: =SUM(Y20:Y23) -> -198275.77 | AB19: =SUM(AB20:AB23) -> -195835.04 | AE19: =SUM(AE20:AE23) -> -190254.01 | AH19: =SUM(AH20:AH23) -> -224901.46 | AK19: =SUM(AK20:AK23) -> -160060.96 | AN19: =SUM(D19,G19,J19,M19,P19,S19,V19,Y19,AB19,AE19,AH19,AK19) -> -2353779.3 | AO19: =SUM(E19,H19,K19,N19,Q19,T19,W19,Z19,AC19,AF19,AI19,AL19) -> -132838.6 | AQ19: =AVERAGE(D19,G19,J19) -> -180690.48 | AR19: =AVERAGE(E19,H19,K19) -> -44279.533 | AT19: =SUM(AT20:AT23) -> -0.082813621 | AV19: =SUM(AV20:AV23) -> -0.082837033 | AW19: =SUM(AW20:AW23) -> -0.082837033 | AX19: =SUM(AX20:AX23) -> -0.082569575 | AY19: =SUM(AY20:AY23) -> -0.082837033 | AZ19: =SUM(AZ20:AZ23) -> -0.082837033 | BA19: =SUM(BA20:BA23) -> -0.082837033 | BB19: =SUM(BB20:BB23) -> -0.082837033 | BC19: =SUM(BC20:BC23) -> -0.082837033 | ... BG19: =SUM(BG20:BG23) -> -0.082837033
A20: ICMS | C20: =SUM(D20,G20,J20,M20,P20,S20,V20,Y20,AB20,AE20,AH20,AK20) -> -1230734.3 | D20: ='04 -Base Orçado 2026'!E22 -> -69437.302 | E20: ='Base Realizado'!D21 -> -11603.07 | G20: ='04 -Base Orçado 2026'!F22 -> -106583.88 | H20: ='B. Despesa'!H2388 -> -1056 | J20: ='04 -Base Orçado 2026'!G22 -> -107414.87 | K20: ='Base Realizado'!H21 -> -37427.25 | M20: ='04 -Base Orçado 2026'!H22 -> -110207.87 | N20: ='Base Realizado'!K20 -> 0 | P20: ='04 -Base Orçado 2026'!I22 -> -123868.92 | S20: ='04 -Base Orçado 2026'!J22 -> -105030.37 | V20: ='04 -Base Orçado 2026'!K22 -> -101353.3 | Y20: ='04 -Base Orçado 2026'!L22 -> -103673.6 | AB20: ='04 -Base Orçado 2026'!M22 -> -102397.4 | AE20: ='04 -Base Orçado 2026'!N22 -> -99479.222 | AH20: ='04 -Base Orçado 2026'!O22 -> -117595.53 | AK20: ='04 -Base Orçado 2026'!P22 -> -83692.003 | AN20: =SUM(D20,G20,J20,M20,P20,S20,V20,Y20,AB20,AE20,AH20,AK20) -> -1230734.3 | AO20: =SUM(E20,H20,K20,N20,Q20,T20,W20,Z20,AC20,AF20,AI20,AL20) -> -50086.32 | AQ20: =AVERAGE(D20,G20,J20) -> -94478.684 | AR20: =AVERAGE(E20,H20,K20) -> -16695.44 | AT20: =IF(ISERROR(C20/C$24),0,(C20/C$24)) -> -0.04330124 | AV20: =IF(ISERROR(D20/D$24),0,(D20/D$24)) -> -0.043313481 | AW20: =IF(ISERROR(G20/G$24),0,(G20/G$24)) -> -0.043313481 | AX20: =IF(ISERROR(J20/J$24),0,(J20/J$24)) -> -0.043173634 | AY20: =IF(ISERROR(M20/M$24),0,(M20/M$24)) -> -0.043313481 | AZ20: =IF(ISERROR(P20/P$24),0,(P20/P$24)) -> -0.043313481 | BA20: =IF(ISERROR(S20/S$24),0,(S20/S$24)) -> -0.043313481 | BB20: =IF(ISERROR(V20/V$24),0,(V20/V$24)) -> -0.043313481 | BC20: =IF(ISERROR(Y20/Y$24),0,(Y20/Y$24)) -> -0.043313481 | BD20: =IF(ISERROR(AB20/AB$24),0,(AB20/AB$24)) -> -0.043313481 | BE20: =IF(ISERROR(AE20/AE$24),0,(AE20/AE$24)) -> -0.043313481 | BF20: =IF(ISERROR(AH20/AH$24),0,(AH20/AH$24)) -> -0.043313481 | BG20: =IF(ISERROR(AK20/AK$24),0,(AK20/AK$24)) -> -0.043313481
A21: COFINS | C21: =SUM(D21,G21,J21,M21,P21,S21,V21,Y21,AB21,AE21,AH21,AK21) -> -923050.71 | D21: ='04 -Base Orçado 2026'!E23 -> -52077.976 | E21: ='Base Realizado'!D22 -> -18007.73 | G21: ='04 -Base Orçado 2026'!F23 -> -79937.913 | H21: ='B. Despesa'!H2389 -> -15493.73 | J21: ='04 -Base Orçado 2026'!G23 -> -80561.15 | K21: ='Base Realizado'!H22 -> -18490.92 | M21: ='04 -Base Orçado 2026'!H23 -> -82655.905 | N21: ='Base Realizado'!K21 -> 0 | P21: ='04 -Base Orçado 2026'!I23 -> -92901.689 | S21: ='04 -Base Orçado 2026'!J23 -> -78772.777 | V21: ='04 -Base Orçado 2026'!K23 -> -76014.979 | Y21: ='04 -Base Orçado 2026'!L23 -> -77755.204 | AB21: ='04 -Base Orçado 2026'!M23 -> -76798.054 | AE21: ='04 -Base Orçado 2026'!N23 -> -74609.416 | AH21: ='04 -Base Orçado 2026'!O23 -> -88196.649 | AK21: ='04 -Base Orçado 2026'!P23 -> -62769.002 | AN21: =SUM(D21,G21,J21,M21,P21,S21,V21,Y21,AB21,AE21,AH21,AK21) -> -923050.71 | AO21: =SUM(E21,H21,K21,N21,Q21,T21,W21,Z21,AC21,AF21,AI21,AL21) -> -51992.38 | AQ21: =AVERAGE(D21,G21,J21) -> -70859.013 | AR21: =AVERAGE(E21,H21,K21) -> -17330.793 | AT21: =IF(ISERROR(C21/C$24),0,(C21/C$24)) -> -0.03247593 | AV21: =IF(ISERROR(D21/D$24),0,(D21/D$24)) -> -0.032485111 | AW21: =IF(ISERROR(G21/G$24),0,(G21/G$24)) -> -0.032485111 | AX21: =IF(ISERROR(J21/J$24),0,(J21/J$24)) -> -0.032380226 | AY21: =IF(ISERROR(M21/M$24),0,(M21/M$24)) -> -0.032485111 | AZ21: =IF(ISERROR(P21/P$24),0,(P21/P$24)) -> -0.032485111 | BA21: =IF(ISERROR(S21/S$24),0,(S21/S$24)) -> -0.032485111 | BB21: =IF(ISERROR(V21/V$24),0,(V21/V$24)) -> -0.032485111 | BC21: =IF(ISERROR(Y21/Y$24),0,(Y21/Y$24)) -> -0.032485111 | BD21: =IF(ISERROR(AB21/AB$24),0,(AB21/AB$24)) -> -0.032485111 | BE21: =IF(ISERROR(AE21/AE$24),0,(AE21/AE$24)) -> -0.032485111 | BF21: =IF(ISERROR(AH21/AH$24),0,(AH21/AH$24)) -> -0.032485111 | BG21: =IF(ISERROR(AK21/AK$24),0,(AK21/AK$24)) -> -0.032485111
A22: PIS | C22: =SUM(D22,G22,J22,M22,P22,S22,V22,Y22,AB22,AE22,AH22,AK22) -> -199994.32 | D22: ='04 -Base Orçado 2026'!E24 -> -11283.562 | E22: ='Base Realizado'!D23 -> -21876.45 | G22: ='04 -Base Orçado 2026'!F24 -> -17319.881 | H22: ='B. Despesa'!H2390 -> -4877.08 | J22: ='04 -Base Orçado 2026'!G24 -> -17454.916 | K22: ='Base Realizado'!H23 -> -4006.37 | M22: ='04 -Base Orçado 2026'!H24 -> -17908.779 | N22: ='Base Realizado'!K22 -> 0 | P22: ='04 -Base Orçado 2026'!I24 -> -20128.699 | S22: ='04 -Base Orçado 2026'!J24 -> -17067.435 | V22: ='04 -Base Orçado 2026'!K24 -> -16469.912 | Y22: ='04 -Base Orçado 2026'!L24 -> -16846.961 | AB22: ='04 -Base Orçado 2026'!M24 -> -16639.578 | AE22: ='04 -Base Orçado 2026'!N24 -> -16165.374 | AH22: ='04 -Base Orçado 2026'!O24 -> -19109.274 | AK22: ='04 -Base Orçado 2026'!P24 -> -13599.95 | AN22: =SUM(D22,G22,J22,M22,P22,S22,V22,Y22,AB22,AE22,AH22,AK22) -> -199994.32 | AO22: =SUM(E22,H22,K22,N22,Q22,T22,W22,Z22,AC22,AF22,AI22,AL22) -> -30759.9 | AQ22: =AVERAGE(D22,G22,J22) -> -15352.786 | AR22: =AVERAGE(E22,H22,K22) -> -10253.3 | AT22: =IF(ISERROR(C22/C$24),0,(C22/C$24)) -> -0.0070364515 | AV22: =IF(ISERROR(D22/D$24),0,(D22/D$24)) -> -0.0070384407 | AW22: =IF(ISERROR(G22/G$24),0,(G22/G$24)) -> -0.0070384407 | AX22: =IF(ISERROR(J22/J$24),0,(J22/J$24)) -> -0.0070157155 | AY22: =IF(ISERROR(M22/M$24),0,(M22/M$24)) -> -0.0070384407 | AZ22: =IF(ISERROR(P22/P$24),0,(P22/P$24)) -> -0.0070384407 | BA22: =IF(ISERROR(S22/S$24),0,(S22/S$24)) -> -0.0070384407 | BB22: =IF(ISERROR(V22/V$24),0,(V22/V$24)) -> -0.0070384407 | BC22: =IF(ISERROR(Y22/Y$24),0,(Y22/Y$24)) -> -0.0070384407 | BD22: =IF(ISERROR(AB22/AB$24),0,(AB22/AB$24)) -> -0.0070384407 | BE22: =IF(ISERROR(AE22/AE$24),0,(AE22/AE$24)) -> -0.0070384407 | BF22: =IF(ISERROR(AH22/AH$24),0,(AH22/AH$24)) -> -0.0070384407 | BG22: =IF(ISERROR(AK22/AK$24),0,(AK22/AK$24)) -> -0.0070384407
C23: =SUM(D23,G23,J23,M23,P23,S23,V23,Y23,AB23,AE23,AH23,AK23) -> 0
A24: Receita Líquida | C24: =SUM(D24,G24,J24,M24,P24,S24,V24,Y24,AB24,AE24,AH24,AK24) -> 28422611 | D24: =D10+D19 -> 1603133.7 | E24: =E10+E19 -> 1338861.7 | G24: =G10+G19 -> 2460755.4 | H24: =H10+H19 -> 1507127.3 | J24: =J10+J19 -> 2487973.7 | K24: =K10+K19 -> 2383612.2 | M24: =M10+M19 -> 2544424.3 | N24: =N10+N19 -> 2296285.6 | P24: =P10+P19 -> 2859823.6 | S24: =S10+S19 -> 2424888.6 | V24: =V10+V19 -> 2339994.4 | Y24: =Y10+Y19 -> 2393564.4 | AB24: =AB10+AB19 -> 2364100.1 | AE24: =AE10+AE19 -> 2296726.5 | AH24: =AH10+AH19 -> 2714986.9 | AK24: =AK10+AK19 -> 1932239.1 | AN24: =SUM(D24,G24,J24,M24,P24,S24,V24,Y24,AB24,AE24,AH24,AK24) -> 28422611 | AO24: =SUM(E24,H24,K24,N24,Q24,T24,W24,Z24,AC24,AF24,AI24,AL24) -> 7525886.8 | AQ24: =AVERAGE(D24,G24,J24) -> 2183954.3 | AR24: =AVERAGE(E24,H24,K24) -> 1743200.4 | AT24: =C24/C10 -> 0.92351997
C25: =SUM(D25,G25,J25,M25,P25,S25,V25,Y25,AB25,AE25,AH25,AK25) -> 0 | AN25: =SUM(D25:AK25) -> 0
A26: CUSTOS/DESPESAS | C26: =SUM(D26,G26,J26,M26,P26,S26,V26,Y26,AB26,AE26,AH26,AK26) -> -21293530 | D26: =SUM(,D28,D44,D49,D50,D51,D52) -> -1368519.3 | E26: =SUM(,E28,E44,E49,E50,E51,E52) -> -1331701.3 | G26: =SUM(,G28,G44,G49,G50,G51,G52) -> -1822211.2 | H26: =SUM(,H28,H44,H49,H50,H51,H52) -> -1408175.9 | J26: =SUM(J29:J52) -> -1821906.4 | K26: =SUM(,K28,K44,K49,K50,K51,K52) -> -1640580.2 | M26: =SUM(M29:M52) -> -1852795.8 | N26: =SUM(,N28,N44,N49,N50,N51,N52) -> -1890226.7 | P26: =SUM(P29:P52) -> -2003880.5 | S26: =SUM(S29:S52) -> -1795535 | V26: =SUM(V29:V52) -> -1772660.2 | Y26: =SUM(Y29:Y52) -> -1798321.7 | AB26: =SUM(AB29:AB52) -> -1784207.5 | AE26: =SUM(AE29:AE52) -> -1751933.7 | AH26: =SUM(AH29:AH52) -> -1952291.7 | AK26: =SUM(AK29:AK52) -> -1569266.8 | AN26: =SUM(D26,G26,J26,M26,P26,S26,V26,Y26,AB26,AE26,AH26,AK26) -> -21293530 | AO26: =SUM(E26,H26,K26,N26,Q26,T26,W26,Z26,AC26,AF26,AI26,AL26) -> -6270684 | AQ26: =AVERAGE(D26,G26,J26) -> -1670879 | AR26: =AVERAGE(E26,H26,K26) -> -1460152.4 | AT26: =SUM(AT28,AT44,AT49,AT50,AT51,AT52) -> -0.74917572 | AV26: =SUM(AV29:AV51) -> -0.81665262 | AW26: =SUM(AW29:AW51) -> -0.70776549 | AX26: =SUM(AX29:AX51) -> -0.69964759 | AY26: =SUM(AY29:AY51) -> -0.69543542 | AZ26: =SUM(AZ29:AZ51) -> -0.66795738 | BA26: =SUM(BA29:BA51) -> -0.70771744 | BB26: =SUM(BB29:BB51) -> -0.72480555 | BC26: =SUM(BC29:BC51) -> -0.718572 | ... BG26: =SUM(BG29:BG51) -> -0.77940602 | BH26: BD | BI26: REAL | BJ26: BD | BK26: REAL | BL26: BD | BM26: REAL | BN26: BD | BO26: REAL
C27: =SUM(D27,G27,J27,M27,P27,S27,V27,Y27,AB27,AE27,AH27,AK27) -> 0 | AN27: =SUM(D27:AK27) -> 0
A28: CMV | C28: =SUM(D28,G28,J28,M28,P28,S28,V28,Y28,AB28,AE28,AH28,AK28) -> -9092664.9 | D28: =SUM(D29:D42) -> -513002.79 | E28: =SUM(E29:E41) -> -600857.5 | G28: =SUM(G29:G42) -> -787441.73 | H28: =SUM(H29:H42) -> -527469.52 | J28: =SUM(J29:J42) -> -793581.04 | K28: =SUM(K29:K42) -> -649970.13 | M28: =SUM(M29:M42) -> -814215.77 | N28: =SUM(N29:N42) -> -895627.39 | P28: =SUM(P29:P42) -> -915143.57 | S28: =SUM(S29:S42) -> -775964.37 | V28: =SUM(V29:V42) -> -748798.22 | Y28: =SUM(Y29:Y42) -> -765940.59 | AB28: =SUM(AB29:AB42) -> -756512.03 | AE28: =SUM(AE29:AE42) -> -734952.49 | AH28: =SUM(AH29:AH42) -> -868795.8 | AK28: =SUM(AK29:AK42) -> -618316.52 | AN28: =SUM(D28,G28,J28,M28,P28,S28,V28,Y28,AB28,AE28,AH28,AK28) -> -9092664.9 | AO28: =SUM(E28,H28,K28,N28,Q28,T28,W28,Z28,AC28,AF28,AI28,AL28) -> -2673924.5 | AQ28: =AVERAGE(D28,G28,J28) -> -698008.52 | AR28: =AVERAGE(E28,H28,K28) -> -592765.72 | AT28: =SUM(AT29:AT42) -> -0.31990956 | AV28: =SUM(AV29:AV42) -> -0.32 | AW28: =SUM(AW29:AW42) -> -0.32 | AX28: =SUM(AX29:AX42) -> -0.31896681 | AY28: =SUM(AY29:AY42) -> -0.32 | AZ28: =SUM(AZ29:AZ42) -> -0.32 | BA28: =SUM(BA29:BA42) -> -0.32 | BB28: =SUM(BB29:BB42) -> -0.32 | BC28: =SUM(BC29:BC42) -> -0.32 | ... BG28: =SUM(BG29:BG42) -> -0.32 | BH28: =D28/$D$24 -> -0.32 | BI28: =E28/$E$24 -> -0.44878234 | BJ28: =G28/$G$24 -> -0.32 | BK28: =H28/$H$24 -> -0.3499834 | BL28: =J28/$J$24 -> -0.31896681 | BM28: =K28/$K$24 -> -0.27268283 | BN28: =M28/$M$24 -> -0.32 | BO28: =N28/$N$24 -> -0.3900331
A29: Carnes Bovina | C29: =SUM(D29,G29,J29,M29,P29,S29,V29,Y29,AB29,AE29,AH29,AK29) -> -4546332.4 | D29: ='04 -Base Orçado 2026'!E32 -> -256501.39 | E29: ='Base Realizado'!D29 -> -170454.81 | G29: ='04 -Base Orçado 2026'!F32 -> -393720.87 | H29: ='Base Realizado'!F29 -> -165532.6 | J29: ='04 -Base Orçado 2026'!G32 -> -396790.52 | K29: ='Base Realizado'!H29 -> -246904.36 | M29: ='04 -Base Orçado 2026'!H32 -> -407107.88 | N29: ='Base Realizado'!K29 -> -214044.67 | P29: ='04 -Base Orçado 2026'!I32 -> -457571.78 | S29: ='04 -Base Orçado 2026'!J32 -> -387982.18 | V29: ='04 -Base Orçado 2026'!K32 -> -374399.11 | Y29: ='04 -Base Orçado 2026'!L32 -> -382970.3 | AB29: ='04 -Base Orçado 2026'!M32 -> -378256.01 | AE29: ='04 -Base Orçado 2026'!N32 -> -367476.25 | AH29: ='04 -Base Orçado 2026'!O32 -> -434397.9 | AK29: ='04 -Base Orçado 2026'!P32 -> -309158.26 | AN29: =SUM(D29:AK29) -> -5343268.9 | AQ29: =AVERAGE(D29,G29,J29) -> -349004.26 | AR29: =AVERAGE(E29,H29,K29) -> -194297.26 | AT29: =IF(ISERROR(C29/C$24),0,(C29/C$24)) -> -0.15995478 | AV29: =IF(ISERROR(D29/D$24),0,(D29/D$24)) -> -0.16 | AW29: =IF(ISERROR(G29/G$24),0,(G29/G$24)) -> -0.16 | AX29: =IF(ISERROR(J29/J$24),0,(J29/J$24)) -> -0.1594834 | AY29: =IF(ISERROR(M29/M$24),0,(M29/M$24)) -> -0.16 | AZ29: =IF(ISERROR(P29/P$24),0,(P29/P$24)) -> -0.16 | BA29: =IF(ISERROR(S29/S$24),0,(S29/S$24)) -> -0.16 | BB29: =IF(ISERROR(V29/V$24),0,(V29/V$24)) -> -0.16 | BC29: =IF(ISERROR(Y29/Y$24),0,(Y29/Y$24)) -> -0.16 | BD29: =IF(ISERROR(AB29/AB$24),0,(AB29/AB$24)) -> -0.16 | BE29: =IF(ISERROR(AE29/AE$24),0,(AE29/AE$24)) -> -0.16 | BF29: =IF(ISERROR(AH29/AH$24),0,(AH29/AH$24)) -> -0.16 | BG29: =IF(ISERROR(AK29/AK$24),0,(AK29/AK$24)) -> -0.16 | BH29: =D29/$D$24 -> -0.16 | BJ29: =G29/$G$24 -> -0.16 | BK29: =H29/$H$24 -> -0.10983319 | BL29: =I29/$G$24 -> 0 | BM29: =J29/$H$24 -> -0.26327606 | BN29: =K29/$G$24 -> -0.10033681 | BO29: =L29/$H$24 -> 0
A30: Carvão | C30: =SUM(D30,G30,J30,M30,P30,S30,V30,Y30,AB30,AE30,AH30,AK30) -> -454633.24 | D30: ='04 -Base Orçado 2026'!E33 -> -25650.139 | E30: ='Base Realizado'!D38 -> -11144 | G30: ='04 -Base Orçado 2026'!F33 -> -39372.087 | H30: ='Base Realizado'!F30 -> -22595.17 | J30: ='04 -Base Orçado 2026'!G33 -> -39679.052 | K30: ='Base Realizado'!H30 -> -57214.49 | M30: ='04 -Base Orçado 2026'!H33 -> -40710.788 | N30: ='Base Realizado'!K30 -> -55787.58 | P30: ='04 -Base Orçado 2026'!I33 -> -45757.178 | S30: ='04 -Base Orçado 2026'!J33 -> -38798.218 | V30: ='04 -Base Orçado 2026'!K33 -> -37439.911 | Y30: ='04 -Base Orçado 2026'!L33 -> -38297.03 | AB30: ='04 -Base Orçado 2026'!M33 -> -37825.601 | AE30: ='04 -Base Orçado 2026'!N33 -> -36747.625 | AH30: ='04 -Base Orçado 2026'!O33 -> -43439.79 | AK30: ='04 -Base Orçado 2026'!P33 -> -30915.826 | AN30: =SUM(D30:AK30) -> -601374.48 | AQ30: =AVERAGE(D30,G30,J30) -> -34900.426 | AR30: =AVERAGE(E30,H30,K30) -> -30317.887 | AT30: =IF(ISERROR(C30/C$24),0,(C30/C$24)) -> -0.015995478 | AV30: =IF(ISERROR(D30/D$24),0,(D30/D$24)) -> -0.016 | AW30: =IF(ISERROR(G30/G$24),0,(G30/G$24)) -> -0.016 | AX30: =IF(ISERROR(J30/J$24),0,(J30/J$24)) -> -0.01594834 | AY30: =IF(ISERROR(M30/M$24),0,(M30/M$24)) -> -0.016 | AZ30: =IF(ISERROR(P30/P$24),0,(P30/P$24)) -> -0.016 | BA30: =IF(ISERROR(S30/S$24),0,(S30/S$24)) -> -0.016 | BB30: =IF(ISERROR(V30/V$24),0,(V30/V$24)) -> -0.016 | BC30: =IF(ISERROR(Y30/Y$24),0,(Y30/Y$24)) -> -0.016 | BD30: =IF(ISERROR(AB30/AB$24),0,(AB30/AB$24)) -> -0.016 | BE30: =IF(ISERROR(AE30/AE$24),0,(AE30/AE$24)) -> -0.016 | BF30: =IF(ISERROR(AH30/AH$24),0,(AH30/AH$24)) -> -0.016 | BG30: =IF(ISERROR(AK30/AK$24),0,(AK30/AK$24)) -> -0.016 | BH30: =D30/$D$24 -> -0.016 | BJ30: =G30/$G$24 -> -0.016 | BK30: =H30/$H$24 -> -0.014992211 | BL30: =I30/$G$24 -> 0 | BM30: =J30/$H$24 -> -0.026327606 | BN30: =K30/$G$24 -> -0.023250783 | BO30: =L30/$H$24 -> 0
A31: Vinhos/Espumantes | C31: =SUM(D31,G31,J31,M31,P31,S31,V31,Y31,AB31,AE31,AH31,AK31) -> -1363899.7 | D31: ='04 -Base Orçado 2026'!E34 -> -76950.418 | E31: ='Base Realizado'!D31 -> -44553.57 | G31: ='04 -Base Orçado 2026'!F34 -> -118116.26 | H31: ='Base Realizado'!F31 -> -104825.14 | J31: ='04 -Base Orçado 2026'!G34 -> -119037.16 | K31: ='Base Realizado'!H31 -> -92357.05 | M31: ='04 -Base Orçado 2026'!H34 -> -122132.37 | N31: ='Base Realizado'!K31 -> -72805.93 | P31: ='04 -Base Orçado 2026'!I34 -> -137271.53 | S31: ='04 -Base Orçado 2026'!J34 -> -116394.66 | V31: ='04 -Base Orçado 2026'!K34 -> -112319.73 | Y31: ='04 -Base Orçado 2026'!L34 -> -114891.09 | AB31: ='04 -Base Orçado 2026'!M34 -> -113476.8 | AE31: ='04 -Base Orçado 2026'!N34 -> -110242.87 | AH31: ='04 -Base Orçado 2026'!O34 -> -130319.37 | AK31: ='04 -Base Orçado 2026'!P34 -> -92747.477 | AN31: =SUM(D31:AK31) -> -1678441.4 | AQ31: =AVERAGE(D31,G31,J31) -> -104701.28 | AR31: =AVERAGE(E31,H31,K31) -> -80578.587 | AT31: =IF(ISERROR(C31/C$24),0,(C31/C$24)) -> -0.047986434 | AV31: =IF(ISERROR(D31/D$24),0,(D31/D$24)) -> -0.048 | AW31: =IF(ISERROR(G31/G$24),0,(G31/G$24)) -> -0.048 | AX31: =IF(ISERROR(J31/J$24),0,(J31/J$24)) -> -0.047845021 | AY31: =IF(ISERROR(M31/M$24),0,(M31/M$24)) -> -0.048 | AZ31: =IF(ISERROR(P31/P$24),0,(P31/P$24)) -> -0.048 | BA31: =IF(ISERROR(S31/S$24),0,(S31/S$24)) -> -0.048 | BB31: =IF(ISERROR(V31/V$24),0,(V31/V$24)) -> -0.048 | BC31: =IF(ISERROR(Y31/Y$24),0,(Y31/Y$24)) -> -0.048 | BD31: =IF(ISERROR(AB31/AB$24),0,(AB31/AB$24)) -> -0.048 | BE31: =IF(ISERROR(AE31/AE$24),0,(AE31/AE$24)) -> -0.048 | BF31: =IF(ISERROR(AH31/AH$24),0,(AH31/AH$24)) -> -0.048 | BG31: =IF(ISERROR(AK31/AK$24),0,(AK31/AK$24)) -> -0.048 | BH31: =D31/$D$24 -> -0.048 | BJ31: =G31/$G$24 -> -0.048 | BK31: =H31/$H$24 -> -0.069552946 | BL31: =I31/$G$24 -> 0 | BM31: =J31/$H$24 -> -0.078982817 | BN31: =K31/$G$24 -> -0.037531991 | BO31: =L31/$H$24 -> 0
A32: Bebidas Alcoólicas | C32: =SUM(D32,G32,J32,M32,P32,S32,V32,Y32,AB32,AE32,AH32,AK32) -> -454633.24 | D32: ='04 -Base Orçado 2026'!E35 -> -25650.139 | E32: ='Base Realizado'!D32 -> -76401.53 | G32: ='04 -Base Orçado 2026'!F35 -> -39372.087 | H32: ='Base Realizado'!F32 -> -73589.02 | J32: ='04 -Base Orçado 2026'!G35 -> -39679.052 | K32: ='Base Realizado'!H32 -> -79703.1 | M32: ='04 -Base Orçado 2026'!H35 -> -40710.788 | N32: ='Base Realizado'!K32 -> -88635.83 | P32: ='04 -Base Orçado 2026'!I35 -> -45757.178 | S32: ='04 -Base Orçado 2026'!J35 -> -38798.218 | V32: ='04 -Base Orçado 2026'!K35 -> -37439.911 | Y32: ='04 -Base Orçado 2026'!L35 -> -38297.03 | AB32: ='04 -Base Orçado 2026'!M35 -> -37825.601 | AE32: ='04 -Base Orçado 2026'!N35 -> -36747.625 | AH32: ='04 -Base Orçado 2026'!O35 -> -43439.79 | AK32: ='04 -Base Orçado 2026'!P35 -> -30915.826 | AN32: =SUM(D32:AK32) -> -772962.72 | AQ32: =AVERAGE(D32,G32,J32) -> -34900.426 | AR32: =AVERAGE(E32,H32,K32) -> -76564.55 | AT32: =IF(ISERROR(C32/C$24),0,(C32/C$24)) -> -0.015995478 | AV32: =IF(ISERROR(D32/D$24),0,(D32/D$24)) -> -0.016 | AW32: =IF(ISERROR(G32/G$24),0,(G32/G$24)) -> -0.016 | AX32: =IF(ISERROR(J32/J$24),0,(J32/J$24)) -> -0.01594834 | AY32: =IF(ISERROR(M32/M$24),0,(M32/M$24)) -> -0.016 | AZ32: =IF(ISERROR(P32/P$24),0,(P32/P$24)) -> -0.016 | BA32: =IF(ISERROR(S32/S$24),0,(S32/S$24)) -> -0.016 | BB32: =IF(ISERROR(V32/V$24),0,(V32/V$24)) -> -0.016 | BC32: =IF(ISERROR(Y32/Y$24),0,(Y32/Y$24)) -> -0.016 | BD32: =IF(ISERROR(AB32/AB$24),0,(AB32/AB$24)) -> -0.016 | BE32: =IF(ISERROR(AE32/AE$24),0,(AE32/AE$24)) -> -0.016 | BF32: =IF(ISERROR(AH32/AH$24),0,(AH32/AH$24)) -> -0.016 | BG32: =IF(ISERROR(AK32/AK$24),0,(AK32/AK$24)) -> -0.016 | BH32: =D32/$D$24 -> -0.016 | BJ32: =G32/$G$24 -> -0.016 | BK32: =H32/$H$24 -> -0.048827344 | BL32: =I32/$G$24 -> 0 | BM32: =J32/$H$24 -> -0.026327606 | BN32: =K32/$G$24 -> -0.032389688 | BO32: =L32/$H$24 -> 0
A33: Pescados | C33: =SUM(D33,G33,J33,M33,P33,S33,V33,Y33,AB33,AE33,AH33,AK33) -> -363706.6 | D33: ='04 -Base Orçado 2026'!E36 -> -20520.111 | E33: ='Base Realizado'!D30 -> -50395.56 | G33: ='04 -Base Orçado 2026'!F36 -> -31497.669 | H33: ='Base Realizado'!F33 -> -26438.81 | J33: ='04 -Base Orçado 2026'!G36 -> -31743.241 | K33: ='Base Realizado'!H33 -> -40716.03 | M33: ='04 -Base Orçado 2026'!H36 -> -32568.631 | N33: ='Base Realizado'!K33 -> -41147.82 | P33: ='04 -Base Orçado 2026'!I36 -> -36605.743 | S33: ='04 -Base Orçado 2026'!J36 -> -31038.575 | V33: ='04 -Base Orçado 2026'!K36 -> -29951.929 | Y33: ='04 -Base Orçado 2026'!L36 -> -30637.624 | AB33: ='04 -Base Orçado 2026'!M36 -> -30260.481 | AE33: ='04 -Base Orçado 2026'!N36 -> -29398.1 | AH33: ='04 -Base Orçado 2026'!O36 -> -34751.832 | AK33: ='04 -Base Orçado 2026'!P36 -> -24732.661 | AN33: =SUM(D33:AK33) -> -522404.82 | AQ33: =AVERAGE(D33,G33,J33) -> -27920.341 | AR33: =AVERAGE(E33,H33,K33) -> -39183.467 | AT33: =IF(ISERROR(C33/C$24),0,(C33/C$24)) -> -0.012796382 | AV33: =IF(ISERROR(D33/D$24),0,(D33/D$24)) -> -0.0128 | AW33: =IF(ISERROR(G33/G$24),0,(G33/G$24)) -> -0.0128 | AX33: =IF(ISERROR(J33/J$24),0,(J33/J$24)) -> -0.012758672 | AY33: =IF(ISERROR(M33/M$24),0,(M33/M$24)) -> -0.0128 | AZ33: =IF(ISERROR(P33/P$24),0,(P33/P$24)) -> -0.0128 | BA33: =IF(ISERROR(S33/S$24),0,(S33/S$24)) -> -0.0128 | BB33: =IF(ISERROR(V33/V$24),0,(V33/V$24)) -> -0.0128 | BC33: =IF(ISERROR(Y33/Y$24),0,(Y33/Y$24)) -> -0.0128 | BD33: =IF(ISERROR(AB33/AB$24),0,(AB33/AB$24)) -> -0.0128 | BE33: =IF(ISERROR(AE33/AE$24),0,(AE33/AE$24)) -> -0.0128 | BF33: =IF(ISERROR(AH33/AH$24),0,(AH33/AH$24)) -> -0.0128 | BG33: =IF(ISERROR(AK33/AK$24),0,(AK33/AK$24)) -> -0.0128 | BH33: =D33/$D$24 -> -0.0128 | BJ33: =G33/$G$24 -> -0.0128 | BK33: =H33/$H$24 -> -0.01754252 | BL33: =I33/$G$24 -> 0 | BM33: =J33/$H$24 -> -0.021062084 | BN33: =K33/$G$24 -> -0.016546151 | BO33: =L33/$H$24 -> 0
A34: Hortifruti | C34: =SUM(D34,G34,J34,M34,P34,S34,V34,Y34,AB34,AE34,AH34,AK34) -> -636486.54 | D34: ='04 -Base Orçado 2026'!E37 -> -35910.195 | E34: ='Base Realizado'!D34 -> -55152.66 | G34: ='04 -Base Orçado 2026'!F37 -> -55120.921 | H34: ='Base Realizado'!F34 -> -41279.5 | J34: ='04 -Base Orçado 2026'!G37 -> -55550.673 | K34: ='Base Realizado'!H34 -> -59990.51 | M34: ='04 -Base Orçado 2026'!H37 -> -56995.104 | N34: ='Base Realizado'!K34 -> -56189.65 | P34: ='04 -Base Orçado 2026'!I37 -> -64060.05 | S34: ='04 -Base Orçado 2026'!J37 -> -54317.506 | V34: ='04 -Base Orçado 2026'!K37 -> -52415.875 | Y34: ='04 -Base Orçado 2026'!L37 -> -53615.841 | AB34: ='04 -Base Orçado 2026'!M37 -> -52955.842 | AE34: ='04 -Base Orçado 2026'!N37 -> -51446.674 | AH34: ='04 -Base Orçado 2026'!O37 -> -60815.706 | AK34: ='04 -Base Orçado 2026'!P37 -> -43282.156 | AN34: =SUM(D34:AK34) -> -849098.86 | AQ34: =AVERAGE(D34,G34,J34) -> -48860.596 | AR34: =AVERAGE(E34,H34,K34) -> -52140.89 | AT34: =IF(ISERROR(C34/C$24),0,(C34/C$24)) -> -0.022393669 | AV34: =IF(ISERROR(D34/D$24),0,(D34/D$24)) -> -0.0224 | AW34: =IF(ISERROR(G34/G$24),0,(G34/G$24)) -> -0.0224 | AX34: =IF(ISERROR(J34/J$24),0,(J34/J$24)) -> -0.022327677 | AY34: =IF(ISERROR(M34/M$24),0,(M34/M$24)) -> -0.0224 | AZ34: =IF(ISERROR(P34/P$24),0,(P34/P$24)) -> -0.0224 | BA34: =IF(ISERROR(S34/S$24),0,(S34/S$24)) -> -0.0224 | BB34: =IF(ISERROR(V34/V$24),0,(V34/V$24)) -> -0.0224 | BC34: =IF(ISERROR(Y34/Y$24),0,(Y34/Y$24)) -> -0.0224 | BD34: =IF(ISERROR(AB34/AB$24),0,(AB34/AB$24)) -> -0.0224 | BE34: =IF(ISERROR(AE34/AE$24),0,(AE34/AE$24)) -> -0.0224 | BF34: =IF(ISERROR(AH34/AH$24),0,(AH34/AH$24)) -> -0.0224 | BG34: =IF(ISERROR(AK34/AK$24),0,(AK34/AK$24)) -> -0.0224 | BH34: =D34/$D$24 -> -0.0224 | BJ34: =G34/$G$24 -> -0.0224 | BK34: =H34/$H$24 -> -0.027389525 | BL34: =I34/$G$24 -> 0 | BM34: =J34/$H$24 -> -0.036858648 | BN34: =K34/$G$24 -> -0.0243789 | BO34: =L34/$H$24 -> 0
A35: Paes, Massas e Salgados | C35: =SUM(D35,G35,J35,M35,P35,S35,V35,Y35,AB35,AE35,AH35,AK35) -> -363706.6 | D35: ='04 -Base Orçado 2026'!E38 -> -20520.111 | E35: ='Base Realizado'!D35 -> -22699.4 | G35: ='04 -Base Orçado 2026'!F38 -> -31497.669 | H35: ='Base Realizado'!F35 -> -18032.34 | J35: ='04 -Base Orçado 2026'!G38 -> -31743.241 | K35: ='Base Realizado'!H35 -> -23525.5 | M35: ='04 -Base Orçado 2026'!H38 -> -32568.631 | N35: ='Base Realizado'!K35 -> -20397.2 | P35: ='04 -Base Orçado 2026'!I38 -> -36605.743 | S35: ='04 -Base Orçado 2026'!J38 -> -31038.575 | V35: ='04 -Base Orçado 2026'!K38 -> -29951.929 | Y35: ='04 -Base Orçado 2026'!L38 -> -30637.624 | AB35: ='04 -Base Orçado 2026'!M38 -> -30260.481 | AE35: ='04 -Base Orçado 2026'!N38 -> -29398.1 | AH35: ='04 -Base Orçado 2026'!O38 -> -34751.832 | AK35: ='04 -Base Orçado 2026'!P38 -> -24732.661 | AN35: =SUM(D35:AK35) -> -448361.04 | AQ35: =AVERAGE(D35,G35,J35) -> -27920.341 | AR35: =AVERAGE(E35,H35,K35) -> -21419.08 | AT35: =IF(ISERROR(C35/C$24),0,(C35/C$24)) -> -0.012796382 | AV35: =IF(ISERROR(D35/D$24),0,(D35/D$24)) -> -0.0128 | AW35: =IF(ISERROR(G35/G$24),0,(G35/G$24)) -> -0.0128 | AX35: =IF(ISERROR(J35/J$24),0,(J35/J$24)) -> -0.012758672 | AY35: =IF(ISERROR(M35/M$24),0,(M35/M$24)) -> -0.0128 | AZ35: =IF(ISERROR(P35/P$24),0,(P35/P$24)) -> -0.0128 | BA35: =IF(ISERROR(S35/S$24),0,(S35/S$24)) -> -0.0128 | BB35: =IF(ISERROR(V35/V$24),0,(V35/V$24)) -> -0.0128 | BC35: =IF(ISERROR(Y35/Y$24),0,(Y35/Y$24)) -> -0.0128 | BD35: =IF(ISERROR(AB35/AB$24),0,(AB35/AB$24)) -> -0.0128 | BE35: =IF(ISERROR(AE35/AE$24),0,(AE35/AE$24)) -> -0.0128 | BF35: =IF(ISERROR(AH35/AH$24),0,(AH35/AH$24)) -> -0.0128 | BG35: =IF(ISERROR(AK35/AK$24),0,(AK35/AK$24)) -> -0.0128 | BH35: =D35/$D$24 -> -0.0128 | BJ35: =G35/$G$24 -> -0.0128 | BK35: =H35/$H$24 -> -0.01196471 | BL35: =I35/$G$24 -> 0 | BM35: =J35/$H$24 -> -0.021062084 | BN35: =K35/$G$24 -> -0.0095602756 | BO35: =L35/$H$24 -> 0
A36: Secos - Mercearia | C36: =SUM(D36,G36,J36,M36,P36,S36,V36,Y36,AB36,AE36,AH36,AK36) -> -454633.24 | D36: ='04 -Base Orçado 2026'!E39 -> -25650.139 | E36: ='Base Realizado'!D36 -> -84020.09 | G36: ='04 -Base Orçado 2026'!F39 -> -39372.087 | H36: ='Base Realizado'!F36 -> -71376.86 | J36: ='04 -Base Orçado 2026'!G39 -> -39679.052 | K36: ='Base Realizado'!H36 -> -108995.77 | M36: ='04 -Base Orçado 2026'!H39 -> -40710.788 | N36: ='Base Realizado'!K36 -> -77993.55 | P36: ='04 -Base Orçado 2026'!I39 -> -45757.178 | S36: ='04 -Base Orçado 2026'!J39 -> -38798.218 | V36: ='04 -Base Orçado 2026'!K39 -> -37439.911 | Y36: ='04 -Base Orçado 2026'!L39 -> -38297.03 | AB36: ='04 -Base Orçado 2026'!M39 -> -37825.601 | AE36: ='04 -Base Orçado 2026'!N39 -> -36747.625 | AH36: ='04 -Base Orçado 2026'!O39 -> -43439.79 | AK36: ='04 -Base Orçado 2026'!P39 -> -30915.826 | AN36: =SUM(D36:AK36) -> -797019.51 | AQ36: =AVERAGE(D36,G36,J36) -> -34900.426 | AR36: =AVERAGE(E36,H36,K36) -> -88130.907 | AT36: =IF(ISERROR(C36/C$24),0,(C36/C$24)) -> -0.015995478 | AV36: =IF(ISERROR(D36/D$24),0,(D36/D$24)) -> -0.016 | AW36: =IF(ISERROR(G36/G$24),0,(G36/G$24)) -> -0.016 | AX36: =IF(ISERROR(J36/J$24),0,(J36/J$24)) -> -0.01594834 | AY36: =IF(ISERROR(M36/M$24),0,(M36/M$24)) -> -0.016 | AZ36: =IF(ISERROR(P36/P$24),0,(P36/P$24)) -> -0.016 | BA36: =IF(ISERROR(S36/S$24),0,(S36/S$24)) -> -0.016 | BB36: =IF(ISERROR(V36/V$24),0,(V36/V$24)) -> -0.016 | BC36: =IF(ISERROR(Y36/Y$24),0,(Y36/Y$24)) -> -0.016 | BD36: =IF(ISERROR(AB36/AB$24),0,(AB36/AB$24)) -> -0.016 | BE36: =IF(ISERROR(AE36/AE$24),0,(AE36/AE$24)) -> -0.016 | BF36: =IF(ISERROR(AH36/AH$24),0,(AH36/AH$24)) -> -0.016 | BG36: =IF(ISERROR(AK36/AK$24),0,(AK36/AK$24)) -> -0.016 | BH36: =D36/$D$24 -> -0.016 | BJ36: =G36/$G$24 -> -0.016 | BK36: =H36/$H$24 -> -0.047359544 | BL36: =I36/$G$24 -> 0 | BM36: =J36/$H$24 -> -0.026327606 | BN36: =K36/$G$24 -> -0.044293622 | BO36: =L36/$H$24 -> 0
A37: Gelo | C37: =SUM(D37,G37,J37,M37,P37,S37,V37,Y37,AB37,AE37,AH37,AK37) -> -218223.96 | D37: ='04 -Base Orçado 2026'!E40 -> -12312.067 | E37: ='Base Realizado'!D39 -> -4076.8 | G37: ='04 -Base Orçado 2026'!F40 -> -18898.602 | H37: ='Base Realizado'!F37 -> -800 | J37: ='04 -Base Orçado 2026'!G40 -> -19045.945 | K37: ='Base Realizado'!H37 -> -800 | M37: ='04 -Base Orçado 2026'!H40 -> -19541.178 | N37: ='Base Realizado'!K37 -> -1000 | P37: ='04 -Base Orçado 2026'!I40 -> -21963.446 | S37: ='04 -Base Orçado 2026'!J40 -> -18623.145 | V37: ='04 -Base Orçado 2026'!K40 -> -17971.157 | Y37: ='04 -Base Orçado 2026'!L40 -> -18382.574 | AB37: ='04 -Base Orçado 2026'!M40 -> -18156.289 | AE37: ='04 -Base Orçado 2026'!N40 -> -17638.86 | AH37: ='04 -Base Orçado 2026'!O40 -> -20851.099 | AK37: ='04 -Base Orçado 2026'!P40 -> -14839.596 | AN37: =SUM(D37:AK37) -> -224900.76 | AQ37: =AVERAGE(D37,G37,J37) -> -16752.204 | AR37: =AVERAGE(E37,H37,K37) -> -1892.2667 | AT37: =IF(ISERROR(C37/C$24),0,(C37/C$24)) -> -0.0076778294 | AV37: =IF(ISERROR(D37/D$24),0,(D37/D$24)) -> -0.00768 | AW37: =IF(ISERROR(G37/G$24),0,(G37/G$24)) -> -0.00768 | AX37: =IF(ISERROR(J37/J$24),0,(J37/J$24)) -> -0.0076552034 | AY37: =IF(ISERROR(M37/M$24),0,(M37/M$24)) -> -0.00768 | AZ37: =IF(ISERROR(P37/P$24),0,(P37/P$24)) -> -0.00768 | BA37: =IF(ISERROR(S37/S$24),0,(S37/S$24)) -> -0.00768 | BB37: =IF(ISERROR(V37/V$24),0,(V37/V$24)) -> -0.00768 | BC37: =IF(ISERROR(Y37/Y$24),0,(Y37/Y$24)) -> -0.00768 | BD37: =IF(ISERROR(AB37/AB$24),0,(AB37/AB$24)) -> -0.00768 | BE37: =IF(ISERROR(AE37/AE$24),0,(AE37/AE$24)) -> -0.00768 | BF37: =IF(ISERROR(AH37/AH$24),0,(AH37/AH$24)) -> -0.00768 | BG37: =IF(ISERROR(AK37/AK$24),0,(AK37/AK$24)) -> -0.00768 | BH37: =D37/$D$24 -> -0.00768 | BJ37: =G37/$G$24 -> -0.00768 | BK37: =H37/$H$24 -> -0.00053081118 | BL37: =I37/$G$24 -> 0 | BM37: =J37/$H$24 -> -0.012637251 | BN37: =K37/$G$24 -> -0.00032510342 | BO37: =L37/$H$24 -> 0
A38: Bebidas não Alcoolicas | C38: =SUM(D38,G38,J38,M38,P38,S38,V38,Y38,AB38,AE38,AH38,AK38) -> -227316.62 | D38: ='04 -Base Orçado 2026'!E41 -> -12825.07 | E38: ='Base Realizado'!D33 -> -20668.66 | G38: ='04 -Base Orçado 2026'!F41 -> -19686.043 | H38: ='Base Realizado'!F38 -> -11940 | J38: ='04 -Base Orçado 2026'!G41 -> -19839.526 | K38: ='Base Realizado'!H38 -> -15922 | M38: ='04 -Base Orçado 2026'!H41 -> -20355.394 | N38: ='Base Realizado'!K38 -> -12570 | P38: ='04 -Base Orçado 2026'!I41 -> -22878.589 | S38: ='04 -Base Orçado 2026'!J41 -> -19399.109 | V38: ='04 -Base Orçado 2026'!K41 -> -18719.955 | Y38: ='04 -Base Orçado 2026'!L41 -> -19148.515 | AB38: ='04 -Base Orçado 2026'!M41 -> -18912.801 | AE38: ='04 -Base Orçado 2026'!N41 -> -18373.812 | AH38: ='04 -Base Orçado 2026'!O41 -> -21719.895 | AK38: ='04 -Base Orçado 2026'!P41 -> -15457.913 | AN38: =SUM(D38:AK38) -> -288417.28 | AQ38: =AVERAGE(D38,G38,J38) -> -17450.213 | AR38: =AVERAGE(E38,H38,K38) -> -16176.887 | AT38: =IF(ISERROR(C38/C$24),0,(C38/C$24)) -> -0.007997739 | AV38: =IF(ISERROR(D38/D$24),0,(D38/D$24)) -> -0.008 | AW38: =IF(ISERROR(G38/G$24),0,(G38/G$24)) -> -0.008 | AX38: =IF(ISERROR(J38/J$24),0,(J38/J$24)) -> -0.0079741702 | AY38: =IF(ISERROR(M38/M$24),0,(M38/M$24)) -> -0.008 | AZ38: =IF(ISERROR(P38/P$24),0,(P38/P$24)) -> -0.008 | BA38: =IF(ISERROR(S38/S$24),0,(S38/S$24)) -> -0.008 | BB38: =IF(ISERROR(V38/V$24),0,(V38/V$24)) -> -0.008 | BC38: =IF(ISERROR(Y38/Y$24),0,(Y38/Y$24)) -> -0.008 | BD38: =IF(ISERROR(AB38/AB$24),0,(AB38/AB$24)) -> -0.008 | BE38: =IF(ISERROR(AE38/AE$24),0,(AE38/AE$24)) -> -0.008 | BF38: =IF(ISERROR(AH38/AH$24),0,(AH38/AH$24)) -> -0.008 | BG38: =IF(ISERROR(AK38/AK$24),0,(AK38/AK$24)) -> -0.008 | BH38: =D38/$D$24 -> -0.008 | BJ38: =G38/$G$24 -> -0.008 | BK38: =H38/$H$24 -> -0.0079223569 | BL38: =I38/$G$24 -> 0 | BM38: =J38/$H$24 -> -0.013163803 | BN38: =K38/$G$24 -> -0.0064703708 | BO38: =L38/$H$24 -> 0
A39: Enlatados e Conservas | C39: =SUM(D39,G39,J39,M39,P39,S39,V39,Y39,AB39,AE39,AH39,AK39) -> -9092.6649 | D39: ='04 -Base Orçado 2026'!E42 -> -513.00279 | E39: ='Base Realizado'!D37 -> -800 | G39: ='04 -Base Orçado 2026'!F42 -> -787.44173 | H39: ='Base Realizado'!F39 -> -4076.8 | J39: ='04 -Base Orçado 2026'!G42 -> -793.58104 | K39: ='Base Realizado'!H39 -> -5096 | M39: ='04 -Base Orçado 2026'!H42 -> -814.21577 | N39: ='Base Realizado'!K39 -> -4076.8 | P39: ='04 -Base Orçado 2026'!I42 -> -915.14357 | S39: ='04 -Base Orçado 2026'!J42 -> -775.96437 | V39: ='04 -Base Orçado 2026'!K42 -> -748.79822 | Y39: ='04 -Base Orçado 2026'!L42 -> -765.94059 | AB39: ='04 -Base Orçado 2026'!M42 -> -756.51203 | AE39: ='04 -Base Orçado 2026'!N42 -> -734.95249 | AH39: ='04 -Base Orçado 2026'!O42 -> -868.7958 | AK39: ='04 -Base Orçado 2026'!P42 -> -618.31652 | AN39: =SUM(D39:AK39) -> -23142.265 | AQ39: =AVERAGE(D39,G39,J39) -> -698.00852 | AR39: =AVERAGE(E39,H39,K39) -> -3324.2667 | AT39: =IF(ISERROR(C39/C$24),0,(C39/C$24)) -> -0.00031990956 | AV39: =IF(ISERROR(D39/D$24),0,(D39/D$24)) -> -0.00032 | AW39: =IF(ISERROR(G39/G$24),0,(G39/G$24)) -> -0.00032 | AX39: =IF(ISERROR(J39/J$24),0,(J39/J$24)) -> -0.00031896681 | AY39: =IF(ISERROR(M39/M$24),0,(M39/M$24)) -> -0.00032 | AZ39: =IF(ISERROR(P39/P$24),0,(P39/P$24)) -> -0.00032 | BA39: =IF(ISERROR(S39/S$24),0,(S39/S$24)) -> -0.00032 | BB39: =IF(ISERROR(V39/V$24),0,(V39/V$24)) -> -0.00032 | BC39: =IF(ISERROR(Y39/Y$24),0,(Y39/Y$24)) -> -0.00032 | BD39: =IF(ISERROR(AB39/AB$24),0,(AB39/AB$24)) -> -0.00032 | BE39: =IF(ISERROR(AE39/AE$24),0,(AE39/AE$24)) -> -0.00032 | BF39: =IF(ISERROR(AH39/AH$24),0,(AH39/AH$24)) -> -0.00032 | BG39: =IF(ISERROR(AK39/AK$24),0,(AK39/AK$24)) -> -0.00032 | BH39: =D39/$D$24 -> -0.00032 | BJ39: =G39/$G$24 -> -0.00032 | BK39: =H39/$H$24 -> -0.0027050138 | BL39: =I39/$G$24 -> 0 | BM39: =J39/$H$24 -> -0.00052655211 | BN39: =K39/$G$24 -> -0.0020709088 | BO39: =L39/$H$24 -> 0
A40: Estoque Final | C40: =SUM(D40,G40,J40,M40,P40,S40,V40,Y40,AB40,AE40,AH40,AK40) -> 0 | D40: ='04 -Base Orçado 2026'!E43 -> 0 | E40: ='Base Realizado'!D40 -> -274355.88 | G40: ='04 -Base Orçado 2026'!F43 -> 0 | H40: ='Base Realizado'!F40 -> -261339.16 | J40: ='04 -Base Orçado 2026'!G43 -> 0 | K40: ='Base Realizado'!H40 -> -180084.48 | M40: ='04 -Base Orçado 2026'!H43 -> 0 | N40: ='Base Realizado'!K40 -> -431062.84 | P40: ='04 -Base Orçado 2026'!I43 -> 0 | S40: ='04 -Base Orçado 2026'!J43 -> 0 | V40: ='04 -Base Orçado 2026'!K43 -> 0 | Y40: ='04 -Base Orçado 2026'!L43 -> 0 | AB40: ='04 -Base Orçado 2026'!M43 -> 0 | AE40: ='04 -Base Orçado 2026'!N43 -> 0 | AH40: ='04 -Base Orçado 2026'!O43 -> 0 | AK40: ='04 -Base Orçado 2026'!P43 -> 0 | AN40: =SUM(D40:AK40) -> -1146842.4 | AQ40: =AVERAGE(D40,G40,J40) -> 0 | AR40: =AVERAGE(E40,H40,K40) -> -238593.17 | AT40: =IF(ISERROR(C40/C$24),0,(C40/C$24)) -> 0 | AV40: =IF(ISERROR(D40/D$24),0,(D40/D$24)) -> 0 | AW40: =IF(ISERROR(G40/G$24),0,(G40/G$24)) -> 0 | AX40: =IF(ISERROR(J40/J$24),0,(J40/J$24)) -> 0 | AY40: =IF(ISERROR(M40/M$24),0,(M40/M$24)) -> 0 | AZ40: =IF(ISERROR(P40/P$24),0,(P40/P$24)) -> 0 | BA40: =IF(ISERROR(S40/S$24),0,(S40/S$24)) -> 0 | BB40: =IF(ISERROR(V40/V$24),0,(V40/V$24)) -> 0 | BC40: =IF(ISERROR(Y40/Y$24),0,(Y40/Y$24)) -> 0 | BD40: =IF(ISERROR(AB40/AB$24),0,(AB40/AB$24)) -> 0 | BE40: =IF(ISERROR(AE40/AE$24),0,(AE40/AE$24)) -> 0 | BF40: =IF(ISERROR(AH40/AH$24),0,(AH40/AH$24)) -> 0 | BG40: =IF(ISERROR(AK40/AK$24),0,(AK40/AK$24)) -> 0 | BH40: =D40/$D$24 -> 0 | BJ40: =G40/$G$24 -> 0 | BK40: =H40/$H$24 -> -0.17340219 | BL40: =I40/$G$24 -> 0 | BM40: =J40/$H$24 -> 0 | BN40: =K40/$G$24 -> -0.0731826 | BO40: =L40/$H$24 -> 0
A41: Estoque Inicial | C41: =SUM(D41,G41,J41,M41,P41,S41,V41,Y41,AB41,AE41,AH41,AK41) -> 0 | D41: ='04 -Base Orçado 2026'!E44 -> 0 | E41: ='Base Realizado'!D41 -> 213865.46 | G41: ='04 -Base Orçado 2026'!F44 -> 0 | H41: ='Base Realizado'!F41 -> 274355.88 | J41: ='04 -Base Orçado 2026'!G44 -> 0 | K41: ='Base Realizado'!H41 -> 261339.16 | M41: ='04 -Base Orçado 2026'!H44 -> 0 | N41: ='Base Realizado'!K41 -> 180084.48 | P41: ='04 -Base Orçado 2026'!I44 -> 0 | S41: ='04 -Base Orçado 2026'!J44 -> 0 | V41: ='04 -Base Orçado 2026'!K44 -> 0 | Y41: ='04 -Base Orçado 2026'!L44 -> 0 | AB41: ='04 -Base Orçado 2026'!M44 -> 0 | AE41: ='04 -Base Orçado 2026'!N44 -> 0 | AH41: ='04 -Base Orçado 2026'!O44 -> 0 | AK41: ='04 -Base Orçado 2026'!P44 -> 0 | AN41: =SUM(D41:AK41) -> 929644.98 | AQ41: =AVERAGE(D41,G41,J41) -> 0 | AR41: =AVERAGE(E41,H41,K41) -> 249853.5 | AT41: =IF(ISERROR(C41/C$24),0,(C41/C$24)) -> 0 | AV41: =IF(ISERROR(D41/D$24),0,(D41/D$24)) -> 0 | AW41: =IF(ISERROR(G41/G$24),0,(G41/G$24)) -> 0 | AX41: =IF(ISERROR(J41/J$24),0,(J41/J$24)) -> 0 | AY41: =IF(ISERROR(M41/M$24),0,(M41/M$24)) -> 0 | AZ41: =IF(ISERROR(P41/P$24),0,(P41/P$24)) -> 0 | BA41: =IF(ISERROR(S41/S$24),0,(S41/S$24)) -> 0 | BB41: =IF(ISERROR(V41/V$24),0,(V41/V$24)) -> 0 | BC41: =IF(ISERROR(Y41/Y$24),0,(Y41/Y$24)) -> 0 | BD41: =IF(ISERROR(AB41/AB$24),0,(AB41/AB$24)) -> 0 | BE41: =IF(ISERROR(AE41/AE$24),0,(AE41/AE$24)) -> 0 | BF41: =IF(ISERROR(AH41/AH$24),0,(AH41/AH$24)) -> 0 | BG41: =IF(ISERROR(AK41/AK$24),0,(AK41/AK$24)) -> 0 | BH41: =D41/$D$24 -> 0 | BJ41: =G41/$G$24 -> 0 | BK41: =H41/$H$24 -> 0.18203896 | BL41: =I41/$G$24 -> 0 | BM41: =J41/$H$24 -> 0 | BN41: =K41/$G$24 -> 0.10620282 | BO41: =L41/$H$24 -> 0
A42: (-) Reclassificação CMV | C42: =SUM(D42,G42,J42,M42,P42,S42,V42,Y42,AB42,AE42,AH42,AK42) -> 0 | D42: ='04 -Base Orçado 2026'!E45 -> 0 | G42: ='04 -Base Orçado 2026'!F45 -> 0 | H42: ='Base Realizado'!F42 -> 0 | J42: ='04 -Base Orçado 2026'!G45 -> 0 | K42: ='Base Realizado'!H42 -> 0 | M42: ='04 -Base Orçado 2026'!H45 -> 0 | N42: ='Base Realizado'!K42 -> 0 | P42: ='04 -Base Orçado 2026'!I45 -> 0 | S42: ='04 -Base Orçado 2026'!J45 -> 0 | V42: ='04 -Base Orçado 2026'!K45 -> 0 | Y42: ='04 -Base Orçado 2026'!L45 -> 0 | AB42: ='04 -Base Orçado 2026'!M45 -> 0 | AE42: ='04 -Base Orçado 2026'!N45 -> 0 | AH42: ='04 -Base Orçado 2026'!O45 -> 0 | AK42: ='04 -Base Orçado 2026'!P45 -> 0 | AN42: =SUM(D42:AK42) -> 0 | AQ42: =AVERAGE(D42,G42,J42) -> 0 | AR42: =AVERAGE(E42,H42,K42) -> 0 | AT42: =IF(ISERROR(C42/C$24),0,(C42/C$24)) -> 0 | AV42: =IF(ISERROR(D42/D$24),0,(D42/D$24)) -> 0 | AW42: =IF(ISERROR(G42/G$24),0,(G42/G$24)) -> 0 | AX42: =IF(ISERROR(J42/J$24),0,(J42/J$24)) -> 0 | AY42: =IF(ISERROR(M42/M$24),0,(M42/M$24)) -> 0 | AZ42: =IF(ISERROR(P42/P$24),0,(P42/P$24)) -> 0 | BA42: =IF(ISERROR(S42/S$24),0,(S42/S$24)) -> 0 | BB42: =IF(ISERROR(V42/V$24),0,(V42/V$24)) -> 0 | BC42: =IF(ISERROR(Y42/Y$24),0,(Y42/Y$24)) -> 0 | BD42: =IF(ISERROR(AB42/AB$24),0,(AB42/AB$24)) -> 0 | BE42: =IF(ISERROR(AE42/AE$24),0,(AE42/AE$24)) -> 0 | BF42: =IF(ISERROR(AH42/AH$24),0,(AH42/AH$24)) -> 0 | BG42: =IF(ISERROR(AK42/AK$24),0,(AK42/AK$24)) -> 0 | BH42: =D42/$D$24 -> 0 | BJ42: =G42/$G$24 -> 0 | BK42: =H42/$H$24 -> 0 | BL42: =I42/$G$24 -> 0 | BM42: =J42/$H$24 -> 0 | BN42: =K42/$G$24 -> 0 | BO42: =L42/$H$24 -> 0
C43: =SUM(D43,G43,J43,M43,P43,S43,V43,Y43,AB43,AE43,AH43,AK43) -> 0 | AN43: =SUM(D43:AK43) -> 0 | AO43: =SUM(E43,H43,K43,N43,Q43,T43,W43,Z43,AC43,AF43,AI43,AL43) -> 0
A44: Pessoal | C44: =SUM(D44,G44,J44,M44,P44,S44,V44,Y44,AB44,AE44,AH44,AK44) -> -8093424.9 | D44: =SUM(D45:D47) -> -552193.44 | E44: =SUM(E45:E47) -> -358659.69 | G44: =SUM(G45:G47) -> -687143.7 | H44: =SUM(H45:H47) -> -506750.72 | J44: ='04 -Base Orçado 2026'!G51 -> -679825.89 | K44: =SUM(K45:K47) -> -611375.76 | M44: ='04 -Base Orçado 2026'!H51 -> -687143.7 | N44: =SUM(N45:N47) -> -589701.16 | P44: ='04 -Base Orçado 2026'!I51 -> -722936.34 | S44: ='04 -Base Orçado 2026'!J51 -> -673578.38 | V44: ='04 -Base Orçado 2026'!K51 -> -681736.13 | Y44: ='04 -Base Orçado 2026'!L51 -> -687815.44 | AB44: ='04 -Base Orçado 2026'!M51 -> -684471.73 | AE44: ='04 -Base Orçado 2026'!N51 -> -676825.94 | AH44: ='04 -Base Orçado 2026'!O51 -> -724291.6 | AK44: ='04 -Base Orçado 2026'!P51 -> -635462.62 | AN44: =SUM(D44,G44,J44,M44,P44,S44,V44,Y44,AB44,AE44,AH44,AK44) -> -8093424.9 | AO44: =SUM(E44,H44,K44,N44,Q44,T44,W44,Z44,AC44,AF44,AI44,AL44) -> -2066487.3 | AQ44: =AVERAGE(D44,G44,J44) -> -639721.01 | AR44: =AVERAGE(E44,H44,K44) -> -492262.06 | AT44: =IF(ISERROR(C44/C$24),0,(C44/C$24)) -> -0.28475304 | AV44: =IF(ISERROR(D44/D$24),0,(D44/D$24)) -> -0.34444628 | AW44: =IF(ISERROR(G44/G$24),0,(G44/G$24)) -> -0.27924096 | AX44: =IF(ISERROR(J44/J$24),0,(J44/J$24)) -> -0.2732448 | AY44: =IF(ISERROR(M44/M$24),0,(M44/M$24)) -> -0.27005862 | AZ44: =IF(ISERROR(P44/P$24),0,(P44/P$24)) -> -0.25279053 | BA44: =IF(ISERROR(S44/S$24),0,(S44/S$24)) -> -0.27777704 | BB44: =IF(ISERROR(V44/V$24),0,(V44/V$24)) -> -0.29134092 | BC44: =IF(ISERROR(Y44/Y$24),0,(Y44/Y$24)) -> -0.28736033 | BD44: =IF(ISERROR(AB44/AB$24),0,(AB44/AB$24)) -> -0.28952739 | BE44: =IF(ISERROR(AE44/AE$24),0,(AE44/AE$24)) -> -0.29469157 | BF44: =IF(ISERROR(AH44/AH$24),0,(AH44/AH$24)) -> -0.26677536 | BG44: =IF(ISERROR(AK44/AK$24),0,(AK44/AK$24)) -> -0.3288737 | BH44: =D44/$D$24 -> -0.34444628 | BI44: =E44/$E$24 -> -0.26788404 | BJ44: =G44/$G$24 -> -0.27924096 | BK44: =H44/$H$24 -> -0.33623619 | BL44: =J44/$J$24 -> -0.2732448 | BM44: =K44/$K$24 -> -0.25649129 | BN44: =M44/$M$24 -> -0.27005862 | BO44: =N44/$N$24 -> -0.25680654
A45: Salários e Encargos | C45: =SUM(D45,G45,J45,M45,P45,S45,V45,Y45,AB45,AE45,AH45,AK45) -> -999623.19 | D45: =SUM('04 -Base Orçado 2026'!E52:E67) -> -475465.22 | E45: =SUM('Base Realizado'!D49:D65) -> -281846.08 | G45: =SUM('04 -Base Orçado 2026'!H52:H67) -> -524157.96 | H45: =SUM('Base Realizado'!F49:F65) -> -408305.09 | K45: =SUM('Base Realizado'!H49:H65) -> -475011.45 | N45: =SUM('Base Realizado'!K49:K65) -> -589701.16 | AQ45: =AVERAGE(D45,G45,J45) -> -499811.59 | AR45: =AVERAGE(E45,H45,K45) -> -388387.54 | BH45: =D45/$D$24 -> -0.29658488 | BJ45: =G45/$G$24 -> -0.21300693 | BK45: =H45/$H$24 -> -0.27091614 | BL45: =I45/$G$24 -> 0 | BM45: =J45/$J$24 -> 0 | BN45: =M45/$M$24 -> 0 | BO45: =L45/$J$24 -> 0
A46: Gorjetas Recebidas | C46: =SUM(D46,G46,J46,M46,P46,S46,V46,Y46,AB46,AE46,AH46,AK46) -> 151463.41 | D46: ='04 -Base Orçado 2026'!E68 -> 74471.506 | E46: ='Base Realizado'!D66 -> 13519.95 | G46: ='04 -Base Orçado 2026'!H68 -> 76991.903 | H46: ='Base Realizado'!F66 -> 22113.35 | K46: ='Base Realizado'!H66 -> 25620.56 | N46: ='Base Realizado'!K66 -> 0 | AQ46: =AVERAGE(D46,G46,J46) -> 75731.705 | AR46: =AVERAGE(E46,H46,K46) -> 20417.953 | BH46: =D46/$D$24 -> 0.046453709 | BJ46: =G46/$G$24 -> 0.031287914 | BK46: =H46/$H$24 -> 0.014672517 | BL46: =I46/$G$24 -> 0 | BM46: =J46/$J$24 -> 0 | BN46: =M46/$M$24 -> 0 | BO46: =L46/$J$24 -> 0
A47: Gorjetas Pagas | C47: =SUM(D47,G47,J47,M47,P47,S47,V47,Y47,AB47,AE47,AH47,AK47) -> -391177.37 | D47: ='04 -Base Orçado 2026'!E69 -> -151199.72 | E47: ='Base Realizado'!D67 -> -90333.56 | G47: ='04 -Base Orçado 2026'!H69 -> -239977.64 | H47: ='Base Realizado'!F67 -> -120558.98 | K47: ='Base Realizado'!H67 -> -161984.87 | N47: ='Base Realizado'!K67 -> 0 | AQ47: =AVERAGE(D47,G47,J47) -> -195588.68 | AR47: =AVERAGE(E47,H47,K47) -> -124292.47 | BH47: =D47/$D$24 -> -0.094315106 | BJ47: =G47/$G$24 -> -0.097521941 | BK47: =H47/$H$24 -> -0.079992569 | BL47: =I47/$G$24 -> 0 | BM47: =J47/$J$24 -> 0 | BN47: =M47/$M$24 -> 0 | BO47: =L47/$J$24 -> 0
C48: =SUM(D48,G48,J48,M48,P48,S48,V48,Y48,AB48,AE48,AH48,AK48) -> 0 | E48: ='Base Realizado'!D68 -> 0 | AR48: =AVERAGE(E48,H48,K48) -> 0
A49: Ocupação | C49: =SUM(D49,G49,J49,M49,P49,S49,V49,Y49,AB49,AE49,AH49,AK49) -> -844692.6 | D49: ='04 -Base Orçado 2026'!E76 -> -63668 | E49: ='Base Realizado'!D74 -> -61112.86 | G49: ='04 -Base Orçado 2026'!F76 -> -71735.66 | H49: ='Base Realizado'!F74 -> -69633.92 | J49: ='04 -Base Orçado 2026'!G76 -> -71735.66 | K49: ='Base Realizado'!H74 -> -69180.52 | M49: ='04 -Base Orçado 2026'!H76 -> -71735.66 | N49: ='Base Realizado'!K74 -> -69180.52 | P49: ='04 -Base Orçado 2026'!I76 -> -71735.66 | S49: ='04 -Base Orçado 2026'!J76 -> -71735.66 | V49: ='04 -Base Orçado 2026'!K76 -> -71735.66 | Y49: ='04 -Base Orçado 2026'!L76 -> -71735.66 | AB49: ='04 -Base Orçado 2026'!M76 -> -71735.66 | AE49: ='04 -Base Orçado 2026'!N76 -> -71735.66 | AH49: ='04 -Base Orçado 2026'!O76 -> -71735.66 | AK49: ='04 -Base Orçado 2026'!P76 -> -63668 | AN49: =SUM(D49,G49,J49,M49,P49,S49,V49,Y49,AB49,AE49,AH49,AK49) -> -844692.6 | AO49: =SUM(E49,H49,K49,N49,Q49,T49,W49,Z49,AC49,AF49,AI49,AL49) -> -269107.82 | AQ49: =AVERAGE(D49,G49,J49) -> -69046.44 | AR49: =AVERAGE(E49,H49,K49) -> -66642.433 | AT49: =IF(ISERROR(C49/C$24),0,(C49/C$24)) -> -0.029719036 | AV49: =IF(ISERROR(D49/D$24),0,(D49/D$24)) -> -0.039714716 | AW49: =IF(ISERROR(G49/G$24),0,(G49/G$24)) -> -0.029151886 | AX49: =IF(ISERROR(J49/J$24),0,(J49/J$24)) -> -0.028832965 | AY49: =IF(ISERROR(M49/M$24),0,(M49/M$24)) -> -0.028193278 | AZ49: =IF(ISERROR(P49/P$24),0,(P49/P$24)) -> -0.025083945 | BA49: =IF(ISERROR(S49/S$24),0,(S49/S$24)) -> -0.029583074 | BB49: =IF(ISERROR(V49/V$24),0,(V49/V$24)) -> -0.030656338 | BC49: =IF(ISERROR(Y49/Y$24),0,(Y49/Y$24)) -> -0.029970224 | BD49: =IF(ISERROR(AB49/AB$24),0,(AB49/AB$24)) -> -0.030343749 | BE49: =IF(ISERROR(AE49/AE$24),0,(AE49/AE$24)) -> -0.031233871 | BF49: =IF(ISERROR(AH49/AH$24),0,(AH49/AH$24)) -> -0.026422102 | BG49: =IF(ISERROR(AK49/AK$24),0,(AK49/AK$24)) -> -0.032950373 | BH49: =D49/$D$24 -> -0.039714716 | BI49: =E49/$E$24 -> -0.045645386 | BJ49: =G49/$G$24 -> -0.029151886 | BK49: =H49/$H$24 -> -0.046203079 | BL49: =J49/$J$24 -> -0.028832965 | BM49: =K49/$K$24 -> -0.029023396 | BN49: =M49/$M$24 -> -0.028193278 | BO49: =N49/$N$24 -> -0.030127141
A50: Utilidades/ Consumo | C50: =SUM(D50,G50,J50,M50,P50,S50,V50,Y50,AB50,AE50,AH50,AK50) -> -683912.04 | D50: ='04 -Base Orçado 2026'!E80 -> -43284.61 | E50: ='Base Realizado'!D78 -> -52795.14 | G50: ='04 -Base Orçado 2026'!F80 -> -58796.811 | H50: ='Base Realizado'!F78 -> -55997.45 | J50: ='04 -Base Orçado 2026'!G80 -> -59255.221 | K50: ='Base Realizado'!H78 -> -53378.87 | M50: ='04 -Base Orçado 2026'!H80 -> -60795.978 | N50: ='Base Realizado'!K78 -> -60529.54 | P50: ='04 -Base Orçado 2026'!I80 -> -68332.069 | S50: ='04 -Base Orçado 2026'!J80 -> -57939.817 | V50: ='04 -Base Orçado 2026'!K80 -> -55911.371 | Y50: ='04 -Base Orçado 2026'!L80 -> -57191.361 | AB50: ='04 -Base Orçado 2026'!M80 -> -56487.347 | AE50: ='04 -Base Orçado 2026'!N80 -> -54877.537 | AH50: ='04 -Base Orçado 2026'!O80 -> -64871.367 | AK50: ='04 -Base Orçado 2026'!P80 -> -46168.545 | AN50: =SUM(D50,G50,J50,M50,P50,S50,V50,Y50,AB50,AE50,AH50,AK50) -> -683912.04 | AO50: =SUM(E50,H50,K50,N50,Q50,T50,W50,Z50,AC50,AF50,AI50,AL50) -> -222701 | AQ50: =AVERAGE(D50,G50,J50) -> -53778.881 | AR50: =AVERAGE(E50,H50,K50) -> -54057.153 | AT50: =IF(ISERROR(C50/C$24),0,(C50/C$24)) -> -0.024062252 | BH50: =D50/$D$24 -> -0.027 | BI50: =E50/$E$24 -> -0.039432855 | BJ50: =G50/$G$24 -> -0.023893805 | BK50: =H50/$H$24 -> -0.037155091 | BL50: =J50/$J$24 -> -0.023816659 | BM50: =K50/$K$24 -> -0.022394108 | BN50: =M50/$M$24 -> -0.023893805 | BO50: =N50/$N$24 -> -0.026359761
A51: Operação | C51: =SUM(D51,G51,J51,M51,P51,S51,V51,Y51,AB51,AE51,AH51,AK51) -> -2325534.6 | D51: ='04 -Base Orçado 2026'!E86 -> -180339.11 | E51: ='Base Realizado'!D86 -> -208148.95 | G51: ='04 -Base Orçado 2026'!F86 -> -195316.67 | H51: ='Base Realizado'!F86 -> -221468.45 | J51: ='04 -Base Orçado 2026'!G86 -> -195562.24 | K51: ='Base Realizado'!H86 -> -238262.48 | M51: ='04 -Base Orçado 2026'!H86 -> -196387.63 | N51: ='Base Realizado'!K86 -> -252889.37 | P51: ='04 -Base Orçado 2026'!I86 -> -200424.74 | S51: ='04 -Base Orçado 2026'!J86 -> -194857.57 | V51: ='04 -Base Orçado 2026'!K86 -> -193770.93 | Y51: ='04 -Base Orçado 2026'!L86 -> -194456.62 | AB51: ='04 -Base Orçado 2026'!M86 -> -194079.48 | AE51: ='04 -Base Orçado 2026'!N86 -> -193217.1 | AH51: ='04 -Base Orçado 2026'!O86 -> -198570.83 | AK51: ='04 -Base Orçado 2026'!P86 -> -188551.66 | AN51: =SUM(D51,G51,J51,M51,P51,S51,V51,Y51,AB51,AE51,AH51,AK51) -> -2325534.6 | AO51: =SUM(E51,H51,K51,N51,Q51,T51,W51,Z51,AC51,AF51,AI51,AL51) -> -920769.25 | AQ51: =AVERAGE(D51,G51,J51) -> -190406.01 | AR51: =AVERAGE(E51,H51,K51) -> -222626.63 | AT51: =IF(ISERROR(C51/C$24),0,(C51/C$24)) -> -0.08181988 | AV51: =IF(ISERROR(D51/D$24),0,(D51/D$24)) -> -0.11249162 | AW51: =IF(ISERROR(G51/G$24),0,(G51/G$24)) -> -0.079372646 | AX51: =IF(ISERROR(J51/J$24),0,(J51/J$24)) -> -0.078603017 | AY51: =IF(ISERROR(M51/M$24),0,(M51/M$24)) -> -0.077183524 | AZ51: =IF(ISERROR(P51/P$24),0,(P51/P$24)) -> -0.070082903 | BA51: =IF(ISERROR(S51/S$24),0,(S51/S$24)) -> -0.080357329 | BB51: =IF(ISERROR(V51/V$24),0,(V51/V$24)) -> -0.082808286 | BC51: =IF(ISERROR(Y51/Y$24),0,(Y51/Y$24)) -> -0.081241444 | BD51: =IF(ISERROR(AB51/AB$24),0,(AB51/AB$24)) -> -0.082094444 | BE51: =IF(ISERROR(AE51/AE$24),0,(AE51/AE$24)) -> -0.084127168 | BF51: =IF(ISERROR(AH51/AH$24),0,(AH51/AH$24)) -> -0.073138782 | BG51: =IF(ISERROR(AK51/AK$24),0,(AK51/AK$24)) -> -0.09758195 | BH51: =D51/$D$24 -> -0.11249162 | BI51: =E51/$E$24 -> -0.1554671 | BJ51: =G51/$G$24 -> -0.079372646 | BK51: =H51/$H$24 -> -0.14694741 | BL51: =J51/$J$24 -> -0.078603017 | BM51: =K51/$K$24 -> -0.099958575 | BN51: =M51/$M$24 -> -0.077183524 | BO51: =N51/$N$24 -> -0.11012975
A52: Manutenção e Conservação | C52: =SUM(D52,G52,J52,M52,P52,S52,V52,Y52,AB52,AE52,AH52,AK52) -> -253300.75 | D52: ='04 -Base Orçado 2026'!E85 -> -16031.337 | E52: ='Base Realizado'!D84 -> -50127.13 | G52: ='04 -Base Orçado 2026'!F85 -> -21776.597 | H52: ='Base Realizado'!F83 -> -26855.8 | J52: ='04 -Base Orçado 2026'!G85 -> -21946.378 | K52: ='Base Realizado'!H83 -> -18412.43 | M52: ='04 -Base Orçado 2026'!H85 -> -22517.029 | N52: ='Base Realizado'!K83 -> -22298.67 | P52: ='04 -Base Orçado 2026'!I85 -> -25308.174 | S52: ='04 -Base Orçado 2026'!J85 -> -21459.192 | V52: ='04 -Base Orçado 2026'!K85 -> -20707.915 | Y52: ='04 -Base Orçado 2026'!L85 -> -21181.985 | AB52: ='04 -Base Orçado 2026'!M85 -> -20921.24 | AE52: ='04 -Base Orçado 2026'!N85 -> -20325.014 | AH52: ='04 -Base Orçado 2026'!O85 -> -24026.432 | AK52: ='04 -Base Orçado 2026'!P85 -> -17099.461 | AN52: =SUM(D52:AK52) -> -370994.78 | AO52: =SUM(E52,H52,K52,N52,Q52,T52,W52,Z52,AC52,AF52,AI52,AL52) -> -117694.03 | AQ52: =AVERAGE(D52,G52,J52) -> -19918.104 | AR52: =AVERAGE(E52,H52,K52) -> -31798.453 | AT52: =IF(ISERROR(C52/C$24),0,(C52/C$24)) -> -0.0089119453 | AV52: =IF(ISERROR(D52/D$24),0,(D52/D$24)) -> -0.01 | AW52: =IF(ISERROR(G52/G$24),0,(G52/G$24)) -> -0.0088495575 | AX52: =IF(ISERROR(J52/J$24),0,(J52/J$24)) -> -0.0088209847 | AY52: =IF(ISERROR(M52/M$24),0,(M52/M$24)) -> -0.0088495575 | AZ52: =IF(ISERROR(P52/P$24),0,(P52/P$24)) -> -0.0088495575 | BA52: =IF(ISERROR(S52/S$24),0,(S52/S$24)) -> -0.0088495575 | BB52: =IF(ISERROR(V52/V$24),0,(V52/V$24)) -> -0.0088495575 | BC52: =IF(ISERROR(Y52/Y$24),0,(Y52/Y$24)) -> -0.0088495575 | BD52: =IF(ISERROR(AB52/AB$24),0,(AB52/AB$24)) -> -0.0088495575 | BE52: =IF(ISERROR(AE52/AE$24),0,(AE52/AE$24)) -> -0.0088495575 | BF52: =IF(ISERROR(AH52/AH$24),0,(AH52/AH$24)) -> -0.0088495575 | BG52: =IF(ISERROR(AK52/AK$24),0,(AK52/AK$24)) -> -0.0088495575 | BH52: =D52/$D$24 -> -0.01 | BI52: =E52/$E$24 -> -0.03744011 | BJ52: =G52/$G$24 -> -0.0088495575 | BK52: =H52/$H$24 -> -0.017819199 | BL52: =J52/$J$24 -> -0.0088209847 | BM52: =K52/$K$24 -> -0.0077245912 | BN52: =M52/$M$24 -> -0.0088495575 | BO52: =N52/$N$24 -> -0.0097107564
A53: Lucro Bruto | C53: =SUM(D53,G53,J53,M53,P53,S53,V53,Y53,AB53,AE53,AH53,AK53) -> 7129081 | D53: =D24+D26 -> 234614.42 | E53: =E24+E26 -> 7160.45 | G53: =G24+G26 -> 638544.24 | H53: =H24+H26 -> 98951.387 | J53: =J24+J26 -> 666067.3 | K53: =K24+K26 -> 743032.03 | M53: =M24+M26 -> 691628.5 | N53: =N24+N26 -> 406058.95 | P53: =P24+P26 -> 855943.09 | S53: =S24+S26 -> 629353.66 | V53: =V24+V26 -> 567334.2 | Y53: =Y24+Y26 -> 595242.69 | AB53: =AB24+AB26 -> 579892.6 | AE53: =AE24+AE26 -> 544792.79 | AH53: =AH24+AH26 -> 762695.18 | AK53: =AK24+AK26 -> 362972.31 | AN53: =SUM(D53,G53,J53,M53,P53,S53,V53,Y53,AB53,AE53,AH53,AK53) -> 7129081 | AO53: =SUM(E53,H53,K53,N53,Q53,T53,W53,Z53,AC53,AF53,AI53,AL53) -> 1255202.8 | AQ53: =AVERAGE(D53,G53,J53) -> 513075.32 | AR53: =AVERAGE(E53,H53,K53) -> 283047.95 | AT53: =IF(ISERROR(C53/C$24),0,(C53/C$24)) -> 0.25082428 | AV53: =IF(ISERROR(D53/D$24),0,(D53/D$24)) -> 0.14634738 | AW53: =IF(ISERROR(G53/G$24),0,(G53/G$24)) -> 0.25949114 | AX53: =IF(ISERROR(J53/J$24),0,(J53/J$24)) -> 0.26771476 | AY53: =IF(ISERROR(M53/M$24),0,(M53/M$24)) -> 0.27182122 | AZ53: =IF(ISERROR(P53/P$24),0,(P53/P$24)) -> 0.29929926 | BA53: =IF(ISERROR(S53/S$24),0,(S53/S$24)) -> 0.2595392 | BB53: =IF(ISERROR(V53/V$24),0,(V53/V$24)) -> 0.24245109 | BC53: =IF(ISERROR(Y53/Y$24),0,(Y53/Y$24)) -> 0.24868464 | BD53: =IF(ISERROR(AB53/AB$24),0,(AB53/AB$24)) -> 0.24529105 | BE53: =IF(ISERROR(AE53/AE$24),0,(AE53/AE$24)) -> 0.23720403 | BF53: =IF(ISERROR(AH53/AH$24),0,(AH53/AH$24)) -> 0.28092039 | BG53: =IF(ISERROR(AK53/AK$24),0,(AK53/AK$24)) -> 0.18785062
C54: =SUM(D54,G54,J54,M54,P54,S54,V54,Y54,AB54,AE54,AH54,AK54) -> 2.9466148 | D54: =IF(ISERROR(D53/D24),"-",(D53/D24)) -> 0.14634738 | E54: =IF(ISERROR(E53/E24),"-",(E53/E24)) -> 0.0053481625 | G54: =IF(ISERROR(G53/G24),"-",(G53/G24)) -> 0.25949114 | H54: =IF(ISERROR(H53/H24),"-",(H53/H24)) -> 0.065655629 | J54: =IF(ISERROR(J53/J24),"-",(J53/J24)) -> 0.26771476 | K54: =IF(ISERROR(K53/K24),"-",(K53/K24)) -> 0.31172521 | M54: =IF(ISERROR(M53/M24),"-",(M53/M24)) -> 0.27182122 | N54: =IF(ISERROR(N53/N24),"-",(N53/N24)) -> 0.17683295 | P54: =IF(ISERROR(P53/P24),"-",(P53/P24)) -> 0.29929926 | S54: =IF(ISERROR(S53/S24),"-",(S53/S24)) -> 0.2595392 | V54: =IF(ISERROR(V53/V24),"-",(V53/V24)) -> 0.24245109 | Y54: =IF(ISERROR(Y53/Y24),"-",(Y53/Y24)) -> 0.24868464 | AB54: =IF(ISERROR(AB53/AB24),"-",(AB53/AB24)) -> 0.24529105 | AE54: =IF(ISERROR(AE53/AE24),"-",(AE53/AE24)) -> 0.23720403 | AH54: =IF(ISERROR(AH53/AH24),"-",(AH53/AH24)) -> 0.28092039 | AK54: =IF(ISERROR(AK53/AK24),"-",(AK53/AK24)) -> 0.18785062 | AN54: =IF(ISERROR(AN53/AN24),"-",(AN53/AN24)) -> 0.25082428 | AO54: =IF(ISERROR(AO53/AO24),"-",(AO53/AO24)) -> 0.16678471 | AQ54: =AVERAGE(D54,G54,J54) -> 0.22451776 | AR54: =AVERAGE(E54,H54,K54) -> 0.12757633
A56: SG&A | C56: =SUM(D56,G56,J56,M56,P56,S56,V56,Y56,AB56,AE56,AH56,AK56) -> -3682512.2 | D56: =SUM(D57:D60) -> -238527.06 | E56: =SUM(E57:E60) -> -251830.75 | G56: =SUM(G57:G60) -> -285925.21 | H56: =SUM(H57:H60) -> -206571.36 | J56: =SUM(J57:J60) -> -283586.05 | K56: =SUM(K57:K60) -> -234266.51 | M56: =SUM(M57:M60) -> -287185.15 | N56: =SUM(N57:N60) -> -201490.35 | P56: =SUM(P57:P60) -> -356172.61 | S56: =SUM(S57:S60) -> -324082.37 | V56: =SUM(V57:V60) -> -317818.73 | Y56: =SUM(Y57:Y60) -> -321771.21 | AB56: =SUM(AB57:AB60) -> -319597.29 | AE56: =SUM(AE57:AE60) -> -314626.35 | AH56: =SUM(AH57:AH60) -> -345486.3 | AK56: =SUM(AK57:AK60) -> -287733.86 | AN56: =SUM(D56,G56,J56,M56,P56,S56,V56,Y56,AB56,AE56,AH56,AK56) -> -3682512.2 | AO56: =SUM(E56,H56,K56,N56,Q56,T56,W56,Z56,AC56,AF56,AI56,AL56) -> -894158.97 | AQ56: =AVERAGE(D56,G56,J56) -> -269346.11 | AR56: =AVERAGE(E56,H56,K56) -> -230889.54 | AT56: =SUM(AT57:AT60) -> -0.12956277 | AV56: =SUM(AV57:AV60) -> -0.148788 | AW56: =SUM(AW57:AW60) -> -0.11619408 | AX56: =SUM(AX57:AX60) -> -0.11398273 | AY56: =SUM(AY57:AY60) -> -0.11286842 | AZ56: =SUM(AZ57:AZ60) -> -0.12454356 | BA56: =SUM(BA57:BA60) -> -0.13364835 | BB56: =SUM(BB57:BB60) -> -0.13582029 | BC56: =SUM(BC57:BC60) -> -0.13443182 | ... BG56: =SUM(BG57:BG60) -> -0.14891214
A57: Administrativa | C57: =SUM(D57,G57,J57,M57,P57,S57,V57,Y57,AB57,AE57,AH57,AK57) -> -2230770.7 | D57: ='04 -Base Orçado 2026'!E102 -> -172743.9 | E57: ='Base Realizado'!D102 -> -160621.07 | G57: ='04 -Base Orçado 2026'!F102 -> -187494.99 | H57: ='Base Realizado'!F102 -> -143661.06 | J57: ='04 -Base Orçado 2026'!G102 -> -187824.98 | K57: ='Base Realizado'!H102 -> -172246.94 | M57: ='04 -Base Orçado 2026'!H102 -> -188934.1 | N57: ='Base Realizado'!K102 -> -109749.19 | P57: ='04 -Base Orçado 2026'!I102 -> -194358.97 | S57: ='04 -Base Orçado 2026'!J102 -> -186878.08 | V57: ='04 -Base Orçado 2026'!K102 -> -185417.9 | Y57: ='04 -Base Orçado 2026'!L102 -> -186339.31 | AB57: ='04 -Base Orçado 2026'!M102 -> -185832.52 | AE57: ='04 -Base Orçado 2026'!N102 -> -184673.7 | AH57: ='04 -Base Orçado 2026'!O102 -> -191867.77 | AK57: ='04 -Base Orçado 2026'!P102 -> -178404.51 | AN57: =SUM(D57,G57,J57,M57,P57,S57,V57,Y57,AB57,AE57,AH57,AK57) -> -2230770.7 | AO57: =SUM(E57,H57,K57,N57,Q57,T57,W57,Z57,AC57,AF57,AI57,AL57) -> -586278.26 | AQ57: =AVERAGE(D57,G57,J57) -> -182687.96 | AR57: =AVERAGE(E57,H57,K57) -> -158843.02 | AT57: =IF(ISERROR(C57/C$24),0,(C57/C$24)) -> -0.078485779 | AV57: =IF(ISERROR(D57/D$24),0,(D57/D$24)) -> -0.10775389 | AW57: =IF(ISERROR(G57/G$24),0,(G57/G$24)) -> -0.076194079 | AX57: =IF(ISERROR(J57/J$24),0,(J57/J$24)) -> -0.075493153 | AY57: =IF(ISERROR(M57/M$24),0,(M57/M$24)) -> -0.074254164 | AZ57: =IF(ISERROR(P57/P$24),0,(P57/P$24)) -> -0.067961871 | BA57: =IF(ISERROR(S57/S$24),0,(S57/S$24)) -> -0.077066667 | BB57: =IF(ISERROR(V57/V$24),0,(V57/V$24)) -> -0.079238609 | BC57: =IF(ISERROR(Y57/Y$24),0,(Y57/Y$24)) -> -0.077850135 | BD57: =IF(ISERROR(AB57/AB$24),0,(AB57/AB$24)) -> -0.07860603 | BE57: =IF(ISERROR(AE57/AE$24),0,(AE57/AE$24)) -> -0.080407351 | BF57: =IF(ISERROR(AH57/AH$24),0,(AH57/AH$24)) -> -0.070669872 | BG57: =IF(ISERROR(AK57/AK$24),0,(AK57/AK$24)) -> -0.092330453 | BH57: =D57/$D$24 -> -0.10775389 | BI57: =E57/$E$24 -> -0.11996838 | BJ57: =G57/$G$24 -> -0.076194079 | BK57: =H57/$H$24 -> -0.095321122 | BL57: =J57/$J$24 -> -0.075493153 | BM57: =K57/$K$24 -> -0.072262988 | BN57: =M57/$M$24 -> -0.074254164 | BO57: =N57/$N$24 -> -0.047794225
A58: Marketing | C58: =SUM(D58,G58,J58,M58,P58,S58,V58,Y58,AB58,AE58,AH58,AK58) -> -568291.56 | D58: ='04 -Base Orçado 2026'!E116 -> -32062.674 | E58: ='Base Realizado'!D118 -> -73694.5 | G58: ='04 -Base Orçado 2026'!F116 -> -49215.108 | H58: ='Base Realizado'!F118 -> -42956.53 | J58: ='04 -Base Orçado 2026'!G116 -> -49598.815 | K58: ='Base Realizado'!H118 -> -34777.84 | M58: ='04 -Base Orçado 2026'!H116 -> -50888.485 | N58: ='Base Realizado'!K118 -> -65831.88 | P58: ='04 -Base Orçado 2026'!I116 -> -57196.473 | S58: ='04 -Base Orçado 2026'!J116 -> -48497.773 | V58: ='04 -Base Orçado 2026'!K116 -> -46799.889 | Y58: ='04 -Base Orçado 2026'!L116 -> -47871.287 | AB58: ='04 -Base Orçado 2026'!M116 -> -47282.002 | AE58: ='04 -Base Orçado 2026'!N116 -> -45934.531 | AH58: ='04 -Base Orçado 2026'!O116 -> -54299.737 | AK58: ='04 -Base Orçado 2026'!P116 -> -38644.782 | AN58: =SUM(D58,G58,J58,M58,P58,S58,V58,Y58,AB58,AE58,AH58,AK58) -> -568291.56 | AO58: =SUM(E58,H58,K58,N58,Q58,T58,W58,Z58,AC58,AF58,AI58,AL58) -> -217260.75 | AQ58: =AVERAGE(D58,G58,J58) -> -43625.532 | AR58: =AVERAGE(E58,H58,K58) -> -50476.29 | AT58: =IF(ISERROR(C58/C$24),0,(C58/C$24)) -> -0.019994347 | AV58: =IF(ISERROR(D58/D$24),0,(D58/D$24)) -> -0.02 | AW58: =IF(ISERROR(G58/G$24),0,(G58/G$24)) -> -0.02 | AX58: =IF(ISERROR(J58/J$24),0,(J58/J$24)) -> -0.019935426 | AY58: =IF(ISERROR(M58/M$24),0,(M58/M$24)) -> -0.02 | AZ58: =IF(ISERROR(P58/P$24),0,(P58/P$24)) -> -0.02 | BA58: =IF(ISERROR(S58/S$24),0,(S58/S$24)) -> -0.02 | BB58: =IF(ISERROR(V58/V$24),0,(V58/V$24)) -> -0.02 | BC58: =IF(ISERROR(Y58/Y$24),0,(Y58/Y$24)) -> -0.02 | BD58: =IF(ISERROR(AB58/AB$24),0,(AB58/AB$24)) -> -0.02 | BE58: =IF(ISERROR(AE58/AE$24),0,(AE58/AE$24)) -> -0.02 | BF58: =IF(ISERROR(AH58/AH$24),0,(AH58/AH$24)) -> -0.02 | BG58: =IF(ISERROR(AK58/AK$24),0,(AK58/AK$24)) -> -0.02 | BH58: =D58/$D$24 -> -0.02 | BI58: =E58/$E$24 -> -0.055042652 | BJ58: =G58/$G$24 -> -0.02 | BK58: =H58/$H$24 -> -0.028502258 | BL58: =J58/$J$24 -> -0.019935426 | BM58: =K58/$K$24 -> -0.014590393 | BN58: =M58/$M$24 -> -0.02 | BO58: =N58/$N$24 -> -0.028668855
A59: Taxa Cartões | C59: =SUM(D59,G59,J59,M59,P59,S59,V59,Y59,AB59,AE59,AH59,AK59) -> -883449.89 | D59: ='04 -Base Orçado 2026'!E120 -> -33720.49 | E59: ='Base Realizado'!D122 -> -17515.18 | G59: ='04 -Base Orçado 2026'!F117 -> -49215.108 | H59: ='Base Realizado'!F122 -> -18701.31 | J59: ='04 -Base Orçado 2026'!G120 -> -46162.252 | K59: ='Base Realizado'!H122 -> -26100.82 | M59: ='04 -Base Orçado 2026'!H120 -> -47362.565 | N59: ='Base Realizado'!K122 -> -25909.28 | P59: ='04 -Base Orçado 2026'!I120 -> -104617.17 | S59: ='04 -Base Orçado 2026'!J120 -> -88706.512 | V59: ='04 -Base Orçado 2026'!K120 -> -85600.938 | Y59: ='04 -Base Orçado 2026'!L120 -> -87560.616 | AB59: ='04 -Base Orçado 2026'!M120 -> -86482.764 | AE59: ='04 -Base Orçado 2026'!N120 -> -84018.126 | AH59: ='04 -Base Orçado 2026'!O120 -> -99318.793 | AK59: ='04 -Base Orçado 2026'!P120 -> -70684.562 | AN59: =SUM(D59,G59,J59,M59,P59,S59,V59,Y59,AB59,AE59,AH59,AK59) -> -883449.89 | AO59: =SUM(E59,H59,K59,N59,Q59,T59,W59,Z59,AC59,AF59,AI59,AL59) -> -88226.59 | AQ59: =AVERAGE(D59,G59,J59) -> -43032.617 | AR59: =AVERAGE(E59,H59,K59) -> -20772.437 | AT59: =IF(ISERROR(C59/C$24),0,(C59/C$24)) -> -0.031082644 | AV59: =IF(ISERROR(D59/D$24),0,(D59/D$24)) -> -0.021034109 | AW59: =IF(ISERROR(G59/G$24),0,(G59/G$24)) -> -0.02 | AX59: =IF(ISERROR(J59/J$24),0,(J59/J$24)) -> -0.018554156 | AY59: =IF(ISERROR(M59/M$24),0,(M59/M$24)) -> -0.018614256 | AZ59: =IF(ISERROR(P59/P$24),0,(P59/P$24)) -> -0.036581685 | BA59: =IF(ISERROR(S59/S$24),0,(S59/S$24)) -> -0.036581685 | BB59: =IF(ISERROR(V59/V$24),0,(V59/V$24)) -> -0.036581685 | BC59: =IF(ISERROR(Y59/Y$24),0,(Y59/Y$24)) -> -0.036581685 | BD59: =IF(ISERROR(AB59/AB$24),0,(AB59/AB$24)) -> -0.036581685 | BE59: =IF(ISERROR(AE59/AE$24),0,(AE59/AE$24)) -> -0.036581685 | BF59: =IF(ISERROR(AH59/AH$24),0,(AH59/AH$24)) -> -0.036581685 | BG59: =IF(ISERROR(AK59/AK$24),0,(AK59/AK$24)) -> -0.036581685 | BH59: =D59/$D$24 -> -0.021034109 | BI59: =E59/$E$24 -> -0.013082143 | BJ59: =G59/$G$24 -> -0.02 | BK59: =H59/$H$24 -> -0.012408581 | BL59: =J59/$J$24 -> -0.018554156 | BM59: =K59/$K$24 -> -0.010950112 | BN59: =M59/$M$24 -> -0.018614256 | BO59: =N59/$N$24 -> -0.011283126
A60: Royalties | C60: =SUM(D60,G60,J60,M60,P60,S60,V60,Y60,AB60,AE60,AH60,AK60) -> 0 | D60: 0 | G60: ='04 -Base Orçado 2026'!F118 -> 0 | H60: ='Base Realizado'!F105 -> -1252.46 | J60: 0 | K60: ='Base Realizado'!H105 -> -1140.91 | M60: 0 | N60: ='Base Realizado'!N105 -> 0 | P60: 0 | S60: 0 | V60: 0 | Y60: 0 | AB60: 0 | AE60: 0 | AH60: 0 | AK60: 0 | AN60: =SUM(D60:AK60) -> -2393.37 | AQ60: =AVERAGE(D60,G60,J60) -> 0 | AR60: =AVERAGE(E60,H60,K60) -> -1196.685 | AT60: =IF(ISERROR(C60/C$24),0,(C60/C$24)) -> 0 | AV60: =IF(ISERROR(D60/D$24),0,(D60/D$24)) -> 0 | AW60: =IF(ISERROR(G60/G$24),0,(G60/G$24)) -> 0 | AX60: =IF(ISERROR(J60/J$24),0,(J60/J$24)) -> 0 | AY60: =IF(ISERROR(M60/M$24),0,(M60/M$24)) -> 0 | AZ60: =IF(ISERROR(P60/P$24),0,(P60/P$24)) -> 0 | BA60: =IF(ISERROR(S60/S$24),0,(S60/S$24)) -> 0 | BB60: =IF(ISERROR(V60/V$24),0,(V60/V$24)) -> 0 | BC60: =IF(ISERROR(Y60/Y$24),0,(Y60/Y$24)) -> 0 | BD60: =IF(ISERROR(AB60/AB$24),0,(AB60/AB$24)) -> 0 | BE60: =IF(ISERROR(AE60/AE$24),0,(AE60/AE$24)) -> 0 | BF60: =IF(ISERROR(AH60/AH$24),0,(AH60/AH$24)) -> 0 | BG60: =IF(ISERROR(AK60/AK$24),0,(AK60/AK$24)) -> 0
C61: =SUM(D61,G61,J61,M61,P61,S61,V61,Y61,AB61,AE61,AH61,AK61) -> 0 | AN61: =SUM(D61:AK61) -> 0
A62: EBITDA | C62: =SUM(D62,G62,J62,M62,P62,S62,V62,Y62,AB62,AE62,AH62,AK62) -> 3446568.8 | D62: =D53+D56 -> -3912.6425 | E62: =E53+E56 -> -244670.3 | G62: =G53+G56 -> 352619.03 | H62: =H53+H56 -> -107619.97 | J62: =J53+J56 -> 382481.25 | K62: =K53+K56 -> 508765.52 | M62: =M53+M56 -> 404443.36 | N62: =N53+N56 -> 204568.6 | P62: =P53+P56 -> 499770.49 | S62: =S53+S56 -> 305271.29 | V62: =V53+V56 -> 249515.47 | Y62: =Y53+Y56 -> 273471.48 | AB62: =AB53+AB56 -> 260295.32 | AE62: =AE53+AE56 -> 230166.44 | AH62: =AH53+AH56 -> 417208.87 | AK62: =AK53+AK56 -> 75238.451 | AN62: =SUM(D62,G62,J62,M62,P62,S62,V62,Y62,AB62,AE62,AH62,AK62) -> 3446568.8 | AO62: =SUM(E62,H62,K62,N62,Q62,T62,W62,Z62,AC62,AF62,AI62,AL62) -> 361043.84 | AQ62: =AVERAGE(D62,G62,J62) -> 243729.21 | AR62: =AVERAGE(E62,H62,K62) -> 52158.414 | AT62: =IF(ISERROR(C62/C$24),0,(C62/C$24)) -> 0.12126151 | AV62: =IF(ISERROR(D62/D$24),0,(D62/D$24)) -> -0.0024406215 | AW62: =IF(ISERROR(G62/G$24),0,(G62/G$24)) -> 0.14329707 | AX62: =IF(ISERROR(J62/J$24),0,(J62/J$24)) -> 0.15373203 | AY62: =IF(ISERROR(M62/M$24),0,(M62/M$24)) -> 0.1589528 | AZ62: =IF(ISERROR(P62/P$24),0,(P62/P$24)) -> 0.1747557 | BA62: =IF(ISERROR(S62/S$24),0,(S62/S$24)) -> 0.12589085 | BB62: =IF(ISERROR(V62/V$24),0,(V62/V$24)) -> 0.1066308 | BC62: =IF(ISERROR(Y62/Y$24),0,(Y62/Y$24)) -> 0.11425282 | BD62: =IF(ISERROR(AB62/AB$24),0,(AB62/AB$24)) -> 0.11010334 | BE62: =IF(ISERROR(AE62/AE$24),0,(AE62/AE$24)) -> 0.100215 | BF62: =IF(ISERROR(AH62/AH$24),0,(AH62/AH$24)) -> 0.15366884 | BG62: =IF(ISERROR(AK62/AK$24),0,(AK62/AK$24)) -> 0.038938479
A63: MARGEM EBITDA | C63: =SUM(D63,G63,J63,M63,P63,S63,V63,Y63,AB63,AE63,AH63,AK63) -> 1.3779971 | D63: =IF(ISERROR(D62/D24),"-",(D62/D24)) -> -0.0024406215 | E63: =IF(ISERROR(E62/E24),"-",(E62/E24)) -> -0.18274501 | G63: =IF(ISERROR(G62/G24),"-",(G62/G24)) -> 0.14329707 | H63: =IF(ISERROR(H62/H24),"-",(H62/H24)) -> -0.071407357 | J63: =IF(ISERROR(J62/J24),"-",(J62/J24)) -> 0.15373203 | K63: =IF(ISERROR(K62/K24),"-",(K62/K24)) -> 0.21344307 | M63: =IF(ISERROR(M62/M24),"-",(M62/M24)) -> 0.1589528 | N63: =IF(ISERROR(N62/N24),"-",(N62/N24)) -> 0.089086739 | P63: =IF(ISERROR(P62/P24),"-",(P62/P24)) -> 0.1747557 | S63: =IF(ISERROR(S62/S24),"-",(S62/S24)) -> 0.12589085 | V63: =IF(ISERROR(V62/V24),"-",(V62/V24)) -> 0.1066308 | Y63: =IF(ISERROR(Y62/Y24),"-",(Y62/Y24)) -> 0.11425282 | AB63: =IF(ISERROR(AB62/AB24),"-",(AB62/AB24)) -> 0.11010334 | AE63: =IF(ISERROR(AE62/AE24),"-",(AE62/AE24)) -> 0.100215 | AH63: =IF(ISERROR(AH62/AH24),"-",(AH62/AH24)) -> 0.15366884 | AK63: =IF(ISERROR(AK62/AK24),"-",(AK62/AK24)) -> 0.038938479 | AN63: =IF(ISERROR(AN62/AN24),"-",(AN62/AN24)) -> 0.12126151 | AO63: =IF(ISERROR(AO62/AO24),"-",(AO62/AO24)) -> 0.047973594 | AQ63: =AVERAGE(D63,G63,J63) -> 0.098196158 | AR63: =AVERAGE(E63,H63,K63) -> -0.013569765
C64: =SUM(D64,G64,J64,M64,P64,S64,V64,Y64,AB64,AE64,AH64,AK64) -> 0 | AN64: =SUM(D64:AK64) -> 0
A65: Depreciação | C65: =SUM(D65,G65,J65,M65,P65,S65,V65,Y65,AB65,AE65,AH65,AK65) -> 0 | D65: ='04 -Base Orçado 2026'!E126 -> 0 | E65: ='04 -Base Orçado 2026'!F126 -> 0 | G65: ='04 -Base Orçado 2026'!F126 -> 0 | J65: ='04 -Base Orçado 2026'!G126 -> 0 | M65: ='04 -Base Orçado 2026'!H126 -> 0 | P65: ='04 -Base Orçado 2026'!I126 -> 0 | S65: ='04 -Base Orçado 2026'!J126 -> 0 | V65: ='04 -Base Orçado 2026'!K126 -> 0 | Y65: ='04 -Base Orçado 2026'!L126 -> 0 | AB65: ='04 -Base Orçado 2026'!M126 -> 0 | AE65: ='04 -Base Orçado 2026'!N126 -> 0 | AH65: ='04 -Base Orçado 2026'!O126 -> 0 | AK65: ='04 -Base Orçado 2026'!P126 -> 0 | AN65: =SUM(D65:AK65) -> 0 | AO65: =SUM(E65,H65,K65,N65,Q65,T65,W65,Z65,AC65,AF65,AI65,AL65) -> 0 | AQ65: =AVERAGE(D65,G65,J65) -> 0 | AR65: =AVERAGE(E65,H65,K65) -> 0 | AT65: =IF(ISERROR(C65/C$24),0,(C65/C$24)) -> 0 | AV65: =IF(ISERROR(D65/D$24),0,(D65/D$24)) -> 0 | AW65: =IF(ISERROR(G65/G$24),0,(G65/G$24)) -> 0 | AX65: =IF(ISERROR(J65/J$24),0,(J65/J$24)) -> 0 | AY65: =IF(ISERROR(M65/M$24),0,(M65/M$24)) -> 0 | AZ65: =IF(ISERROR(P65/P$24),0,(P65/P$24)) -> 0 | BA65: =IF(ISERROR(S65/S$24),0,(S65/S$24)) -> 0 | BB65: =IF(ISERROR(V65/V$24),0,(V65/V$24)) -> 0 | BC65: =IF(ISERROR(Y65/Y$24),0,(Y65/Y$24)) -> 0 | BD65: =IF(ISERROR(AB65/AB$24),0,(AB65/AB$24)) -> 0 | BE65: =IF(ISERROR(AE65/AE$24),0,(AE65/AE$24)) -> 0 | BF65: =IF(ISERROR(AH65/AH$24),0,(AH65/AH$24)) -> 0 | BG65: =IF(ISERROR(AK65/AK$24),0,(AK65/AK$24)) -> 0
A66: Amortização | C66: =SUM(D66,G66,J66,M66,P66,S66,V66,Y66,AB66,AE66,AH66,AK66) -> 0 | D66: 0 | E66: ='04 -Base Orçado 2026'!F127 -> 0 | G66: 0 | J66: 0 | M66: 0 | P66: 0 | S66: 0 | V66: 0 | Y66: 0 | AB66: 0 | AE66: 0 | AH66: 0 | AK66: 0 | AN66: =SUM(D66:AK66) -> 0 | AO66: =SUM(E66,H66,K66,N66,Q66,T66,W66,Z66,AC66,AF66,AI66,AL66) -> 0 | AQ66: =AVERAGE(D66,G66,J66) -> 0 | AR66: =AVERAGE(E66,H66,K66) -> 0 | AT66: =IF(ISERROR(C66/C$24),0,(C66/C$24)) -> 0 | AV66: =IF(ISERROR(D66/D$24),0,(D66/D$24)) -> 0 | AW66: =IF(ISERROR(G66/G$24),0,(G66/G$24)) -> 0 | AX66: =IF(ISERROR(J66/J$24),0,(J66/J$24)) -> 0 | AY66: =IF(ISERROR(M66/M$24),0,(M66/M$24)) -> 0 | AZ66: =IF(ISERROR(P66/P$24),0,(P66/P$24)) -> 0 | BA66: =IF(ISERROR(S66/S$24),0,(S66/S$24)) -> 0 | BB66: =IF(ISERROR(V66/V$24),0,(V66/V$24)) -> 0 | BC66: =IF(ISERROR(Y66/Y$24),0,(Y66/Y$24)) -> 0 | BD66: =IF(ISERROR(AB66/AB$24),0,(AB66/AB$24)) -> 0 | BE66: =IF(ISERROR(AE66/AE$24),0,(AE66/AE$24)) -> 0 | BF66: =IF(ISERROR(AH66/AH$24),0,(AH66/AH$24)) -> 0 | BG66: =IF(ISERROR(AK66/AK$24),0,(AK66/AK$24)) -> 0
A67: EBIT | C67: =SUM(D67,G67,J67,M67,P67,S67,V67,Y67,AB67,AE67,AH67,AK67) -> 3446568.8 | D67: =D62+D65+D66 -> -3912.6425 | E67: =E62+E65+E66 -> -244670.3 | G67: =G62+G65+G66 -> 352619.03 | H67: =H62+H65+H66 -> -107619.97 | J67: =J62+J65+J66 -> 382481.25 | K67: =K62+K65+K66 -> 508765.52 | M67: =M62+M65+M66 -> 404443.36 | N67: =N62+N65+N66 -> 204568.6 | P67: =P62+P65+P66 -> 499770.49 | S67: =S62+S65+S66 -> 305271.29 | V67: =V62+V65+V66 -> 249515.47 | Y67: =Y62+Y65+Y66 -> 273471.48 | AB67: =AB62+AB65+AB66 -> 260295.32 | AE67: =AE62+AE65+AE66 -> 230166.44 | AH67: =AH62+AH65+AH66 -> 417208.87 | AK67: =AK62+AK65+AK66 -> 75238.451 | AN67: =SUM(D67,G67,J67,M67,P67,S67,V67,Y67,AB67,AE67,AH67,AK67) -> 3446568.8 | AO67: =SUM(E67,H67,K67,N67,Q67,T67,W67,Z67,AC67,AF67,AI67,AL67) -> 361043.84 | AQ67: =AVERAGE(D67,G67,J67) -> 243729.21 | AR67: =AVERAGE(E67,H67,K67) -> 52158.414 | AT67: =SUM(AT64:AT66) -> 0 | AV67: =SUM(AV64:AV66) -> 0 | AW67: =SUM(AW64:AW66) -> 0 | AX67: =SUM(AX64:AX66) -> 0 | AY67: =SUM(AY64:AY66) -> 0 | AZ67: =SUM(AZ64:AZ66) -> 0 | BA67: =SUM(BA64:BA66) -> 0 | BB67: =SUM(BB64:BB66) -> 0 | BC67: =SUM(BC64:BC66) -> 0 | ... BG67: =SUM(BG64:BG66) -> 0
A68: MARGEM EBIT | C68: =SUM(D68,G68,J68,M68,P68,S68,V68,Y68,AB68,AE68,AH68,AK68) -> 1.3779971 | D68: =IF(ISERROR(D67/D24),"-",(D67/D24)) -> -0.0024406215 | E68: =IF(ISERROR(E67/E24),"-",(E67/E24)) -> -0.18274501 | G68: =IF(ISERROR(G67/G24),"-",(G67/G24)) -> 0.14329707 | H68: =IF(ISERROR(H67/H24),"-",(H67/H24)) -> -0.071407357 | J68: =IF(ISERROR(J67/J24),"-",(J67/J24)) -> 0.15373203 | K68: =IF(ISERROR(K67/K24),"-",(K67/K24)) -> 0.21344307 | M68: =IF(ISERROR(M67/M24),"-",(M67/M24)) -> 0.1589528 | N68: =IF(ISERROR(N67/N24),"-",(N67/N24)) -> 0.089086739 | P68: =IF(ISERROR(P67/P24),"-",(P67/P24)) -> 0.1747557 | S68: =IF(ISERROR(S67/S24),"-",(S67/S24)) -> 0.12589085 | V68: =IF(ISERROR(V67/V24),"-",(V67/V24)) -> 0.1066308 | Y68: =IF(ISERROR(Y67/Y24),"-",(Y67/Y24)) -> 0.11425282 | AB68: =IF(ISERROR(AB67/AB24),"-",(AB67/AB24)) -> 0.11010334 | AE68: =IF(ISERROR(AE67/AE24),"-",(AE67/AE24)) -> 0.100215 | AH68: =IF(ISERROR(AH67/AH24),"-",(AH67/AH24)) -> 0.15366884 | AK68: =IF(ISERROR(AK67/AK24),"-",(AK67/AK24)) -> 0.038938479 | AN68: =IF(ISERROR(AN67/AN24),"-",(AN67/AN24)) -> 0.12126151 | AO68: =IF(ISERROR(AO67/AO24),"-",(AO67/AO24)) -> 0.047973594 | AQ68: =AVERAGE(D68,G68,J68) -> 0.098196158 | AR68: =AVERAGE(E68,H68,K68) -> -0.013569765
A69: Despesas Financeiras | C69: =SUM(D69,G69,J69,M69,P69,S69,V69,Y69,AB69,AE69,AH69,AK69) -> -215378.5 | D69: ='04 -Base Orçado 2026'!E130 -> -12151.528 | E69: ='Base Realizado'!D132 -> -2305.52 | G69: ='04 -Base Orçado 2026'!F130 -> -18652.18 | H69: ='Base Realizado'!F132 -> -776.06 | J69: ='04 -Base Orçado 2026'!G130 -> -18797.602 | K69: ='Base Realizado'!H132 -> -451 | M69: ='04 -Base Orçado 2026'!H130 -> -19286.378 | N69: ='Base Realizado'!N132 -> 0 | P69: ='04 -Base Orçado 2026'!I130 -> -21677.061 | S69: ='04 -Base Orçado 2026'!J130 -> -18380.315 | V69: ='04 -Base Orçado 2026'!K130 -> -17736.828 | Y69: ='04 -Base Orçado 2026'!L130 -> -18142.881 | AB69: ='04 -Base Orçado 2026'!M130 -> -17919.546 | AE69: ='04 -Base Orçado 2026'!N130 -> -17408.864 | AH69: ='04 -Base Orçado 2026'!O130 -> -20579.218 | AK69: ='04 -Base Orçado 2026'!P130 -> -14646.1 | AN69: =SUM(D69,G69,J69,M69,P69,S69,V69,Y69,AB69,AE69,AH69,AK69) -> -215378.5 | AO69: =SUM(E69,H69,K69,N69,Q69,T69,W69,Z69,AC69,AF69,AI69,AL69) -> -3532.58 | AQ69: =AVERAGE(D69,G69,J69) -> -16533.77 | AR69: =AVERAGE(E69,H69,K69) -> -1177.5267 | AT69: =IF(ISERROR(C69/C$24),0,(C69/C$24)) -> -0.007577717 | AV69: =IF(ISERROR(D69/D$24),0,(D69/D$24)) -> -0.0075798592 | AW69: =IF(ISERROR(G69/G$24),0,(G69/G$24)) -> -0.0075798592 | AX69: =IF(ISERROR(J69/J$24),0,(J69/J$24)) -> -0.007555386 | AY69: =IF(ISERROR(M69/M$24),0,(M69/M$24)) -> -0.0075798592 | AZ69: =IF(ISERROR(P69/P$24),0,(P69/P$24)) -> -0.0075798592 | BA69: =IF(ISERROR(S69/S$24),0,(S69/S$24)) -> -0.0075798592 | BB69: =IF(ISERROR(V69/V$24),0,(V69/V$24)) -> -0.0075798592 | BC69: =IF(ISERROR(Y69/Y$24),0,(Y69/Y$24)) -> -0.0075798592 | BD69: =IF(ISERROR(AB69/AB$24),0,(AB69/AB$24)) -> -0.0075798592 | BE69: =IF(ISERROR(AE69/AE$24),0,(AE69/AE$24)) -> -0.0075798592 | BF69: =IF(ISERROR(AH69/AH$24),0,(AH69/AH$24)) -> -0.0075798592 | BG69: =IF(ISERROR(AK69/AK$24),0,(AK69/AK$24)) -> -0.0075798592
A70: Rec/Desp não Operacionais | C70: =SUM(D70,G70,J70,M70,P70,S70,V70,Y70,AB70,AE70,AH70,AK70) -> 0 | D70: 0 | G70: 0 | J70: 0 | M70: 0 | P70: 0 | S70: 0 | V70: 0 | Y70: 0 | AB70: 0 | AE70: 0 | AH70: 0 | AK70: 0 | AN70: =SUM(D70:AK70) -> 0 | AQ70: =AVERAGE(D70,G70,J70) -> 0 | AR70: =AVERAGE(E70,H70,K70) -> #DIV/0! | AT70: =IF(ISERROR(C70/C$24),0,(C70/C$24)) -> 0 | AV70: =IF(ISERROR(D70/D$24),0,(D70/D$24)) -> 0 | AW70: =IF(ISERROR(G70/G$24),0,(G70/G$24)) -> 0 | AX70: =IF(ISERROR(J70/J$24),0,(J70/J$24)) -> 0 | AY70: =IF(ISERROR(M70/M$24),0,(M70/M$24)) -> 0 | AZ70: =IF(ISERROR(P70/P$24),0,(P70/P$24)) -> 0 | BA70: =IF(ISERROR(S70/S$24),0,(S70/S$24)) -> 0 | BB70: =IF(ISERROR(V70/V$24),0,(V70/V$24)) -> 0 | BC70: =IF(ISERROR(Y70/Y$24),0,(Y70/Y$24)) -> 0 | BD70: =IF(ISERROR(AB70/AB$24),0,(AB70/AB$24)) -> 0 | BE70: =IF(ISERROR(AE70/AE$24),0,(AE70/AE$24)) -> 0 | BF70: =IF(ISERROR(AH70/AH$24),0,(AH70/AH$24)) -> 0 | BG70: =IF(ISERROR(AK70/AK$24),0,(AK70/AK$24)) -> 0
A71: Impostos (IRPJ/CSLL) | C71: =SUM(D71,G71,J71,M71,P71,S71,V71,Y71,AB71,AE71,AH71,AK71) -> 0 | AN71: =SUM(D71,G71,J71,M71,P71,S71,V71,Y71,AB71,AE71,AH71,AK71) -> 0 | AO71: =SUM(E71,H71,K71,N71,Q71,T71,W71,Z71,AC71,AF71,AI71,AL71) -> 0 | AV71: =IF(ISERROR(D71/D$24),0,(D71/D$24)) -> 0 | AW71: =IF(ISERROR(G71/G$24),0,(G71/G$24)) -> 0 | AX71: =IF(ISERROR(J71/J$24),0,(J71/J$24)) -> 0 | AY71: =IF(ISERROR(M71/M$24),0,(M71/M$24)) -> 0 | AZ71: =IF(ISERROR(P71/P$24),0,(P71/P$24)) -> 0 | BA71: =IF(ISERROR(S71/S$24),0,(S71/S$24)) -> 0 | BB71: =IF(ISERROR(V71/V$24),0,(V71/V$24)) -> 0 | BC71: =IF(ISERROR(Y71/Y$24),0,(Y71/Y$24)) -> 0 | BD71: =IF(ISERROR(AB71/AB$24),0,(AB71/AB$24)) -> 0 | BE71: =IF(ISERROR(AE71/AE$24),0,(AE71/AE$24)) -> 0 | BF71: =IF(ISERROR(AH71/AH$24),0,(AH71/AH$24)) -> 0 | BG71: =IF(ISERROR(AK71/AK$24),0,(AK71/AK$24)) -> 0
A72: Resultado Operacional | C72: =SUM(D72,G72,J72,M72,P72,S72,V72,Y72,AB72,AE72,AH72,AK72) -> 3231190.3 | D72: =D67+SUM(D69:D71) -> -16064.17 | E72: =E67+SUM(E69:E71) -> -246975.82 | G72: =G67+SUM(G69:G71) -> 333966.85 | H72: =H67+SUM(H69:H71) -> -108396.03 | J72: =J67+SUM(J69:J71) -> 363683.65 | K72: =K67+SUM(K69:K71) -> 508314.52 | M72: =M67+SUM(M69:M71) -> 385156.98 | N72: =N67+SUM(N69:N71) -> 204568.6 | P72: =P67+SUM(P69:P71) -> 478093.43 | S72: =S67+SUM(S69:S71) -> 286890.97 | V72: =V67+SUM(V69:V71) -> 231778.64 | Y72: =Y67+SUM(Y69:Y71) -> 255328.6 | AB72: =AB67+SUM(AB69:AB71) -> 242375.77 | AE72: =AE67+SUM(AE69:AE71) -> 212757.58 | AH72: =AH67+SUM(AH69:AH71) -> 396629.65 | AK72: =AK67+SUM(AK69:AK71) -> 60592.351 | AN72: =SUM(D72,G72,J72,M72,P72,S72,V72,Y72,AB72,AE72,AH72,AK72) -> 3231190.3 | AO72: =SUM(E72,H72,K72,N72,Q72,T72,W72,Z72,AC72,AF72,AI72,AL72) -> 357511.26 | AQ72: =AVERAGE(D72,G72,J72) -> 227195.44 | AR72: =AVERAGE(E72,H72,K72) -> 50980.888 | AT72: =IF(ISERROR(C72/C$24),0,(C72/C$24)) -> 0.1136838 | AV72: =IF(ISERROR(D72/D$24),0,(D72/D$24)) -> -0.010020481 | AW72: =IF(ISERROR(G72/G$24),0,(G72/G$24)) -> 0.13571721 | AX72: =IF(ISERROR(J72/J$24),0,(J72/J$24)) -> 0.14617664 | AY72: =IF(ISERROR(M72/M$24),0,(M72/M$24)) -> 0.15137294 | AZ72: =IF(ISERROR(P72/P$24),0,(P72/P$24)) -> 0.16717584 | BA72: =IF(ISERROR(S72/S$24),0,(S72/S$24)) -> 0.11831099 | BB72: =IF(ISERROR(V72/V$24),0,(V72/V$24)) -> 0.099050939 | BC72: =IF(ISERROR(Y72/Y$24),0,(Y72/Y$24)) -> 0.10667296 | BD72: =IF(ISERROR(AB72/AB$24),0,(AB72/AB$24)) -> 0.10252348 | BE72: =IF(ISERROR(AE72/AE$24),0,(AE72/AE$24)) -> 0.092635137 | BF72: =IF(ISERROR(AH72/AH$24),0,(AH72/AH$24)) -> 0.14608898 | BG72: =IF(ISERROR(AK72/AK$24),0,(AK72/AK$24)) -> 0.031358619
A73: MARGEM LÍQUIDA | C73: =SUM(D73,G73,J73,M73,P73,S73,V73,Y73,AB73,AE73,AH73,AK73) -> 1.2870633 | D73: =IF(ISERROR(D72/D24),"-",(D72/D24)) -> -0.010020481 | E73: =IF(ISERROR(E72/E24),"-",(E72/E24)) -> -0.18446701 | G73: =IF(ISERROR(G72/G24),"-",(G72/G24)) -> 0.13571721 | H73: =IF(ISERROR(H72/H24),"-",(H72/H24)) -> -0.071922283 | J73: =IF(ISERROR(J72/J24),"-",(J72/J24)) -> 0.14617664 | K73: =IF(ISERROR(K72/K24),"-",(K72/K24)) -> 0.21325386 | M73: =IF(ISERROR(M72/M24),"-",(M72/M24)) -> 0.15137294 | N73: =IF(ISERROR(N72/N24),"-",(N72/N24)) -> 0.089086739 | P73: =IF(ISERROR(P72/P24),"-",(P72/P24)) -> 0.16717584 | S73: =IF(ISERROR(S72/S24),"-",(S72/S24)) -> 0.11831099 | V73: =IF(ISERROR(V72/V24),"-",(V72/V24)) -> 0.099050939 | Y73: =IF(ISERROR(Y72/Y24),"-",(Y72/Y24)) -> 0.10667296 | AB73: =IF(ISERROR(AB72/AB24),"-",(AB72/AB24)) -> 0.10252348 | AE73: =IF(ISERROR(AE72/AE24),"-",(AE72/AE24)) -> 0.092635137 | AH73: =IF(ISERROR(AH72/AH24),"-",(AH72/AH24)) -> 0.14608898 | AK73: =IF(ISERROR(AK72/AK24),"-",(AK72/AK24)) -> 0.031358619 | AN73: =IF(ISERROR(AN72/AN24),"-",(AN72/AN24)) -> 0.1136838 | AO73: =IF(ISERROR(AO72/AO24),"-",(AO72/AO24)) -> 0.047504204 | AQ73: =AVERAGE(D73,G73,J73) -> 0.090624456 | AR73: =AVERAGE(E73,H73,K73) -> -0.014378477
A87: CHECK
A96: Faturamento Bruto | C96: =C10 -> 30776390 | D96: =D10 -> 1735932.5 | G96: =G10 -> 2664597.1 | J96: =J10 -> 2693404.7 | M96: =M10 -> 2755196.8 | P96: =P10 -> 3096723 | S96: =S10 -> 2625759.2 | V96: =V10 -> 2533832.6 | Y96: =Y10 -> 2591840.1 | AB96: =AB10 -> 2559935.1 | AE96: =AE10 -> 2486980.5 | AH96: =AH10 -> 2939888.3 | AK96: =AK10 -> 2092300.1
A97: Receita Líquida | C97: =C24 -> 28422611 | D97: =D24 -> 1603133.7 | G97: =G24 -> 2460755.4 | J97: =J24 -> 2487973.7 | M97: =M24 -> 2544424.3 | P97: =P24 -> 2859823.6 | S97: =S24 -> 2424888.6 | V97: =V24 -> 2339994.4 | Y97: =Y24 -> 2393564.4 | AB97: =AB24 -> 2364100.1 | AE97: =AE24 -> 2296726.5 | AH97: =AH24 -> 2714986.9 | AK97: =AK24 -> 1932239.1
A98: DESPESAS OPERACIONAIS | C98: =C26+C56+C65+C66+C69+C70+C71 -> -25191420 | D98: =D26+D56+D65+D66+D69+D70+D71 -> -1619197.9 | G98: =G26+G56+G65+G66+G69+G70+G71 -> -2126788.6 | J98: =J26+J56+J65+J66+J69+J70+J71 -> -2124290.1 | M98: =M26+M56+M65+M66+M69+M70+M71 -> -2159267.3 | P98: =P26+P56+P65+P66+P69+P70+P71 -> -2381730.2 | S98: =S26+S56+S65+S66+S69+S70+S71 -> -2137997.7 | V98: =V26+V56+V65+V66+V69+V70+V71 -> -2108215.8 | Y98: =Y26+Y56+Y65+Y66+Y69+Y70+Y71 -> -2138235.7 | AB98: =AB26+AB56+AB65+AB66+AB69+AB70+AB71 -> -2121724.3 | AE98: =AE26+AE56+AE65+AE66+AE69+AE70+AE71 -> -2083969 | AH98: =AH26+AH56+AH65+AH66+AH69+AH70+AH71 -> -2318357.2 | AK98: =AK26+AK56+AK65+AK66+AK69+AK70+AK71 -> -1871646.8
A99: EBITDA | C99: =C62 -> 3446568.8 | D99: =D62 -> -3912.6425 | G99: =G62 -> 352619.03 | J99: =J62 -> 382481.25 | M99: =M62 -> 404443.36 | P99: =P62 -> 499770.49 | S99: =S62 -> 305271.29 | V99: =V62 -> 249515.47 | Y99: =Y62 -> 273471.48 | AB99: =AB62 -> 260295.32 | AE99: =AE62 -> 230166.44 | AH99: =AH62 -> 417208.87 | AK99: =AK62 -> 75238.451
A100: Margem EBITDA | C100: =IF(ISERROR(C99/C97),0,(C99/C97)) -> 0.12126151 | D100: =IF(ISERROR(D99/D97),0,(D99/D97)) -> -0.0024406215 | G100: =IF(ISERROR(G99/G97),0,(G99/G97)) -> 0.14329707 | J100: =IF(ISERROR(J99/J97),0,(J99/J97)) -> 0.15373203 | M100: =IF(ISERROR(M99/M97),0,(M99/M97)) -> 0.1589528 | P100: =IF(ISERROR(P99/P97),0,(P99/P97)) -> 0.1747557 | S100: =IF(ISERROR(S99/S97),0,(S99/S97)) -> 0.12589085 | V100: =IF(ISERROR(V99/V97),0,(V99/V97)) -> 0.1066308 | Y100: =IF(ISERROR(Y99/Y97),0,(Y99/Y97)) -> 0.11425282 | AB100: =IF(ISERROR(AB99/AB97),0,(AB99/AB97)) -> 0.11010334 | AE100: =IF(ISERROR(AE99/AE97),0,(AE99/AE97)) -> 0.100215 | AH100: =IF(ISERROR(AH99/AH97),0,(AH99/AH97)) -> 0.15366884 | AK100: =IF(ISERROR(AK99/AK97),0,(AK99/AK97)) -> 0.038938479
A101: Lucro Líquido | C101: =C97+C98 -> 3231190.3 | D101: =D97+D98 -> -16064.17 | G101: =G97+G98 -> 333966.85 | J101: =J97+J98 -> 363683.65 | M101: =M97+M98 -> 385156.98 | P101: =P97+P98 -> 478093.43 | S101: =S97+S98 -> 286890.97 | V101: =V97+V98 -> 231778.64 | Y101: =Y97+Y98 -> 255328.6 | AB101: =AB97+AB98 -> 242375.77 | AE101: =AE97+AE98 -> 212757.58 | AH101: =AH97+AH98 -> 396629.65 | AK101: =AK97+AK98 -> 60592.351
A102: Margem LL | C102: =IF(ISERROR(C101/C97),0,(C101/C97)) -> 0.1136838 | D102: =IF(ISERROR(D101/D97),0,(D101/D97)) -> -0.010020481 | G102: =IF(ISERROR(G101/G97),0,(G101/G97)) -> 0.13571721 | J102: =IF(ISERROR(J101/J97),0,(J101/J97)) -> 0.14617664 | M102: =IF(ISERROR(M101/M97),0,(M101/M97)) -> 0.15137294 | P102: =IF(ISERROR(P101/P97),0,(P101/P97)) -> 0.16717584 | S102: =IF(ISERROR(S101/S97),0,(S101/S97)) -> 0.11831099 | V102: =IF(ISERROR(V101/V97),0,(V101/V97)) -> 0.099050939 | Y102: =IF(ISERROR(Y101/Y97),0,(Y101/Y97)) -> 0.10667296 | AB102: =IF(ISERROR(AB101/AB97),0,(AB101/AB97)) -> 0.10252348 | AE102: =IF(ISERROR(AE101/AE97),0,(AE101/AE97)) -> 0.092635137 | AH102: =IF(ISERROR(AH101/AH97),0,(AH101/AH97)) -> 0.14608898 | AK102: =IF(ISERROR(AK101/AK97),0,(AK101/AK97)) -> 0.031358619
J105: =J72-J101 -> 0

Sheet 04 -Base Orçado 2026
E1: BD26 - BASE DE DADOS
B5: DESCRIÇÃO | C5: CONTA | E5: JAN 2026 | F5: FEV 2026 | G5: MAR 2026 | H5: ABR 2026 | I5: MAIO 2026 | J5: JUN 2026 | K5: JUL 2026 | L5: AGO 2026 | M5: SET 2026 | N5: OUT 2026 | O5: NOV 2026 | P5: DEZ 2026 | R5: TOTAL
B7: CLIENTES | C7: x.x.x.xx.xxxxx | E7: ='Base Faturamento'!K6 -> 5786.4418 | F7: ='Base Faturamento'!K7 -> 7860.1684 | G7: ='Base Faturamento'!K8 -> 7921.4504 | H7: ='Base Faturamento'!K9 -> 8127.4243 | I7: ='Base Faturamento'!K10 -> 9134.876 | J7: ='Base Faturamento'!K11 -> 7745.6024 | K7: ='Base Faturamento'!K12 -> 7474.4325 | L7: ='Base Faturamento'!K13 -> 7645.5461 | M7: ='Base Faturamento'!K14 -> 7551.431 | N7: ='Base Faturamento'!K15 -> 7336.2258 | O7: ='Base Faturamento'!K16 -> 8672.2369 | P7: ='Base Faturamento'!K17 -> 6171.9766 | R7: =SUM(E7:P7) -> 91427.812
B8: TICKET MEDIO | C8: x.x.x.xx.xxxxx | E8: =E10/E7 -> 300 | F8: =F10/F7 -> 300 | G8: =G10/G7 -> 300 | H8: =H10/H7 -> 300 | I8: =I10/I7 -> 300 | J8: =J10/J7 -> 300 | K8: =K10/K7 -> 300 | L8: =L10/L7 -> 300 | ... P8: =P10/P7 -> 300 | R8: =R11/R7 -> 336.5317
B10: Rec.Venda no Merc.Int.de Prod.Fabr.Próp. | C10: 3.1.1.01.00004 | E10: ='Base Faturamento'!I6 -> 1735932.5 | F10: ='Base Faturamento'!I7 -> 2358050.5 | G10: ='Base Faturamento'!I8 -> 2376435.1 | H10: ='Base Faturamento'!I9 -> 2438227.3 | I10: ='Base Faturamento'!I10 -> 2740462.8 | J10: ='Base Faturamento'!I11 -> 2323680.7 | K10: ='Base Faturamento'!I12 -> 2242329.8 | L10: ='Base Faturamento'!I13 -> 2293663.8 | M10: ='Base Faturamento'!I14 -> 2265429.3 | N10: ='Base Faturamento'!I15 -> 2200867.7 | O10: ='Base Faturamento'!I16 -> 2601671.1 | P10: ='Base Faturamento'!I17 -> 1851593 | R10: =SUM(E10:P10) -> 27428344
B11: FATURAMENTO Liquido de Gorjeta | E11: =SUM(E13:E19)-E13 -> 1735932.5 | F11: =SUM(F13:F19) -> 2664597.1 | G11: =SUM(G13:G19) -> 2685371.7 | H11: =SUM(H13:H19) -> 2755196.8 | I11: =SUM(I13:I19) -> 3096723 | J11: =SUM(J13:J19) -> 2625759.2 | K11: =SUM(K13:K19) -> 2533832.6 | L11: =SUM(L13:L19) -> 2591840.1 | M11: =SUM(M13:M19) -> 2559935.1 | ... P11: =SUM(P13:P19) -> 2092300.1 | R11: =SUM(E11:P11) -> 30768357 | T11: =SUM(T14:T19) -> 1
E12: 1735932.5 | F12: 2358050.5 | G12: 2376435.1 | H12: 2438227.3 | I12: 2740462.8 | J12: 2323680.7 | K12: 2242329.8 | L12: 2293663.8 | M12: 2265429.3 | N12: 2200867.7 | O12: 2601671.1 | P12: 1851593
B13: Gorjetas Recebidas | E13: =E12*13% -> 225671.23 | F13: =F12*13% -> 306546.57 | G13: =G12*13% -> 308936.56 | H13: =H12*13% -> 316969.55 | I13: =I12*13% -> 356260.16 | J13: =J12*13% -> 302078.5 | K13: =K12*13% -> 291502.87 | L13: =L12*13% -> 298176.3 | ... P13: =P12*13% -> 240707.09 | R13: =SUM(E13:P13) -> 3565684.7
B14: Dinheiro | C14: x.x.x.xx.xxxxx | E14: =E$10*$T14 -> 34718.651 | F14: =F$10*$T14 -> 47161.01 | G14: =G$10*$T14 -> 47528.702 | H14: =H$10*$T14 -> 48764.546 | I14: =I$10*$T14 -> 54809.256 | J14: =J$10*$T14 -> 46473.615 | K14: =K$10*$T14 -> 44846.595 | L14: =L$10*$T14 -> 45873.276 | ... P14: =P$10*$T14 -> 37031.86 | R14: =SUM(E14:P14) -> 548566.87 | T14: 0.02
B15: Cartão de Débito | C15: x.x.x.xx.xxxxx | E15: =E$10*$T15 -> 121515.28 | F15: =F$10*$T15 -> 165063.54 | G15: =G$10*$T15 -> 166350.46 | H15: =H$10*$T15 -> 170675.91 | I15: =I$10*$T15 -> 191832.4 | J15: =J$10*$T15 -> 162657.65 | K15: =K$10*$T15 -> 156963.08 | L15: =L$10*$T15 -> 160556.47 | ... P15: =P$10*$T15 -> 129611.51 | R15: =SUM(E15:P15) -> 1919984.1 | T15: 0.07
B16: Cartão de Crédito | C16: x.x.x.xx.xxxxx | E16: =E$10*$T16 -> 1138771.7 | F16: =F$10*$T16 -> 1546881.1 | G16: =G$10*$T16 -> 1558941.4 | H16: =H$10*$T16 -> 1599477.1 | I16: =I$10*$T16 -> 1797743.6 | J16: =J$10*$T16 -> 1524334.6 | K16: =K$10*$T16 -> 1470968.3 | L16: =L$10*$T16 -> 1504643.5 | ... P16: =P$10*$T16 -> 1214645 | R16: =SUM(E16:P16) -> 17992993 | T16: 0.656
B17: Evento Faturado | C17: x.x.x.xx.xxxxx | E17: =E$10*$T17 -> 173593.25 | F17: =F$10*$T17 -> 235805.05 | G17: =G$10*$T17 -> 237643.51 | H17: =H$10*$T17 -> 243822.73 | I17: =I$10*$T17 -> 274046.28 | J17: =J$10*$T17 -> 232368.07 | K17: =K$10*$T17 -> 224232.98 | L17: =L$10*$T17 -> 229366.38 | ... P17: =P$10*$T17 -> 185159.3 | R17: =SUM(E17:P17) -> 2742834.4 | T17: 0.1
B18: Delivery | C18: x.x.x.xx.xxxxx | E18: =E$10*$T18 -> 260389.88 | F18: =F$10*$T18 -> 353707.58 | G18: =G$10*$T18 -> 356465.27 | H18: =H$10*$T18 -> 365734.09 | I18: =I$10*$T18 -> 411069.42 | J18: =J$10*$T18 -> 348552.11 | K18: =K$10*$T18 -> 336349.46 | L18: =L$10*$T18 -> 344049.57 | ... P18: =P$10*$T18 -> 277738.95 | R18: =SUM(E18:P18) -> 4114251.5 | T18: 0.15
B19: Voucher | C19: x.x.x.xx.xxxxx | E19: =E$10*$T19 -> 6943.7302 | F19: =F$10*$T19 -> 9432.2021 | G19: =G$10*$T19 -> 9505.7404 | H19: =H$10*$T19 -> 9752.9091 | I19: =I$10*$T19 -> 10961.851 | J19: =J$10*$T19 -> 9294.7229 | K19: =K$10*$T19 -> 8969.319 | L19: =L$10*$T19 -> 9174.6553 | ... P19: =P$10*$T19 -> 7406.3719 | R19: =SUM(E19:P19) -> 109713.37 | T19: 0.004
B21: IMPOSTOS | E21: =SUM(E22:E29) -> -184265.56 | F21: =SUM(F22:F29) -> -276922.01 | G21: =SUM(G22:G29) -> -279096.63 | H21: =SUM(H22:H29) -> -286405.71 | I21: =SUM(I22:I29) -> -322155.64 | J21: =SUM(J22:J29) -> -272856.58 | K21: =SUM(K22:K29) -> -263233.98 | L21: =SUM(L22:L29) -> -269306.03 | ... P21: =SUM(P22:P29) -> -217015.68 | R21: =SUM(E21:P21) -> -3201292.4 | T21: %
B22: (-) ICMS | C22: 3.1.1.02.00002 | E22: =-(E11*$T$22) -> -69437.302 | F22: =-(F11*$T$22) -> -106583.88 | G22: =-(G11*$T$22) -> -107414.87 | H22: =-(H11*$T$22) -> -110207.87 | I22: =-(I11*$T$22) -> -123868.92 | J22: =-(J11*$T$22) -> -105030.37 | K22: =-(K11*$T$22) -> -101353.3 | L22: =-(L11*$T$22) -> -103673.6 | ... P22: =-(P11*$T$22) -> -83692.003 | R22: =SUM(E22:P22) -> -1230734.3 | T22: 0.04
B23: (-) Cofins | C23: 3.1.1.02.00003 | E23: =-(E11*$T$23) -> -52077.976 | F23: =-(F11*$T$23) -> -79937.913 | G23: =-(G11*$T$23) -> -80561.15 | H23: =-(H11*$T$23) -> -82655.905 | I23: =-(I11*$T$23) -> -92901.689 | J23: =-(J11*$T$23) -> -78772.777 | K23: =-(K11*$T$23) -> -76014.979 | L23: =-(L11*$T$23) -> -77755.204 | ... P23: =-(P11*$T$23) -> -62769.002 | R23: =SUM(E23:P23) -> -923050.71 | T23: 0.03
B24: (-) PIS/Pasep | C24: 3.1.1.02.00004 | E24: =-E11*$T$24 -> -11283.562 | F24: =-F11*$T$24 -> -17319.881 | G24: =-G11*$T$24 -> -17454.916 | H24: =-H11*$T$24 -> -17908.779 | I24: =-I11*$T$24 -> -20128.699 | J24: =-J11*$T$24 -> -17067.435 | K24: =-K11*$T$24 -> -16469.912 | L24: =-L11*$T$24 -> -16846.961 | ... P24: =-P11*$T$24 -> -13599.95 | R24: =SUM(E24:P24) -> -199994.32 | T24: 0.0065
B25: (-) ICMS Diferencial Aliquota Simples | C25: 5.4.1.03.00035 | E25: =-E11*$T$25 -> 0 | F25: =-F11*$T$25 -> 0 | G25: =-G11*$T$25 -> 0 | H25: =-H11*$T$25 -> 0 | I25: =-I11*$T$25 -> 0 | J25: =-J11*$T$25 -> 0 | K25: =-K11*$T$25 -> 0 | L25: =-L11*$T$25 -> 0 | ... P25: =-P11*$T$25 -> 0 | R25: =SUM(E25:P25) -> 0 | T25: 0
B26: IRPJ | C26: 6.1.1.01.00001 | E26: =-((E10*$T$26)*$U$26)-E158 -> -32718.651 | F26: =-((F10*$T$26)*$U$26)-F158 -> -47613.383 | G26: =-((G10*$T$26)*$U$26)-G158 -> -48000.195 | H26: =-((H10*$T$26)*$U$26)-H158 -> -49300.302 | I26: =-((I10*$T$26)*$U$26)-I158 -> -55659.337 | J26: =-((J10*$T$26)*$U$26)-J158 -> -46890.243 | K26: =-((K10*$T$26)*$U$26)-K158 -> -45178.618 | L26: =-((L10*$T$26)*$U$26)-L158 -> -46258.687 | ... P26: =-((P10*$T$26)*$U$26)-P158 -> -36957.516 | R26: =SUM(E26:P26) -> -551286.98 | T26: 0.08 | U26: 0.15
B27: CSSL | C27: 6.1.1.01.00002 | E27: =-(E10*$T$27)*$U$27 -> -18748.071 | F27: =-(F10*$T$27)*$U$27 -> -25466.946 | G27: =-(G10*$T$27)*$U$27 -> -25665.499 | H27: =-(H10*$T$27)*$U$27 -> -26332.855 | I27: =-(I10*$T$27)*$U$27 -> -29596.998 | J27: =-(J10*$T$27)*$U$27 -> -25095.752 | K27: =-(K10*$T$27)*$U$27 -> -24217.161 | L27: =-(L10*$T$27)*$U$27 -> -24771.569 | ... P27: =-(P10*$T$27)*$U$27 -> -19997.204 | R27: =SUM(E27:P27) -> -296226.11 | T27: 0.12 | U27: 0.09
B28: IRPJ | C28: 4.1.2.04.00002 | E28: =-E15*$T$25 -> 0 | F28: =-F15*$T$25 -> 0 | G28: =-G15*$T$25 -> 0 | H28: =-H15*$T$25 -> 0 | I28: =-I15*$T$25 -> 0 | J28: =-J15*$T$25 -> 0 | K28: =-K15*$T$25 -> 0 | L28: =-L15*$T$25 -> 0 | ... P28: =-P15*$T$25 -> 0 | R28: =SUM(E28:P28) -> 0 | T28: 0
B29: CSLL | C29: 4.1.2.04.00001 | E29: 0 | F29: 0 | G29: 0 | H29: 0 | I29: 0 | J29: 0 | K29: 0 | L29: 0 | M29: 0 | N29: 0 | O29: 0 | P29: 0 | R29: =SUM(E29:P29) -> 0 | T29: 0
B31: CUSTOS DOS PRODUTOS VENDIDOS | E31: =SUM(E32:E45) -> -513002.79 | F31: =SUM(F32:F45) -> -787441.73 | G31: =SUM(G32:G45) -> -793581.04 | H31: =SUM(H32:H45) -> -814215.77 | I31: =SUM(I32:I45) -> -915143.57 | J31: =SUM(J32:J45) -> -775964.37 | K31: =SUM(K32:K45) -> -748798.22 | L31: =SUM(L32:L45) -> -765940.59 | ... P31: =SUM(P32:P45) -> -618316.52 | R31: =SUM(R32:R45) -> -9092664.9 | T31: =SUM(T32:T45) -> 1 | U31: 1 | V31: =T31-U31 -> 0
B32: Carnes e Aves | C32: 5.4.1.01.00002 | E32: =-E$49*$T32 -> -256501.39 | F32: =-F$49*$T32 -> -393720.87 | G32: =-G$49*$T32 -> -396790.52 | H32: =-H$49*$T32 -> -407107.88 | I32: =-I$49*$T32 -> -457571.78 | J32: =-J$49*$T32 -> -387982.18 | K32: =-K$49*$T32 -> -374399.11 | L32: =-L$49*$T32 -> -382970.3 | ... P32: =-P$49*$T32 -> -309158.26 | R32: =SUM(E32:P32) -> -4546332.4 | T32: 0.5
B33: Pescados | C33: 5.4.1.01.00003 | E33: =-E$49*$T33 -> -25650.139 | F33: =-F$49*$T33 -> -39372.087 | G33: =-G$49*$T33 -> -39679.052 | H33: =-H$49*$T33 -> -40710.788 | I33: =-I$49*$T33 -> -45757.178 | J33: =-J$49*$T33 -> -38798.218 | K33: =-K$49*$T33 -> -37439.911 | L33: =-L$49*$T33 -> -38297.03 | ... P33: =-P$49*$T33 -> -30915.826 | R33: =SUM(E33:P33) -> -454633.24 | T33: 0.05
B34: Vinhos/Espumantes | C34: 5.4.1.01.00006 | E34: =-E$49*$T34 -> -76950.418 | F34: =-F$49*$T34 -> -118116.26 | G34: =-G$49*$T34 -> -119037.16 | H34: =-H$49*$T34 -> -122132.37 | I34: =-I$49*$T34 -> -137271.53 | J34: =-J$49*$T34 -> -116394.66 | K34: =-K$49*$T34 -> -112319.73 | L34: =-L$49*$T34 -> -114891.09 | ... P34: =-P$49*$T34 -> -92747.477 | R34: =SUM(E34:P34) -> -1363899.7 | T34: 0.15
B35: Bebidas Alcoólicas | C35: 5.4.1.01.00007 | E35: =-E$49*$T35 -> -25650.139 | F35: =-F$49*$T35 -> -39372.087 | G35: =-G$49*$T35 -> -39679.052 | H35: =-H$49*$T35 -> -40710.788 | I35: =-I$49*$T35 -> -45757.178 | J35: =-J$49*$T35 -> -38798.218 | K35: =-K$49*$T35 -> -37439.911 | L35: =-L$49*$T35 -> -38297.03 | ... P35: =-P$49*$T35 -> -30915.826 | R35: =SUM(E35:P35) -> -454633.24 | T35: 0.05
B36: Bebidas não Alcoolicas | C36: 5.4.1.01.00008 | E36: =-E$49*$T36 -> -20520.111 | F36: =-F$49*$T36 -> -31497.669 | G36: =-G$49*$T36 -> -31743.241 | H36: =-H$49*$T36 -> -32568.631 | I36: =-I$49*$T36 -> -36605.743 | J36: =-J$49*$T36 -> -31038.575 | K36: =-K$49*$T36 -> -29951.929 | L36: =-L$49*$T36 -> -30637.624 | ... P36: =-P$49*$T36 -> -24732.661 | R36: =SUM(E36:P36) -> -363706.6 | T36: 0.04
B37: Hortifruti | C37: 5.4.1.01.00009 | E37: =-E$49*$T37 -> -35910.195 | F37: =-F$49*$T37 -> -55120.921 | G37: =-G$49*$T37 -> -55550.673 | H37: =-H$49*$T37 -> -56995.104 | I37: =-I$49*$T37 -> -64060.05 | J37: =-J$49*$T37 -> -54317.506 | K37: =-K$49*$T37 -> -52415.875 | L37: =-L$49*$T37 -> -53615.841 | ... P37: =-P$49*$T37 -> -43282.156 | R37: =SUM(E37:P37) -> -636486.54 | T37: 0.07
B38: Paes, Massas e Salgados | C38: 5.4.1.01.00010 | E38: =-E$49*$T38 -> -20520.111 | F38: =-F$49*$T38 -> -31497.669 | G38: =-G$49*$T38 -> -31743.241 | H38: =-H$49*$T38 -> -32568.631 | I38: =-I$49*$T38 -> -36605.743 | J38: =-J$49*$T38 -> -31038.575 | K38: =-K$49*$T38 -> -29951.929 | L38: =-L$49*$T38 -> -30637.624 | ... P38: =-P$49*$T38 -> -24732.661 | R38: =SUM(E38:P38) -> -363706.6 | T38: 0.04
B39: Secos - Mercearia | C39: 5.4.1.01.00011 | E39: =-E$49*$T39 -> -25650.139 | F39: =-F$49*$T39 -> -39372.087 | G39: =-G$49*$T39 -> -39679.052 | H39: =-H$49*$T39 -> -40710.788 | I39: =-I$49*$T39 -> -45757.178 | J39: =-J$49*$T39 -> -38798.218 | K39: =-K$49*$T39 -> -37439.911 | L39: =-L$49*$T39 -> -38297.03 | ... P39: =-P$49*$T39 -> -30915.826 | R39: =SUM(E39:P39) -> -454633.24 | T39: 0.05
B40: Enlatados e Conservas | C40: 5.4.1.01.00012 | E40: =-E$49*$T40 -> -12312.067 | F40: =-F$49*$T40 -> -18898.602 | G40: =-G$49*$T40 -> -19045.945 | H40: =-H$49*$T40 -> -19541.178 | I40: =-I$49*$T40 -> -21963.446 | J40: =-J$49*$T40 -> -18623.145 | K40: =-K$49*$T40 -> -17971.157 | L40: =-L$49*$T40 -> -18382.574 | ... P40: =-P$49*$T40 -> -14839.596 | R40: =SUM(E40:P40) -> -218223.96 | T40: 0.024
B41: Carvão | C41: 5.4.1.01.00013 | E41: =-E$49*$T41 -> -12825.07 | F41: =-F$49*$T41 -> -19686.043 | G41: =-G$49*$T41 -> -19839.526 | H41: =-H$49*$T41 -> -20355.394 | I41: =-I$49*$T41 -> -22878.589 | J41: =-J$49*$T41 -> -19399.109 | K41: =-K$49*$T41 -> -18719.955 | L41: =-L$49*$T41 -> -19148.515 | ... P41: =-P$49*$T41 -> -15457.913 | R41: =SUM(E41:P41) -> -227316.62 | T41: 0.025
B42: Gelo | C42: 5.4.1.01.00015 | E42: =-E$49*$T42 -> -513.00279 | F42: =-F$49*$T42 -> -787.44173 | G42: =-G$49*$T42 -> -793.58104 | H42: =-H$49*$T42 -> -814.21577 | I42: =-I$49*$T42 -> -915.14357 | J42: =-J$49*$T42 -> -775.96437 | K42: =-K$49*$T42 -> -748.79822 | L42: =-L$49*$T42 -> -765.94059 | ... P42: =-P$49*$T42 -> -618.31652 | R42: =SUM(E42:P42) -> -9092.6649 | T42: 0.001
B43: Estoque Final | C43: 5.4.1.01.00016 | E43: =-E$49*$T43 -> 0 | F43: =-F$49*$T43 -> 0 | G43: =-G$49*$T43 -> 0 | H43: =-H$49*$T43 -> 0 | I43: =-I$49*$T43 -> 0 | J43: =-J$49*$T43 -> 0 | K43: =-K$49*$T43 -> 0 | L43: =-L$49*$T43 -> 0 | ... P43: =-P$49*$T43 -> 0 | R43: =SUM(E43:P43) -> 0 | T43: 0
... B45: (-) Reclassificação CMV | C45: 5.4.1.01.00017 | E45: =-E$49*$T45 -> 0 | F45: =-F$49*$T45 -> 0 | G45: =-G$49*$T45 -> 0 | H45: =-H$49*$T45 -> 0 | I45: =-I$49*$T45 -> 0 | J45: =-J$49*$T45 -> 0 | K45: =-K$49*$T45 -> 0 | L45: =-L$49*$T45 -> 0 | ... P45: =-P$49*$T45 -> 0 | R45: =SUM(E45:P45) -> 0 | T45: 0
B47: ÍNDICE | E47: 0.32 | F47: =$E$47 -> 0.32 | G47: =$E$47 -> 0.32 | H47: =$E$47 -> 0.32 | I47: =$E$47 -> 0.32 | J47: =$E$47 -> 0.32 | K47: =$E$47 -> 0.32 | L47: =$E$47 -> 0.32 | M47: =$E$47 -> 0.32 | ... P47: =$E$47 -> 0.32 | R47: =P47 -> 0.32
B48: RECEITA LÍQUIDA | E48: =E11+E22+E23+E24 -> 1603133.7 | F48: =F11+F22+F23+F24 -> 2460755.4 | G48: =G11+G22+G23+G24 -> 2479940.7 | H48: =H11+H22+H23+H24 -> 2544424.3 | I48: =I11+I22+I23+I24 -> 2859823.6 | J48: =J11+J22+J23+J24 -> 2424888.6 | K48: =K11+K22+K23+K24 -> 2339994.4 | L48: =L11+L22+L23+L24 -> 2393564.4 | ... P48: =P11+P22+P23+P24 -> 1932239.1 | R48: =SUM(E48:P48) -> 28414578
B49: CMV | E49: =E48*E47 -> 513002.79 | F49: =F48*F47 -> 787441.73 | G49: =G48*G47 -> 793581.04 | H49: =H48*H47 -> 814215.77 | I49: =I48*I47 -> 915143.57 | J49: =J48*J47 -> 775964.37 | K49: =K48*K47 -> 748798.22 | L49: =L48*L47 -> 765940.59 | ... P49: =P48*P47 -> 618316.52 | R49: =SUM(E49:P49) -> 9092664.9
B51: PESSOAL | E51: =SUM(E52:E75) -> -552193.44 | F51: =SUM(F52:F75) -> -677648.67 | G51: =SUM(G52:G75) -> -679825.89 | H51: =SUM(H52:H75) -> -687143.7 | I51: =SUM(I52:I75) -> -722936.34 | J51: =SUM(J52:J75) -> -673578.38 | K51: =SUM(K52:K75) -> -681736.13 | L51: =SUM(L52:L75) -> -687815.44 | ... P51: =SUM(P52:P75) -> -635462.62 | R51: =SUM(E51:P51) -> -8083929.9 | T51: %
B52: Salários e Encargos | C52: 5.4.1.02.00001 | D52: F | E52: -305252.28 | F52: -305252.28 | G52: -305252.28 | H52: -305252.28 | I52: -305252.28 | J52: -305252.28 | K52: -322695.26 | L52: -322695.26 | M52: -322695.26 | N52: -322695.26 | O52: -322695.26 | P52: -322695.26 | R52: =SUM(E52:P52) -> -3767685.2
B53: 13º Salário | C53: 5.4.1.02.00004 | D53: F | E53: ='Base Folha'!$P$90 -> -17829.31 | F53: ='Base Folha'!$P$90 -> -17829.31 | G53: ='Base Folha'!$P$90 -> -17829.31 | H53: ='Base Folha'!$P$90 -> -17829.31 | I53: ='Base Folha'!$P$90 -> -17829.31 | J53: ='Base Folha'!$P$90 -> -17829.31 | K53: ='Base Folha'!$P$90 -> -17829.31 | L53: ='Base Folha'!$P$90 -> -17829.31 | ... P53: ='Base Folha'!$P$90 -> -17829.31 | R53: =SUM(E53:P53) -> -213951.73
B54: Férias | C54: 5.4.1.02.00005 | D54: F | E54: ='Base Folha'!$O$90 -> -12048.422 | F54: ='Base Folha'!$O$90 -> -12048.422 | G54: ='Base Folha'!$O$90 -> -12048.422 | H54: ='Base Folha'!$O$90 -> -12048.422 | I54: ='Base Folha'!$O$90 -> -12048.422 | J54: ='Base Folha'!$O$90 -> -12048.422 | K54: ='Base Folha'!$O$90 -> -12048.422 | L54: ='Base Folha'!$O$90 -> -12048.422 | ... P54: ='Base Folha'!$O$90 -> -12048.422 | R54: =SUM(E54:P54) -> -144581.06
B55: INSS | C55: 5.4.1.02.00006 | D55: V | E55: ='Base Folha'!$R$90+'Base Gorjeta'!D21 -> -46592.981 | F55: ='Base Folha'!$R$90+'Base Gorjeta'!E21 -> -74845.081 | G55: ='Base Folha'!$R$90+'Base Gorjeta'!F21 -> -75428.612 | H55: ='Base Folha'!$R$90+'Base Gorjeta'!G21 -> -77389.91 | I55: ='Base Folha'!$R$90+'Base Gorjeta'!H21 -> -86982.937 | J55: ='Base Folha'!$R$90+'Base Gorjeta'!I21 -> -73754.176 | K55: ='Base Folha'!$R$90+'Base Gorjeta'!J21 -> -71172.077 | L55: ='Base Folha'!$R$90+'Base Gorjeta'!K21 -> -72801.432 | ... P55: ='Base Folha'!$R$90+'Base Gorjeta'!O21 -> -58769.999 | R55: =SUM(E55:P55) -> -862076.18
B56: FGTS | C56: 5.4.1.02.00007 | D56: V | E56: ='Base Folha'!$Q$90+'Base Gorjeta'!D20 -> -31570.423 | F56: ='Base Folha'!$Q$90+'Base Gorjeta'!E20 -> -39299.307 | G56: ='Base Folha'!$Q$90+'Base Gorjeta'!F20 -> -39472.206 | H56: ='Base Folha'!$Q$90+'Base Gorjeta'!G20 -> -40053.331 | I56: ='Base Folha'!$Q$90+'Base Gorjeta'!H20 -> -42895.709 | J56: ='Base Folha'!$Q$90+'Base Gorjeta'!I20 -> -38976.076 | K56: ='Base Folha'!$Q$90+'Base Gorjeta'!J20 -> -38211.01 | L56: ='Base Folha'!$Q$90+'Base Gorjeta'!K20 -> -38693.782 | ... P56: ='Base Folha'!$Q$90+'Base Gorjeta'!O20 -> -34536.32 | R56: =SUM(E56:P56) -> -461547.94
B57: Indenizações e Aviso Prévio | C57: 5.4.1.02.00008 | D57: F | E57: 0 | F57: 0 | G57: 0 | H57: 0 | I57: 0 | J57: 0 | K57: 0 | L57: 0 | M57: 0 | N57: 0 | O57: 0 | P57: 0 | R57: =SUM(E57:P57) -> 0
B58: Assistência Médica e Social | C58: 5.4.1.02.00009 | D58: F | E58: ='Base Folha'!$S$90 -> -9975.26 | F58: ='Base Folha'!$S$90 -> -9975.26 | G58: ='Base Folha'!$S$90 -> -9975.26 | H58: ='Base Folha'!$S$90 -> -9975.26 | I58: ='Base Folha'!$S$90 -> -9975.26 | J58: ='Base Folha'!$S$90 -> -9975.26 | K58: ='Base Folha'!$S$90 -> -9975.26 | L58: ='Base Folha'!$S$90 -> -9975.26 | ... P58: ='Base Folha'!$S$90 -> -9975.26 | R58: =SUM(E58:P58) -> -119703.12
B59: Horas Extras | C59: 5.4.1.02.00010 | D59: F | E59: ='Base Folha'!$M$90 -> 0 | F59: ='Base Folha'!$M$90 -> 0 | G59: ='Base Folha'!$M$90 -> 0 | H59: ='Base Folha'!$M$90 -> 0 | I59: ='Base Folha'!$M$90 -> 0 | J59: ='Base Folha'!$M$90 -> 0 | K59: ='Base Folha'!$M$90 -> 0 | L59: ='Base Folha'!$M$90 -> 0 | ... P59: ='Base Folha'!$M$90 -> 0 | R59: =SUM(E59:P59) -> 0
B60: Banco de Horas | C60: 5.4.1.02.00011 | D60: F | E60: 0 | F60: 0 | G60: 0 | H60: 0 | I60: 0 | J60: 0 | K60: 0 | L60: 0 | M60: 0 | N60: 0 | O60: 0 | P60: 0 | R60: =SUM(E60:P60) -> 0
B61: Vale Transporte | C61: 5.4.1.02.00012 | D61: F | E61: ='Base Folha'!$T$90 -> -21693.796 | F61: ='Base Folha'!$T$90 -> -21693.796 | G61: ='Base Folha'!$T$90 -> -21693.796 | H61: ='Base Folha'!$T$90 -> -21693.796 | I61: ='Base Folha'!$T$90 -> -21693.796 | J61: ='Base Folha'!$T$90 -> -21693.796 | K61: ='Base Folha'!$T$90 -> -21693.796 | L61: ='Base Folha'!$T$90 -> -21693.796 | ... P61: ='Base Folha'!$T$90 -> -21693.796 | R61: =SUM(E61:P61) -> -260325.55
B62: Contribuição Sindical | C62: 5.4.1.02.00016 | D62: F | E62: =E$52*$T$62 -> -6105.0455 | F62: =F$52*$T$62 -> -6105.0455 | G62: =G$52*$T$62 -> -6105.0455 | H62: =H$52*$T$62 -> -6105.0455 | I62: =I$52*$T$62 -> -6105.0455 | J62: =J$52*$T$62 -> -6105.0455 | K62: =K$52*$T$62 -> -6453.9053 | L62: =L$52*$T$62 -> -6453.9053 | ... P62: =P$52*$T$62 -> -6453.9053 | R62: =SUM(E62:P62) -> -75353.705 | T62: 0.02
B63: Seguro De Vida | C63: 5.4.1.02.00018 | D63: F | E63: ='Base Folha'!$U$90 -> -800.52 | F63: ='Base Folha'!$U$90 -> -800.52 | G63: ='Base Folha'!$U$90 -> -800.52 | H63: ='Base Folha'!$U$90 -> -800.52 | I63: ='Base Folha'!$U$90 -> -800.52 | J63: ='Base Folha'!$U$90 -> -800.52 | K63: ='Base Folha'!$U$90 -> -800.52 | L63: ='Base Folha'!$U$90 -> -800.52 | ... P63: ='Base Folha'!$U$90 -> -800.52 | R63: =SUM(E63:P63) -> -9606.24
B64: Beneficios | D64: F | E64: ='Base Folha'!$Y$90 -> -579.6 | F64: ='Base Folha'!$Y$90 -> -579.6 | G64: ='Base Folha'!$Y$90 -> -579.6 | H64: ='Base Folha'!$Y$90 -> -579.6 | I64: ='Base Folha'!$Y$90 -> -579.6 | J64: ='Base Folha'!$Y$90 -> -579.6 | K64: ='Base Folha'!$Y$90 -> -579.6 | L64: ='Base Folha'!$Y$90 -> -579.6 | ... P64: ='Base Folha'!$Y$90 -> -579.6
B65: Uniforme | C65: 5.4.1.02.00020 | D65: F | E65: ='Base Folha'!$W$90 -> -6986.25 | F65: ='Base Folha'!$W$90 -> -6986.25 | G65: ='Base Folha'!$W$90 -> -6986.25 | H65: ='Base Folha'!$W$90 -> -6986.25 | I65: ='Base Folha'!$W$90 -> -6986.25 | J65: ='Base Folha'!$W$90 -> -6986.25 | K65: ='Base Folha'!$W$90 -> -6986.25 | L65: ='Base Folha'!$W$90 -> -6986.25 | ... P65: ='Base Folha'!$W$90 -> -6986.25 | R65: =SUM(E65:P65) -> -83835 | T65: 0.003
B66: Colaborador Extra | C66: 5.4.1.02.00022 | D66: F | E66: =($E$11+$E$22+$E$23+$E$24)*-$T$66 -> -16031.337 | F66: =(F11+F22+F23+F24)*-$T$66 -> -24607.554 | G66: =(G11+G22+G23+G24)*-$T$66 -> -24799.407 | H66: =(H11+H22+H23+H24)*-$T$66 -> -25444.243 | I66: =(I11+I22+I23+I24)*-$T$66 -> -28598.236 | J66: =(J11+J22+J23+J24)*-$T$66 -> -24248.886 | K66: =(K11+K22+K23+K24)*-$T$66 -> -23399.944 | L66: =(L11+L22+L23+L24)*-$T$66 -> -23935.644 | M66: =(M11+M22+M23+M24)*-$T$66 -> -23641.001 | ... P66: =(P11+P22+P23+P24)*-$T$66 -> -19322.391 | R66: =SUM(E66:P66) -> -284145.78 | T66: 0.01
B67: Adicional Noturno | C67: 5.4.1.02.00027 | D67: F | E67: ='Base Folha'!$L$90 -> 0 | F67: ='Base Folha'!$L$90 -> 0 | G67: ='Base Folha'!$L$90 -> 0 | H67: ='Base Folha'!$L$90 -> 0 | I67: ='Base Folha'!$L$90 -> 0 | J67: ='Base Folha'!$L$90 -> 0 | K67: ='Base Folha'!$L$90 -> 0 | L67: ='Base Folha'!$L$90 -> 0 | ... P67: ='Base Folha'!$L$90 -> 0 | R67: =SUM(E67:P67) -> 0
B68: Gorjetas Recebidas | C68: 5.4.1.02.00031 | D68: V | E68: =E69+E13 -> 74471.506 | F68: =F69+F13 -> 74460.161 | G68: =G69+G13 -> 75040.691 | H68: =H69+H13 -> 76991.903 | I68: =I69+I13 -> 86535.593 | J68: =J69+J13 -> 73374.866 | K68: =K69+K13 -> 70806.047 | L68: =L69+L13 -> 72427.023 | ... P68: =P69+P13 -> 58467.752 | R68: =SUM(E68:P68) -> 885760.77
B69: Gorjetas Pagas | C69: 3.1.1.03.00009 | D69: V | E69: =-'Base Gorjeta'!D5 -> -151199.72 | F69: =-'Base Gorjeta'!E5 -> -232086.41 | G69: =-'Base Gorjeta'!F5 -> -233895.87 | H69: =-'Base Gorjeta'!G5 -> -239977.64 | I69: =-'Base Gorjeta'!H5 -> -269724.57 | J69: =-'Base Gorjeta'!I5 -> -228703.63 | K69: =-'Base Gorjeta'!J5 -> -220696.82 | L69: =-'Base Gorjeta'!K5 -> -225749.27 | ... P69: =-'Base Gorjeta'!O5 -> -182239.34 | R69: =SUM(E69:P69) -> -2679923.9
B70: Gratificações | C70: 3.1.1.03.00008 | D70: F | R70: =SUM(E70:P70) -> 0
B71: DSR | C71: x.x.x.xx.xxxxx | E71: ='Base Folha'!$N$90 -> 0 | F71: ='Base Folha'!$N$90 -> 0 | G71: ='Base Folha'!$N$90 -> 0 | H71: ='Base Folha'!$N$90 -> 0 | I71: ='Base Folha'!$N$90 -> 0 | J71: ='Base Folha'!$N$90 -> 0 | K71: ='Base Folha'!$N$90 -> 0 | L71: ='Base Folha'!$N$90 -> 0 | ... P71: ='Base Folha'!$N$90 -> 0 | R71: =SUM(E71:P71) -> 0
B72: GRATIFICAÇÃO - INSS | C72: x.x.x.xx.xxxxx | E72: 0 | F72: 0 | G72: 0 | H72: 0 | I72: 0 | J72: 0 | K72: 0 | L72: 0 | M72: 0 | N72: 0 | O72: 0 | P72: 0 | R72: =SUM(E72:P72) -> 0
B73: GRATIFICAÇÃO 13. SALÁRIO | C73: x.x.x.xx.xxxxx | E73: 0 | F73: 0 | G73: 0 | H73: 0 | I73: 0 | J73: 0 | K73: 0 | L73: 0 | M73: 0 | N73: 0 | O73: 0 | P73: 0 | R73: =SUM(E73:P73) -> 0
B74: GRATIFICAÇÃO FGTS | C74: x.x.x.xx.xxxxx | E74: 0 | F74: 0 | G74: 0 | H74: 0 | I74: 0 | J74: 0 | K74: 0 | L74: 0 | M74: 0 | N74: 0 | O74: 0 | P74: 0 | R74: =SUM(E74:P74) -> 0
B75: GRATIFICAÇÃO FÉRIAS | C75: x.x.x.xx.xxxxx | E75: 0 | F75: 0 | G75: 0 | H75: 0 | I75: 0 | J75: 0 | K75: 0 | L75: 0 | M75: 0 | N75: 0 | O75: 0 | P75: 0 | R75: =SUM(E75:P75) -> 0
B76: OCUPAÇÃO | E76: =SUM(E77:E79) -> -63668 | F76: =SUM(F77:F79) -> -71735.66 | G76: =SUM(G77:G79) -> -71735.66 | H76: =SUM(H77:H79) -> -71735.66 | I76: =SUM(I77:I79) -> -71735.66 | J76: =SUM(J77:J79) -> -71735.66 | K76: =SUM(K77:K79) -> -71735.66 | L76: =SUM(L77:L79) -> -71735.66 | ... P76: =SUM(P77:P79) -> -63668 | R76: =SUM(R77:R79) -> -844692.6 | T76: %
B77: Aluguéis | C77: 4.1.1.02.00002 | D77: F | E77: -45000 | F77: -45000 | G77: -45000 | H77: -45000 | I77: -45000 | J77: -45000 | K77: -45000 | L77: -45000 | M77: -45000 | N77: -45000 | O77: -45000 | P77: -45000 | R77: =SUM(E77:P77) -> -540000
B78: Casa de Apoio | C78: 4.1.1.02.00003 | D78: F | E78: -18668 | F78: -18668 | G78: -18668 | H78: -18668 | I78: -18668 | J78: -18668 | K78: -18668 | L78: -18668 | M78: -18668 | N78: -18668 | O78: -18668 | P78: -18668 | R78: =SUM(E78:P78) -> -224016
B79: IPTU | C79: 4.1.1.02.00004 | D79: F | F79: -8067.66 | G79: -8067.66 | H79: -8067.66 | I79: -8067.66 | J79: -8067.66 | K79: -8067.66 | L79: -8067.66 | M79: -8067.66 | N79: -8067.66 | O79: -8067.66 | R79: =SUM(E79:P79) -> -80676.6
B80: UTILIDADES/ CONSUMO | C80: 3.1.2.01.00005 | E80: =SUM(E81:E83) -> -43284.61 | F80: =SUM(F81:F83) -> -58796.811 | G80: =SUM(G81:G83) -> -59255.221 | H80: =SUM(H81:H83) -> -60795.978 | I80: =SUM(I81:I83) -> -68332.069 | J80: =SUM(J81:J83) -> -57939.817 | K80: =SUM(K81:K83) -> -55911.371 | L80: =SUM(L81:L83) -> -57191.361 | ... P80: =SUM(P81:P83) -> -46168.545 | R80: =SUM(R81:R83) -> -683912.04
B81: Água e Esgoto | C81: 5.4.1.03.00001 | D81: V | E81: -16031.337 | F81: -21776.597 | G81: -21946.378 | H81: -22517.029 | I81: -25308.174 | J81: -21459.192 | K81: -20707.915 | L81: -21181.985 | M81: -20921.24 | N81: -20325.014 | O81: -24026.432 | P81: -17099.461 | R81: =SUM(E81:P81) -> -253300.75
B82: Energia Elétrica | C82: x.x.x.xx.xxxxx | D82: V | E82: -19237.604 | F82: -26131.916 | G82: -26335.654 | H82: -27020.435 | I82: -30369.809 | J82: -25751.03 | K82: -24849.498 | L82: -25418.382 | M82: -25105.488 | N82: -24390.016 | O82: -28831.719 | P82: -20519.353 | R82: =SUM(E82:P82) -> -303960.9
B83: Gás Encanado | D83: V | E83: -8015.6685 | F83: -10888.298 | G83: -10973.189 | H83: -11258.514 | I83: -12654.087 | J83: -10729.596 | K83: -10353.958 | L83: -10590.993 | M83: -10460.62 | N83: -10162.507 | O83: -12013.216 | P83: -8549.7306 | R83: =SUM(E83:P83) -> -126650.38
B84: MANUTENÇÃO | E84: =SUM(E85) -> -16031.337 | F84: =SUM(F85) -> -21776.597 | G84: =SUM(G85) -> -21946.378 | H84: =SUM(H85) -> -22517.029 | I84: =SUM(I85) -> -25308.174 | J84: =SUM(J85) -> -21459.192 | K84: =SUM(K85) -> -20707.915 | L84: =SUM(L85) -> -21181.985 | ... P84: =SUM(P85) -> -17099.461 | R84: =SUM(R85) -> -253300.75
B85: Manutenção e Conservação | D85: V | E85: -16031.337 | F85: -21776.597 | G85: -21946.378 | H85: -22517.029 | I85: -25308.174 | J85: -21459.192 | K85: -20707.915 | L85: -21181.985 | M85: -20921.24 | N85: -20325.014 | O85: -24026.432 | P85: -17099.461 | R85: =SUM(E85:P85) -> -253300.75
B86: OPERAÇÃO | E86: =SUM(E87:E100) -> -180339.11 | F86: =SUM(F87:F100) -> -195316.67 | G86: =SUM(G87:G100) -> -195562.24 | H86: =SUM(H87:H100) -> -196387.63 | I86: =SUM(I87:I100) -> -200424.74 | J86: =SUM(J87:J100) -> -194857.57 | K86: =SUM(K87:K100) -> -193770.93 | L86: =SUM(L87:L100) -> -194456.62 | ... P86: =SUM(P87:P100) -> -188551.66 | R86: =SUM(R87:R100) -> -2279884.6 | T86: %
B87: Aluguel de Maquinas | C87: 5.4.1.03.00002 | D87: F | E87: -25000 | F87: -25000 | G87: -25000 | H87: -25000 | I87: -25000 | J87: -25000 | K87: -25000 | L87: -25000 | M87: -25000 | N87: -25000 | O87: -25000 | P87: -25000 | R87: =SUM(E87:P87) -> -300000 | T87: =-R87/R11 -> 0.0097502768
B88: Assessoria Nutricional | C88: 5.4.1.03.00003 | D88: F | E88: -4150 | F88: -4150 | G88: -4150 | H88: -4150 | I88: -4150 | J88: -4150 | K88: -4150 | L88: -4150 | M88: -4150 | N88: -4150 | O88: -4150 | P88: -4150 | R88: -4150 | T88: 0.0024
B89: Decoração e Paisagismo | C89: 5.4.1.03.00008 | D89: V | E89: =(E$11+E$22+E$23+E$24)*-$T89 -> -1603.1337 | F89: =(F$11+F$22+F$23+F$24)*-$T89 -> -2460.7554 | G89: =(G$11+G$22+G$23+G$24)*-$T89 -> -2479.9407 | H89: =(H$11+H$22+H$23+H$24)*-$T89 -> -2544.4243 | I89: =(I$11+I$22+I$23+I$24)*-$T89 -> -2859.8236 | J89: =(J$11+J$22+J$23+J$24)*-$T89 -> -2424.8886 | K89: =(K$11+K$22+K$23+K$24)*-$T89 -> -2339.9944 | L89: =(L$11+L$22+L$23+L$24)*-$T89 -> -2393.5644 | ... P89: =(P$11+P$22+P$23+P$24)*-$T89 -> -1932.2391 | R89: =SUM(E89:P89) -> -28414.578 | T89: 0.001
B90: Dedetização | C90: 5.4.1.03.00009 | D90: F | E90: -2800 | F90: -2800 | G90: -2800 | H90: -2800 | I90: -2800 | J90: -2800 | K90: -2800 | L90: -2800 | M90: -2800 | N90: -2800 | O90: -2800 | P90: -2800 | R90: =SUM(E90:P90) -> -33600 | T90: =-R90/R11 -> 0.001092031
B91: Despesas com Segurança | C91: 5.4.1.03.00016 | D91: F | E91: -26000 | F91: -30000 | G91: -30000 | H91: -30000 | I91: -30000 | J91: -30000 | K91: -30000 | L91: -30000 | M91: -30000 | N91: -30000 | O91: -30000 | P91: -30000 | R91: =SUM(E91:P91) -> -356000 | T91: =-R91/R11 -> 0.011570329
B92: Embalagens | C92: 5.4.1.03.00019 | D92: V | E92: =(E$11+E$22+E$23+E$24)*-$T92 -> -1603.1337 | F92: =(F$11+F$22+F$23+F$24)*-$T92 -> -2460.7554 | G92: =(G$11+G$22+G$23+G$24)*-$T92 -> -2479.9407 | H92: =(H$11+H$22+H$23+H$24)*-$T92 -> -2544.4243 | I92: =(I$11+I$22+I$23+I$24)*-$T92 -> -2859.8236 | J92: =(J$11+J$22+J$23+J$24)*-$T92 -> -2424.8886 | K92: =(K$11+K$22+K$23+K$24)*-$T92 -> -2339.9944 | L92: =(L$11+L$22+L$23+L$24)*-$T92 -> -2393.5644 | ... P92: =(P$11+P$22+P$23+P$24)*-$T92 -> -1932.2391 | R92: =SUM(E92:P92) -> -28414.578 | T92: 0.001
B93: Lavanderia | C93: 5.4.1.03.00022 | D93: V | E93: -2300 | F93: -2300 | G93: -2300 | H93: -2300 | I93: -2300 | J93: -2300 | K93: -2300 | L93: -2300 | M93: -2300 | N93: -2300 | O93: -2300 | P93: -2300 | R93: =SUM(E93:P93) -> -27600 | T93: 0.001
B94: Material de limpeza | C94: 5.4.1.03.00026 | D94: V | E94: =(E$11+E$22+E$23+E$24)*-$T94 -> -3847.5209 | F94: =(F$11+F$22+F$23+F$24)*-$T94 -> -5905.813 | G94: =(G$11+G$22+G$23+G$24)*-$T94 -> -5951.8578 | H94: =(H$11+H$22+H$23+H$24)*-$T94 -> -6106.6183 | I94: =(I$11+I$22+I$23+I$24)*-$T94 -> -6863.5767 | J94: =(J$11+J$22+J$23+J$24)*-$T94 -> -5819.7328 | K94: =(K$11+K$22+K$23+K$24)*-$T94 -> -5615.9866 | L94: =(L$11+L$22+L$23+L$24)*-$T94 -> -5744.5544 | ... P94: =(P$11+P$22+P$23+P$24)*-$T94 -> -4637.3739 | R94: =SUM(E94:P94) -> -68194.987 | T94: 0.0024
B95: Limpeza e Conservação | D95: V | E95: =(E$11+E$22+E$23+E$24)*-$T95 -> -3847.5209 | F95: =(F$11+F$22+F$23+F$24)*-$T95 -> -5905.813 | G95: =(G$11+G$22+G$23+G$24)*-$T95 -> -5951.8578 | H95: =(H$11+H$22+H$23+H$24)*-$T95 -> -6106.6183 | I95: =(I$11+I$22+I$23+I$24)*-$T95 -> -6863.5767 | J95: =(J$11+J$22+J$23+J$24)*-$T95 -> -5819.7328 | K95: =(K$11+K$22+K$23+K$24)*-$T95 -> -5615.9866 | L95: =(L$11+L$22+L$23+L$24)*-$T95 -> -5744.5544 | ... P95: =(P$11+P$22+P$23+P$24)*-$T95 -> -4637.3739 | R95: =SUM(E95:P95) -> -68194.987 | T95: 0.0024
B96: Ações (Eventos com Funcionários) | D96: V | E96: =(E11+E22+E23+E24)*-$T$96 -> -1603.1337 | F96: =(F11+F22+F23+F24)*-$T$96 -> -2460.7554 | G96: =(G11+G22+G23+G24)*-$T$96 -> -2479.9407 | H96: =(H11+H22+H23+H24)*-$T$96 -> -2544.4243 | I96: =(I11+I22+I23+I24)*-$T$96 -> -2859.8236 | J96: =(J11+J22+J23+J24)*-$T$96 -> -2424.8886 | K96: =(K11+K22+K23+K24)*-$T$96 -> -2339.9944 | L96: =(L11+L22+L23+L24)*-$T$96 -> -2393.5644 | ... P96: =(P11+P22+P23+P24)*-$T$96 -> -1932.2391 | R96: =SUM(E96:P96) -> -28414.578 | T96: 0.001
B97: Uniforme | C97: 5.4.1.03.00027 | D97: V | E97: =(E$11+E$22+E$23+E$24)*-$T97 -> -3206.2674 | F97: =(F$11+F$22+F$23+F$24)*-$T97 -> -4921.5108 | G97: =(G$11+G$22+G$23+G$24)*-$T97 -> -4959.8815 | H97: =(H$11+H$22+H$23+H$24)*-$T97 -> -5088.8485 | I97: =(I$11+I$22+I$23+I$24)*-$T97 -> -5719.6473 | J97: =(J$11+J$22+J$23+J$24)*-$T97 -> -4849.7773 | K97: =(K$11+K$22+K$23+K$24)*-$T97 -> -4679.9889 | L97: =(L$11+L$22+L$23+L$24)*-$T97 -> -4787.1287 | ... P97: =(P$11+P$22+P$23+P$24)*-$T97 -> -3864.4782 | R97: =SUM(E97:P97) -> -56829.156 | T97: 0.002
B98: Utensílios | C98: 5.4.1.03.00028 | D98: V | E98: =(E$11+E$22+E$23+E$24)*-$T98 -> -4809.4011 | F98: =(F$11+F$22+F$23+F$24)*-$T98 -> -7382.2662 | G98: =(G$11+G$22+G$23+G$24)*-$T98 -> -7439.8222 | H98: =(H$11+H$22+H$23+H$24)*-$T98 -> -7633.2728 | I98: =(I$11+I$22+I$23+I$24)*-$T98 -> -8579.4709 | J98: =(J$11+J$22+J$23+J$24)*-$T98 -> -7274.6659 | K98: =(K$11+K$22+K$23+K$24)*-$T98 -> -7019.9833 | L98: =(L$11+L$22+L$23+L$24)*-$T98 -> -7180.6931 | ... P98: =(P$11+P$22+P$23+P$24)*-$T98 -> -5796.7173 | R98: =SUM(E98:P98) -> -85243.733 | T98: 0.003
B99: Despesas de Seguros | C99: 5.4.1.03.00033 | D99: F | E99: -2819 | F99: -2819 | G99: -2819 | H99: -2819 | I99: -2819 | J99: -2819 | K99: -2819 | L99: -2819 | M99: -2819 | N99: -2819 | O99: -2819 | P99: -2819 | R99: =SUM(E99:P99) -> -33828 | T99: =-R99/R11 -> 0.0010994412
B100: Prestação de Serviço Pessoa Jurídica OP | C100: 5.4.1.03.00037 | D100: F | E100: -96750 | F100: -96750 | G100: -96750 | H100: -96750 | I100: -96750 | J100: -96750 | K100: -96750 | L100: -96750 | M100: -96750 | N100: -96750 | O100: -96750 | P100: -96750 | R100: =SUM(E100:P100) -> -1161000 | T100: =-R100/R11 -> 0.037733571
B101: Honorários dos Administradores | D101: F | E101: -50000 | F101: -50000 | G101: -50000 | H101: -50000 | I101: -50000 | J101: -50000 | K101: -50000 | L101: -50000 | M101: -50000 | N101: -50000 | O101: -50000 | P101: -50000 | R101: =SUM(E101:P101) -> -600000
B102: ADMINISTRATIVA | E102: =SUM(E103:E114) -> -172743.9 | F102: =SUM(F103:F114) -> -187494.99 | G102: =SUM(G103:G114) -> -187824.98 | H102: =SUM(H103:H114) -> -188934.1 | I102: =SUM(I103:I114) -> -194358.97 | J102: =SUM(J103:J114) -> -186878.08 | K102: =SUM(K103:K114) -> -185417.9 | L102: =SUM(L103:L114) -> -186339.31 | ... P102: =SUM(P103:P114) -> -178404.51 | R102: =SUM(R103:R114) -> -2230770.7 | T102: %
B103: Prestação de Serviço Pessoa Jurídica ADM | C103: 4.1.1.03.00009 | D103: F | E103: =-66000-(6600*70)/100 -> -70620 | F103: =-66000-(6600*70)/100 -> -70620 | G103: =-66000-(6600*70)/100 -> -70620 | H103: =-66000-(6600*70)/100 -> -70620 | I103: =-66000-(6600*70)/100 -> -70620 | J103: =-66000-(6600*70)/100 -> -70620 | K103: =-66000-(6600*70)/100 -> -70620 | L103: =-66000-(6600*70)/100 -> -70620 | ... P103: =-66000-(6600*70)/100 -> -70620 | R103: =SUM(E103:P103) -> -847440 | T103: =-R103/$R$11 -> 0.027542582
B104: Transporte/Fretes | C104: 5.4.1.03.00022 | D104: F | E104: -1000 | F104: -1000 | G104: -1000 | H104: -1000 | I104: -1000 | J104: -1000 | K104: -1000 | L104: -1000 | M104: -1000 | N104: -1000 | O104: -1000 | P104: -1000 | R104: =SUM(E104:P104) -> -12000 | T104: =-R104/$R$11 -> 0.00039001107
B105: Telefone e Internet | C105: 4.1.1.03.00018 | D105: F | E105: -1550 | F105: -1550 | G105: -1550 | H105: -1550 | I105: -1550 | J105: -1550 | K105: -1550 | L105: -1550 | M105: -1550 | N105: -1550 | O105: -1550 | P105: -1550 | R105: =SUM(E105:P105) -> -18600 | T105: =-R105/$R$11 -> 0.00060451716
B106: Material de Escritório | C106: 4.1.1.03.00024 | D106: V | E106: =(E$11+E$22+E$23+E$24)*-$T106 -> -4809.4011 | F106: =(F$11+F$22+F$23+F$24)*-$T106 -> -7382.2662 | G106: =(G$11+G$22+G$23+G$24)*-$T106 -> -7439.8222 | H106: =(H$11+H$22+H$23+H$24)*-$T106 -> -7633.2728 | I106: =(I$11+I$22+I$23+I$24)*-$T106 -> -8579.4709 | J106: =(J$11+J$22+J$23+J$24)*-$T106 -> -7274.6659 | K106: =(K$11+K$22+K$23+K$24)*-$T106 -> -7019.9833 | L106: =(L$11+L$22+L$23+L$24)*-$T106 -> -7180.6931 | ... P106: =(P$11+P$22+P$23+P$24)*-$T106 -> -5796.7173 | R106: =SUM(E106:P106) -> -85243.733 | T106: 0.003
B107: Material de Copa e Limpeza | C107: 4.1.1.03.00025 | D107: V | E107: =(E$11+E$22+E$23+E$24)*-$T107 -> -22443.872 | F107: =(F$11+F$22+F$23+F$24)*-$T107 -> -34450.576 | G107: =(G$11+G$22+G$23+G$24)*-$T107 -> -34719.17 | H107: =(H$11+H$22+H$23+H$24)*-$T107 -> -35621.94 | I107: =(I$11+I$22+I$23+I$24)*-$T107 -> -40037.531 | J107: =(J$11+J$22+J$23+J$24)*-$T107 -> -33948.441 | K107: =(K$11+K$22+K$23+K$24)*-$T107 -> -32759.922 | L107: =(L$11+L$22+L$23+L$24)*-$T107 -> -33509.901 | ... P107: =(P$11+P$22+P$23+P$24)*-$T107 -> -27051.348 | R107: =SUM(E107:P107) -> -397804.09 | T107: 0.014
B108: Serviços de Informatica/TI | C108: 4.1.1.03.00030 | D108: F | E108: -12000 | F108: -12000 | G108: -12000 | H108: -12000 | I108: -12000 | J108: -12000 | K108: -12000 | L108: -12000 | M108: -12000 | N108: -12000 | O108: -12000 | P108: -12000 | R108: =SUM(E108:P108) -> -144000 | T108: =-R108/$R$11 -> 0.0046801329
B109: Contabilidade | C109: 4.1.1.03.00031 | D109: F | E109: -14000 | F109: -14000 | G109: -14000 | H109: -14000 | I109: -14000 | J109: -14000 | K109: -14000 | L109: -14000 | M109: -14000 | N109: -14000 | O109: -14000 | P109: -14000 | R109: =SUM(E109:P109) -> -168000 | T109: =-R109/$R$11 -> 0.005460155
B110: Consultoria | C110: 4.1.1.03.00033 | D110: F | E110: =-22000-15000-4000 -> -41000 | F110: =-22000-15000-4000 -> -41000 | G110: =-22000-15000-4000 -> -41000 | H110: =-22000-15000-4000 -> -41000 | I110: =-22000-15000-4000 -> -41000 | J110: =-22000-15000-4000 -> -41000 | K110: =-22000-15000-4000 -> -41000 | L110: =-22000-15000-4000 -> -41000 | ... P110: =-22000-15000-4000 -> -41000 | R110: =SUM(E110:P110) -> -492000 | T110: =-R110/$R$11 -> 0.015990454
...

Sheet Base Realizado
D1: REALIZADO/26 - BASE DE DADOS
B5: DESCRIÇÃO | C5: CONTA | D5: JAN 2026 | E5: AV | F5: FEV 2026 | G5: AV | H5: MAR 2026 | I5: AV | K5: ABR 2026 | L5: AV | M5: MAIO 2026 | N5: JUN 2026 | O5: JUL 2026 | P5: AGO 2026 | Q5: SET 2026 | R5: OUT 2026 | S5: NOV 2026 | T5: DEZ 2026 | V5: TOTAL
B7: CLIENTES | C7: x.x.x.xx.xxxxx | D7: 4761 | F7: 4661 | H7: 6592 | V7: 91427.812
B8: TICKET MEDIO | C8: x.x.x.xx.xxxxx | D8: =(D11-D16)/D7 -> 289.76034 | F8: =(F11-F16)/F7 -> 312.20426 | H8: =(H11-H16)/H7 -> 317.16391 | V8: 300
B10: Rec.Venda no Merc.Int.de Prod.Fabr.Próp. | C10: 3.1.1.01.00004 | V10: 27428344
B11: FATURAMENTO | D11: =SUM(D12:D18)-D12 -> 1390349 | E11: =SUM(E13:E18) -> 1 | F11: =SUM(F12:F18)-F12 -> 1528554.1 | G11: =SUM(G13:G18) -> 1 | H11: =SUM(H12:H18)-H12 -> 2443536.8 | I11: =SUM(I13:I18) -> 1 | K11: =SUM(K12:K18)-K12 -> 2304709.6 | L11: =SUM(L13:L18) -> 1 | M11: =SUM(M12:M18)-M12 -> 0 | N11: =SUM(N12:N18)-N12 -> 0 | O11: =SUM(O12:O18)-O12 -> 0 | P11: =SUM(P12:P18)-P12 -> 0 | Q11: =SUM(Q12:Q18)-Q12 -> 0 | R11: =SUM(R12:R18)-R12 -> 0 | S11: =SUM(S12:S18)-S12 -> 0 | T11: =SUM(T12:T18)-T12 -> 0 | V11: 27428344 | X11: =SUM(X13:X18) -> 1
B12: Gorjetas Recebidas | D12: 110797.62 | E12: =D12/D$11 -> 0.079690511 | F12: 198712 | G12: =F12/F$11 -> 0.12999998 | H12: 116627.58 | I12: =H12/H$11 -> 0.047729006 | L12: =K12/K$11 -> 0 | V12: 0
B13: Dinheiro/Pix | C13: x.x.x.xx.xxxxx | D13: =SUMIFS(B.Receita!$E:$E,B.Receita!$F:$F,'Base Realizado'!$B13,B.Receita!$H:$H,'Base Realizado'!D$5) -> 191219.93 | E13: =D13/D$11 -> 0.13753377 | F13: =SUMIFS(B.Receita!$E:$E,B.Receita!$F:$F,'Base Realizado'!$B13,B.Receita!$H:$H,'Base Realizado'!F$5) -> 232968.95 | G13: =F13/F$11 -> 0.15241133 | H13: =SUMIFS(B.Receita!$E:$E,B.Receita!$F:$F,'Base Realizado'!$B13,B.Receita!$H:$H,'Base Realizado'!H$5) -> 339893.43 | I13: =H13/H$11 -> 0.13909896 | K13: =SUMIFS(B.Receita!$E:$E,B.Receita!$F:$F,'Base Realizado'!$B13,B.Receita!$H:$H,'Base Realizado'!K$5) -> 299094.7 | L13: =K13/K$11 -> 0.12977544 | V13: 548566.87 | X13: 0.02
B14: Cartão de Débito | C14: x.x.x.xx.xxxxx | D14: =SUMIFS(B.Receita!$E:$E,B.Receita!$F:$F,'Base Realizado'!$B14,B.Receita!$H:$H,'Base Realizado'!D$5) -> 213780.01 | E14: =D14/D$11 -> 0.15375997 | F14: =SUMIFS(B.Receita!$E:$E,B.Receita!$F:$F,'Base Realizado'!$B14,B.Receita!$H:$H,'Base Realizado'!F$5) -> 988071.98 | G14: =F14/F$11 -> 0.64640957 | H14: =SUMIFS(B.Receita!$E:$E,B.Receita!$F:$F,'Base Realizado'!$B14,B.Receita!$H:$H,'Base Realizado'!H$5) -> 289846.25 | I14: =H14/H$11 -> 0.11861751 | K14: =SUMIFS(B.Receita!$E:$E,B.Receita!$F:$F,'Base Realizado'!$B14,B.Receita!$H:$H,'Base Realizado'!K$5) -> 313558.29 | L14: =K14/K$11 -> 0.13605111 | V14: 1919984.1 | X14: 0.07
B15: Cartão de Crédito | C15: x.x.x.xx.xxxxx | D15: =SUMIFS(B.Receita!$E:$E,B.Receita!$F:$F,'Base Realizado'!$B15,B.Receita!$H:$H,'Base Realizado'!D$5) -> 963659.96 | E15: =D15/D$11 -> 0.69310654 | F15: =SUMIFS(B.Receita!$E:$E,B.Receita!$F:$F,'Base Realizado'!$B15,B.Receita!$H:$H,'Base Realizado'!F$5) -> 223553.48 | G15: =F15/F$11 -> 0.1462516 | H15: =SUMIFS(B.Receita!$E:$E,B.Receita!$F:$F,'Base Realizado'!$B15,B.Receita!$H:$H,'Base Realizado'!H$5) -> 1455192.1 | I15: =H15/H$11 -> 0.59552698 | K15: =SUMIFS(B.Receita!$E:$E,B.Receita!$F:$F,'Base Realizado'!$B15,B.Receita!$H:$H,'Base Realizado'!K$5) -> 1524543.3 | L15: =K15/K$11 -> 0.66149042 | V15: 17992993 | X15: 0.656
B16: Evento Faturado | C16: x.x.x.xx.xxxxx | D16: =SUMIFS(B.Receita!$E:$E,B.Receita!$F:$F,'Base Realizado'!$B16,B.Receita!$H:$H,'Base Realizado'!D$5) -> 10800 | E16: =D16/D$11 -> 0.007767834 | F16: =SUMIFS(B.Receita!$E:$E,B.Receita!$F:$F,'Base Realizado'!$B16,B.Receita!$H:$H,'Base Realizado'!F$5) -> 73370 | G16: =F16/F$11 -> 0.047999611 | H16: =SUMIFS(B.Receita!$E:$E,B.Receita!$F:$F,'Base Realizado'!$B16,B.Receita!$H:$H,'Base Realizado'!H$5) -> 352792.26 | I16: =H16/H$11 -> 0.14437772 | K16: =SUMIFS(B.Receita!$E:$E,B.Receita!$F:$F,'Base Realizado'!$B16,B.Receita!$H:$H,'Base Realizado'!K$5) -> 159089.31 | L16: =K16/K$11 -> 0.069027921 | V16: 2742834.4 | X16: 0.1
B17: Delivery | C17: x.x.x.xx.xxxxx | D17: =SUMIFS(B.Receita!$E:$E,B.Receita!$F:$F,'Base Realizado'!$B17,B.Receita!$H:$H,'Base Realizado'!D$5) -> 0 | V17: 4114251.5 | X17: 0.15
B18: Voucher | C18: x.x.x.xx.xxxxx | D18: =SUMIFS(B.Receita!$E:$E,B.Receita!$F:$F,'Base Realizado'!$B18,B.Receita!$H:$H,'Base Realizado'!D$5) -> 10889.07 | E18: =D18/D$11 -> 0.0078318971 | F18: =SUMIFS(B.Receita!$E:$E,B.Receita!$F:$F,'Base Realizado'!$B18,B.Receita!$H:$H,'Base Realizado'!F$5) -> 10589.65 | G18: =F18/F$11 -> 0.0069278871 | H18: =SUMIFS(B.Receita!$E:$E,B.Receita!$F:$F,'Base Realizado'!$B18,B.Receita!$H:$H,'Base Realizado'!H$5) -> 5812.74 | I18: =H18/H$11 -> 0.0023788224 | K18: =SUMIFS(B.Receita!$E:$E,B.Receita!$F:$F,'Base Realizado'!$B18,B.Receita!$H:$H,'Base Realizado'!K$5) -> 8423.97 | L18: =K18/K$11 -> 0.0036551113 | V18: 109713.37 | X18: 0.004
B20: IMPOSTOS | D20: =SUM(D21:D25) -> -51487.25 | F20: =SUM(F21:F25) -> -21426.81 | H20: =SUM(H21:H25) -> -59924.54 | K20: =SUM(K21:K25) -> 0 | M20: =SUM(M21:M25) -> 0 | N20: =SUM(N21:N25) -> 0 | O20: =SUM(O21:O25) -> 0 | P20: =SUM(P21:P25) -> 0 | Q20: =SUM(Q21:Q25) -> 0 | R20: =SUM(R21:R25) -> 0 | S20: =SUM(S21:S25) -> 0 | T20: =SUM(T21:T25) -> 0 | V20: -2919061.3 | X20: %
B21: (-) ICMS | C21: 3.1.1.02.00002 | D21: =SUMIFS('B. Despesa'!$H$2:$H$1048576,'B. Despesa'!$I$2:$I$1048576,'Base Realizado'!D$5,'B. Despesa'!$K$2:$K$1048576,'Base Realizado'!$B21) -> -11603.07 | E21: =-D21/$D$11 -> 0.0083454372 | F21: =SUMIFS('B. Despesa'!$H$2:$H$1048576,'B. Despesa'!$I$2:$I$1048576,'Base Realizado'!F$5,'B. Despesa'!$K$2:$K$1048576,'Base Realizado'!$B21) -> -15493.73 | G21: =-F21/$D$11 -> 0.011143771 | H21: =SUMIFS('B. Despesa'!$H$2:$H$1048576,'B. Despesa'!$I$2:$I$1048576,'Base Realizado'!H$5,'B. Despesa'!$K$2:$K$1048576,'Base Realizado'!$B21) -> -37427.25 | I21: =-H21/$D$11 -> 0.026919321 | K21: =SUMIFS('B. Despesa'!$H$2:$H$1048576,'B. Despesa'!$I$2:$I$1048576,'Base Realizado'!K$5,'B. Despesa'!$K$2:$K$1048576,'Base Realizado'!$B21) -> 0 | L21: =-K21/$D$11 -> 0 | M21: =SUMIFS('B. Despesa'!$H$2:$H$1048576,'B. Despesa'!$I$2:$I$1048576,'Base Realizado'!M$5,'B. Despesa'!$K$2:$K$1048576,'Base Realizado'!$B21) -> 0 | N21: =SUMIFS('B. Despesa'!$H$2:$H$1048576,'B. Despesa'!$I$2:$I$1048576,'Base Realizado'!N$5,'B. Despesa'!$K$2:$K$1048576,'Base Realizado'!$B21) -> 0 | O21: =SUMIFS('B. Despesa'!$H$2:$H$1048576,'B. Despesa'!$I$2:$I$1048576,'Base Realizado'!O$5,'B. Despesa'!$K$2:$K$1048576,'Base Realizado'!$B21) -> 0 | P21: =SUMIFS('B. Despesa'!$H$2:$H$1048576,'B. Despesa'!$I$2:$I$1048576,'Base Realizado'!P$5,'B. Despesa'!$K$2:$K$1048576,'Base Realizado'!$B21) -> 0 | Q21: =SUMIFS('B. Despesa'!$H$2:$H$1048576,'B. Despesa'!$I$2:$I$1048576,'Base Realizado'!Q$5,'B. Despesa'!$K$2:$K$1048576,'Base Realizado'!$B21) -> 0 | R21: =SUMIFS('B. Despesa'!$H$2:$H$1048576,'B. Despesa'!$I$2:$I$1048576,'Base Realizado'!R$5,'B. Despesa'!$K$2:$K$1048576,'Base Realizado'!$B21) -> 0 | S21: =SUMIFS('B. Despesa'!$H$2:$H$1048576,'B. Despesa'!$I$2:$I$1048576,'Base Realizado'!S$5,'B. Despesa'!$K$2:$K$1048576,'Base Realizado'!$B21) -> 0 | T21: =SUMIFS('B. Despesa'!$H$2:$H$1048576,'B. Despesa'!$I$2:$I$1048576,'Base Realizado'!T$5,'B. Despesa'!$K$2:$K$1048576,'Base Realizado'!$B21) -> 0 | V21: -1097133.7 | X21: 0.04
B22: (-) COFINS | C22: 3.1.1.02.00003 | D22: =SUMIFS('B. Despesa'!$H$2:$H$1048576,'B. Despesa'!$I$2:$I$1048576,'Base Realizado'!D$5,'B. Despesa'!$K$2:$K$1048576,'Base Realizado'!$B22) -> -18007.73 | E22: =-D22/$D$11 -> 0.01295195 | F22: =SUMIFS('B. Despesa'!$H$2:$H$1048576,'B. Despesa'!$I$2:$I$1048576,'Base Realizado'!F$5,'B. Despesa'!$K$2:$K$1048576,'Base Realizado'!$B22) -> -4877.08 | G22: =-F22/$D$11 -> 0.00350781 | H22: =SUMIFS('B. Despesa'!$H$2:$H$1048576,'B. Despesa'!$I$2:$I$1048576,'Base Realizado'!H$5,'B. Despesa'!$K$2:$K$1048576,'Base Realizado'!$B22) -> -18490.92 | I22: =-H22/$D$11 -> 0.013299481 | K22: =SUMIFS('B. Despesa'!$H$2:$H$1048576,'B. Despesa'!$I$2:$I$1048576,'Base Realizado'!K$5,'B. Despesa'!$K$2:$K$1048576,'Base Realizado'!$B22) -> 0 | L22: =-K22/$D$11 -> 0 | M22: =SUMIFS('B. Despesa'!$H$2:$H$1048576,'B. Despesa'!$I$2:$I$1048576,'Base Realizado'!M$5,'B. Despesa'!$K$2:$K$1048576,'Base Realizado'!$B22) -> 0 | N22: =SUMIFS('B. Despesa'!$H$2:$H$1048576,'B. Despesa'!$I$2:$I$1048576,'Base Realizado'!N$5,'B. Despesa'!$K$2:$K$1048576,'Base Realizado'!$B22) -> 0 | O22: =SUMIFS('B. Despesa'!$H$2:$H$1048576,'B. Despesa'!$I$2:$I$1048576,'Base Realizado'!O$5,'B. Despesa'!$K$2:$K$1048576,'Base Realizado'!$B22) -> 0 | P22: =SUMIFS('B. Despesa'!$H$2:$H$1048576,'B. Despesa'!$I$2:$I$1048576,'Base Realizado'!P$5,'B. Despesa'!$K$2:$K$1048576,'Base Realizado'!$B22) -> 0 | Q22: =SUMIFS('B. Despesa'!$H$2:$H$1048576,'B. Despesa'!$I$2:$I$1048576,'Base Realizado'!Q$5,'B. Despesa'!$K$2:$K$1048576,'Base Realizado'!$B22) -> 0 | R22: =SUMIFS('B. Despesa'!$H$2:$H$1048576,'B. Despesa'!$I$2:$I$1048576,'Base Realizado'!R$5,'B. Despesa'!$K$2:$K$1048576,'Base Realizado'!$B22) -> 0 | S22: =SUMIFS('B. Despesa'!$H$2:$H$1048576,'B. Despesa'!$I$2:$I$1048576,'Base Realizado'!S$5,'B. Despesa'!$K$2:$K$1048576,'Base Realizado'!$B22) -> 0 | T22: =SUMIFS('B. Despesa'!$H$2:$H$1048576,'B. Despesa'!$I$2:$I$1048576,'Base Realizado'!T$5,'B. Despesa'!$K$2:$K$1048576,'Base Realizado'!$B22) -> 0 | V22: -822850.31 | X22: 0.03
B23: (-) PIS/Pasep | C23: 3.1.1.02.00004 | D23: =SUMIFS('B. Despesa'!$H$2:$H$1048576,'B. Despesa'!$I$2:$I$1048576,'Base Realizado'!D$5,'B. Despesa'!$K$2:$K$1048576,'Base Realizado'!$B23) -> -21876.45 | E23: =-D23/$D$11 -> 0.015734503 | F23: =SUMIFS('B. Despesa'!$H$2:$H$1048576,'B. Despesa'!$I$2:$I$1048576,'Base Realizado'!F$5,'B. Despesa'!$K$2:$K$1048576,'Base Realizado'!$B23) -> -1056 | G23: =-F23/$D$11 -> 0.00075952155 | H23: =SUMIFS('B. Despesa'!$H$2:$H$1048576,'B. Despesa'!$I$2:$I$1048576,'Base Realizado'!H$5,'B. Despesa'!$K$2:$K$1048576,'Base Realizado'!$B23) -> -4006.37 | I23: =-H23/$D$11 -> 0.0028815571 | K23: =SUMIFS('B. Despesa'!$H$2:$H$1048576,'B. Despesa'!$I$2:$I$1048576,'Base Realizado'!K$5,'B. Despesa'!$K$2:$K$1048576,'Base Realizado'!$B23) -> 0 | L23: =-K23/$D$11 -> 0 | M23: =SUMIFS('B. Despesa'!$H$2:$H$1048576,'B. Despesa'!$I$2:$I$1048576,'Base Realizado'!M$5,'B. Despesa'!$K$2:$K$1048576,'Base Realizado'!$B23) -> 0 | N23: =SUMIFS('B. Despesa'!$H$2:$H$1048576,'B. Despesa'!$I$2:$I$1048576,'Base Realizado'!N$5,'B. Despesa'!$K$2:$K$1048576,'Base Realizado'!$B23) -> 0 | O23: =SUMIFS('B. Despesa'!$H$2:$H$1048576,'B. Despesa'!$I$2:$I$1048576,'Base Realizado'!O$5,'B. Despesa'!$K$2:$K$1048576,'Base Realizado'!$B23) -> 0 | P23: =SUMIFS('B. Despesa'!$H$2:$H$1048576,'B. Despesa'!$I$2:$I$1048576,'Base Realizado'!P$5,'B. Despesa'!$K$2:$K$1048576,'Base Realizado'!$B23) -> 0 | Q23: =SUMIFS('B. Despesa'!$H$2:$H$1048576,'B. Despesa'!$I$2:$I$1048576,'Base Realizado'!Q$5,'B. Despesa'!$K$2:$K$1048576,'Base Realizado'!$B23) -> 0 | R23: =SUMIFS('B. Despesa'!$H$2:$H$1048576,'B. Despesa'!$I$2:$I$1048576,'Base Realizado'!R$5,'B. Despesa'!$K$2:$K$1048576,'Base Realizado'!$B23) -> 0 | S23: =SUMIFS('B. Despesa'!$H$2:$H$1048576,'B. Despesa'!$I$2:$I$1048576,'Base Realizado'!S$5,'B. Despesa'!$K$2:$K$1048576,'Base Realizado'!$B23) -> 0 | T23: =SUMIFS('B. Despesa'!$H$2:$H$1048576,'B. Despesa'!$I$2:$I$1048576,'Base Realizado'!T$5,'B. Despesa'!$K$2:$K$1048576,'Base Realizado'!$B23) -> 0 | V23: -178284.23 | X23: 0.0065
B24: (-) ISS | C24: 5.4.1.03.00035 | D24: =SUMIFS('B. Despesa'!$H$2:$H$1048576,'B. Despesa'!$I$2:$I$1048576,'Base Realizado'!D$5,'B. Despesa'!$K$2:$K$1048576,'Base Realizado'!$B24) -> 0 | F24: =SUMIFS('B. Despesa'!$H$2:$H$1048576,'B. Despesa'!$I$2:$I$1048576,'Base Realizado'!F$5,'B. Despesa'!$K$2:$K$1048576,'Base Realizado'!$B24) -> 0 | H24: =SUMIFS('B. Despesa'!$H$2:$H$1048576,'B. Despesa'!$I$2:$I$1048576,'Base Realizado'!H$5,'B. Despesa'!$K$2:$K$1048576,'Base Realizado'!$B24) -> 0 | K24: =SUMIFS('B. Despesa'!$H$2:$H$1048576,'B. Despesa'!$I$2:$I$1048576,'Base Realizado'!K$5,'B. Despesa'!$K$2:$K$1048576,'Base Realizado'!$B24) -> 0 | M24: =SUMIFS('B. Despesa'!$H$2:$H$1048576,'B. Despesa'!$I$2:$I$1048576,'Base Realizado'!M$5,'B. Despesa'!$K$2:$K$1048576,'Base Realizado'!$B24) -> 0 | N24: =SUMIFS('B. Despesa'!$H$2:$H$1048576,'B. Despesa'!$I$2:$I$1048576,'Base Realizado'!N$5,'B. Despesa'!$K$2:$K$1048576,'Base Realizado'!$B24) -> 0 | O24: =SUMIFS('B. Despesa'!$H$2:$H$1048576,'B. Despesa'!$I$2:$I$1048576,'Base Realizado'!O$5,'B. Despesa'!$K$2:$K$1048576,'Base Realizado'!$B24) -> 0 | P24: =SUMIFS('B. Despesa'!$H$2:$H$1048576,'B. Despesa'!$I$2:$I$1048576,'Base Realizado'!P$5,'B. Despesa'!$K$2:$K$1048576,'Base Realizado'!$B24) -> 0 | Q24: =SUMIFS('B. Despesa'!$H$2:$H$1048576,'B. Despesa'!$I$2:$I$1048576,'Base Realizado'!Q$5,'B. Despesa'!$K$2:$K$1048576,'Base Realizado'!$B24) -> 0 | R24: =SUMIFS('B. Despesa'!$H$2:$H$1048576,'B. Despesa'!$I$2:$I$1048576,'Base Realizado'!R$5,'B. Despesa'!$K$2:$K$1048576,'Base Realizado'!$B24) -> 0 | S24: =SUMIFS('B. Despesa'!$H$2:$H$1048576,'B. Despesa'!$I$2:$I$1048576,'Base Realizado'!S$5,'B. Despesa'!$K$2:$K$1048576,'Base Realizado'!$B24) -> 0 | T24: =SUMIFS('B. Despesa'!$H$2:$H$1048576,'B. Despesa'!$I$2:$I$1048576,'Base Realizado'!T$5,'B. Despesa'!$K$2:$K$1048576,'Base Realizado'!$B24) -> 0 | V24: 0 | X24: 0
B25: IRPJ | C25: 4.1.2.04.00002 | D25: 0 | F25: 0 | H25: 0 | K25: 0 | M25: 0 | N25: 0 | O25: 0 | P25: 0 | Q25: 0 | R25: 0 | S25: 0 | T25: 0 | V25: 0 | X25: 0
B26: CSLL | C26: 4.1.2.04.00001 | D26: 0 | F26: 0 | H26: 0 | K26: 0 | M26: 0 | N26: 0 | O26: 0 | P26: 0 | Q26: 0 | R26: 0 | S26: 0 | T26: 0 | V26: 0 | X26: 0
B28: CUSTOS DOS PRODUTOS VENDIDOS | D28: =SUM(D29:D42) -> -600857.5 | F28: =SUM(F29:F42) -> -527469.52 | H28: =SUM(H29:H42) -> -649970.13 | K28: =SUM(K29:K41) -> -895627.39 | M28: =SUM(M29:M39) -> 0 | N28: =SUM(N29:N39) -> 0 | O28: =SUM(O29:O39) -> 0 | P28: =SUM(P29:P39) -> 0 | Q28: =SUM(Q29:Q39) -> 0 | R28: =SUM(R29:R39) -> 0 | S28: =SUM(S29:S39) -> 0 | T28: =SUM(T29:T39) -> 0 | V28: -8105624.1 | X28: =SUM(X29:X42) -> 1 | Y28: 1 | Z28: =X28-Y28 -> 0
B29: Carnes e Aves | C29: 5.4.1.01.00002 | D29: =SUMIFS('B. Despesa'!$H$2:$H$1048576,'B. Despesa'!$I$2:$I$1048576,'Base Realizado'!D$5,'B. Despesa'!$K$2:$K$1048576,'Base Realizado'!$B29) -> -170454.81 | E29: =-D29/D$11 -> 0.12259858 | F29: =SUMIFS('B. Despesa'!$H$2:$H$1048576,'B. Despesa'!$I$2:$I$1048576,'Base Realizado'!F$5,'B. Despesa'!$K$2:$K$1048576,'Base Realizado'!$B29) -> -165532.6 | G29: =-F29/F$11 -> 0.10829359 | H29: =SUMIFS('B. Despesa'!$H$2:$H$1048576,'B. Despesa'!$I$2:$I$1048576,'Base Realizado'!H$5,'B. Despesa'!$K$2:$K$1048576,'Base Realizado'!$B29) -> -246904.36 | I29: =-H29/H$11 -> 0.10104385 | K29: =SUMIFS('B. Despesa'!$H$2:$H$1048576,'B. Despesa'!$I$2:$I$1048576,'Base Realizado'!K$5,'B. Despesa'!$K$2:$K$1048576,'Base Realizado'!$B29) -> -214044.67 | L29: =-K29/K$11 -> 0.09287273 | M29: =SUMIFS('B. Despesa'!$H$2:$H$1048576,'B. Despesa'!$I$2:$I$1048576,'Base Realizado'!M$5,'B. Despesa'!$K$2:$K$1048576,'Base Realizado'!$B29) -> 0 | N29: =SUMIFS('B. Despesa'!$H$2:$H$1048576,'B. Despesa'!$I$2:$I$1048576,'Base Realizado'!N$5,'B. Despesa'!$K$2:$K$1048576,'Base Realizado'!$B29) -> 0 | O29: =SUMIFS('B. Despesa'!$H$2:$H$1048576,'B. Despesa'!$I$2:$I$1048576,'Base Realizado'!O$5,'B. Despesa'!$K$2:$K$1048576,'Base Realizado'!$B29) -> 0 | P29: =SUMIFS('B. Despesa'!$H$2:$H$1048576,'B. Despesa'!$I$2:$I$1048576,'Base Realizado'!P$5,'B. Despesa'!$K$2:$K$1048576,'Base Realizado'!$B29) -> 0 | Q29: =SUMIFS('B. Despesa'!$H$2:$H$1048576,'B. Despesa'!$I$2:$I$1048576,'Base Realizado'!Q$5,'B. Despesa'!$K$2:$K$1048576,'Base Realizado'!$B29) -> 0 | R29: =SUMIFS('B. Despesa'!$H$2:$H$1048576,'B. Despesa'!$I$2:$I$1048576,'Base Realizado'!R$5,'B. Despesa'!$K$2:$K$1048576,'Base Realizado'!$B29) -> 0 | S29: =SUMIFS('B. Despesa'!$H$2:$H$1048576,'B. Despesa'!$I$2:$I$1048576,'Base Realizado'!S$5,'B. Despesa'!$K$2:$K$1048576,'Base Realizado'!$B29) -> 0 | T29: =SUMIFS('B. Despesa'!$H$2:$H$1048576,'B. Despesa'!$I$2:$I$1048576,'Base Realizado'!T$5,'B. Despesa'!$K$2:$K$1048576,'Base Realizado'!$B29) -> 0 | V29: -4052812.1 | X29: 0.5
B30: Pescados | C30: 5.4.1.01.00003 | D30: =SUMIFS('B. Despesa'!$H$2:$H$1048576,'B. Despesa'!$I$2:$I$1048576,'Base Realizado'!D$5,'B. Despesa'!$K$2:$K$1048576,'Base Realizado'!$B30) -> -50395.56 | E30: =-D30/D$11 -> 0.036246699 | F30: =SUMIFS('B. Despesa'!$H$2:$H$1048576,'B. Despesa'!$I$2:$I$1048576,'Base Realizado'!F$5,'B. Despesa'!$K$2:$K$1048576,'Base Realizado'!$B30) -> -22595.17 | G30: =-F30/F$11 -> 0.014782055 | H30: =SUMIFS('B. Despesa'!$H$2:$H$1048576,'B. Despesa'!$I$2:$I$1048576,'Base Realizado'!H$5,'B. Despesa'!$K$2:$K$1048576,'Base Realizado'!$B30) -> -57214.49 | I30: =-H30/H$11 -> 0.023414622 | K30: =SUMIFS('B. Despesa'!$H$2:$H$1048576,'B. Despesa'!$I$2:$I$1048576,'Base Realizado'!K$5,'B. Despesa'!$K$2:$K$1048576,'Base Realizado'!$B30) -> -55787.58 | L30: =-K30/K$11 -> 0.024205905 | M30: =SUMIFS('B. Despesa'!$H$2:$H$1048576,'B. Despesa'!$I$2:$I$1048576,'Base Realizado'!M$5,'B. Despesa'!$K$2:$K$1048576,'Base Realizado'!$B30) -> 0 | N30: =SUMIFS('B. Despesa'!$H$2:$H$1048576,'B. Despesa'!$I$2:$I$1048576,'Base Realizado'!N$5,'B. Despesa'!$K$2:$K$1048576,'Base Realizado'!$B30) -> 0 | O30: =SUMIFS('B. Despesa'!$H$2:$H$1048576,'B. Despesa'!$I$2:$I$1048576,'Base Realizado'!O$5,'B. Despesa'!$K$2:$K$1048576,'Base Realizado'!$B30) -> 0 | P30: =SUMIFS('B. Despesa'!$H$2:$H$1048576,'B. Despesa'!$I$2:$I$1048576,'Base Realizado'!P$5,'B. Despesa'!$K$2:$K$1048576,'Base Realizado'!$B30) -> 0 | Q30: =SUMIFS('B. Despesa'!$H$2:$H$1048576,'B. Despesa'!$I$2:$I$1048576,'Base Realizado'!Q$5,'B. Despesa'!$K$2:$K$1048576,'Base Realizado'!$B30) -> 0 | R30: =SUMIFS('B. Despesa'!$H$2:$H$1048576,'B. Despesa'!$I$2:$I$1048576,'Base Realizado'!R$5,'B. Despesa'!$K$2:$K$1048576,'Base Realizado'!$B30) -> 0 | S30: =SUMIFS('B. Despesa'!$H$2:$H$1048576,'B. Despesa'!$I$2:$I$1048576,'Base Realizado'!S$5,'B. Despesa'!$K$2:$K$1048576,'Base Realizado'!$B30) -> 0 | T30: =SUMIFS('B. Despesa'!$H$2:$H$1048576,'B. Despesa'!$I$2:$I$1048576,'Base Realizado'!T$5,'B. Despesa'!$K$2:$K$1048576,'Base Realizado'!$B30) -> 0 | V30: -405281.21 | X30: 0.05
B31: Vinhos/Espumantes | C31: 5.4.1.01.00006 | D31: =SUMIFS('B. Despesa'!$H$2:$H$1048576,'B. Despesa'!$I$2:$I$1048576,'Base Realizado'!D$5,'B. Despesa'!$K$2:$K$1048576,'Base Realizado'!$B31) -> -44553.57 | E31: =-D31/D$11 -> 0.032044883 | F31: =SUMIFS('B. Despesa'!$H$2:$H$1048576,'B. Despesa'!$I$2:$I$1048576,'Base Realizado'!F$5,'B. Despesa'!$K$2:$K$1048576,'Base Realizado'!$B31) -> -104825.14 | G31: =-F31/F$11 -> 0.068577974 | H31: =SUMIFS('B. Despesa'!$H$2:$H$1048576,'B. Despesa'!$I$2:$I$1048576,'Base Realizado'!H$5,'B. Despesa'!$K$2:$K$1048576,'Base Realizado'!$B31) -> -92357.05 | I31: =-H31/H$11 -> 0.037796464 | K31: =SUMIFS('B. Despesa'!$H$2:$H$1048576,'B. Despesa'!$I$2:$I$1048576,'Base Realizado'!K$5,'B. Despesa'!$K$2:$K$1048576,'Base Realizado'!$B31) -> -72805.93 | L31: =-K31/K$11 -> 0.031590067 | M31: =SUMIFS('B. Despesa'!$H$2:$H$1048576,'B. Despesa'!$I$2:$I$1048576,'Base Realizado'!M$5,'B. Despesa'!$K$2:$K$1048576,'Base Realizado'!$B31) -> 0 | N31: =SUMIFS('B. Despesa'!$H$2:$H$1048576,'B. Despesa'!$I$2:$I$1048576,'Base Realizado'!N$5,'B. Despesa'!$K$2:$K$1048576,'Base Realizado'!$B31) -> 0 | O31: =SUMIFS('B. Despesa'!$H$2:$H$1048576,'B. Despesa'!$I$2:$I$1048576,'Base Realizado'!O$5,'B. Despesa'!$K$2:$K$1048576,'Base Realizado'!$B31) -> 0 | P31: =SUMIFS('B. Despesa'!$H$2:$H$1048576,'B. Despesa'!$I$2:$I$1048576,'Base Realizado'!P$5,'B. Despesa'!$K$2:$K$1048576,'Base Realizado'!$B31) -> 0 | Q31: =SUMIFS('B. Despesa'!$H$2:$H$1048576,'B. Despesa'!$I$2:$I$1048576,'Base Realizado'!Q$5,'B. Despesa'!$K$2:$K$1048576,'Base Realizado'!$B31) -> 0 | R31: =SUMIFS('B. Despesa'!$H$2:$H$1048576,'B. Despesa'!$I$2:$I$1048576,'Base Realizado'!R$5,'B. Despesa'!$K$2:$K$1048576,'Base Realizado'!$B31) -> 0 | S31: =SUMIFS('B. Despesa'!$H$2:$H$1048576,'B. Despesa'!$I$2:$I$1048576,'Base Realizado'!S$5,'B. Despesa'!$K$2:$K$1048576,'Base Realizado'!$B31) -> 0 | T31: =SUMIFS('B. Despesa'!$H$2:$H$1048576,'B. Despesa'!$I$2:$I$1048576,'Base Realizado'!T$5,'B. Despesa'!$K$2:$K$1048576,'Base Realizado'!$B31) -> 0 | V31: -1215843.6 | X31: 0.15
B32: Bebidas Alcoólicas | C32: 5.4.1.01.00007 | D32: =SUMIFS('B. Despesa'!$H$2:$H$1048576,'B. Despesa'!$I$2:$I$1048576,'Base Realizado'!D$5,'B. Despesa'!$K$2:$K$1048576,'Base Realizado'!$B32) -> -76401.53 | E32: =-D32/D$11 -> 0.054951334 | F32: =SUMIFS('B. Despesa'!$H$2:$H$1048576,'B. Despesa'!$I$2:$I$1048576,'Base Realizado'!F$5,'B. Despesa'!$K$2:$K$1048576,'Base Realizado'!$B32) -> -73589.02 | G32: =-F32/F$11 -> 0.048142897 | H32: =SUMIFS('B. Despesa'!$H$2:$H$1048576,'B. Despesa'!$I$2:$I$1048576,'Base Realizado'!H$5,'B. Despesa'!$K$2:$K$1048576,'Base Realizado'!$B32) -> -79703.1 | I32: =-H32/H$11 -> 0.032617926 | K32: =SUMIFS('B. Despesa'!$H$2:$H$1048576,'B. Despesa'!$I$2:$I$1048576,'Base Realizado'!K$5,'B. Despesa'!$K$2:$K$1048576,'Base Realizado'!$B32) -> -88635.83 | L32: =-K32/K$11 -> 0.038458568 | M32: =SUMIFS('B. Despesa'!$H$2:$H$1048576,'B. Despesa'!$I$2:$I$1048576,'Base Realizado'!M$5,'B. Despesa'!$K$2:$K$1048576,'Base Realizado'!$B32) -> 0 | N32: =SUMIFS('B. Despesa'!$H$2:$H$1048576,'B. Despesa'!$I$2:$I$1048576,'Base Realizado'!N$5,'B. Despesa'!$K$2:$K$1048576,'Base Realizado'!$B32) -> 0 | O32: =SUMIFS('B. Despesa'!$H$2:$H$1048576,'B. Despesa'!$I$2:$I$1048576,'Base Realizado'!O$5,'B. Despesa'!$K$2:$K$1048576,'Base Realizado'!$B32) -> 0 | P32: =SUMIFS('B. Despesa'!$H$2:$H$1048576,'B. Despesa'!$I$2:$I$1048576,'Base Realizado'!P$5,'B. Despesa'!$K$2:$K$1048576,'Base Realizado'!$B32) -> 0 | Q32: =SUMIFS('B. Despesa'!$H$2:$H$1048576,'B. Despesa'!$I$2:$I$1048576,'Base Realizado'!Q$5,'B. Despesa'!$K$2:$K$1048576,'Base Realizado'!$B32) -> 0 | R32: =SUMIFS('B. Despesa'!$H$2:$H$1048576,'B. Despesa'!$I$2:$I$1048576,'Base Realizado'!R$5,'B. Despesa'!$K$2:$K$1048576,'Base Realizado'!$B32) -> 0 | S32: =SUMIFS('B. Despesa'!$H$2:$H$1048576,'B. Despesa'!$I$2:$I$1048576,'Base Realizado'!S$5,'B. Despesa'!$K$2:$K$1048576,'Base Realizado'!$B32) -> 0 | T32: =SUMIFS('B. Despesa'!$H$2:$H$1048576,'B. Despesa'!$I$2:$I$1048576,'Base Realizado'!T$5,'B. Despesa'!$K$2:$K$1048576,'Base Realizado'!$B32) -> 0 | V32: -405281.21 | X32: 0.05
B33: Bebidas não Alcoolicas | C33: 5.4.1.01.00008 | D33: =SUMIFS('B. Despesa'!$H$2:$H$1048576,'B. Despesa'!$I$2:$I$1048576,'Base Realizado'!D$5,'B. Despesa'!$K$2:$K$1048576,'Base Realizado'!$B33) -> -20668.66 | E33: =-D33/D$11 -> 0.014865807 | F33: =SUMIFS('B. Despesa'!$H$2:$H$1048576,'B. Despesa'!$I$2:$I$1048576,'Base Realizado'!F$5,'B. Despesa'!$K$2:$K$1048576,'Base Realizado'!$B33) -> -26438.81 | G33: =-F33/F$11 -> 0.017296614 | H33: =SUMIFS('B. Despesa'!$H$2:$H$1048576,'B. Despesa'!$I$2:$I$1048576,'Base Realizado'!H$5,'B. Despesa'!$K$2:$K$1048576,'Base Realizado'!$B33) -> -40716.03 | I33: =-H33/H$11 -> 0.016662745 | K33: =SUMIFS('B. Despesa'!$H$2:$H$1048576,'B. Despesa'!$I$2:$I$1048576,'Base Realizado'!K$5,'B. Despesa'!$K$2:$K$1048576,'Base Realizado'!$B33) -> -41147.82 | L33: =-K33/K$11 -> 0.017853798 | M33: =SUMIFS('B. Despesa'!$H$2:$H$1048576,'B. Despesa'!$I$2:$I$1048576,'Base Realizado'!M$5,'B. Despesa'!$K$2:$K$1048576,'Base Realizado'!$B33) -> 0 | N33: =SUMIFS('B. Despesa'!$H$2:$H$1048576,'B. Despesa'!$I$2:$I$1048576,'Base Realizado'!N$5,'B. Despesa'!$K$2:$K$1048576,'Base Realizado'!$B33) -> 0 | O33: =SUMIFS('B. Despesa'!$H$2:$H$1048576,'B. Despesa'!$I$2:$I$1048576,'Base Realizado'!O$5,'B. Despesa'!$K$2:$K$1048576,'Base Realizado'!$B33) -> 0 | P33: =SUMIFS('B. Despesa'!$H$2:$H$1048576,'B. Despesa'!$I$2:$I$1048576,'Base Realizado'!P$5,'B. Despesa'!$K$2:$K$1048576,'Base Realizado'!$B33) -> 0 | Q33: =SUMIFS('B. Despesa'!$H$2:$H$1048576,'B. Despesa'!$I$2:$I$1048576,'Base Realizado'!Q$5,'B. Despesa'!$K$2:$K$1048576,'Base Realizado'!$B33) -> 0 | R33: =SUMIFS('B. Despesa'!$H$2:$H$1048576,'B. Despesa'!$I$2:$I$1048576,'Base Realizado'!R$5,'B. Despesa'!$K$2:$K$1048576,'Base Realizado'!$B33) -> 0 | S33: =SUMIFS('B. Despesa'!$H$2:$H$1048576,'B. Despesa'!$I$2:$I$1048576,'Base Realizado'!S$5,'B. Despesa'!$K$2:$K$1048576,'Base Realizado'!$B33) -> 0 | T33: =SUMIFS('B. Despesa'!$H$2:$H$1048576,'B. Despesa'!$I$2:$I$1048576,'Base Realizado'!T$5,'B. Despesa'!$K$2:$K$1048576,'Base Realizado'!$B33) -> 0 | V33: -324224.96 | X33: 0.04
B34: Hortifruti | C34: 5.4.1.01.00009 | D34: =SUMIFS('B. Despesa'!$H$2:$H$1048576,'B. Despesa'!$I$2:$I$1048576,'Base Realizado'!D$5,'B. Despesa'!$K$2:$K$1048576,'Base Realizado'!$B34) -> -55152.66 | E34: =-D34/D$11 -> 0.039668214 | F34: =SUMIFS('B. Despesa'!$H$2:$H$1048576,'B. Despesa'!$I$2:$I$1048576,'Base Realizado'!F$5,'B. Despesa'!$K$2:$K$1048576,'Base Realizado'!$B34) -> -41279.5 | G34: =-F34/F$11 -> 0.027005587 | H34: =SUMIFS('B. Despesa'!$H$2:$H$1048576,'B. Despesa'!$I$2:$I$1048576,'Base Realizado'!H$5,'B. Despesa'!$K$2:$K$1048576,'Base Realizado'!$B34) -> -59990.51 | I34: =-H34/H$11 -> 0.024550689 | K34: =SUMIFS('B. Despesa'!$H$2:$H$1048576,'B. Despesa'!$I$2:$I$1048576,'Base Realizado'!K$5,'B. Despesa'!$K$2:$K$1048576,'Base Realizado'!$B34) -> -56189.65 | L34: =-K34/K$11 -> 0.02438036 | M34: =SUMIFS('B. Despesa'!$H$2:$H$1048576,'B. Despesa'!$I$2:$I$1048576,'Base Realizado'!M$5,'B. Despesa'!$K$2:$K$1048576,'Base Realizado'!$B34) -> 0 | N34: =SUMIFS('B. Despesa'!$H$2:$H$1048576,'B. Despesa'!$I$2:$I$1048576,'Base Realizado'!N$5,'B. Despesa'!$K$2:$K$1048576,'Base Realizado'!$B34) -> 0 | O34: =SUMIFS('B. Despesa'!$H$2:$H$1048576,'B. Despesa'!$I$2:$I$1048576,'Base Realizado'!O$5,'B. Despesa'!$K$2:$K$1048576,'Base Realizado'!$B34) -> 0 | P34: =SUMIFS('B. Despesa'!$H$2:$H$1048576,'B. Despesa'!$I$2:$I$1048576,'Base Realizado'!P$5,'B. Despesa'!$K$2:$K$1048576,'Base Realizado'!$B34) -> 0 | Q34: =SUMIFS('B. Despesa'!$H$2:$H$1048576,'B. Despesa'!$I$2:$I$1048576,'Base Realizado'!Q$5,'B. Despesa'!$K$2:$K$1048576,'Base Realizado'!$B34) -> 0 | R34: =SUMIFS('B. Despesa'!$H$2:$H$1048576,'B. Despesa'!$I$2:$I$1048576,'Base Realizado'!R$5,'B. Despesa'!$K$2:$K$1048576,'Base Realizado'!$B34) -> 0 | S34: =SUMIFS('B. Despesa'!$H$2:$H$1048576,'B. Despesa'!$I$2:$I$1048576,'Base Realizado'!S$5,'B. Despesa'!$K$2:$K$1048576,'Base Realizado'!$B34) -> 0 | T34: =SUMIFS('B. Despesa'!$H$2:$H$1048576,'B. Despesa'!$I$2:$I$1048576,'Base Realizado'!T$5,'B. Despesa'!$K$2:$K$1048576,'Base Realizado'!$B34) -> 0 | V34: -567393.69 | X34: 0.07
B35: Paes, Massas e Salgados | C35: 5.4.1.01.00010 | D35: =SUMIFS('B. Despesa'!$H$2:$H$1048576,'B. Despesa'!$I$2:$I$1048576,'Base Realizado'!D$5,'B. Despesa'!$K$2:$K$1048576,'Base Realizado'!$B35) -> -22699.4 | E35: =-D35/D$11 -> 0.016326405 | F35: =SUMIFS('B. Despesa'!$H$2:$H$1048576,'B. Despesa'!$I$2:$I$1048576,'Base Realizado'!F$5,'B. Despesa'!$K$2:$K$1048576,'Base Realizado'!$B35) -> -18032.34 | G35: =-F35/F$11 -> 0.011796992 | H35: =SUMIFS('B. Despesa'!$H$2:$H$1048576,'B. Despesa'!$I$2:$I$1048576,'Base Realizado'!H$5,'B. Despesa'!$K$2:$K$1048576,'Base Realizado'!$B35) -> -23525.5 | I35: =-H35/H$11 -> 0.0096276432 | K35: =SUMIFS('B. Despesa'!$H$2:$H$1048576,'B. Despesa'!$I$2:$I$1048576,'Base Realizado'!K$5,'B. Despesa'!$K$2:$K$1048576,'Base Realizado'!$B35) -> -20397.2 | L35: =-K35/K$11 -> 0.0088502258 | M35: =SUMIFS('B. Despesa'!$H$2:$H$1048576,'B. Despesa'!$I$2:$I$1048576,'Base Realizado'!M$5,'B. Despesa'!$K$2:$K$1048576,'Base Realizado'!$B35) -> 0 | N35: =SUMIFS('B. Despesa'!$H$2:$H$1048576,'B. Despesa'!$I$2:$I$1048576,'Base Realizado'!N$5,'B. Despesa'!$K$2:$K$1048576,'Base Realizado'!$B35) -> 0 | O35: =SUMIFS('B. Despesa'!$H$2:$H$1048576,'B. Despesa'!$I$2:$I$1048576,'Base Realizado'!O$5,'B. Despesa'!$K$2:$K$1048576,'Base Realizado'!$B35) -> 0 | P35: =SUMIFS('B. Despesa'!$H$2:$H$1048576,'B. Despesa'!$I$2:$I$1048576,'Base Realizado'!P$5,'B. Despesa'!$K$2:$K$1048576,'Base Realizado'!$B35) -> 0 | Q35: =SUMIFS('B. Despesa'!$H$2:$H$1048576,'B. Despesa'!$I$2:$I$1048576,'Base Realizado'!Q$5,'B. Despesa'!$K$2:$K$1048576,'Base Realizado'!$B35) -> 0 | R35: =SUMIFS('B. Despesa'!$H$2:$H$1048576,'B. Despesa'!$I$2:$I$1048576,'Base Realizado'!R$5,'B. Despesa'!$K$2:$K$1048576,'Base Realizado'!$B35) -> 0 | S35: =SUMIFS('B. Despesa'!$H$2:$H$1048576,'B. Despesa'!$I$2:$I$1048576,'Base Realizado'!S$5,'B. Despesa'!$K$2:$K$1048576,'Base Realizado'!$B35) -> 0 | T35: =SUMIFS('B. Despesa'!$H$2:$H$1048576,'B. Despesa'!$I$2:$I$1048576,'Base Realizado'!T$5,'B. Despesa'!$K$2:$K$1048576,'Base Realizado'!$B35) -> 0 | V35: -324224.96 | X35: 0.04
B36: Secos - Mercearia | C36: 5.4.1.01.00011 | D36: =SUMIFS('B. Despesa'!$H$2:$H$1048576,'B. Despesa'!$I$2:$I$1048576,'Base Realizado'!D$5,'B. Despesa'!$K$2:$K$1048576,'Base Realizado'!$B36) -> -84020.09 | E36: =-D36/D$11 -> 0.060430936 | F36: =SUMIFS('B. Despesa'!$H$2:$H$1048576,'B. Despesa'!$I$2:$I$1048576,'Base Realizado'!F$5,'B. Despesa'!$K$2:$K$1048576,'Base Realizado'!$B36) -> -71376.86 | G36: =-F36/F$11 -> 0.046695673 | H36: =SUMIFS('B. Despesa'!$H$2:$H$1048576,'B. Despesa'!$I$2:$I$1048576,'Base Realizado'!H$5,'B. Despesa'!$K$2:$K$1048576,'Base Realizado'!$B36) -> -108995.77 | I36: =-H36/H$11 -> 0.044605742 | K36: =SUMIFS('B. Despesa'!$H$2:$H$1048576,'B. Despesa'!$I$2:$I$1048576,'Base Realizado'!K$5,'B. Despesa'!$K$2:$K$1048576,'Base Realizado'!$B36) -> -77993.55 | L36: =-K36/K$11 -> 0.033840945 | M36: =SUMIFS('B. Despesa'!$H$2:$H$1048576,'B. Despesa'!$I$2:$I$1048576,'Base Realizado'!M$5,'B. Despesa'!$K$2:$K$1048576,'Base Realizado'!$B36) -> 0 | N36: =SUMIFS('B. Despesa'!$H$2:$H$1048576,'B. Despesa'!$I$2:$I$1048576,'Base Realizado'!N$5,'B. Despesa'!$K$2:$K$1048576,'Base Realizado'!$B36) -> 0 | O36: =SUMIFS('B. Despesa'!$H$2:$H$1048576,'B. Despesa'!$I$2:$I$1048576,'Base Realizado'!O$5,'B. Despesa'!$K$2:$K$1048576,'Base Realizado'!$B36) -> 0 | P36: =SUMIFS('B. Despesa'!$H$2:$H$1048576,'B. Despesa'!$I$2:$I$1048576,'Base Realizado'!P$5,'B. Despesa'!$K$2:$K$1048576,'Base Realizado'!$B36) -> 0 | Q36: =SUMIFS('B. Despesa'!$H$2:$H$1048576,'B. Despesa'!$I$2:$I$1048576,'Base Realizado'!Q$5,'B. Despesa'!$K$2:$K$1048576,'Base Realizado'!$B36) -> 0 | R36: =SUMIFS('B. Despesa'!$H$2:$H$1048576,'B. Despesa'!$I$2:$I$1048576,'Base Realizado'!R$5,'B. Despesa'!$K$2:$K$1048576,'Base Realizado'!$B36) -> 0 | S36: =SUMIFS('B. Despesa'!$H$2:$H$1048576,'B. Despesa'!$I$2:$I$1048576,'Base Realizado'!S$5,'B. Despesa'!$K$2:$K$1048576,'Base Realizado'!$B36) -> 0 | T36: =SUMIFS('B. Despesa'!$H$2:$H$1048576,'B. Despesa'!$I$2:$I$1048576,'Base Realizado'!T$5,'B. Despesa'!$K$2:$K$1048576,'Base Realizado'!$B36) -> 0 | V36: -405281.21 | X36: 0.05
B37: Enlatados e Conservas | C37: 5.4.1.01.00012 | D37: =SUMIFS('B. Despesa'!$H$2:$H$1048576,'B. Despesa'!$I$2:$I$1048576,'Base Realizado'!D$5,'B. Despesa'!$K$2:$K$1048576,'Base Realizado'!$B37) -> -800 | E37: =-D37/D$11 -> 0.00057539511 | F37: =SUMIFS('B. Despesa'!$H$2:$H$1048576,'B. Despesa'!$I$2:$I$1048576,'Base Realizado'!F$5,'B. Despesa'!$K$2:$K$1048576,'Base Realizado'!$B37) -> -800 | G37: =-F37/F$11 -> 0.00052337043 | H37: =SUMIFS('B. Despesa'!$H$2:$H$1048576,'B. Despesa'!$I$2:$I$1048576,'Base Realizado'!H$5,'B. Despesa'!$K$2:$K$1048576,'Base Realizado'!$B37) -> -800 | I37: =-H37/H$11 -> 0.0003273943 | K37: =SUMIFS('B. Despesa'!$H$2:$H$1048576,'B. Despesa'!$I$2:$I$1048576,'Base Realizado'!K$5,'B. Despesa'!$K$2:$K$1048576,'Base Realizado'!$B37) -> -1000 | L37: =-K37/K$11 -> 0.00043389415 | M37: =SUMIFS('B. Despesa'!$H$2:$H$1048576,'B. Despesa'!$I$2:$I$1048576,'Base Realizado'!M$5,'B. Despesa'!$K$2:$K$1048576,'Base Realizado'!$B37) -> 0 | N37: =SUMIFS('B. Despesa'!$H$2:$H$1048576,'B. Despesa'!$I$2:$I$1048576,'Base Realizado'!N$5,'B. Despesa'!$K$2:$K$1048576,'Base Realizado'!$B37) -> 0 | O37: =SUMIFS('B. Despesa'!$H$2:$H$1048576,'B. Despesa'!$I$2:$I$1048576,'Base Realizado'!O$5,'B. Despesa'!$K$2:$K$1048576,'Base Realizado'!$B37) -> 0 | P37: =SUMIFS('B. Despesa'!$H$2:$H$1048576,'B. Despesa'!$I$2:$I$1048576,'Base Realizado'!P$5,'B. Despesa'!$K$2:$K$1048576,'Base Realizado'!$B37) -> 0 | Q37: =SUMIFS('B. Despesa'!$H$2:$H$1048576,'B. Despesa'!$I$2:$I$1048576,'Base Realizado'!Q$5,'B. Despesa'!$K$2:$K$1048576,'Base Realizado'!$B37) -> 0 | R37: =SUMIFS('B. Despesa'!$H$2:$H$1048576,'B. Despesa'!$I$2:$I$1048576,'Base Realizado'!R$5,'B. Despesa'!$K$2:$K$1048576,'Base Realizado'!$B37) -> 0 | S37: =SUMIFS('B. Despesa'!$H$2:$H$1048576,'B. Despesa'!$I$2:$I$1048576,'Base Realizado'!S$5,'B. Despesa'!$K$2:$K$1048576,'Base Realizado'!$B37) -> 0 | T37: =SUMIFS('B. Despesa'!$H$2:$H$1048576,'B. Despesa'!$I$2:$I$1048576,'Base Realizado'!T$5,'B. Despesa'!$K$2:$K$1048576,'Base Realizado'!$B37) -> 0 | V37: -194534.98 | X37: 0.024
B38: Carvão | C38: 5.4.1.01.00013 | D38: =SUMIFS('B. Despesa'!$H$2:$H$1048576,'B. Despesa'!$I$2:$I$1048576,'Base Realizado'!D$5,'B. Despesa'!$K$2:$K$1048576,'Base Realizado'!$B38) -> -11144 | E38: =-D38/D$11 -> 0.0080152539 | F38: =SUMIFS('B. Despesa'!$H$2:$H$1048576,'B. Despesa'!$I$2:$I$1048576,'Base Realizado'!F$5,'B. Despesa'!$K$2:$K$1048576,'Base Realizado'!$B38) -> -11940 | G38: =-F38/F$11 -> 0.0078113037 | H38: =SUMIFS('B. Despesa'!$H$2:$H$1048576,'B. Despesa'!$I$2:$I$1048576,'Base Realizado'!H$5,'B. Despesa'!$K$2:$K$1048576,'Base Realizado'!$B38) -> -15922 | I38: =-H38/H$11 -> 0.006515965 | K38: =SUMIFS('B. Despesa'!$H$2:$H$1048576,'B. Despesa'!$I$2:$I$1048576,'Base Realizado'!K$5,'B. Despesa'!$K$2:$K$1048576,'Base Realizado'!$B38) -> -12570 | L38: =-K38/K$11 -> 0.0054540495 | M38: =SUMIFS('B. Despesa'!$H$2:$H$1048576,'B. Despesa'!$I$2:$I$1048576,'Base Realizado'!M$5,'B. Despesa'!$K$2:$K$1048576,'Base Realizado'!$B38) -> 0 | N38: =SUMIFS('B. Despesa'!$H$2:$H$1048576,'B. Despesa'!$I$2:$I$1048576,'Base Realizado'!N$5,'B. Despesa'!$K$2:$K$1048576,'Base Realizado'!$B38) -> 0 | O38: =SUMIFS('B. Despesa'!$H$2:$H$1048576,'B. Despesa'!$I$2:$I$1048576,'Base Realizado'!O$5,'B. Despesa'!$K$2:$K$1048576,'Base Realizado'!$B38) -> 0 | P38: =SUMIFS('B. Despesa'!$H$2:$H$1048576,'B. Despesa'!$I$2:$I$1048576,'Base Realizado'!P$5,'B. Despesa'!$K$2:$K$1048576,'Base Realizado'!$B38) -> 0 | Q38: =SUMIFS('B. Despesa'!$H$2:$H$1048576,'B. Despesa'!$I$2:$I$1048576,'Base Realizado'!Q$5,'B. Despesa'!$K$2:$K$1048576,'Base Realizado'!$B38) -> 0 | R38: =SUMIFS('B. Despesa'!$H$2:$H$1048576,'B. Despesa'!$I$2:$I$1048576,'Base Realizado'!R$5,'B. Despesa'!$K$2:$K$1048576,'Base Realizado'!$B38) -> 0 | S38: =SUMIFS('B. Despesa'!$H$2:$H$1048576,'B. Despesa'!$I$2:$I$1048576,'Base Realizado'!S$5,'B. Despesa'!$K$2:$K$1048576,'Base Realizado'!$B38) -> 0 | T38: =SUMIFS('B. Despesa'!$H$2:$H$1048576,'B. Despesa'!$I$2:$I$1048576,'Base Realizado'!T$5,'B. Despesa'!$K$2:$K$1048576,'Base Realizado'!$B38) -> 0 | V38: -202640.6 | X38: 0.025
B39: Gelo | C39: 5.4.1.01.00015 | D39: =SUMIFS('B. Despesa'!$H$2:$H$1048576,'B. Despesa'!$I$2:$I$1048576,'Base Realizado'!D$5,'B. Despesa'!$K$2:$K$1048576,'Base Realizado'!$B39) -> -4076.8 | E39: =-D39/D$11 -> 0.0029322135 | F39: =SUMIFS('B. Despesa'!$H$2:$H$1048576,'B. Despesa'!$I$2:$I$1048576,'Base Realizado'!F$5,'B. Despesa'!$K$2:$K$1048576,'Base Realizado'!$B39) -> -4076.8 | G39: =-F39/F$11 -> 0.0026670957 | H39: =SUMIFS('B. Despesa'!$H$2:$H$1048576,'B. Despesa'!$I$2:$I$1048576,'Base Realizado'!H$5,'B. Despesa'!$K$2:$K$1048576,'Base Realizado'!$B39) -> -5096 | I39: =-H39/H$11 -> 0.0020855017 | K39: =SUMIFS('B. Despesa'!$H$2:$H$1048576,'B. Despesa'!$I$2:$I$1048576,'Base Realizado'!K$5,'B. Despesa'!$K$2:$K$1048576,'Base Realizado'!$B39) -> -4076.8 | L39: =-K39/K$11 -> 0.0017688997 | M39: =SUMIFS('B. Despesa'!$H$2:$H$1048576,'B. Despesa'!$I$2:$I$1048576,'Base Realizado'!M$5,'B. Despesa'!$K$2:$K$1048576,'Base Realizado'!$B39) -> 0 | N39: =SUMIFS('B. Despesa'!$H$2:$H$1048576,'B. Despesa'!$I$2:$I$1048576,'Base Realizado'!N$5,'B. Despesa'!$K$2:$K$1048576,'Base Realizado'!$B39) -> 0 | O39: =SUMIFS('B. Despesa'!$H$2:$H$1048576,'B. Despesa'!$I$2:$I$1048576,'Base Realizado'!O$5,'B. Despesa'!$K$2:$K$1048576,'Base Realizado'!$B39) -> 0 | P39: =SUMIFS('B. Despesa'!$H$2:$H$1048576,'B. Despesa'!$I$2:$I$1048576,'Base Realizado'!P$5,'B. Despesa'!$K$2:$K$1048576,'Base Realizado'!$B39) -> 0 | Q39: =SUMIFS('B. Despesa'!$H$2:$H$1048576,'B. Despesa'!$I$2:$I$1048576,'Base Realizado'!Q$5,'B. Despesa'!$K$2:$K$1048576,'Base Realizado'!$B39) -> 0 | R39: =SUMIFS('B. Despesa'!$H$2:$H$1048576,'B. Despesa'!$I$2:$I$1048576,'Base Realizado'!R$5,'B. Despesa'!$K$2:$K$1048576,'Base Realizado'!$B39) -> 0 | S39: =SUMIFS('B. Despesa'!$H$2:$H$1048576,'B. Despesa'!$I$2:$I$1048576,'Base Realizado'!S$5,'B. Despesa'!$K$2:$K$1048576,'Base Realizado'!$B39) -> 0 | T39: =SUMIFS('B. Despesa'!$H$2:$H$1048576,'B. Despesa'!$I$2:$I$1048576,'Base Realizado'!T$5,'B. Despesa'!$K$2:$K$1048576,'Base Realizado'!$B39) -> 0 | V39: -8105.6241 | X39: 0.001
B40: Estoque Final | C40: 5.4.1.01.00016 | D40: =-102070.05-172285.83 -> -274355.88 | E40: =-D40/D$11 -> 0.19732879 | F40: -261339.16 | G40: =-F40/F$11 -> 0.17097149 | H40: =-175084.48-5000 -> -180084.48 | I40: =-H40/H$11 -> 0.07369829 | K40: -431062.84 | L40: =-K40/K$11 -> 0.18703565 | V40: 0 | X40: 0
B41: Estoque Inicial | C41: 5.4.1.01.00001 | D41: 213865.46 | E41: =D41/D$11 -> 0.15382143 | F41: =-D40 -> 274355.88 | G41: =F41/F$11 -> 0.17948719 | H41: =-F40 -> 261339.16 | I41: =H41/H$11 -> 0.10695119 | K41: =-H40 -> 180084.48 | L41: =K41/K$11 -> 0.078137602 | M41: 0 | N41: 0 | O41: 0 | P41: 0 | Q41: 0 | R41: 0 | S41: 0 | T41: 0 | V41: 0 | X41: 0
B42: (-) Reclassificação CMV | C42: 5.4.1.01.00017 | F42: 0 | H42: 0 | K42: 0 | M42: 0 | N42: 0 | O42: 0 | P42: 0 | Q42: 0 | R42: 0 | S42: 0 | T42: 0 | V42: 0 | X42: 0
B44: ÍNDICE | D44: =D46/D45 -> 0.44878234 | F44: =F46/F45 -> 0.3499834 | H44: =H46/H45 -> 0.27268283 | K44: =K46/K45 -> 0.38860749 | V44: 0.32
B45: RECEITA LÍQUIDA | D45: =D11+D20 -> 1338861.7 | F45: =F11+F20 -> 1507127.3 | H45: =H11+H20 -> 2383612.2 | K45: =K11+K20 -> 2304709.6 | M45: =M11+M20 -> 0 | N45: =N11+N20 -> 0 | O45: =O11+O20 -> 0 | P45: =P11+P20 -> 0 | Q45: =Q11+Q20 -> 0 | R45: =R11+R20 -> 0 | S45: =S11+S20 -> 0 | T45: =T11+T20 -> 0 | V45: 25330075
B46: CMV | D46: =-D28 -> 600857.5 | F46: =-F28 -> 527469.52 | H46: =-H28 -> 649970.13 | K46: =-K28 -> 895627.39 | M46: =-M28 -> 0 | N46: =-N28 -> 0 | O46: =-O28 -> 0 | P46: =-P28 -> 0 | Q46: =-Q28 -> 0 | R46: =-R28 -> 0 | S46: =-S28 -> 0 | T46: =-T28 -> 0 | V46: 8105624.1
B48: PESSOAL | D48: =SUM(D49:D66) -> -268326.13 | E48: =SUM(E49:E66) -> 0.19299193 | F48: =SUM(F49:F66) -> -386191.74 | G48: =SUM(G49:G66) -> 0.25265167 | H48: =SUM(H49:H66) -> -449390.89 | I48: =SUM(I49:I66) -> 0.18391002 | K48: =SUM(K49:K73) -> -589701.16 | L48: =SUM(L49:L66) -> 0.25586788 | M48: =SUM(M49:M73) -> 0 | N48: =SUM(N49:N73) -> 0 | O48: =SUM(O49:O73) -> 0 | P48: =SUM(P49:P73) -> 0 | Q48: =SUM(Q49:Q73) -> 0 | R48: =SUM(R49:R73) -> 0 | S48: =SUM(S49:S73) -> 0 | T48: =SUM(T49:T73) -> 0 | V48: -6739721.6 | X48: %
B49: Salários e Ordenados | C49: 5.4.1.02.00001 | D49: =SUMIFS('B. Despesa'!$H$2:$H$1048576,'B. Despesa'!$I$2:$I$1048576,'Base Realizado'!D$5,'B. Despesa'!$K$2:$K$1048576,'Base Realizado'!$B49) -> -116300.64 | E49: =-D49/D$11 -> 0.083648525 | F49: =SUMIFS('B. Despesa'!$H$2:$H$1048576,'B. Despesa'!$I$2:$I$1048576,'Base Realizado'!F$5,'B. Despesa'!$K$2:$K$1048576,'Base Realizado'!$B49) -> -120558.98 | G49: =-F49/F$11 -> 0.078871257 | H49: =SUMIFS('B. Despesa'!$H$2:$H$1048576,'B. Despesa'!$I$2:$I$1048576,'Base Realizado'!H$5,'B. Despesa'!$K$2:$K$1048576,'Base Realizado'!$B49) -> -126223.22 | I49: =-H49/H$11 -> 0.051655953 | K49: =SUMIFS('B. Despesa'!$H$2:$H$1048576,'B. Despesa'!$I$2:$I$1048576,'Base Realizado'!K$5,'B. Despesa'!$K$2:$K$1048576,'Base Realizado'!$B49) -> -257302.51 | L49: =-K49/K$11 -> 0.11164205 | M49: =SUMIFS('B. Despesa'!$H$2:$H$1048576,'B. Despesa'!$I$2:$I$1048576,'Base Realizado'!M$5,'B. Despesa'!$K$2:$K$1048576,'Base Realizado'!$B49) -> 0 | N49: =SUMIFS('B. Despesa'!$H$2:$H$1048576,'B. Despesa'!$I$2:$I$1048576,'Base Realizado'!N$5,'B. Despesa'!$K$2:$K$1048576,'Base Realizado'!$B49) -> 0 | O49: =SUMIFS('B. Despesa'!$H$2:$H$1048576,'B. Despesa'!$I$2:$I$1048576,'Base Realizado'!O$5,'B. Despesa'!$K$2:$K$1048576,'Base Realizado'!$B49) -> 0 | P49: =SUMIFS('B. Despesa'!$H$2:$H$1048576,'B. Despesa'!$I$2:$I$1048576,'Base Realizado'!P$5,'B. Despesa'!$K$2:$K$1048576,'Base Realizado'!$B49) -> 0 | Q49: =SUMIFS('B. Despesa'!$H$2:$H$1048576,'B. Despesa'!$I$2:$I$1048576,'Base Realizado'!Q$5,'B. Despesa'!$K$2:$K$1048576,'Base Realizado'!$B49) -> 0 | R49: =SUMIFS('B. Despesa'!$H$2:$H$1048576,'B. Despesa'!$I$2:$I$1048576,'Base Realizado'!R$5,'B. Despesa'!$K$2:$K$1048576,'Base Realizado'!$B49) -> 0 | S49: =SUMIFS('B. Despesa'!$H$2:$H$1048576,'B. Despesa'!$I$2:$I$1048576,'Base Realizado'!S$5,'B. Despesa'!$K$2:$K$1048576,'Base Realizado'!$B49) -> 0 | T49: =SUMIFS('B. Despesa'!$H$2:$H$1048576,'B. Despesa'!$I$2:$I$1048576,'Base Realizado'!T$5,'B. Despesa'!$K$2:$K$1048576,'Base Realizado'!$B49) -> 0 | V49: -2616448.1
