Workbook
Name __FDS_HYPERLINK_TOGGLE_STATE__: "ON"
Name _Order1: 0
Name _Order2: 0
Name a: -15987005.5299987
Name ADM: #REF!
Name ADM: #REF!
Name ADM: #REF!
Name ADM: #REF!
Name ADM: #REF!
Name ADM: #REF!
Name ADM: [0]!ADM
Name ALPHA: #REF!
Name ALPHA: #REF!
Name ALPHA: #REF!
Name ALPHA: #REF!
Name ALPHA: #REF!
Name ALPHA: #REF!
Name Amountin2: "Thousands"
Name AnoDoCalendário: #REF!
Name AnoDoCalendário: #REF!
Name AnoDoCalendário: #REF!
Name Ativo: #REF!
Name Ativo: #REF!
Name Ativo: #REF!
Name Ativo: #REF!
Name AV: #REF!
Name Balanço: #REF!
Name Balanço: #REF!
Name Balanço: #REF!
Name Balanço: #REF!
Name BaseYear: #REF!
Name BaseYear: #REF!
Name BaseYear: #REF!
Name BBQ: #REF!
Name BD_Fluxo_Entradas: #REF!
Name BD_Fluxo_Entradas: #REF!
Name BD_Fluxo_Entradas: #REF!
Name BD_Fluxo_Entradas: #REF!
Name BD_Fluxo_Entradas: #REF!
Name BD_Fluxo_Entradas: #REF!
Name BD_Fluxo_Entradas: #REF!
Name BD_Fluxo_Saidas: #REF!
Name BD_Fluxo_Saidas: #REF!
Name BD_Fluxo_Saidas: #REF!
Name BD_Fluxo_Saidas: #REF!
Name BD_Fluxo_Saidas: #REF!
Name BD_Fluxo_Saidas: #REF!
Name BD_Fluxo_Saidas: #REF!
Name BH: #REF!
Name BreakComercial: '01 Base Realizado'!BreakComercial
Name BreakComercial: #REF!
Name BreakComercial: '04 -Base Orçado 2026'!BreakComercial
Name BreakComercial: #REF!
Name BreakComercial: #REF!
Name BreakComercial: #REF!
Name BreakComercial: '04 -Base Orçado 2026'!BreakComercial
Name BS: #REF!
Name BS_Deferred_Taxes: #REF!
Name BS_Deferred_Taxes: #REF!
Name BS_Deferred_Taxes: #REF!

Sheet 01 Base Realizado
D1: REALIZADO/26 - BASE DE DADOS
B5: DESCRIÇÃO | C5: CONTA | D5: JAN 2026 | E5: AV | F5: FEV 2026 | G5: AV | H5: MAR 2026 | I5: AV | J5: ABR 2026 | K5: MAIO 2026 | L5: JUN 2026 | M5: JUL 2026 | N5: AGO 2026 | O5: SET 2026 | P5: OUT 2026 | Q5: NOV 2026 | R5: DEZ 2026 | T5: TOTAL | Y5: Comentários
B7: CLIENTES | C7: x.x.x.xx.xxxxx | D7: 4761 | T7: 91427.812
B8: TICKET MEDIO | C8: x.x.x.xx.xxxxx | D8: 292 | T8: 300
B10: Rec.Venda no Merc.Int.de Prod.Fabr.Próp. | C10: 3.1.1.01.00004 | T10: 27428344
B11: FATURAMENTO | D11: =SUM(D12:D17)-D12 -> 211614.21 | E11: =SUM(E13:E17) -> 1 | F11: =SUM(F12:F17)-F12 -> 260183.47 | G11: =SUM(G13:G14) -> 1 | H11: =SUM(H12:H14)-H12 -> 401985.89 | I11: =SUM(I13:I14) -> 1 | J11: =SUM(J13:J17) -> 0 | K11: =SUM(K13:K17) -> 0 | L11: =SUM(L13:L17) -> 0 | M11: =SUM(M13:M17) -> 0 | N11: =SUM(N13:N17) -> 0 | O11: =SUM(O13:O17) -> 0 | P11: =SUM(P13:P17) -> 0 | Q11: =SUM(Q13:Q17) -> 0 | R11: =SUM(R13:R17) -> 0 | T11: 27428344 | V11: =SUM(V13:V17) -> 0.344
B12: Gorjetas Recebidas | D12: 24239 | E12: =D12/D$11 -> 0.11454335 | F12: 29204.66 | G12: =F12/F$11 -> 0.11224641 | H12: 46878.24 | I12: =H12/H$11 -> 0.11661663 | T12: 0
B13: Dinheiro/Pix | C13: x.x.x.xx.xxxxx | D13: 6593.74 | E13: =D13/D$11 -> 0.03115925 | F13: =5809.29+10718.3 -> 16527.59 | G13: =F13/F$11 -> 0.063522829 | H13: 23177.13 | I13: =H13/H$11 -> 0.057656576 | T13: 548566.87 | V13: 0.02
B14: Cartão de Débito/ Crédito | C14: x.x.x.xx.xxxxx | D14: 205020.47 | E14: =D14/D$11 -> 0.96884075 | F14: =214451.22+F12 -> 243655.88 | G14: =F14/F$11 -> 0.93647717 | H14: =331930.52+H12 -> 378808.76 | I14: =H14/H$11 -> 0.94234342 | T14: 1919984.1 | V14: 0.07
B15: Evento Faturado | C15: x.x.x.xx.xxxxx | D15: =SUMIFS(B.Receita!$E:$E,B.Receita!$F:$F,'01 Base Realizado'!$B15,B.Receita!$H:$H,'01 Base Realizado'!D$5) -> 0 | T15: 2742834.4 | V15: 0.1
B16: Delivery | C16: x.x.x.xx.xxxxx | D16: =SUMIFS(B.Receita!$E:$E,B.Receita!$F:$F,'01 Base Realizado'!$B16,B.Receita!$H:$H,'01 Base Realizado'!D$5) -> 0 | T16: 4114251.5 | V16: 0.15
B17: Voucher | C17: x.x.x.xx.xxxxx | D17: =SUMIFS(B.Receita!$E:$E,B.Receita!$F:$F,'01 Base Realizado'!$B17,B.Receita!$H:$H,'01 Base Realizado'!D$5) -> 0 | T17: 109713.37 | V17: 0.004
B19: IMPOSTOS | D19: =SUM(D20:D26) -> -461.04 | F19: =SUM(F20:F26) -> -819.32 | H19: =SUM(H20:H26) -> -2604.39 | J19: =SUM(J20:J26) -> 0 | K19: =SUM(K20:K26) -> 0 | L19: =SUM(L20:L26) -> 0 | M19: =SUM(M20:M26) -> 0 | N19: =SUM(N20:N26) -> 0 | O19: =SUM(O20:O26) -> 0 | P19: =SUM(P20:P26) -> 0 | Q19: =SUM(Q20:Q26) -> 0 | R19: =SUM(R20:R26) -> 0 | T19: -2919061.3 | V19: %
B20: (-) ICMS | C20: 3.1.1.02.00002 | D20: =SUMIFS('B. Despesa'!$H:$H,'B. Despesa'!$I:$I,'01 Base Realizado'!D$5,'B. Despesa'!$K:$K,'01 Base Realizado'!$B20) -> -461.04 | F20: =SUMIFS('B. Despesa'!$H:$H,'B. Despesa'!$I:$I,'01 Base Realizado'!F$5,'B. Despesa'!$K:$K,'01 Base Realizado'!$B20) -> 0 | H20: =SUMIFS('B. Despesa'!$H$5:$H$1048576,'B. Despesa'!$I$5:$I$1048576,'01 Base Realizado'!H$5,'B. Despesa'!$K$5:$K$1048576,'01 Base Realizado'!$B20) -> 0 | J20: =SUMIFS('B. Despesa'!$H$5:$H$1048576,'B. Despesa'!$I$5:$I$1048576,'01 Base Realizado'!J$5,'B. Despesa'!$K$5:$K$1048576,'01 Base Realizado'!$B20) -> 0 | K20: =SUMIFS('B. Despesa'!$H$5:$H$1048576,'B. Despesa'!$I$5:$I$1048576,'01 Base Realizado'!K$5,'B. Despesa'!$K$5:$K$1048576,'01 Base Realizado'!$B20) -> 0 | L20: =SUMIFS('B. Despesa'!$H$5:$H$1048576,'B. Despesa'!$I$5:$I$1048576,'01 Base Realizado'!L$5,'B. Despesa'!$K$5:$K$1048576,'01 Base Realizado'!$B20) -> 0 | M20: =SUMIFS('B. Despesa'!$H$5:$H$1048576,'B. Despesa'!$I$5:$I$1048576,'01 Base Realizado'!M$5,'B. Despesa'!$K$5:$K$1048576,'01 Base Realizado'!$B20) -> 0 | N20: =SUMIFS('B. Despesa'!$H$5:$H$1048576,'B. Despesa'!$I$5:$I$1048576,'01 Base Realizado'!N$5,'B. Despesa'!$K$5:$K$1048576,'01 Base Realizado'!$B20) -> 0 | O20: =SUMIFS('B. Despesa'!$H$5:$H$1048576,'B. Despesa'!$I$5:$I$1048576,'01 Base Realizado'!O$5,'B. Despesa'!$K$5:$K$1048576,'01 Base Realizado'!$B20) -> 0 | P20: =SUMIFS('B. Despesa'!$H$5:$H$1048576,'B. Despesa'!$I$5:$I$1048576,'01 Base Realizado'!P$5,'B. Despesa'!$K$5:$K$1048576,'01 Base Realizado'!$B20) -> 0 | Q20: =SUMIFS('B. Despesa'!$H$5:$H$1048576,'B. Despesa'!$I$5:$I$1048576,'01 Base Realizado'!Q$5,'B. Despesa'!$K$5:$K$1048576,'01 Base Realizado'!$B20) -> 0 | R20: =SUMIFS('B. Despesa'!$H$5:$H$1048576,'B. Despesa'!$I$5:$I$1048576,'01 Base Realizado'!R$5,'B. Despesa'!$K$5:$K$1048576,'01 Base Realizado'!$B20) -> 0 | T20: -1097133.7 | V20: 0.04
B21: (-) PIS/Cofins | C21: 3.1.1.02.00003 | D21: =SUMIFS('B. Despesa'!$H:$H,'B. Despesa'!$I:$I,'01 Base Realizado'!D$5,'B. Despesa'!$K:$K,'01 Base Realizado'!$B21) -> 0 | F21: =SUMIFS('B. Despesa'!$H$5:$H$1048576,'B. Despesa'!$I$5:$I$1048576,'01 Base Realizado'!F$5,'B. Despesa'!$K$5:$K$1048576,'01 Base Realizado'!$B21) -> -819.32 | H21: =SUMIFS('B. Despesa'!$H$5:$H$1048576,'B. Despesa'!$I$5:$I$1048576,'01 Base Realizado'!H$5,'B. Despesa'!$K$5:$K$1048576,'01 Base Realizado'!$B21) -> -929.52 | J21: =SUMIFS('B. Despesa'!$H$5:$H$1048576,'B. Despesa'!$I$5:$I$1048576,'01 Base Realizado'!J$5,'B. Despesa'!$K$5:$K$1048576,'01 Base Realizado'!$B21) -> 0 | K21: =SUMIFS('B. Despesa'!$H$5:$H$1048576,'B. Despesa'!$I$5:$I$1048576,'01 Base Realizado'!K$5,'B. Despesa'!$K$5:$K$1048576,'01 Base Realizado'!$B21) -> 0 | L21: =SUMIFS('B. Despesa'!$H$5:$H$1048576,'B. Despesa'!$I$5:$I$1048576,'01 Base Realizado'!L$5,'B. Despesa'!$K$5:$K$1048576,'01 Base Realizado'!$B21) -> 0 | M21: =SUMIFS('B. Despesa'!$H$5:$H$1048576,'B. Despesa'!$I$5:$I$1048576,'01 Base Realizado'!M$5,'B. Despesa'!$K$5:$K$1048576,'01 Base Realizado'!$B21) -> 0 | N21: =SUMIFS('B. Despesa'!$H$5:$H$1048576,'B. Despesa'!$I$5:$I$1048576,'01 Base Realizado'!N$5,'B. Despesa'!$K$5:$K$1048576,'01 Base Realizado'!$B21) -> 0 | O21: =SUMIFS('B. Despesa'!$H$5:$H$1048576,'B. Despesa'!$I$5:$I$1048576,'01 Base Realizado'!O$5,'B. Despesa'!$K$5:$K$1048576,'01 Base Realizado'!$B21) -> 0 | P21: =SUMIFS('B. Despesa'!$H$5:$H$1048576,'B. Despesa'!$I$5:$I$1048576,'01 Base Realizado'!P$5,'B. Despesa'!$K$5:$K$1048576,'01 Base Realizado'!$B21) -> 0 | Q21: =SUMIFS('B. Despesa'!$H$5:$H$1048576,'B. Despesa'!$I$5:$I$1048576,'01 Base Realizado'!Q$5,'B. Despesa'!$K$5:$K$1048576,'01 Base Realizado'!$B21) -> 0 | R21: =SUMIFS('B. Despesa'!$H$5:$H$1048576,'B. Despesa'!$I$5:$I$1048576,'01 Base Realizado'!R$5,'B. Despesa'!$K$5:$K$1048576,'01 Base Realizado'!$B21) -> 0 | T21: -822850.31 | V21: 0.03
B22: (-) PIS/Pasep | C22: 3.1.1.02.00004 | D22: =SUMIFS('B. Despesa'!$H:$H,'B. Despesa'!$I:$I,'01 Base Realizado'!D$5,'B. Despesa'!$K:$K,'01 Base Realizado'!$B22) -> 0 | F22: =SUMIFS('B. Despesa'!$H$5:$H$1048576,'B. Despesa'!$I$5:$I$1048576,'01 Base Realizado'!F$5,'B. Despesa'!$K$5:$K$1048576,'01 Base Realizado'!$B22) -> 0 | H22: =SUMIFS('B. Despesa'!$H$5:$H$1048576,'B. Despesa'!$I$5:$I$1048576,'01 Base Realizado'!H$5,'B. Despesa'!$K$5:$K$1048576,'01 Base Realizado'!$B22) -> 0 | J22: =SUMIFS('B. Despesa'!$H$5:$H$1048576,'B. Despesa'!$I$5:$I$1048576,'01 Base Realizado'!J$5,'B. Despesa'!$K$5:$K$1048576,'01 Base Realizado'!$B22) -> 0 | K22: =SUMIFS('B. Despesa'!$H$5:$H$1048576,'B. Despesa'!$I$5:$I$1048576,'01 Base Realizado'!K$5,'B. Despesa'!$K$5:$K$1048576,'01 Base Realizado'!$B22) -> 0 | L22: =SUMIFS('B. Despesa'!$H$5:$H$1048576,'B. Despesa'!$I$5:$I$1048576,'01 Base Realizado'!L$5,'B. Despesa'!$K$5:$K$1048576,'01 Base Realizado'!$B22) -> 0 | M22: =SUMIFS('B. Despesa'!$H$5:$H$1048576,'B. Despesa'!$I$5:$I$1048576,'01 Base Realizado'!M$5,'B. Despesa'!$K$5:$K$1048576,'01 Base Realizado'!$B22) -> 0 | N22: =SUMIFS('B. Despesa'!$H$5:$H$1048576,'B. Despesa'!$I$5:$I$1048576,'01 Base Realizado'!N$5,'B. Despesa'!$K$5:$K$1048576,'01 Base Realizado'!$B22) -> 0 | O22: =SUMIFS('B. Despesa'!$H$5:$H$1048576,'B. Despesa'!$I$5:$I$1048576,'01 Base Realizado'!O$5,'B. Despesa'!$K$5:$K$1048576,'01 Base Realizado'!$B22) -> 0 | P22: =SUMIFS('B. Despesa'!$H$5:$H$1048576,'B. Despesa'!$I$5:$I$1048576,'01 Base Realizado'!P$5,'B. Despesa'!$K$5:$K$1048576,'01 Base Realizado'!$B22) -> 0 | Q22: =SUMIFS('B. Despesa'!$H$5:$H$1048576,'B. Despesa'!$I$5:$I$1048576,'01 Base Realizado'!Q$5,'B. Despesa'!$K$5:$K$1048576,'01 Base Realizado'!$B22) -> 0 | R22: =SUMIFS('B. Despesa'!$H$5:$H$1048576,'B. Despesa'!$I$5:$I$1048576,'01 Base Realizado'!R$5,'B. Despesa'!$K$5:$K$1048576,'01 Base Realizado'!$B22) -> 0 | T22: -178284.23 | V22: 0.0065
B23: (-) ISS | C23: 5.4.1.03.00035 | D23: =SUMIFS('B. Despesa'!$H:$H,'B. Despesa'!$I:$I,'01 Base Realizado'!D$5,'B. Despesa'!$K:$K,'01 Base Realizado'!$B23) -> 0 | F23: =SUMIFS('B. Despesa'!$H$5:$H$1048576,'B. Despesa'!$I$5:$I$1048576,'01 Base Realizado'!F$5,'B. Despesa'!$K$5:$K$1048576,'01 Base Realizado'!$B23) -> 0 | H23: =SUMIFS('B. Despesa'!$H$5:$H$1048576,'B. Despesa'!$I$5:$I$1048576,'01 Base Realizado'!H$5,'B. Despesa'!$K$5:$K$1048576,'01 Base Realizado'!$B23) -> 0 | J23: =SUMIFS('B. Despesa'!$H$5:$H$1048576,'B. Despesa'!$I$5:$I$1048576,'01 Base Realizado'!J$5,'B. Despesa'!$K$5:$K$1048576,'01 Base Realizado'!$B23) -> 0 | K23: =SUMIFS('B. Despesa'!$H$5:$H$1048576,'B. Despesa'!$I$5:$I$1048576,'01 Base Realizado'!K$5,'B. Despesa'!$K$5:$K$1048576,'01 Base Realizado'!$B23) -> 0 | L23: =SUMIFS('B. Despesa'!$H$5:$H$1048576,'B. Despesa'!$I$5:$I$1048576,'01 Base Realizado'!L$5,'B. Despesa'!$K$5:$K$1048576,'01 Base Realizado'!$B23) -> 0 | M23: =SUMIFS('B. Despesa'!$H$5:$H$1048576,'B. Despesa'!$I$5:$I$1048576,'01 Base Realizado'!M$5,'B. Despesa'!$K$5:$K$1048576,'01 Base Realizado'!$B23) -> 0 | N23: =SUMIFS('B. Despesa'!$H$5:$H$1048576,'B. Despesa'!$I$5:$I$1048576,'01 Base Realizado'!N$5,'B. Despesa'!$K$5:$K$1048576,'01 Base Realizado'!$B23) -> 0 | O23: =SUMIFS('B. Despesa'!$H$5:$H$1048576,'B. Despesa'!$I$5:$I$1048576,'01 Base Realizado'!O$5,'B. Despesa'!$K$5:$K$1048576,'01 Base Realizado'!$B23) -> 0 | P23: =SUMIFS('B. Despesa'!$H$5:$H$1048576,'B. Despesa'!$I$5:$I$1048576,'01 Base Realizado'!P$5,'B. Despesa'!$K$5:$K$1048576,'01 Base Realizado'!$B23) -> 0 | Q23: =SUMIFS('B. Despesa'!$H$5:$H$1048576,'B. Despesa'!$I$5:$I$1048576,'01 Base Realizado'!Q$5,'B. Despesa'!$K$5:$K$1048576,'01 Base Realizado'!$B23) -> 0 | R23: =SUMIFS('B. Despesa'!$H$5:$H$1048576,'B. Despesa'!$I$5:$I$1048576,'01 Base Realizado'!R$5,'B. Despesa'!$K$5:$K$1048576,'01 Base Realizado'!$B23) -> 0 | T23: 0 | V23: 0
B24: (-) IRPJ/CSLL | C24: 6.1.1.01.00001 | D24: =SUMIFS('B. Despesa'!$H:$H,'B. Despesa'!$I:$I,'01 Base Realizado'!D$5,'B. Despesa'!$K:$K,'01 Base Realizado'!$B24) -> 0 | F24: =SUMIFS('B. Despesa'!$H$5:$H$1048576,'B. Despesa'!$I$5:$I$1048576,'01 Base Realizado'!F$5,'B. Despesa'!$K$5:$K$1048576,'01 Base Realizado'!$B24) -> 0 | H24: =SUMIFS('B. Despesa'!$H$5:$H$1048576,'B. Despesa'!$I$5:$I$1048576,'01 Base Realizado'!H$5,'B. Despesa'!$K$5:$K$1048576,'01 Base Realizado'!$B24) -> -1674.87 | J24: =SUMIFS('B. Despesa'!$H$5:$H$1048576,'B. Despesa'!$I$5:$I$1048576,'01 Base Realizado'!J$5,'B. Despesa'!$K$5:$K$1048576,'01 Base Realizado'!$B24) -> 0 | K24: =SUMIFS('B. Despesa'!$H$5:$H$1048576,'B. Despesa'!$I$5:$I$1048576,'01 Base Realizado'!K$5,'B. Despesa'!$K$5:$K$1048576,'01 Base Realizado'!$B24) -> 0 | L24: =SUMIFS('B. Despesa'!$H$5:$H$1048576,'B. Despesa'!$I$5:$I$1048576,'01 Base Realizado'!L$5,'B. Despesa'!$K$5:$K$1048576,'01 Base Realizado'!$B24) -> 0 | M24: =SUMIFS('B. Despesa'!$H$5:$H$1048576,'B. Despesa'!$I$5:$I$1048576,'01 Base Realizado'!M$5,'B. Despesa'!$K$5:$K$1048576,'01 Base Realizado'!$B24) -> 0 | N24: =SUMIFS('B. Despesa'!$H$5:$H$1048576,'B. Despesa'!$I$5:$I$1048576,'01 Base Realizado'!N$5,'B. Despesa'!$K$5:$K$1048576,'01 Base Realizado'!$B24) -> 0 | O24: =SUMIFS('B. Despesa'!$H$5:$H$1048576,'B. Despesa'!$I$5:$I$1048576,'01 Base Realizado'!O$5,'B. Despesa'!$K$5:$K$1048576,'01 Base Realizado'!$B24) -> 0 | P24: =SUMIFS('B. Despesa'!$H$5:$H$1048576,'B. Despesa'!$I$5:$I$1048576,'01 Base Realizado'!P$5,'B. Despesa'!$K$5:$K$1048576,'01 Base Realizado'!$B24) -> 0 | Q24: =SUMIFS('B. Despesa'!$H$5:$H$1048576,'B. Despesa'!$I$5:$I$1048576,'01 Base Realizado'!Q$5,'B. Despesa'!$K$5:$K$1048576,'01 Base Realizado'!$B24) -> 0 | R24: =SUMIFS('B. Despesa'!$H$5:$H$1048576,'B. Despesa'!$I$5:$I$1048576,'01 Base Realizado'!R$5,'B. Despesa'!$K$5:$K$1048576,'01 Base Realizado'!$B24) -> 0 | T24: -524566.87 | V24: 0.08 | W24: 0.15
C25: 6.1.1.01.00002 | D25: =SUMIFS('B. Despesa'!$H:$H,'B. Despesa'!$I:$I,'01 Base Realizado'!D$5,'B. Despesa'!$K:$K,'01 Base Realizado'!$B25) -> 0 | F25: =SUMIFS('B. Despesa'!$H$5:$H$1048576,'B. Despesa'!$I$5:$I$1048576,'01 Base Realizado'!F$5,'B. Despesa'!$K$5:$K$1048576,'01 Base Realizado'!$B25) -> 0 | H25: =SUMIFS('B. Despesa'!$H$5:$H$1048576,'B. Despesa'!$I$5:$I$1048576,'01 Base Realizado'!H$5,'B. Despesa'!$K$5:$K$1048576,'01 Base Realizado'!$B25) -> 0 | J25: =SUMIFS('B. Despesa'!$H$5:$H$1048576,'B. Despesa'!$I$5:$I$1048576,'01 Base Realizado'!J$5,'B. Despesa'!$K$5:$K$1048576,'01 Base Realizado'!$B25) -> 0 | K25: =SUMIFS('B. Despesa'!$H$5:$H$1048576,'B. Despesa'!$I$5:$I$1048576,'01 Base Realizado'!K$5,'B. Despesa'!$K$5:$K$1048576,'01 Base Realizado'!$B25) -> 0 | L25: =SUMIFS('B. Despesa'!$H$5:$H$1048576,'B. Despesa'!$I$5:$I$1048576,'01 Base Realizado'!L$5,'B. Despesa'!$K$5:$K$1048576,'01 Base Realizado'!$B25) -> 0 | M25: =SUMIFS('B. Despesa'!$H$5:$H$1048576,'B. Despesa'!$I$5:$I$1048576,'01 Base Realizado'!M$5,'B. Despesa'!$K$5:$K$1048576,'01 Base Realizado'!$B25) -> 0 | N25: =SUMIFS('B. Despesa'!$H$5:$H$1048576,'B. Despesa'!$I$5:$I$1048576,'01 Base Realizado'!N$5,'B. Despesa'!$K$5:$K$1048576,'01 Base Realizado'!$B25) -> 0 | O25: =SUMIFS('B. Despesa'!$H$5:$H$1048576,'B. Despesa'!$I$5:$I$1048576,'01 Base Realizado'!O$5,'B. Despesa'!$K$5:$K$1048576,'01 Base Realizado'!$B25) -> 0 | P25: =SUMIFS('B. Despesa'!$H$5:$H$1048576,'B. Despesa'!$I$5:$I$1048576,'01 Base Realizado'!P$5,'B. Despesa'!$K$5:$K$1048576,'01 Base Realizado'!$B25) -> 0 | Q25: =SUMIFS('B. Despesa'!$H$5:$H$1048576,'B. Despesa'!$I$5:$I$1048576,'01 Base Realizado'!Q$5,'B. Despesa'!$K$5:$K$1048576,'01 Base Realizado'!$B25) -> 0 | R25: =SUMIFS('B. Despesa'!$H$5:$H$1048576,'B. Despesa'!$I$5:$I$1048576,'01 Base Realizado'!R$5,'B. Despesa'!$K$5:$K$1048576,'01 Base Realizado'!$B25) -> 0 | T25: -296226.11 | V25: 0.12 | W25: 0.09
B26: IRPJ | C26: 4.1.2.04.00002 | D26: =SUMIFS('B. Despesa'!$H:$H,'B. Despesa'!$I:$I,'01 Base Realizado'!D$5,'B. Despesa'!$K:$K,'01 Base Realizado'!$B26) -> 0 | F26: 0 | H26: 0 | J26: 0 | K26: 0 | L26: 0 | M26: 0 | N26: 0 | O26: 0 | P26: 0 | Q26: 0 | R26: 0 | T26: 0 | V26: 0
B27: CSLL | C27: 4.1.2.04.00001 | D27: =SUMIFS('B. Despesa'!$H:$H,'B. Despesa'!$I:$I,'01 Base Realizado'!D$5,'B. Despesa'!$K:$K,'01 Base Realizado'!$B27) -> 0 | F27: 0 | H27: 0 | J27: 0 | K27: 0 | L27: 0 | M27: 0 | N27: 0 | O27: 0 | P27: 0 | Q27: 0 | R27: 0 | T27: 0 | V27: 0
B28: CUSTOS DOS PRODUTOS VENDIDOS | D28: =SUM(D29:D34)-D35 -> 40294.722 | F28: =SUM(F29:F34)-F35 -> 68959.922 | H28: =SUM(H29:H34)-H35 -> 77942.836 | J28: =SUM(J29:J35) -> 0 | K28: =SUM(K29:K35) -> 0 | L28: =SUM(L29:L35) -> 0 | M28: =SUM(M29:M35) -> 0 | N28: =SUM(N29:N35) -> 0 | O28: =SUM(O29:O35) -> 0 | P28: =SUM(P29:P35) -> 0 | Q28: =SUM(Q29:Q35) -> 0 | R28: =SUM(R29:R35) -> 0 | T28: -8105624.1 | V28: =SUM(V29:V35) -> 0.79 | W28: 1 | X28: =V28-W28 -> -0.21
B29: Estoque Inicial | C29: 5.4.1.01.00002 | D29: ='SALDO INICIAL DEZEMBRO'!B11 -> 141723.27 | F29: =-D33 -> 127034.79 | H29: =-F33 -> 122710.94 | J29: =SUMIFS('B. Despesa'!$H$5:$H$1048576,'B. Despesa'!$I$5:$I$1048576,'01 Base Realizado'!J$5,'B. Despesa'!$K$5:$K$1048576,'01 Base Realizado'!$B29) -> 0 | K29: =SUMIFS('B. Despesa'!$H$5:$H$1048576,'B. Despesa'!$I$5:$I$1048576,'01 Base Realizado'!K$5,'B. Despesa'!$K$5:$K$1048576,'01 Base Realizado'!$B29) -> 0 | L29: =SUMIFS('B. Despesa'!$H$5:$H$1048576,'B. Despesa'!$I$5:$I$1048576,'01 Base Realizado'!L$5,'B. Despesa'!$K$5:$K$1048576,'01 Base Realizado'!$B29) -> 0 | M29: =SUMIFS('B. Despesa'!$H$5:$H$1048576,'B. Despesa'!$I$5:$I$1048576,'01 Base Realizado'!M$5,'B. Despesa'!$K$5:$K$1048576,'01 Base Realizado'!$B29) -> 0 | N29: =SUMIFS('B. Despesa'!$H$5:$H$1048576,'B. Despesa'!$I$5:$I$1048576,'01 Base Realizado'!N$5,'B. Despesa'!$K$5:$K$1048576,'01 Base Realizado'!$B29) -> 0 | O29: =SUMIFS('B. Despesa'!$H$5:$H$1048576,'B. Despesa'!$I$5:$I$1048576,'01 Base Realizado'!O$5,'B. Despesa'!$K$5:$K$1048576,'01 Base Realizado'!$B29) -> 0 | P29: =SUMIFS('B. Despesa'!$H$5:$H$1048576,'B. Despesa'!$I$5:$I$1048576,'01 Base Realizado'!P$5,'B. Despesa'!$K$5:$K$1048576,'01 Base Realizado'!$B29) -> 0 | Q29: =SUMIFS('B. Despesa'!$H$5:$H$1048576,'B. Despesa'!$I$5:$I$1048576,'01 Base Realizado'!Q$5,'B. Despesa'!$K$5:$K$1048576,'01 Base Realizado'!$B29) -> 0 | R29: =SUMIFS('B. Despesa'!$H$5:$H$1048576,'B. Despesa'!$I$5:$I$1048576,'01 Base Realizado'!R$5,'B. Despesa'!$K$5:$K$1048576,'01 Base Realizado'!$B29) -> 0 | T29: -4052812.1 | V29: 0.5
B30: Compra Mês | C30: 5.4.1.01.00003 | D30: =-SUMIFS('B. Despesa'!$H$5:$H$1048576,'B. Despesa'!$I$5:$I$1048576,'01 Base Realizado'!D$5,'B. Despesa'!$K$5:$K$1048576,'01 Base Realizado'!$B30) -> 27342.98 | E30: =D30/D$11 -> 0.12921146 | F30: =-SUMIFS('B. Despesa'!$H$5:$H$1048576,'B. Despesa'!$I$5:$I$1048576,'01 Base Realizado'!F$5,'B. Despesa'!$K$5:$K$1048576,'01 Base Realizado'!$B30) -> 61684.24 | G30: =F30/F$11 -> 0.23707978 | H30: =-SUMIFS('B. Despesa'!$H$5:$H$1048576,'B. Despesa'!$I$5:$I$1048576,'01 Base Realizado'!H$5,'B. Despesa'!$K$5:$K$1048576,'01 Base Realizado'!$B30) -> 91589.48 | I30: =H30/H$11 -> 0.22784252 | J30: =SUMIFS('B. Despesa'!$H$5:$H$1048576,'B. Despesa'!$I$5:$I$1048576,'01 Base Realizado'!J$5,'B. Despesa'!$K$5:$K$1048576,'METRICS MDNA'!$B2) -> 0 | K30: =SUMIFS('B. Despesa'!$H$5:$H$1048576,'B. Despesa'!$I$5:$I$1048576,'01 Base Realizado'!K$5,'B. Despesa'!$K$5:$K$1048576,'METRICS MDNA'!$B2) -> 0 | L30: =SUMIFS('B. Despesa'!$H$5:$H$1048576,'B. Despesa'!$I$5:$I$1048576,'01 Base Realizado'!L$5,'B. Despesa'!$K$5:$K$1048576,'METRICS MDNA'!$B2) -> 0 | M30: =SUMIFS('B. Despesa'!$H$5:$H$1048576,'B. Despesa'!$I$5:$I$1048576,'01 Base Realizado'!M$5,'B. Despesa'!$K$5:$K$1048576,'METRICS MDNA'!$B2) -> 0 | N30: =SUMIFS('B. Despesa'!$H$5:$H$1048576,'B. Despesa'!$I$5:$I$1048576,'01 Base Realizado'!N$5,'B. Despesa'!$K$5:$K$1048576,'METRICS MDNA'!$B2) -> 0 | O30: =SUMIFS('B. Despesa'!$H$5:$H$1048576,'B. Despesa'!$I$5:$I$1048576,'01 Base Realizado'!O$5,'B. Despesa'!$K$5:$K$1048576,'METRICS MDNA'!$B2) -> 0 | P30: =SUMIFS('B. Despesa'!$H$5:$H$1048576,'B. Despesa'!$I$5:$I$1048576,'01 Base Realizado'!P$5,'B. Despesa'!$K$5:$K$1048576,'METRICS MDNA'!$B2) -> 0 | Q30: =SUMIFS('B. Despesa'!$H$5:$H$1048576,'B. Despesa'!$I$5:$I$1048576,'01 Base Realizado'!Q$5,'B. Despesa'!$K$5:$K$1048576,'METRICS MDNA'!$B2) -> 0 | R30: =SUMIFS('B. Despesa'!$H$5:$H$1048576,'B. Despesa'!$I$5:$I$1048576,'01 Base Realizado'!R$5,'B. Despesa'!$K$5:$K$1048576,'METRICS MDNA'!$B2) -> 0 | T30: -405281.21 | V30: 0.05 | Y30: Valor de compra em média estavel entre Fev e Mar/26, e baixo volume de compras em Jan/26 por estoque alto
B31: Transferência de Estoque Entrada | E31: =D31/D$11 -> 0 | F31: ='TRANSF. ESTOQUE FEV '!B11 -> 8902.82 | G31: =F31/F$11 -> 0.03421747 | H31: ='TRANSF. ESTOQUE FEV '!E8 -> 9675.06 | I31: =H31/H$11 -> 0.024068158 | Y31: Houve falha na apuração de Jan/26
B32: Transferência de Estoque Saída | E32: =D32/D$11 -> 0 | F32: =-'TRANSF. ESTOQUE FEV '!B17 -> -1110.51 | G32: =-F32/F$11 -> 0.0042681804 | H32: =-'TRANSF. ESTOQUE FEV '!E17 -> -98.85 | I32: =H32/H$11 -> -0.00024590415 | Y32: Houve falha na apuração de Jan/26
B33: Estoque Final | C33: 5.4.1.01.00006 | D33: =-SUMIFS(Inventário!$L:$L,Inventário!$N:$N,'01 Base Realizado'!D$5,Inventário!$P:$P,'01 Base Realizado'!$B33) -> -127034.79 | E33: =-D33/D$11 -> 0.60031312 | F33: =-SUMIFS(Inventário!$L:$L,Inventário!$N:$N,'01 Base Realizado'!F$5,Inventário!$P:$P,'01 Base Realizado'!$B33) -> -122710.94 | G33: =-F33/F$11 -> 0.47163236 | H33: =-SUMIFS(Inventário!$L:$L,Inventário!$N:$N,'01 Base Realizado'!H$5,Inventário!$P:$P,'01 Base Realizado'!$B33) -> -142103.99 | I33: =-H33/H$11 -> 0.35350492 | J33: =SUMIFS('B. Despesa'!$H$5:$H$1048576,'B. Despesa'!$I$5:$I$1048576,'01 Base Realizado'!J$5,'B. Despesa'!$K$5:$K$1048576,'01 Base Realizado'!$B33) -> 0 | K33: =SUMIFS('B. Despesa'!$H$5:$H$1048576,'B. Despesa'!$I$5:$I$1048576,'01 Base Realizado'!K$5,'B. Despesa'!$K$5:$K$1048576,'01 Base Realizado'!$B33) -> 0 | L33: =SUMIFS('B. Despesa'!$H$5:$H$1048576,'B. Despesa'!$I$5:$I$1048576,'01 Base Realizado'!L$5,'B. Despesa'!$K$5:$K$1048576,'01 Base Realizado'!$B33) -> 0 | M33: =SUMIFS('B. Despesa'!$H$5:$H$1048576,'B. Despesa'!$I$5:$I$1048576,'01 Base Realizado'!M$5,'B. Despesa'!$K$5:$K$1048576,'01 Base Realizado'!$B33) -> 0 | N33: =SUMIFS('B. Despesa'!$H$5:$H$1048576,'B. Despesa'!$I$5:$I$1048576,'01 Base Realizado'!N$5,'B. Despesa'!$K$5:$K$1048576,'01 Base Realizado'!$B33) -> 0 | O33: =SUMIFS('B. Despesa'!$H$5:$H$1048576,'B. Despesa'!$I$5:$I$1048576,'01 Base Realizado'!O$5,'B. Despesa'!$K$5:$K$1048576,'01 Base Realizado'!$B33) -> 0 | P33: =SUMIFS('B. Despesa'!$H$5:$H$1048576,'B. Despesa'!$I$5:$I$1048576,'01 Base Realizado'!P$5,'B. Despesa'!$K$5:$K$1048576,'01 Base Realizado'!$B33) -> 0 | Q33: =SUMIFS('B. Despesa'!$H$5:$H$1048576,'B. Despesa'!$I$5:$I$1048576,'01 Base Realizado'!Q$5,'B. Despesa'!$K$5:$K$1048576,'01 Base Realizado'!$B33) -> 0 | R33: =SUMIFS('B. Despesa'!$H$5:$H$1048576,'B. Despesa'!$I$5:$I$1048576,'01 Base Realizado'!R$5,'B. Despesa'!$K$5:$K$1048576,'01 Base Realizado'!$B33) -> 0 | T33: -1215843.6 | V33: 0.15 | Y33: Estoque de março, 87k (61%)= vinhos e champ. o saldo restante de 55k, média de 21 dias de estoque! Atuar em redução
B34: Bonificações | C34: 5.4.1.01.00007 | H34: =SUMIFS('B. Despesa'!$H$5:$H$1048576,'B. Despesa'!$I$5:$I$1048576,'01 Base Realizado'!H$5,'B. Despesa'!$K$5:$K$1048576,'01 Base Realizado'!$B34) -> 0 | J34: =SUMIFS('B. Despesa'!$H$5:$H$1048576,'B. Despesa'!$I$5:$I$1048576,'01 Base Realizado'!J$5,'B. Despesa'!$K$5:$K$1048576,'01 Base Realizado'!$B34) -> 0 | K34: =SUMIFS('B. Despesa'!$H$5:$H$1048576,'B. Despesa'!$I$5:$I$1048576,'01 Base Realizado'!K$5,'B. Despesa'!$K$5:$K$1048576,'01 Base Realizado'!$B34) -> 0 | L34: =SUMIFS('B. Despesa'!$H$5:$H$1048576,'B. Despesa'!$I$5:$I$1048576,'01 Base Realizado'!L$5,'B. Despesa'!$K$5:$K$1048576,'01 Base Realizado'!$B34) -> 0 | M34: =SUMIFS('B. Despesa'!$H$5:$H$1048576,'B. Despesa'!$I$5:$I$1048576,'01 Base Realizado'!M$5,'B. Despesa'!$K$5:$K$1048576,'01 Base Realizado'!$B34) -> 0 | N34: =SUMIFS('B. Despesa'!$H$5:$H$1048576,'B. Despesa'!$I$5:$I$1048576,'01 Base Realizado'!N$5,'B. Despesa'!$K$5:$K$1048576,'01 Base Realizado'!$B34) -> 0 | O34: =SUMIFS('B. Despesa'!$H$5:$H$1048576,'B. Despesa'!$I$5:$I$1048576,'01 Base Realizado'!O$5,'B. Despesa'!$K$5:$K$1048576,'01 Base Realizado'!$B34) -> 0 | P34: =SUMIFS('B. Despesa'!$H$5:$H$1048576,'B. Despesa'!$I$5:$I$1048576,'01 Base Realizado'!P$5,'B. Despesa'!$K$5:$K$1048576,'01 Base Realizado'!$B34) -> 0 | Q34: =SUMIFS('B. Despesa'!$H$5:$H$1048576,'B. Despesa'!$I$5:$I$1048576,'01 Base Realizado'!Q$5,'B. Despesa'!$K$5:$K$1048576,'01 Base Realizado'!$B34) -> 0 | R34: =SUMIFS('B. Despesa'!$H$5:$H$1048576,'B. Despesa'!$I$5:$I$1048576,'01 Base Realizado'!R$5,'B. Despesa'!$K$5:$K$1048576,'01 Base Realizado'!$B34) -> 0 | T34: -405281.21 | V34: 0.05
B35: (-) Reclassificação CMV | C35: 5.4.1.01.00008 | D35: =-D54 -> 1736.74 | F35: =-F54 -> 4840.47 | H35: 3829.81 | J35: =SUMIFS('B. Despesa'!$H$5:$H$1048576,'B. Despesa'!$I$5:$I$1048576,'01 Base Realizado'!J$5,'B. Despesa'!$K$5:$K$1048576,'01 Base Realizado'!$B35) -> 0 | K35: =SUMIFS('B. Despesa'!$H$5:$H$1048576,'B. Despesa'!$I$5:$I$1048576,'01 Base Realizado'!K$5,'B. Despesa'!$K$5:$K$1048576,'01 Base Realizado'!$B35) -> 0 | L35: =SUMIFS('B. Despesa'!$H$5:$H$1048576,'B. Despesa'!$I$5:$I$1048576,'01 Base Realizado'!L$5,'B. Despesa'!$K$5:$K$1048576,'01 Base Realizado'!$B35) -> 0 | M35: =SUMIFS('B. Despesa'!$H$5:$H$1048576,'B. Despesa'!$I$5:$I$1048576,'01 Base Realizado'!M$5,'B. Despesa'!$K$5:$K$1048576,'01 Base Realizado'!$B35) -> 0 | N35: =SUMIFS('B. Despesa'!$H$5:$H$1048576,'B. Despesa'!$I$5:$I$1048576,'01 Base Realizado'!N$5,'B. Despesa'!$K$5:$K$1048576,'01 Base Realizado'!$B35) -> 0 | O35: =SUMIFS('B. Despesa'!$H$5:$H$1048576,'B. Despesa'!$I$5:$I$1048576,'01 Base Realizado'!O$5,'B. Despesa'!$K$5:$K$1048576,'01 Base Realizado'!$B35) -> 0 | P35: =SUMIFS('B. Despesa'!$H$5:$H$1048576,'B. Despesa'!$I$5:$I$1048576,'01 Base Realizado'!P$5,'B. Despesa'!$K$5:$K$1048576,'01 Base Realizado'!$B35) -> 0 | Q35: =SUMIFS('B. Despesa'!$H$5:$H$1048576,'B. Despesa'!$I$5:$I$1048576,'01 Base Realizado'!Q$5,'B. Despesa'!$K$5:$K$1048576,'01 Base Realizado'!$B35) -> 0 | R35: =SUMIFS('B. Despesa'!$H$5:$H$1048576,'B. Despesa'!$I$5:$I$1048576,'01 Base Realizado'!R$5,'B. Despesa'!$K$5:$K$1048576,'01 Base Realizado'!$B35) -> 0 | T35: -324224.96 | V35: 0.04 | Y35: Em meados de Jan/26 iniciou-se os controles via sistema Everest e em Março houve uma redução de aproveitamento de aparas
B37: ÍNDICE | D37: =-D39/D38 -> 0.19083172 | F37: =-F39/F38 -> 0.2658807 | H37: =-H39/H38 -> 0.19515885 | T37: 0.32 | Y37: O motivo pelo qual houve um descolamento se dá pela refeição, ajustes de fichas tecnicas e preço de venda.
B38: RECEITA LÍQUIDA | D38: =D11+D19 -> 211153.17 | F38: =F11+F19 -> 259364.15 | H38: =H11+H19 -> 399381.5 | J38: =J11+J19 -> 0 | K38: =K11+K19 -> 0 | L38: =L11+L19 -> 0 | M38: =M11+M19 -> 0 | N38: =N11+N19 -> 0 | O38: =O11+O19 -> 0 | P38: =P11+P19 -> 0 | Q38: =Q11+Q19 -> 0 | R38: =R11+R19 -> 0 | T38: 25330075 | Y38: Utilizamos as planilhas de excel para efetuar os lançamento no sistema, em Abril será 100% plan Everest
B39: CMV | D39: =-D28 -> -40294.722 | F39: =-F28 -> -68959.922 | H39: =-H28 -> -77942.836 | J39: =-J28 -> 0 | K39: =-K28 -> 0 | L39: =-L28 -> 0 | M39: =-M28 -> 0 | N39: =-N28 -> 0 | O39: =-O28 -> 0 | P39: =-P28 -> 0 | Q39: =-Q28 -> 0 | R39: =-R28 -> 0 | T39: 8105624.1
B41: PESSOAL | D41: =SUM(D42:D66) -> -50083.16 | E41: =SUM(E42:E66) -> 0.23718877 | F41: =SUM(F42:F66) -> -44395.31 | G41: =SUM(G42:G66) -> 0.1711698 | H41: =SUM(H42:H66) -> -61583.06 | I41: =SUM(I42:I66) -> 0.15419608 | J41: =SUM(J42:J66) -> 0 | K41: =SUM(K42:K66) -> 0 | ... R41: =SUM(R42:R66) -> 0 | T41: -6739721.6 | V41: %
B42: Salários e Ordenados | C42: 5.4.1.02.00001 | D42: =SUMIFS('B. Despesa'!$H:$H,'B. Despesa'!$I:$I,'01 Base Realizado'!D$5,'B. Despesa'!$K:$K,'01 Base Realizado'!$B42) -> -19897.66 | E42: =-D42/D$38 -> 0.0942333 | F42: =SUMIFS('B. Despesa'!$H$5:$H$1048576,'B. Despesa'!$I$5:$I$1048576,'01 Base Realizado'!F$5,'B. Despesa'!$K$5:$K$1048576,'01 Base Realizado'!$B42) -> -24163.94 | G42: =-F42/F$38 -> 0.093166076 | H42: =SUMIFS('B. Despesa'!$H$5:$H$1048576,'B. Despesa'!$I$5:$I$1048576,'01 Base Realizado'!H$5,'B. Despesa'!$K$5:$K$1048576,'01 Base Realizado'!$B42) -> -29225.09 | I42: =-H42/H$38 -> 0.073175873 | J42: =SUMIFS('B. Despesa'!$H$5:$H$1048576,'B. Despesa'!$I$5:$I$1048576,'01 Base Realizado'!J$5,'B. Despesa'!$K$5:$K$1048576,'01 Base Realizado'!$B42) -> 0 | K42: =SUMIFS('B. Despesa'!$H$5:$H$1048576,'B. Despesa'!$I$5:$I$1048576,'01 Base Realizado'!K$5,'B. Despesa'!$K$5:$K$1048576,'01 Base Realizado'!$B42) -> 0 | L42: =SUMIFS('B. Despesa'!$H$5:$H$1048576,'B. Despesa'!$I$5:$I$1048576,'01 Base Realizado'!L$5,'B. Despesa'!$K$5:$K$1048576,'01 Base Realizado'!$B42) -> 0 | M42: =SUMIFS('B. Despesa'!$H$5:$H$1048576,'B. Despesa'!$I$5:$I$1048576,'01 Base Realizado'!M$5,'B. Despesa'!$K$5:$K$1048576,'01 Base Realizado'!$B42) -> 0 | N42: =SUMIFS('B. Despesa'!$H$5:$H$1048576,'B. Despesa'!$I$5:$I$1048576,'01 Base Realizado'!N$5,'B. Despesa'!$K$5:$K$1048576,'01 Base Realizado'!$B42) -> 0 | O42: =SUMIFS('B. Despesa'!$H$5:$H$1048576,'B. Despesa'!$I$5:$I$1048576,'01 Base Realizado'!O$5,'B. Despesa'!$K$5:$K$1048576,'01 Base Realizado'!$B42) -> 0 | P42: =SUMIFS('B. Despesa'!$H$5:$H$1048576,'B. Despesa'!$I$5:$I$1048576,'01 Base Realizado'!P$5,'B. Despesa'!$K$5:$K$1048576,'01 Base Realizado'!$B42) -> 0 | Q42: =SUMIFS('B. Despesa'!$H$5:$H$1048576,'B. Despesa'!$I$5:$I$1048576,'01 Base Realizado'!Q$5,'B. Despesa'!$K$5:$K$1048576,'01 Base Realizado'!$B42) -> 0 | R42: =SUMIFS('B. Despesa'!$H$5:$H$1048576,'B. Despesa'!$I$5:$I$1048576,'01 Base Realizado'!R$5,'B. Despesa'!$K$5:$K$1048576,'01 Base Realizado'!$B42) -> 0 | T42: -2616448.1
B43: 13º Salário | C43: 5.4.1.02.00004 | D43: =SUMIFS('B. Despesa'!$H:$H,'B. Despesa'!$I:$I,'01 Base Realizado'!D$5,'B. Despesa'!$K:$K,'01 Base Realizado'!$B43) -> 0 | E43: =-D43/D$38 -> 0 | F43: =SUMIFS('B. Despesa'!$H$5:$H$1048576,'B. Despesa'!$I$5:$I$1048576,'01 Base Realizado'!F$5,'B. Despesa'!$K$5:$K$1048576,'01 Base Realizado'!$B43) -> 0 | G43: =-F43/F$38 -> 0 | H43: =SUMIFS('B. Despesa'!$H$5:$H$1048576,'B. Despesa'!$I$5:$I$1048576,'01 Base Realizado'!H$5,'B. Despesa'!$K$5:$K$1048576,'01 Base Realizado'!$B43) -> 0 | I43: =-H43/H$38 -> 0 | J43: =SUMIFS('B. Despesa'!$H$5:$H$1048576,'B. Despesa'!$I$5:$I$1048576,'01 Base Realizado'!J$5,'B. Despesa'!$K$5:$K$1048576,'01 Base Realizado'!$B43) -> 0 | K43: =SUMIFS('B. Despesa'!$H$5:$H$1048576,'B. Despesa'!$I$5:$I$1048576,'01 Base Realizado'!K$5,'B. Despesa'!$K$5:$K$1048576,'01 Base Realizado'!$B43) -> 0 | L43: =SUMIFS('B. Despesa'!$H$5:$H$1048576,'B. Despesa'!$I$5:$I$1048576,'01 Base Realizado'!L$5,'B. Despesa'!$K$5:$K$1048576,'01 Base Realizado'!$B43) -> 0 | M43: =SUMIFS('B. Despesa'!$H$5:$H$1048576,'B. Despesa'!$I$5:$I$1048576,'01 Base Realizado'!M$5,'B. Despesa'!$K$5:$K$1048576,'01 Base Realizado'!$B43) -> 0 | N43: =SUMIFS('B. Despesa'!$H$5:$H$1048576,'B. Despesa'!$I$5:$I$1048576,'01 Base Realizado'!N$5,'B. Despesa'!$K$5:$K$1048576,'01 Base Realizado'!$B43) -> 0 | O43: =SUMIFS('B. Despesa'!$H$5:$H$1048576,'B. Despesa'!$I$5:$I$1048576,'01 Base Realizado'!O$5,'B. Despesa'!$K$5:$K$1048576,'01 Base Realizado'!$B43) -> 0 | P43: =SUMIFS('B. Despesa'!$H$5:$H$1048576,'B. Despesa'!$I$5:$I$1048576,'01 Base Realizado'!P$5,'B. Despesa'!$K$5:$K$1048576,'01 Base Realizado'!$B43) -> 0 | Q43: =SUMIFS('B. Despesa'!$H$5:$H$1048576,'B. Despesa'!$I$5:$I$1048576,'01 Base Realizado'!Q$5,'B. Despesa'!$K$5:$K$1048576,'01 Base Realizado'!$B43) -> 0 | R43: =SUMIFS('B. Despesa'!$H$5:$H$1048576,'B. Despesa'!$I$5:$I$1048576,'01 Base Realizado'!R$5,'B. Despesa'!$K$5:$K$1048576,'01 Base Realizado'!$B43) -> 0 | T43: -213951.73
B44: Férias | C44: 5.4.1.02.00005 | D44: =SUMIFS('B. Despesa'!$H:$H,'B. Despesa'!$I:$I,'01 Base Realizado'!D$5,'B. Despesa'!$K:$K,'01 Base Realizado'!$B44) -> 0 | E44: =-D44/D$38 -> 0 | F44: =SUMIFS('B. Despesa'!$H$5:$H$1048576,'B. Despesa'!$I$5:$I$1048576,'01 Base Realizado'!F$5,'B. Despesa'!$K$5:$K$1048576,'01 Base Realizado'!$B44) -> 0 | G44: =-F44/F$38 -> 0 | H44: =SUMIFS('B. Despesa'!$H$5:$H$1048576,'B. Despesa'!$I$5:$I$1048576,'01 Base Realizado'!H$5,'B. Despesa'!$K$5:$K$1048576,'01 Base Realizado'!$B44) -> 0 | I44: =-H44/H$38 -> 0 | J44: =SUMIFS('B. Despesa'!$H$5:$H$1048576,'B. Despesa'!$I$5:$I$1048576,'01 Base Realizado'!J$5,'B. Despesa'!$K$5:$K$1048576,'01 Base Realizado'!$B44) -> 0 | K44: =SUMIFS('B. Despesa'!$H$5:$H$1048576,'B. Despesa'!$I$5:$I$1048576,'01 Base Realizado'!K$5,'B. Despesa'!$K$5:$K$1048576,'01 Base Realizado'!$B44) -> 0 | L44: =SUMIFS('B. Despesa'!$H$5:$H$1048576,'B. Despesa'!$I$5:$I$1048576,'01 Base Realizado'!L$5,'B. Despesa'!$K$5:$K$1048576,'01 Base Realizado'!$B44) -> 0 | M44: =SUMIFS('B. Despesa'!$H$5:$H$1048576,'B. Despesa'!$I$5:$I$1048576,'01 Base Realizado'!M$5,'B. Despesa'!$K$5:$K$1048576,'01 Base Realizado'!$B44) -> 0 | N44: =SUMIFS('B. Despesa'!$H$5:$H$1048576,'B. Despesa'!$I$5:$I$1048576,'01 Base Realizado'!N$5,'B. Despesa'!$K$5:$K$1048576,'01 Base Realizado'!$B44) -> 0 | O44: =SUMIFS('B. Despesa'!$H$5:$H$1048576,'B. Despesa'!$I$5:$I$1048576,'01 Base Realizado'!O$5,'B. Despesa'!$K$5:$K$1048576,'01 Base Realizado'!$B44) -> 0 | P44: =SUMIFS('B. Despesa'!$H$5:$H$1048576,'B. Despesa'!$I$5:$I$1048576,'01 Base Realizado'!P$5,'B. Despesa'!$K$5:$K$1048576,'01 Base Realizado'!$B44) -> 0 | Q44: =SUMIFS('B. Despesa'!$H$5:$H$1048576,'B. Despesa'!$I$5:$I$1048576,'01 Base Realizado'!Q$5,'B. Despesa'!$K$5:$K$1048576,'01 Base Realizado'!$B44) -> 0 | R44: =SUMIFS('B. Despesa'!$H$5:$H$1048576,'B. Despesa'!$I$5:$I$1048576,'01 Base Realizado'!R$5,'B. Despesa'!$K$5:$K$1048576,'01 Base Realizado'!$B44) -> 0 | T44: -144581.06
B45: IR/INSS | C45: 5.4.1.02.00006 | D45: =SUMIFS('B. Despesa'!$H:$H,'B. Despesa'!$I:$I,'01 Base Realizado'!D$5,'B. Despesa'!$K:$K,'01 Base Realizado'!$B45) -> -10278.92 | E45: =-D45/D$38 -> 0.048679923 | F45: =SUMIFS('B. Despesa'!$H$5:$H$1048576,'B. Despesa'!$I$5:$I$1048576,'01 Base Realizado'!F$5,'B. Despesa'!$K$5:$K$1048576,'01 Base Realizado'!$B45) -> -12947.34 | G45: =-F45/F$38 -> 0.049919544 | H45: =SUMIFS('B. Despesa'!$H$5:$H$1048576,'B. Despesa'!$I$5:$I$1048576,'01 Base Realizado'!H$5,'B. Despesa'!$K$5:$K$1048576,'01 Base Realizado'!$B45) -> -16676.19 | I45: =-H45/H$38 -> 0.041755039 | J45: =SUMIFS('B. Despesa'!$H$5:$H$1048576,'B. Despesa'!$I$5:$I$1048576,'01 Base Realizado'!J$5,'B. Despesa'!$K$5:$K$1048576,'01 Base Realizado'!$B45) -> 0 | K45: =SUMIFS('B. Despesa'!$H$5:$H$1048576,'B. Despesa'!$I$5:$I$1048576,'01 Base Realizado'!K$5,'B. Despesa'!$K$5:$K$1048576,'01 Base Realizado'!$B45) -> 0 | L45: =SUMIFS('B. Despesa'!$H$5:$H$1048576,'B. Despesa'!$I$5:$I$1048576,'01 Base Realizado'!L$5,'B. Despesa'!$K$5:$K$1048576,'01 Base Realizado'!$B45) -> 0 | M45: =SUMIFS('B. Despesa'!$H$5:$H$1048576,'B. Despesa'!$I$5:$I$1048576,'01 Base Realizado'!M$5,'B. Despesa'!$K$5:$K$1048576,'01 Base Realizado'!$B45) -> 0 | N45: =SUMIFS('B. Despesa'!$H$5:$H$1048576,'B. Despesa'!$I$5:$I$1048576,'01 Base Realizado'!N$5,'B. Despesa'!$K$5:$K$1048576,'01 Base Realizado'!$B45) -> 0 | O45: =SUMIFS('B. Despesa'!$H$5:$H$1048576,'B. Despesa'!$I$5:$I$1048576,'01 Base Realizado'!O$5,'B. Despesa'!$K$5:$K$1048576,'01 Base Realizado'!$B45) -> 0 | P45: =SUMIFS('B. Despesa'!$H$5:$H$1048576,'B. Despesa'!$I$5:$I$1048576,'01 Base Realizado'!P$5,'B. Despesa'!$K$5:$K$1048576,'01 Base Realizado'!$B45) -> 0 | Q45: =SUMIFS('B. Despesa'!$H$5:$H$1048576,'B. Despesa'!$I$5:$I$1048576,'01 Base Realizado'!Q$5,'B. Despesa'!$K$5:$K$1048576,'01 Base Realizado'!$B45) -> 0 | R45: =SUMIFS('B. Despesa'!$H$5:$H$1048576,'B. Despesa'!$I$5:$I$1048576,'01 Base Realizado'!R$5,'B. Despesa'!$K$5:$K$1048576,'01 Base Realizado'!$B45) -> 0 | T45: -768259.53
B46: FGTS | C46: 5.4.1.02.00007 | D46: =SUMIFS('B. Despesa'!$H:$H,'B. Despesa'!$I:$I,'01 Base Realizado'!D$5,'B. Despesa'!$K:$K,'01 Base Realizado'!$B46) -> -2229.48 | E46: =-D46/D$38 -> 0.010558591 | F46: =SUMIFS('B. Despesa'!$H$5:$H$1048576,'B. Despesa'!$I$5:$I$1048576,'01 Base Realizado'!F$5,'B. Despesa'!$K$5:$K$1048576,'01 Base Realizado'!$B46) -> -2718.39 | G46: =-F46/F$38 -> 0.010480978 | H46: =SUMIFS('B. Despesa'!$H$5:$H$1048576,'B. Despesa'!$I$5:$I$1048576,'01 Base Realizado'!H$5,'B. Despesa'!$K$5:$K$1048576,'01 Base Realizado'!$B46) -> -3529.18 | I46: =-H46/H$38 -> 0.0088366136 | J46: =SUMIFS('B. Despesa'!$H$5:$H$1048576,'B. Despesa'!$I$5:$I$1048576,'01 Base Realizado'!J$5,'B. Despesa'!$K$5:$K$1048576,'01 Base Realizado'!$B46) -> 0 | K46: =SUMIFS('B. Despesa'!$H$5:$H$1048576,'B. Despesa'!$I$5:$I$1048576,'01 Base Realizado'!K$5,'B. Despesa'!$K$5:$K$1048576,'01 Base Realizado'!$B46) -> 0 | L46: =SUMIFS('B. Despesa'!$H$5:$H$1048576,'B. Despesa'!$I$5:$I$1048576,'01 Base Realizado'!L$5,'B. Despesa'!$K$5:$K$1048576,'01 Base Realizado'!$B46) -> 0 | M46: =SUMIFS('B. Despesa'!$H$5:$H$1048576,'B. Despesa'!$I$5:$I$1048576,'01 Base Realizado'!M$5,'B. Despesa'!$K$5:$K$1048576,'01 Base Realizado'!$B46) -> 0 | N46: =SUMIFS('B. Despesa'!$H$5:$H$1048576,'B. Despesa'!$I$5:$I$1048576,'01 Base Realizado'!N$5,'B. Despesa'!$K$5:$K$1048576,'01 Base Realizado'!$B46) -> 0 | O46: =SUMIFS('B. Despesa'!$H$5:$H$1048576,'B. Despesa'!$I$5:$I$1048576,'01 Base Realizado'!O$5,'B. Despesa'!$K$5:$K$1048576,'01 Base Realizado'!$B46) -> 0 | P46: =SUMIFS('B. Despesa'!$H$5:$H$1048576,'B. Despesa'!$I$5:$I$1048576,'01 Base Realizado'!P$5,'B. Despesa'!$K$5:$K$1048576,'01 Base Realizado'!$B46) -> 0 | Q46: =SUMIFS('B. Despesa'!$H$5:$H$1048576,'B. Despesa'!$I$5:$I$1048576,'01 Base Realizado'!Q$5,'B. Despesa'!$K$5:$K$1048576,'01 Base Realizado'!$B46) -> 0 | R46: =SUMIFS('B. Despesa'!$H$5:$H$1048576,'B. Despesa'!$I$5:$I$1048576,'01 Base Realizado'!R$5,'B. Despesa'!$K$5:$K$1048576,'01 Base Realizado'!$B46) -> 0 | T46: -433750.41
B47: Rescisões Trabalhistas | C47: 5.4.1.02.00008 | D47: =SUMIFS('B. Despesa'!$H:$H,'B. Despesa'!$I:$I,'01 Base Realizado'!D$5,'B. Despesa'!$K:$K,'01 Base Realizado'!$B47) -> -2339.06 | E47: =-D47/D$38 -> 0.011077551 | F47: =SUMIFS('B. Despesa'!$H$5:$H$1048576,'B. Despesa'!$I$5:$I$1048576,'01 Base Realizado'!F$5,'B. Despesa'!$K$5:$K$1048576,'01 Base Realizado'!$B47) -> -1236.16 | G47: =-F47/F$38 -> 0.0047661174 | H47: =SUMIFS('B. Despesa'!$H$5:$H$1048576,'B. Despesa'!$I$5:$I$1048576,'01 Base Realizado'!H$5,'B. Despesa'!$K$5:$K$1048576,'01 Base Realizado'!$B47) -> 0 | I47: =-H47/H$38 -> 0 | J47: =SUMIFS('B. Despesa'!$H$5:$H$1048576,'B. Despesa'!$I$5:$I$1048576,'01 Base Realizado'!J$5,'B. Despesa'!$K$5:$K$1048576,'01 Base Realizado'!$B47) -> 0 | K47: =SUMIFS('B. Despesa'!$H$5:$H$1048576,'B. Despesa'!$I$5:$I$1048576,'01 Base Realizado'!K$5,'B. Despesa'!$K$5:$K$1048576,'01 Base Realizado'!$B47) -> 0 | L47: =SUMIFS('B. Despesa'!$H$5:$H$1048576,'B. Despesa'!$I$5:$I$1048576,'01 Base Realizado'!L$5,'B. Despesa'!$K$5:$K$1048576,'01 Base Realizado'!$B47) -> 0 | M47: =SUMIFS('B. Despesa'!$H$5:$H$1048576,'B. Despesa'!$I$5:$I$1048576,'01 Base Realizado'!M$5,'B. Despesa'!$K$5:$K$1048576,'01 Base Realizado'!$B47) -> 0 | N47: =SUMIFS('B. Despesa'!$H$5:$H$1048576,'B. Despesa'!$I$5:$I$1048576,'01 Base Realizado'!N$5,'B. Despesa'!$K$5:$K$1048576,'01 Base Realizado'!$B47) -> 0 | O47: =SUMIFS('B. Despesa'!$H$5:$H$1048576,'B. Despesa'!$I$5:$I$1048576,'01 Base Realizado'!O$5,'B. Despesa'!$K$5:$K$1048576,'01 Base Realizado'!$B47) -> 0 | P47: =SUMIFS('B. Despesa'!$H$5:$H$1048576,'B. Despesa'!$I$5:$I$1048576,'01 Base Realizado'!P$5,'B. Despesa'!$K$5:$K$1048576,'01 Base Realizado'!$B47) -> 0 | Q47: =SUMIFS('B. Despesa'!$H$5:$H$1048576,'B. Despesa'!$I$5:$I$1048576,'01 Base Realizado'!Q$5,'B. Despesa'!$K$5:$K$1048576,'01 Base Realizado'!$B47) -> 0 | R47: =SUMIFS('B. Despesa'!$H$5:$H$1048576,'B. Despesa'!$I$5:$I$1048576,'01 Base Realizado'!R$5,'B. Despesa'!$K$5:$K$1048576,'01 Base Realizado'!$B47) -> 0 | T47: 0 | Y47: Em Jan/26 rescisão da equipe de bar (2), em Fev/26 garçom (1)
B48: Assistência Médica e Social | C48: 5.4.1.02.00009 | D48: =SUMIFS('B. Despesa'!$H:$H,'B. Despesa'!$I:$I,'01 Base Realizado'!D$5,'B. Despesa'!$K:$K,'01 Base Realizado'!$B48) -> -400.64 | E48: =-D48/D$38 -> 0.0018973904 | F48: =SUMIFS('B. Despesa'!$H$5:$H$1048576,'B. Despesa'!$I$5:$I$1048576,'01 Base Realizado'!F$5,'B. Despesa'!$K$5:$K$1048576,'01 Base Realizado'!$B48) -> 0 | G48: =-F48/F$38 -> 0 | H48: =SUMIFS('B. Despesa'!$H$5:$H$1048576,'B. Despesa'!$I$5:$I$1048576,'01 Base Realizado'!H$5,'B. Despesa'!$K$5:$K$1048576,'01 Base Realizado'!$B48) -> 0 | I48: =-H48/H$38 -> 0 | J48: =SUMIFS('B. Despesa'!$H$5:$H$1048576,'B. Despesa'!$I$5:$I$1048576,'01 Base Realizado'!J$5,'B. Despesa'!$K$5:$K$1048576,'01 Base Realizado'!$B48) -> 0 | K48: =SUMIFS('B. Despesa'!$H$5:$H$1048576,'B. Despesa'!$I$5:$I$1048576,'01 Base Realizado'!K$5,'B. Despesa'!$K$5:$K$1048576,'01 Base Realizado'!$B48) -> 0 | L48: =SUMIFS('B. Despesa'!$H$5:$H$1048576,'B. Despesa'!$I$5:$I$1048576,'01 Base Realizado'!L$5,'B. Despesa'!$K$5:$K$1048576,'01 Base Realizado'!$B48) -> 0 | M48: =SUMIFS('B. Despesa'!$H$5:$H$1048576,'B. Despesa'!$I$5:$I$1048576,'01 Base Realizado'!M$5,'B. Despesa'!$K$5:$K$1048576,'01 Base Realizado'!$B48) -> 0 | N48: =SUMIFS('B. Despesa'!$H$5:$H$1048576,'B. Despesa'!$I$5:$I$1048576,'01 Base Realizado'!N$5,'B. Despesa'!$K$5:$K$1048576,'01 Base Realizado'!$B48) -> 0 | O48: =SUMIFS('B. Despesa'!$H$5:$H$1048576,'B. Despesa'!$I$5:$I$1048576,'01 Base Realizado'!O$5,'B. Despesa'!$K$5:$K$1048576,'01 Base Realizado'!$B48) -> 0 | P48: =SUMIFS('B. Despesa'!$H$5:$H$1048576,'B. Despesa'!$I$5:$I$1048576,'01 Base Realizado'!P$5,'B. Despesa'!$K$5:$K$1048576,'01 Base Realizado'!$B48) -> 0 | Q48: =SUMIFS('B. Despesa'!$H$5:$H$1048576,'B. Despesa'!$I$5:$I$1048576,'01 Base Realizado'!Q$5,'B. Despesa'!$K$5:$K$1048576,'01 Base Realizado'!$B48) -> 0 | R48: =SUMIFS('B. Despesa'!$H$5:$H$1048576,'B. Despesa'!$I$5:$I$1048576,'01 Base Realizado'!R$5,'B. Despesa'!$K$5:$K$1048576,'01 Base Realizado'!$B48) -> 0 | T48: -119703.12
B49: Horas Extras | C49: 5.4.1.02.00010 | D49: =SUMIFS('B. Despesa'!$H:$H,'B. Despesa'!$I:$I,'01 Base Realizado'!D$5,'B. Despesa'!$K:$K,'01 Base Realizado'!$B49) -> 0 | E49: =-D49/D$38 -> 0 | F49: =SUMIFS('B. Despesa'!$H$5:$H$1048576,'B. Despesa'!$I$5:$I$1048576,'01 Base Realizado'!F$5,'B. Despesa'!$K$5:$K$1048576,'01 Base Realizado'!$B49) -> 0 | G49: =-F49/F$38 -> 0 | H49: =SUMIFS('B. Despesa'!$H$5:$H$1048576,'B. Despesa'!$I$5:$I$1048576,'01 Base Realizado'!H$5,'B. Despesa'!$K$5:$K$1048576,'01 Base Realizado'!$B49) -> 0 | I49: =-H49/H$38 -> 0 | J49: =SUMIFS('B. Despesa'!$H$5:$H$1048576,'B. Despesa'!$I$5:$I$1048576,'01 Base Realizado'!J$5,'B. Despesa'!$K$5:$K$1048576,'01 Base Realizado'!$B49) -> 0 | K49: =SUMIFS('B. Despesa'!$H$5:$H$1048576,'B. Despesa'!$I$5:$I$1048576,'01 Base Realizado'!K$5,'B. Despesa'!$K$5:$K$1048576,'01 Base Realizado'!$B49) -> 0 | L49: =SUMIFS('B. Despesa'!$H$5:$H$1048576,'B. Despesa'!$I$5:$I$1048576,'01 Base Realizado'!L$5,'B. Despesa'!$K$5:$K$1048576,'01 Base Realizado'!$B49) -> 0 | M49: =SUMIFS('B. Despesa'!$H$5:$H$1048576,'B. Despesa'!$I$5:$I$1048576,'01 Base Realizado'!M$5,'B. Despesa'!$K$5:$K$1048576,'01 Base Realizado'!$B49) -> 0 | N49: =SUMIFS('B. Despesa'!$H$5:$H$1048576,'B. Despesa'!$I$5:$I$1048576,'01 Base Realizado'!N$5,'B. Despesa'!$K$5:$K$1048576,'01 Base Realizado'!$B49) -> 0 | O49: =SUMIFS('B. Despesa'!$H$5:$H$1048576,'B. Despesa'!$I$5:$I$1048576,'01 Base Realizado'!O$5,'B. Despesa'!$K$5:$K$1048576,'01 Base Realizado'!$B49) -> 0 | P49: =SUMIFS('B. Despesa'!$H$5:$H$1048576,'B. Despesa'!$I$5:$I$1048576,'01 Base Realizado'!P$5,'B. Despesa'!$K$5:$K$1048576,'01 Base Realizado'!$B49) -> 0 | Q49: =SUMIFS('B. Despesa'!$H$5:$H$1048576,'B. Despesa'!$I$5:$I$1048576,'01 Base Realizado'!Q$5,'B. Despesa'!$K$5:$K$1048576,'01 Base Realizado'!$B49) -> 0 | R49: =SUMIFS('B. Despesa'!$H$5:$H$1048576,'B. Despesa'!$I$5:$I$1048576,'01 Base Realizado'!R$5,'B. Despesa'!$K$5:$K$1048576,'01 Base Realizado'!$B49) -> 0 | T49: 0
B50: Banco de Horas | C50: 5.4.1.02.00011 | D50: =SUMIFS('B. Despesa'!$H:$H,'B. Despesa'!$I:$I,'01 Base Realizado'!D$5,'B. Despesa'!$K:$K,'01 Base Realizado'!$B50) -> 0 | E50: =-D50/D$38 -> 0 | F50: =SUMIFS('B. Despesa'!$H$5:$H$1048576,'B. Despesa'!$I$5:$I$1048576,'01 Base Realizado'!F$5,'B. Despesa'!$K$5:$K$1048576,'01 Base Realizado'!$B50) -> 0 | G50: =-F50/F$38 -> 0 | H50: =SUMIFS('B. Despesa'!$H$5:$H$1048576,'B. Despesa'!$I$5:$I$1048576,'01 Base Realizado'!H$5,'B. Despesa'!$K$5:$K$1048576,'01 Base Realizado'!$B50) -> 0 | I50: =-H50/H$38 -> 0 | J50: =SUMIFS('B. Despesa'!$H$5:$H$1048576,'B. Despesa'!$I$5:$I$1048576,'01 Base Realizado'!J$5,'B. Despesa'!$K$5:$K$1048576,'01 Base Realizado'!$B50) -> 0 | K50: =SUMIFS('B. Despesa'!$H$5:$H$1048576,'B. Despesa'!$I$5:$I$1048576,'01 Base Realizado'!K$5,'B. Despesa'!$K$5:$K$1048576,'01 Base Realizado'!$B50) -> 0 | L50: =SUMIFS('B. Despesa'!$H$5:$H$1048576,'B. Despesa'!$I$5:$I$1048576,'01 Base Realizado'!L$5,'B. Despesa'!$K$5:$K$1048576,'01 Base Realizado'!$B50) -> 0 | M50: =SUMIFS('B. Despesa'!$H$5:$H$1048576,'B. Despesa'!$I$5:$I$1048576,'01 Base Realizado'!M$5,'B. Despesa'!$K$5:$K$1048576,'01 Base Realizado'!$B50) -> 0 | N50: =SUMIFS('B. Despesa'!$H$5:$H$1048576,'B. Despesa'!$I$5:$I$1048576,'01 Base Realizado'!N$5,'B. Despesa'!$K$5:$K$1048576,'01 Base Realizado'!$B50) -> 0 | O50: =SUMIFS('B. Despesa'!$H$5:$H$1048576,'B. Despesa'!$I$5:$I$1048576,'01 Base Realizado'!O$5,'B. Despesa'!$K$5:$K$1048576,'01 Base Realizado'!$B50) -> 0 | P50: =SUMIFS('B. Despesa'!$H$5:$H$1048576,'B. Despesa'!$I$5:$I$1048576,'01 Base Realizado'!P$5,'B. Despesa'!$K$5:$K$1048576,'01 Base Realizado'!$B50) -> 0 | Q50: =SUMIFS('B. Despesa'!$H$5:$H$1048576,'B. Despesa'!$I$5:$I$1048576,'01 Base Realizado'!Q$5,'B. Despesa'!$K$5:$K$1048576,'01 Base Realizado'!$B50) -> 0 | R50: =SUMIFS('B. Despesa'!$H$5:$H$1048576,'B. Despesa'!$I$5:$I$1048576,'01 Base Realizado'!R$5,'B. Despesa'!$K$5:$K$1048576,'01 Base Realizado'!$B50) -> 0 | T50: 0
B51: Vale Transporte | C51: 5.4.1.02.00012 | D51: =SUMIFS('B. Despesa'!$H:$H,'B. Despesa'!$I:$I,'01 Base Realizado'!D$5,'B. Despesa'!$K:$K,'01 Base Realizado'!$B51) -> -2701.44 | E51: =-D51/D$38 -> 0.012793746 | F51: =SUMIFS('B. Despesa'!$H$5:$H$1048576,'B. Despesa'!$I$5:$I$1048576,'01 Base Realizado'!F$5,'B. Despesa'!$K$5:$K$1048576,'01 Base Realizado'!$B51) -> -3601.92 | G51: =-F51/F$38 -> 0.013887501 | H51: =SUMIFS('B. Despesa'!$H$5:$H$1048576,'B. Despesa'!$I$5:$I$1048576,'01 Base Realizado'!H$5,'B. Despesa'!$K$5:$K$1048576,'01 Base Realizado'!$B51) -> -5541.12 | I51: =-H51/H$38 -> 0.013874253 | J51: =SUMIFS('B. Despesa'!$H$5:$H$1048576,'B. Despesa'!$I$5:$I$1048576,'01 Base Realizado'!J$5,'B. Despesa'!$K$5:$K$1048576,'01 Base Realizado'!$B51) -> 0 | K51: =SUMIFS('B. Despesa'!$H$5:$H$1048576,'B. Despesa'!$I$5:$I$1048576,'01 Base Realizado'!K$5,'B. Despesa'!$K$5:$K$1048576,'01 Base Realizado'!$B51) -> 0 | L51: =SUMIFS('B. Despesa'!$H$5:$H$1048576,'B. Despesa'!$I$5:$I$1048576,'01 Base Realizado'!L$5,'B. Despesa'!$K$5:$K$1048576,'01 Base Realizado'!$B51) -> 0 | M51: =SUMIFS('B. Despesa'!$H$5:$H$1048576,'B. Despesa'!$I$5:$I$1048576,'01 Base Realizado'!M$5,'B. Despesa'!$K$5:$K$1048576,'01 Base Realizado'!$B51) -> 0 | N51: =SUMIFS('B. Despesa'!$H$5:$H$1048576,'B. Despesa'!$I$5:$I$1048576,'01 Base Realizado'!N$5,'B. Despesa'!$K$5:$K$1048576,'01 Base Realizado'!$B51) -> 0 | O51: =SUMIFS('B. Despesa'!$H$5:$H$1048576,'B. Despesa'!$I$5:$I$1048576,'01 Base Realizado'!O$5,'B. Despesa'!$K$5:$K$1048576,'01 Base Realizado'!$B51) -> 0 | P51: =SUMIFS('B. Despesa'!$H$5:$H$1048576,'B. Despesa'!$I$5:$I$1048576,'01 Base Realizado'!P$5,'B. Despesa'!$K$5:$K$1048576,'01 Base Realizado'!$B51) -> 0 | Q51: =SUMIFS('B. Despesa'!$H$5:$H$1048576,'B. Despesa'!$I$5:$I$1048576,'01 Base Realizado'!Q$5,'B. Despesa'!$K$5:$K$1048576,'01 Base Realizado'!$B51) -> 0 | R51: =SUMIFS('B. Despesa'!$H$5:$H$1048576,'B. Despesa'!$I$5:$I$1048576,'01 Base Realizado'!R$5,'B. Despesa'!$K$5:$K$1048576,'01 Base Realizado'!$B51) -> 0 | T51: -260325.55 | Y51: Em Mar/26 houve um aumeto na passagem dos colaboradores
B52: Contribuição Sindical | C52: 5.4.1.02.00016 | D52: =SUMIFS('B. Despesa'!$H:$H,'B. Despesa'!$I:$I,'01 Base Realizado'!D$5,'B. Despesa'!$K:$K,'01 Base Realizado'!$B52) -> 0 | E52: =-D52/D$38 -> 0 | F52: =SUMIFS('B. Despesa'!$H$5:$H$1048576,'B. Despesa'!$I$5:$I$1048576,'01 Base Realizado'!F$5,'B. Despesa'!$K$5:$K$1048576,'01 Base Realizado'!$B52) -> 0 | G52: =-F52/F$38 -> 0 | H52: =SUMIFS('B. Despesa'!$H$5:$H$1048576,'B. Despesa'!$I$5:$I$1048576,'01 Base Realizado'!H$5,'B. Despesa'!$K$5:$K$1048576,'01 Base Realizado'!$B52) -> 0 | I52: =-H52/H$38 -> 0 | J52: =SUMIFS('B. Despesa'!$H$5:$H$1048576,'B. Despesa'!$I$5:$I$1048576,'01 Base Realizado'!J$5,'B. Despesa'!$K$5:$K$1048576,'01 Base Realizado'!$B52) -> 0 | K52: =SUMIFS('B. Despesa'!$H$5:$H$1048576,'B. Despesa'!$I$5:$I$1048576,'01 Base Realizado'!K$5,'B. Despesa'!$K$5:$K$1048576,'01 Base Realizado'!$B52) -> 0 | L52: =SUMIFS('B. Despesa'!$H$5:$H$1048576,'B. Despesa'!$I$5:$I$1048576,'01 Base Realizado'!L$5,'B. Despesa'!$K$5:$K$1048576,'01 Base Realizado'!$B52) -> 0 | M52: =SUMIFS('B. Despesa'!$H$5:$H$1048576,'B. Despesa'!$I$5:$I$1048576,'01 Base Realizado'!M$5,'B. Despesa'!$K$5:$K$1048576,'01 Base Realizado'!$B52) -> 0 | N52: =SUMIFS('B. Despesa'!$H$5:$H$1048576,'B. Despesa'!$I$5:$I$1048576,'01 Base Realizado'!N$5,'B. Despesa'!$K$5:$K$1048576,'01 Base Realizado'!$B52) -> 0 | O52: =SUMIFS('B. Despesa'!$H$5:$H$1048576,'B. Despesa'!$I$5:$I$1048576,'01 Base Realizado'!O$5,'B. Despesa'!$K$5:$K$1048576,'01 Base Realizado'!$B52) -> 0 | P52: =SUMIFS('B. Despesa'!$H$5:$H$1048576,'B. Despesa'!$I$5:$I$1048576,'01 Base Realizado'!P$5,'B. Despesa'!$K$5:$K$1048576,'01 Base Realizado'!$B52) -> 0 | Q52: =SUMIFS('B. Despesa'!$H$5:$H$1048576,'B. Despesa'!$I$5:$I$1048576,'01 Base Realizado'!Q$5,'B. Despesa'!$K$5:$K$1048576,'01 Base Realizado'!$B52) -> 0 | R52: =SUMIFS('B. Despesa'!$H$5:$H$1048576,'B. Despesa'!$I$5:$I$1048576,'01 Base Realizado'!R$5,'B. Despesa'!$K$5:$K$1048576,'01 Base Realizado'!$B52) -> 0 | T52: -52328.962 | V52: 0.02
B53: Seguro de Vida | C53: 5.4.1.02.00018 | D53: =SUMIFS('B. Despesa'!$H:$H,'B. Despesa'!$I:$I,'01 Base Realizado'!D$5,'B. Despesa'!$K:$K,'01 Base Realizado'!$B53) -> 0 | E53: =-D53/D$38 -> 0 | F53: =SUMIFS('B. Despesa'!$H$5:$H$1048576,'B. Despesa'!$I$5:$I$1048576,'01 Base Realizado'!F$5,'B. Despesa'!$K$5:$K$1048576,'01 Base Realizado'!$B53) -> 0 | G53: =-F53/F$38 -> 0 | H53: =SUMIFS('B. Despesa'!$H$5:$H$1048576,'B. Despesa'!$I$5:$I$1048576,'01 Base Realizado'!H$5,'B. Despesa'!$K$5:$K$1048576,'01 Base Realizado'!$B53) -> 0 | I53: =-H53/H$38 -> 0 | J53: =SUMIFS('B. Despesa'!$H$5:$H$1048576,'B. Despesa'!$I$5:$I$1048576,'01 Base Realizado'!J$5,'B. Despesa'!$K$5:$K$1048576,'01 Base Realizado'!$B53) -> 0 | K53: =SUMIFS('B. Despesa'!$H$5:$H$1048576,'B. Despesa'!$I$5:$I$1048576,'01 Base Realizado'!K$5,'B. Despesa'!$K$5:$K$1048576,'01 Base Realizado'!$B53) -> 0 | L53: =SUMIFS('B. Despesa'!$H$5:$H$1048576,'B. Despesa'!$I$5:$I$1048576,'01 Base Realizado'!L$5,'B. Despesa'!$K$5:$K$1048576,'01 Base Realizado'!$B53) -> 0 | M53: =SUMIFS('B. Despesa'!$H$5:$H$1048576,'B. Despesa'!$I$5:$I$1048576,'01 Base Realizado'!M$5,'B. Despesa'!$K$5:$K$1048576,'01 Base Realizado'!$B53) -> 0 | N53: =SUMIFS('B. Despesa'!$H$5:$H$1048576,'B. Despesa'!$I$5:$I$1048576,'01 Base Realizado'!N$5,'B. Despesa'!$K$5:$K$1048576,'01 Base Realizado'!$B53) -> 0 | O53: =SUMIFS('B. Despesa'!$H$5:$H$1048576,'B. Despesa'!$I$5:$I$1048576,'01 Base Realizado'!O$5,'B. Despesa'!$K$5:$K$1048576,'01 Base Realizado'!$B53) -> 0 | P53: =SUMIFS('B. Despesa'!$H$5:$H$1048576,'B. Despesa'!$I$5:$I$1048576,'01 Base Realizado'!P$5,'B. Despesa'!$K$5:$K$1048576,'01 Base Realizado'!$B53) -> 0 | Q53: =SUMIFS('B. Despesa'!$H$5:$H$1048576,'B. Despesa'!$I$5:$I$1048576,'01 Base Realizado'!Q$5,'B. Despesa'!$K$5:$K$1048576,'01 Base Realizado'!$B53) -> 0 | R53: =SUMIFS('B. Despesa'!$H$5:$H$1048576,'B. Despesa'!$I$5:$I$1048576,'01 Base Realizado'!R$5,'B. Despesa'!$K$5:$K$1048576,'01 Base Realizado'!$B53) -> 0 | T53: -9606.24
B54: Beneficios | D54: =SUMIFS('B. Despesa'!$H:$H,'B. Despesa'!$I:$I,'01 Base Realizado'!D$5,'B. Despesa'!$K:$K,'01 Base Realizado'!$B54) -> -1736.74 | E54: =-D54/D$38 -> 0.0082250245 | F54: =SUMIFS('B. Despesa'!$H$5:$H$1048576,'B. Despesa'!$I$5:$I$1048576,'01 Base Realizado'!F$5,'B. Despesa'!$K$5:$K$1048576,'01 Base Realizado'!$B54) -> -4840.47 | G54: =-F54/F$38 -> 0.018662834 | H54: =SUMIFS('B. Despesa'!$H$5:$H$1048576,'B. Despesa'!$I$5:$I$1048576,'01 Base Realizado'!H$5,'B. Despesa'!$K$5:$K$1048576,'01 Base Realizado'!$B54) -> -3858.08 | I54: =-H54/H$38 -> 0.009660137 | J54: =SUMIFS('B. Despesa'!$H$5:$H$1048576,'B. Despesa'!$I$5:$I$1048576,'01 Base Realizado'!J$5,'B. Despesa'!$K$5:$K$1048576,'01 Base Realizado'!$B54) -> 0 | K54: =SUMIFS('B. Despesa'!$H$5:$H$1048576,'B. Despesa'!$I$5:$I$1048576,'01 Base Realizado'!K$5,'B. Despesa'!$K$5:$K$1048576,'01 Base Realizado'!$B54) -> 0 | L54: =SUMIFS('B. Despesa'!$H$5:$H$1048576,'B. Despesa'!$I$5:$I$1048576,'01 Base Realizado'!L$5,'B. Despesa'!$K$5:$K$1048576,'01 Base Realizado'!$B54) -> 0 | M54: =SUMIFS('B. Despesa'!$H$5:$H$1048576,'B. Despesa'!$I$5:$I$1048576,'01 Base Realizado'!M$5,'B. Despesa'!$K$5:$K$1048576,'01 Base Realizado'!$B54) -> 0 | N54: =SUMIFS('B. Despesa'!$H$5:$H$1048576,'B. Despesa'!$I$5:$I$1048576,'01 Base Realizado'!N$5,'B. Despesa'!$K$5:$K$1048576,'01 Base Realizado'!$B54) -> 0 | O54: =SUMIFS('B. Despesa'!$H$5:$H$1048576,'B. Despesa'!$I$5:$I$1048576,'01 Base Realizado'!O$5,'B. Despesa'!$K$5:$K$1048576,'01 Base Realizado'!$B54) -> 0 | P54: =SUMIFS('B. Despesa'!$H$5:$H$1048576,'B. Despesa'!$I$5:$I$1048576,'01 Base Realizado'!P$5,'B. Despesa'!$K$5:$K$1048576,'01 Base Realizado'!$B54) -> 0 | Q54: =SUMIFS('B. Despesa'!$H$5:$H$1048576,'B. Despesa'!$I$5:$I$1048576,'01 Base Realizado'!Q$5,'B. Despesa'!$K$5:$K$1048576,'01 Base Realizado'!$B54) -> 0 | R54: =SUMIFS('B. Despesa'!$H$5:$H$1048576,'B. Despesa'!$I$5:$I$1048576,'01 Base Realizado'!R$5,'B. Despesa'!$K$5:$K$1048576,'01 Base Realizado'!$B54) -> 0
B55: Uniforme/EPI | C55: 5.4.1.02.00020 | D55: =SUMIFS('B. Despesa'!$H:$H,'B. Despesa'!$I:$I,'01 Base Realizado'!D$5,'B. Despesa'!$K:$K,'01 Base Realizado'!$B55) -> -39.22 | E55: =-D55/D$38 -> 0.00018574194 | F55: =SUMIFS('B. Despesa'!$H$5:$H$1048576,'B. Despesa'!$I$5:$I$1048576,'01 Base Realizado'!F$5,'B. Despesa'!$K$5:$K$1048576,'01 Base Realizado'!$B55) -> 0 | G55: =-F55/F$38 -> 0 | H55: =SUMIFS('B. Despesa'!$H$5:$H$1048576,'B. Despesa'!$I$5:$I$1048576,'01 Base Realizado'!H$5,'B. Despesa'!$K$5:$K$1048576,'01 Base Realizado'!$B55) -> -3020 | I55: =-H55/H$38 -> 0.0075616923 | J55: =SUMIFS('B. Despesa'!$H$5:$H$1048576,'B. Despesa'!$I$5:$I$1048576,'01 Base Realizado'!J$5,'B. Despesa'!$K$5:$K$1048576,'01 Base Realizado'!$B55) -> 0 | K55: =SUMIFS('B. Despesa'!$H$5:$H$1048576,'B. Despesa'!$I$5:$I$1048576,'01 Base Realizado'!K$5,'B. Despesa'!$K$5:$K$1048576,'01 Base Realizado'!$B55) -> 0 | L55: =SUMIFS('B. Despesa'!$H$5:$H$1048576,'B. Despesa'!$I$5:$I$1048576,'01 Base Realizado'!L$5,'B. Despesa'!$K$5:$K$1048576,'01 Base Realizado'!$B55) -> 0 | M55: =SUMIFS('B. Despesa'!$H$5:$H$1048576,'B. Despesa'!$I$5:$I$1048576,'01 Base Realizado'!M$5,'B. Despesa'!$K$5:$K$1048576,'01 Base Realizado'!$B55) -> 0 | N55: =SUMIFS('B. Despesa'!$H$5:$H$1048576,'B. Despesa'!$I$5:$I$1048576,'01 Base Realizado'!N$5,'B. Despesa'!$K$5:$K$1048576,'01 Base Realizado'!$B55) -> 0 | O55: =SUMIFS('B. Despesa'!$H$5:$H$1048576,'B. Despesa'!$I$5:$I$1048576,'01 Base Realizado'!O$5,'B. Despesa'!$K$5:$K$1048576,'01 Base Realizado'!$B55) -> 0 | P55: =SUMIFS('B. Despesa'!$H$5:$H$1048576,'B. Despesa'!$I$5:$I$1048576,'01 Base Realizado'!P$5,'B. Despesa'!$K$5:$K$1048576,'01 Base Realizado'!$B55) -> 0 | Q55: =SUMIFS('B. Despesa'!$H$5:$H$1048576,'B. Despesa'!$I$5:$I$1048576,'01 Base Realizado'!Q$5,'B. Despesa'!$K$5:$K$1048576,'01 Base Realizado'!$B55) -> 0 | R55: =SUMIFS('B. Despesa'!$H$5:$H$1048576,'B. Despesa'!$I$5:$I$1048576,'01 Base Realizado'!R$5,'B. Despesa'!$K$5:$K$1048576,'01 Base Realizado'!$B55) -> 0 | T55: -83835 | V55: 0.003 | Y55: Em Mar/26 houve compra de Uniforme Di Marino. Ternos para Kaique e Roberto
B56: Colaborador Extra | C56: 5.4.1.02.00022 | D56: =SUMIFS('B. Despesa'!$H:$H,'B. Despesa'!$I:$I,'01 Base Realizado'!D$5,'B. Despesa'!$K:$K,'01 Base Realizado'!$B56) -> -10460 | E56: =-D56/D$38 -> 0.049537499 | F56: =SUMIFS('B. Despesa'!$H$5:$H$1048576,'B. Despesa'!$I$5:$I$1048576,'01 Base Realizado'!F$5,'B. Despesa'!$K$5:$K$1048576,'01 Base Realizado'!$B56) -> -6920 | G56: =-F56/F$38 -> 0.026680634 | H56: =SUMIFS('B. Despesa'!$H$5:$H$1048576,'B. Despesa'!$I$5:$I$1048576,'01 Base Realizado'!H$5,'B. Despesa'!$K$5:$K$1048576,'01 Base Realizado'!$B56) -> -8370 | I56: =-H56/H$38 -> 0.020957405 | J56: =SUMIFS('B. Despesa'!$H$5:$H$1048576,'B. Despesa'!$I$5:$I$1048576,'01 Base Realizado'!J$5,'B. Despesa'!$K$5:$K$1048576,'01 Base Realizado'!$B56) -> 0 | K56: =SUMIFS('B. Despesa'!$H$5:$H$1048576,'B. Despesa'!$I$5:$I$1048576,'01 Base Realizado'!K$5,'B. Despesa'!$K$5:$K$1048576,'01 Base Realizado'!$B56) -> 0 | L56: =SUMIFS('B. Despesa'!$H$5:$H$1048576,'B. Despesa'!$I$5:$I$1048576,'01 Base Realizado'!L$5,'B. Despesa'!$K$5:$K$1048576,'01 Base Realizado'!$B56) -> 0 | M56: =SUMIFS('B. Despesa'!$H$5:$H$1048576,'B. Despesa'!$I$5:$I$1048576,'01 Base Realizado'!M$5,'B. Despesa'!$K$5:$K$1048576,'01 Base Realizado'!$B56) -> 0 | N56: =SUMIFS('B. Despesa'!$H$5:$H$1048576,'B. Despesa'!$I$5:$I$1048576,'01 Base Realizado'!N$5,'B. Despesa'!$K$5:$K$1048576,'01 Base Realizado'!$B56) -> 0 | O56: =SUMIFS('B. Despesa'!$H$5:$H$1048576,'B. Despesa'!$I$5:$I$1048576,'01 Base Realizado'!O$5,'B. Despesa'!$K$5:$K$1048576,'01 Base Realizado'!$B56) -> 0 | P56: =SUMIFS('B. Despesa'!$H$5:$H$1048576,'B. Despesa'!$I$5:$I$1048576,'01 Base Realizado'!P$5,'B. Despesa'!$K$5:$K$1048576,'01 Base Realizado'!$B56) -> 0 | Q56: =SUMIFS('B. Despesa'!$H$5:$H$1048576,'B. Despesa'!$I$5:$I$1048576,'01 Base Realizado'!Q$5,'B. Despesa'!$K$5:$K$1048576,'01 Base Realizado'!$B56) -> 0 | R56: =SUMIFS('B. Despesa'!$H$5:$H$1048576,'B. Despesa'!$I$5:$I$1048576,'01 Base Realizado'!R$5,'B. Despesa'!$K$5:$K$1048576,'01 Base Realizado'!$B56) -> 0
B57: Gratificações | C57: 3.1.1.03.00008 | D57: =SUMIFS('B. Despesa'!$H:$H,'B. Despesa'!$I:$I,'01 Base Realizado'!D$5,'B. Despesa'!$K:$K,'01 Base Realizado'!$B57) -> 0 | E57: =-D57/D$38 -> 0 | F57: =SUMIFS('B. Despesa'!$H$5:$H$1048576,'B. Despesa'!$I$5:$I$1048576,'01 Base Realizado'!F$5,'B. Despesa'!$K$5:$K$1048576,'01 Base Realizado'!$B57) -> 0 | G57: =-F57/F$38 -> 0 | H57: =SUMIFS('B. Despesa'!$H$5:$H$1048576,'B. Despesa'!$I$5:$I$1048576,'01 Base Realizado'!H$5,'B. Despesa'!$K$5:$K$1048576,'01 Base Realizado'!$B57) -> 0 | I57: =-H57/H$38 -> 0 | J57: =SUMIFS('B. Despesa'!$H$5:$H$1048576,'B. Despesa'!$I$5:$I$1048576,'01 Base Realizado'!J$5,'B. Despesa'!$K$5:$K$1048576,'01 Base Realizado'!$B57) -> 0 | K57: =SUMIFS('B. Despesa'!$H$5:$H$1048576,'B. Despesa'!$I$5:$I$1048576,'01 Base Realizado'!K$5,'B. Despesa'!$K$5:$K$1048576,'01 Base Realizado'!$B57) -> 0 | L57: =SUMIFS('B. Despesa'!$H$5:$H$1048576,'B. Despesa'!$I$5:$I$1048576,'01 Base Realizado'!L$5,'B. Despesa'!$K$5:$K$1048576,'01 Base Realizado'!$B57) -> 0 | M57: =SUMIFS('B. Despesa'!$H$5:$H$1048576,'B. Despesa'!$I$5:$I$1048576,'01 Base Realizado'!M$5,'B. Despesa'!$K$5:$K$1048576,'01 Base Realizado'!$B57) -> 0 | N57: =SUMIFS('B. Despesa'!$H$5:$H$1048576,'B. Despesa'!$I$5:$I$1048576,'01 Base Realizado'!N$5,'B. Despesa'!$K$5:$K$1048576,'01 Base Realizado'!$B57) -> 0 | O57: =SUMIFS('B. Despesa'!$H$5:$H$1048576,'B. Despesa'!$I$5:$I$1048576,'01 Base Realizado'!O$5,'B. Despesa'!$K$5:$K$1048576,'01 Base Realizado'!$B57) -> 0 | P57: =SUMIFS('B. Despesa'!$H$5:$H$1048576,'B. Despesa'!$I$5:$I$1048576,'01 Base Realizado'!P$5,'B. Despesa'!$K$5:$K$1048576,'01 Base Realizado'!$B57) -> 0 | Q57: =SUMIFS('B. Despesa'!$H$5:$H$1048576,'B. Despesa'!$I$5:$I$1048576,'01 Base Realizado'!Q$5,'B. Despesa'!$K$5:$K$1048576,'01 Base Realizado'!$B57) -> 0 | R57: =SUMIFS('B. Despesa'!$H$5:$H$1048576,'B. Despesa'!$I$5:$I$1048576,'01 Base Realizado'!R$5,'B. Despesa'!$K$5:$K$1048576,'01 Base Realizado'!$B57) -> 0
B58: Pro-Labore | C58: 5.4.1.02.00028 | D58: =SUMIFS('B. Despesa'!$H:$H,'B. Despesa'!$I:$I,'01 Base Realizado'!D$5,'B. Despesa'!$K:$K,'01 Base Realizado'!$B58) -> 0 | E58: =-D58/D$38 -> 0 | F58: =SUMIFS('B. Despesa'!$H$5:$H$1048576,'B. Despesa'!$I$5:$I$1048576,'01 Base Realizado'!F$5,'B. Despesa'!$K$5:$K$1048576,'01 Base Realizado'!$B58) -> 0 | G58: =-F58/F$38 -> 0 | H58: =SUMIFS('B. Despesa'!$H$5:$H$1048576,'B. Despesa'!$I$5:$I$1048576,'01 Base Realizado'!H$5,'B. Despesa'!$K$5:$K$1048576,'01 Base Realizado'!$B58) -> 0 | I58: =-H58/H$38 -> 0 | J58: =SUMIFS('B. Despesa'!$H$5:$H$1048576,'B. Despesa'!$I$5:$I$1048576,'01 Base Realizado'!J$5,'B. Despesa'!$K$5:$K$1048576,'01 Base Realizado'!$B58) -> 0 | K58: =SUMIFS('B. Despesa'!$H$5:$H$1048576,'B. Despesa'!$I$5:$I$1048576,'01 Base Realizado'!K$5,'B. Despesa'!$K$5:$K$1048576,'01 Base Realizado'!$B58) -> 0 | L58: =SUMIFS('B. Despesa'!$H$5:$H$1048576,'B. Despesa'!$I$5:$I$1048576,'01 Base Realizado'!L$5,'B. Despesa'!$K$5:$K$1048576,'01 Base Realizado'!$B58) -> 0 | M58: =SUMIFS('B. Despesa'!$H$5:$H$1048576,'B. Despesa'!$I$5:$I$1048576,'01 Base Realizado'!M$5,'B. Despesa'!$K$5:$K$1048576,'01 Base Realizado'!$B58) -> 0 | N58: =SUMIFS('B. Despesa'!$H$5:$H$1048576,'B. Despesa'!$I$5:$I$1048576,'01 Base Realizado'!N$5,'B. Despesa'!$K$5:$K$1048576,'01 Base Realizado'!$B58) -> 0 | O58: =SUMIFS('B. Despesa'!$H$5:$H$1048576,'B. Despesa'!$I$5:$I$1048576,'01 Base Realizado'!O$5,'B. Despesa'!$K$5:$K$1048576,'01 Base Realizado'!$B58) -> 0 | P58: =SUMIFS('B. Despesa'!$H$5:$H$1048576,'B. Despesa'!$I$5:$I$1048576,'01 Base Realizado'!P$5,'B. Despesa'!$K$5:$K$1048576,'01 Base Realizado'!$B58) -> 0 | Q58: =SUMIFS('B. Despesa'!$H$5:$H$1048576,'B. Despesa'!$I$5:$I$1048576,'01 Base Realizado'!Q$5,'B. Despesa'!$K$5:$K$1048576,'01 Base Realizado'!$B58) -> 0 | R58: =SUMIFS('B. Despesa'!$H$5:$H$1048576,'B. Despesa'!$I$5:$I$1048576,'01 Base Realizado'!R$5,'B. Despesa'!$K$5:$K$1048576,'01 Base Realizado'!$B58) -> 0 | T58: -600000
B59: Retenção de Gorjetas PJ | C59: 5.4.1.02.00031 | D59: 0 | E59: =-D59/D$38 -> 0 | F59: =7922.08+4110.83 -> 12032.91 | G59: =-F59/F$38 -> -0.046393883 | H59: =3283.98+5352.62 -> 8636.6 | I59: =-H59/H$38 -> -0.021624938 | J59: =SUMIFS('B. Despesa'!$H$5:$H$1048576,'B. Despesa'!$I$5:$I$1048576,'01 Base Realizado'!J$5,'B. Despesa'!$K$5:$K$1048576,'01 Base Realizado'!$B59) -> 0 | K59: =SUMIFS('B. Despesa'!$H$5:$H$1048576,'B. Despesa'!$I$5:$I$1048576,'01 Base Realizado'!K$5,'B. Despesa'!$K$5:$K$1048576,'01 Base Realizado'!$B59) -> 0 | L59: =SUMIFS('B. Despesa'!$H$5:$H$1048576,'B. Despesa'!$I$5:$I$1048576,'01 Base Realizado'!L$5,'B. Despesa'!$K$5:$K$1048576,'01 Base Realizado'!$B59) -> 0 | M59: =SUMIFS('B. Despesa'!$H$5:$H$1048576,'B. Despesa'!$I$5:$I$1048576,'01 Base Realizado'!M$5,'B. Despesa'!$K$5:$K$1048576,'01 Base Realizado'!$B59) -> 0 | N59: =SUMIFS('B. Despesa'!$H$5:$H$1048576,'B. Despesa'!$I$5:$I$1048576,'01 Base Realizado'!N$5,'B. Despesa'!$K$5:$K$1048576,'01 Base Realizado'!$B59) -> 0 | O59: =SUMIFS('B. Despesa'!$H$5:$H$1048576,'B. Despesa'!$I$5:$I$1048576,'01 Base Realizado'!O$5,'B. Despesa'!$K$5:$K$1048576,'01 Base Realizado'!$B59) -> 0 | P59: =SUMIFS('B. Despesa'!$H$5:$H$1048576,'B. Despesa'!$I$5:$I$1048576,'01 Base Realizado'!P$5,'B. Despesa'!$K$5:$K$1048576,'01 Base Realizado'!$B59) -> 0 | Q59: =SUMIFS('B. Despesa'!$H$5:$H$1048576,'B. Despesa'!$I$5:$I$1048576,'01 Base Realizado'!Q$5,'B. Despesa'!$K$5:$K$1048576,'01 Base Realizado'!$B59) -> 0 | R59: =SUMIFS('B. Despesa'!$H$5:$H$1048576,'B. Despesa'!$I$5:$I$1048576,'01 Base Realizado'!R$5,'B. Despesa'!$K$5:$K$1048576,'01 Base Realizado'!$B59) -> 0 | T59: -3565684.7 | Y59: Retenção ref. Aos PJs que não repassamos o valor, dando um impacto positivo na linha de pessoal como um todo
B60: Gorjetas Pagas | C60: 3.1.1.03.00009 | D60: =SUMIFS('B. Despesa'!$H:$H,'B. Despesa'!$I:$I,'01 Base Realizado'!D$5,'B. Despesa'!$K:$K,'01 Base Realizado'!$B60) -> 0 | E60: =-D60/D$38 -> 0 | F60: =SUMIFS('B. Despesa'!$H$5:$H$1048576,'B. Despesa'!$I$5:$I$1048576,'01 Base Realizado'!F$5,'B. Despesa'!$K$5:$K$1048576,'01 Base Realizado'!$B60) -> 0 | G60: =-F60/F$38 -> 0 | H60: =SUMIFS('B. Despesa'!$H$5:$H$1048576,'B. Despesa'!$I$5:$I$1048576,'01 Base Realizado'!H$5,'B. Despesa'!$K$5:$K$1048576,'01 Base Realizado'!$B60) -> 0 | I60: =-H60/H$38 -> 0 | J60: =SUMIFS('B. Despesa'!$H$5:$H$1048576,'B. Despesa'!$I$5:$I$1048576,'01 Base Realizado'!J$5,'B. Despesa'!$K$5:$K$1048576,'01 Base Realizado'!$B60) -> 0 | K60: =SUMIFS('B. Despesa'!$H$5:$H$1048576,'B. Despesa'!$I$5:$I$1048576,'01 Base Realizado'!K$5,'B. Despesa'!$K$5:$K$1048576,'01 Base Realizado'!$B60) -> 0 | L60: =SUMIFS('B. Despesa'!$H$5:$H$1048576,'B. Despesa'!$I$5:$I$1048576,'01 Base Realizado'!L$5,'B. Despesa'!$K$5:$K$1048576,'01 Base Realizado'!$B60) -> 0 | M60: =SUMIFS('B. Despesa'!$H$5:$H$1048576,'B. Despesa'!$I$5:$I$1048576,'01 Base Realizado'!M$5,'B. Despesa'!$K$5:$K$1048576,'01 Base Realizado'!$B60) -> 0 | N60: =SUMIFS('B. Despesa'!$H$5:$H$1048576,'B. Despesa'!$I$5:$I$1048576,'01 Base Realizado'!N$5,'B. Despesa'!$K$5:$K$1048576,'01 Base Realizado'!$B60) -> 0 | O60: =SUMIFS('B. Despesa'!$H$5:$H$1048576,'B. Despesa'!$I$5:$I$1048576,'01 Base Realizado'!O$5,'B. Despesa'!$K$5:$K$1048576,'01 Base Realizado'!$B60) -> 0 | P60: =SUMIFS('B. Despesa'!$H$5:$H$1048576,'B. Despesa'!$I$5:$I$1048576,'01 Base Realizado'!P$5,'B. Despesa'!$K$5:$K$1048576,'01 Base Realizado'!$B60) -> 0 | Q60: =SUMIFS('B. Despesa'!$H$5:$H$1048576,'B. Despesa'!$I$5:$I$1048576,'01 Base Realizado'!Q$5,'B. Despesa'!$K$5:$K$1048576,'01 Base Realizado'!$B60) -> 0 | R60: =SUMIFS('B. Despesa'!$H$5:$H$1048576,'B. Despesa'!$I$5:$I$1048576,'01 Base Realizado'!R$5,'B. Despesa'!$K$5:$K$1048576,'01 Base Realizado'!$B60) -> 0 | T60: 2389008.7
B61: DSR | C61: x.x.x.xx.xxxxx | D61: 0 | E61: =-D61/D$38 -> 0 | F61: 0 | G61: =-F61/F$38 -> 0 | H61: 0 | I61: =-H61/H$38 -> 0 | J61: 0 | K61: 0 | L61: 0 | M61: 0 | N61: 0 | O61: 0 | P61: 0 | Q61: 0 | R61: 0 | T61: 0
B62: GRATIFICAÇÃO - INSS | C62: x.x.x.xx.xxxxx | D62: 0 | E62: =-D62/D$38 -> 0 | F62: 0 | G62: =-F62/F$38 -> 0 | H62: 0 | I62: =-H62/H$38 -> 0 | J62: 0 | K62: 0 | L62: 0 | M62: 0 | N62: 0 | O62: 0 | P62: 0 | Q62: 0 | R62: 0 | T62: 0
B63: GRATIFICAÇÃO 13. SALÁRIO | C63: x.x.x.xx.xxxxx | D63: 0 | E63: =-D63/D$38 -> 0 | F63: 0 | G63: =-F63/F$38 -> 0 | H63: 0 | I63: =-H63/H$38 -> 0 | J63: 0 | K63: 0 | L63: 0 | M63: 0 | N63: 0 | O63: 0 | P63: 0 | Q63: 0 | R63: 0 | T63: 0
B64: GRATIFICAÇÃO FGTS | C64: x.x.x.xx.xxxxx | D64: 0 | E64: =-D64/D$38 -> 0 | F64: 0 | G64: =-F64/F$38 -> 0 | H64: 0 | I64: =-H64/H$38 -> 0 | J64: 0 | K64: 0 | L64: 0 | M64: 0 | N64: 0 | O64: 0 | P64: 0 | Q64: 0 | R64: 0 | T64: 0
B65: GRATIFICAÇÃO FÉRIAS | C65: x.x.x.xx.xxxxx | D65: 0 | E65: =-D65/D$38 -> 0 | F65: 0 | G65: =-F65/F$38 -> 0 | H65: 0 | I65: =-H65/H$38 -> 0 | J65: 0 | K65: 0 | L65: 0 | M65: 0 | N65: 0 | O65: 0 | P65: 0 | Q65: 0 | R65: 0 | T65: 0
E66: =-D66/D$38 -> 0 | G66: =-F66/F$38 -> 0 | I66: =-H66/H$38 -> 0
B67: OCUPAÇÃO | D67: =SUM(D68:D71) -> -23800 | E67: =-D67/D$38 -> 0.11271439 | F67: =SUM(F68:F71) -> -23800 | G67: =-F67/F$38 -> 0.091762875 | H67: =SUM(H68:H71) -> -23800 | I67: =-H67/H$38 -> 0.059592144 | J67: =SUM(J68:J74) -> 0 | K67: =SUM(K68:K74) -> 0 | L67: =SUM(L68:L74) -> 0 | M67: =SUM(M68:M74) -> 0 | N67: =SUM(N68:N74) -> 0 | O67: =SUM(O68:O74) -> 0 | P67: =SUM(P68:P74) -> 0 | Q67: =SUM(Q68:Q74) -> 0 | R67: =SUM(R68:R74) -> 0 | T67: -844692.6 | V67: %
B68: Aluguéis | C68: 4.1.1.02.00002 | D68: =SUMIFS('B. Despesa'!$H:$H,'B. Despesa'!$I:$I,'01 Base Realizado'!D$5,'B. Despesa'!$K:$K,'01 Base Realizado'!$B68) -> -18000 | E68: =-D68/D$38 -> 0.085246175 | F68: =SUMIFS('B. Despesa'!$H$5:$H$1048576,'B. Despesa'!$I$5:$I$1048576,'01 Base Realizado'!F$5,'B. Despesa'!$K$5:$K$1048576,'01 Base Realizado'!$B68) -> -18000 | G68: =-F68/F$38 -> 0.069400493 | H68: =SUMIFS('B. Despesa'!$H$5:$H$1048576,'B. Despesa'!$I$5:$I$1048576,'01 Base Realizado'!H$5,'B. Despesa'!$K$5:$K$1048576,'01 Base Realizado'!$B68) -> -18000 | I68: =-H68/H$38 -> 0.045069689 | J68: =SUMIFS('B. Despesa'!$H$5:$H$1048576,'B. Despesa'!$I$5:$I$1048576,'01 Base Realizado'!J$5,'B. Despesa'!$K$5:$K$1048576,'01 Base Realizado'!$B68) -> 0 | K68: =SUMIFS('B. Despesa'!$H$5:$H$1048576,'B. Despesa'!$I$5:$I$1048576,'01 Base Realizado'!K$5,'B. Despesa'!$K$5:$K$1048576,'01 Base Realizado'!$B68) -> 0 | L68: =SUMIFS('B. Despesa'!$H$5:$H$1048576,'B. Despesa'!$I$5:$I$1048576,'01 Base Realizado'!L$5,'B. Despesa'!$K$5:$K$1048576,'01 Base Realizado'!$B68) -> 0 | M68: =SUMIFS('B. Despesa'!$H$5:$H$1048576,'B. Despesa'!$I$5:$I$1048576,'01 Base Realizado'!M$5,'B. Despesa'!$K$5:$K$1048576,'01 Base Realizado'!$B68) -> 0 | N68: =SUMIFS('B. Despesa'!$H$5:$H$1048576,'B. Despesa'!$I$5:$I$1048576,'01 Base Realizado'!N$5,'B. Despesa'!$K$5:$K$1048576,'01 Base Realizado'!$B68) -> 0 | O68: =SUMIFS('B. Despesa'!$H$5:$H$1048576,'B. Despesa'!$I$5:$I$1048576,'01 Base Realizado'!O$5,'B. Despesa'!$K$5:$K$1048576,'01 Base Realizado'!$B68) -> 0 | P68: =SUMIFS('B. Despesa'!$H$5:$H$1048576,'B. Despesa'!$I$5:$I$1048576,'01 Base Realizado'!P$5,'B. Despesa'!$K$5:$K$1048576,'01 Base Realizado'!$B68) -> 0 | Q68: =SUMIFS('B. Despesa'!$H$5:$H$1048576,'B. Despesa'!$I$5:$I$1048576,'01 Base Realizado'!Q$5,'B. Despesa'!$K$5:$K$1048576,'01 Base Realizado'!$B68) -> 0 | R68: =SUMIFS('B. Despesa'!$H$5:$H$1048576,'B. Despesa'!$I$5:$I$1048576,'01 Base Realizado'!R$5,'B. Despesa'!$K$5:$K$1048576,'01 Base Realizado'!$B68) -> 0 | T68: -540000
B69: Casa de Apoio | C69: 4.1.1.02.00003 | D69: =SUMIFS('B. Despesa'!$H:$H,'B. Despesa'!$I:$I,'01 Base Realizado'!D$5,'B. Despesa'!$K:$K,'01 Base Realizado'!$B69) -> 0 | E69: =-D69/D$38 -> 0 | F69: =SUMIFS('B. Despesa'!$H$5:$H$1048576,'B. Despesa'!$I$5:$I$1048576,'01 Base Realizado'!F$5,'B. Despesa'!$K$5:$K$1048576,'01 Base Realizado'!$B69) -> 0 | G69: =-F69/F$38 -> 0 | H69: =SUMIFS('B. Despesa'!$H$5:$H$1048576,'B. Despesa'!$I$5:$I$1048576,'01 Base Realizado'!H$5,'B. Despesa'!$K$5:$K$1048576,'01 Base Realizado'!$B69) -> 0 | I69: =-H69/H$38 -> 0 | J69: =SUMIFS('B. Despesa'!$H$5:$H$1048576,'B. Despesa'!$I$5:$I$1048576,'01 Base Realizado'!J$5,'B. Despesa'!$K$5:$K$1048576,'01 Base Realizado'!$B69) -> 0 | K69: =SUMIFS('B. Despesa'!$H$5:$H$1048576,'B. Despesa'!$I$5:$I$1048576,'01 Base Realizado'!K$5,'B. Despesa'!$K$5:$K$1048576,'01 Base Realizado'!$B69) -> 0 | L69: =SUMIFS('B. Despesa'!$H$5:$H$1048576,'B. Despesa'!$I$5:$I$1048576,'01 Base Realizado'!L$5,'B. Despesa'!$K$5:$K$1048576,'01 Base Realizado'!$B69) -> 0 | M69: =SUMIFS('B. Despesa'!$H$5:$H$1048576,'B. Despesa'!$I$5:$I$1048576,'01 Base Realizado'!M$5,'B. Despesa'!$K$5:$K$1048576,'01 Base Realizado'!$B69) -> 0 | N69: =SUMIFS('B. Despesa'!$H$5:$H$1048576,'B. Despesa'!$I$5:$I$1048576,'01 Base Realizado'!N$5,'B. Despesa'!$K$5:$K$1048576,'01 Base Realizado'!$B69) -> 0 | O69: =SUMIFS('B. Despesa'!$H$5:$H$1048576,'B. Despesa'!$I$5:$I$1048576,'01 Base Realizado'!O$5,'B. Despesa'!$K$5:$K$1048576,'01 Base Realizado'!$B69) -> 0 | P69: =SUMIFS('B. Despesa'!$H$5:$H$1048576,'B. Despesa'!$I$5:$I$1048576,'01 Base Realizado'!P$5,'B. Despesa'!$K$5:$K$1048576,'01 Base Realizado'!$B69) -> 0 | Q69: =SUMIFS('B. Despesa'!$H$5:$H$1048576,'B. Despesa'!$I$5:$I$1048576,'01 Base Realizado'!Q$5,'B. Despesa'!$K$5:$K$1048576,'01 Base Realizado'!$B69) -> 0 | R69: =SUMIFS('B. Despesa'!$H$5:$H$1048576,'B. Despesa'!$I$5:$I$1048576,'01 Base Realizado'!R$5,'B. Despesa'!$K$5:$K$1048576,'01 Base Realizado'!$B69) -> 0 | T69: -224016
B70: IPTU | C70: 4.1.1.02.00004 | D70: =SUMIFS('B. Despesa'!$H:$H,'B. Despesa'!$I:$I,'01 Base Realizado'!D$5,'B. Despesa'!$K:$K,'01 Base Realizado'!$B70) -> -800 | E70: =-D70/D$38 -> 0.0037887189 | F70: =SUMIFS('B. Despesa'!$H$5:$H$1048576,'B. Despesa'!$I$5:$I$1048576,'01 Base Realizado'!F$5,'B. Despesa'!$K$5:$K$1048576,'01 Base Realizado'!$B70) -> -800 | G70: =-F70/F$38 -> 0.0030844664 | H70: =SUMIFS('B. Despesa'!$H$5:$H$1048576,'B. Despesa'!$I$5:$I$1048576,'01 Base Realizado'!H$5,'B. Despesa'!$K$5:$K$1048576,'01 Base Realizado'!$B70) -> -800 | I70: =-H70/H$38 -> 0.0020030973 | J70: =SUMIFS('B. Despesa'!$H$5:$H$1048576,'B. Despesa'!$I$5:$I$1048576,'01 Base Realizado'!J$5,'B. Despesa'!$K$5:$K$1048576,'01 Base Realizado'!$B70) -> 0 | K70: =SUMIFS('B. Despesa'!$H$5:$H$1048576,'B. Despesa'!$I$5:$I$1048576,'01 Base Realizado'!K$5,'B. Despesa'!$K$5:$K$1048576,'01 Base Realizado'!$B70) -> 0 | L70: =SUMIFS('B. Despesa'!$H$5:$H$1048576,'B. Despesa'!$I$5:$I$1048576,'01 Base Realizado'!L$5,'B. Despesa'!$K$5:$K$1048576,'01 Base Realizado'!$B70) -> 0 | M70: =SUMIFS('B. Despesa'!$H$5:$H$1048576,'B. Despesa'!$I$5:$I$1048576,'01 Base Realizado'!M$5,'B. Despesa'!$K$5:$K$1048576,'01 Base Realizado'!$B70) -> 0 | N70: =SUMIFS('B. Despesa'!$H$5:$H$1048576,'B. Despesa'!$I$5:$I$1048576,'01 Base Realizado'!N$5,'B. Despesa'!$K$5:$K$1048576,'01 Base Realizado'!$B70) -> 0 | O70: =SUMIFS('B. Despesa'!$H$5:$H$1048576,'B. Despesa'!$I$5:$I$1048576,'01 Base Realizado'!O$5,'B. Despesa'!$K$5:$K$1048576,'01 Base Realizado'!$B70) -> 0 | P70: =SUMIFS('B. Despesa'!$H$5:$H$1048576,'B. Despesa'!$I$5:$I$1048576,'01 Base Realizado'!P$5,'B. Despesa'!$K$5:$K$1048576,'01 Base Realizado'!$B70) -> 0 | Q70: =SUMIFS('B. Despesa'!$H$5:$H$1048576,'B. Despesa'!$I$5:$I$1048576,'01 Base Realizado'!Q$5,'B. Despesa'!$K$5:$K$1048576,'01 Base Realizado'!$B70) -> 0 | R70: =SUMIFS('B. Despesa'!$H$5:$H$1048576,'B. Despesa'!$I$5:$I$1048576,'01 Base Realizado'!R$5,'B. Despesa'!$K$5:$K$1048576,'01 Base Realizado'!$B70) -> 0 | T70: -80676.6 | Y70: Pagto de Jan/26 indevido e será descontado na última parcela do ano
B71: Valet | D71: =SUMIFS('B. Despesa'!$H:$H,'B. Despesa'!$I:$I,'01 Base Realizado'!D$5,'B. Despesa'!$K:$K,'01 Base Realizado'!$B71) -> -5000 | E71: =-D71/D$38 -> 0.023679493 | F71: =SUMIFS('B. Despesa'!$H$5:$H$1048576,'B. Despesa'!$I$5:$I$1048576,'01 Base Realizado'!F$5,'B. Despesa'!$K$5:$K$1048576,'01 Base Realizado'!$B71) -> -5000 | G71: =-F71/F$38 -> 0.019277915 | H71: =SUMIFS('B. Despesa'!$H$5:$H$1048576,'B. Despesa'!$I$5:$I$1048576,'01 Base Realizado'!H$5,'B. Despesa'!$K$5:$K$1048576,'01 Base Realizado'!$B71) -> -5000 | I71: =-H71/H$38 -> 0.012519358 | Y71: Negociação mensal para serviço de Valet Mdna
B72: UTILIDADES/ CONSUMO | D72: =SUM(D73:D75) -> -3508.22 | E72: =-D72/D$38 -> 0.016614574 | F72: =SUM(F73:F74) -> -1710.94 | G72: =-F72/F$38 -> 0.0065966711 | H72: =SUM(H73:H74) -> -1327.81 | I72: =-H72/H$38 -> 0.0033246658 | J72: =SUM(J73:J81) -> 0 | K72: =SUM(K73:K81) -> 0 | L72: =SUM(L73:L81) -> 0 | M72: =SUM(M73:M81) -> 0 | N72: =SUM(N73:N81) -> 0 | O72: =SUM(O73:O81) -> 0 | P72: =SUM(P73:P81) -> 0 | Q72: =SUM(Q73:Q81) -> 0 | R72: =SUM(R73:R81) -> 0 | T72: -844692.6 | V72: %
B73: Água e Esgoto | C73: 5.4.1.03.00001 | D73: =SUMIFS('B. Despesa'!$H:$H,'B. Despesa'!$I:$I,'01 Base Realizado'!D$5,'B. Despesa'!$K:$K,'01 Base Realizado'!$B73) -> -1032.13 | E73: =-D73/D$38 -> 0.004888063 | F73: =SUMIFS('B. Despesa'!$H$5:$H$1048576,'B. Despesa'!$I$5:$I$1048576,'01 Base Realizado'!F$5,'B. Despesa'!$K$5:$K$1048576,'01 Base Realizado'!$B73) -> -479.94 | G73: =-F73/F$38 -> 0.0018504485 | H73: =SUMIFS('B. Despesa'!$H$5:$H$1048576,'B. Despesa'!$I$5:$I$1048576,'01 Base Realizado'!H$5,'B. Despesa'!$K$5:$K$1048576,'01 Base Realizado'!$B73) -> 0 | I73: =-H73/H$38 -> 0 | J73: =SUMIFS('B. Despesa'!$H$5:$H$1048576,'B. Despesa'!$I$5:$I$1048576,'01 Base Realizado'!J$5,'B. Despesa'!$K$5:$K$1048576,'01 Base Realizado'!$B73) -> 0 | K73: =SUMIFS('B. Despesa'!$H$5:$H$1048576,'B. Despesa'!$I$5:$I$1048576,'01 Base Realizado'!K$5,'B. Despesa'!$K$5:$K$1048576,'01 Base Realizado'!$B73) -> 0 | L73: =SUMIFS('B. Despesa'!$H$5:$H$1048576,'B. Despesa'!$I$5:$I$1048576,'01 Base Realizado'!L$5,'B. Despesa'!$K$5:$K$1048576,'01 Base Realizado'!$B73) -> 0 | M73: =SUMIFS('B. Despesa'!$H$5:$H$1048576,'B. Despesa'!$I$5:$I$1048576,'01 Base Realizado'!M$5,'B. Despesa'!$K$5:$K$1048576,'01 Base Realizado'!$B73) -> 0 | N73: =SUMIFS('B. Despesa'!$H$5:$H$1048576,'B. Despesa'!$I$5:$I$1048576,'01 Base Realizado'!N$5,'B. Despesa'!$K$5:$K$1048576,'01 Base Realizado'!$B73) -> 0 | O73: =SUMIFS('B. Despesa'!$H$5:$H$1048576,'B. Despesa'!$I$5:$I$1048576,'01 Base Realizado'!O$5,'B. Despesa'!$K$5:$K$1048576,'01 Base Realizado'!$B73) -> 0 | P73: =SUMIFS('B. Despesa'!$H$5:$H$1048576,'B. Despesa'!$I$5:$I$1048576,'01 Base Realizado'!P$5,'B. Despesa'!$K$5:$K$1048576,'01 Base Realizado'!$B73) -> 0 | Q73: =SUMIFS('B. Despesa'!$H$5:$H$1048576,'B. Despesa'!$I$5:$I$1048576,'01 Base Realizado'!Q$5,'B. Despesa'!$K$5:$K$1048576,'01 Base Realizado'!$B73) -> 0 | R73: =SUMIFS('B. Despesa'!$H$5:$H$1048576,'B. Despesa'!$I$5:$I$1048576,'01 Base Realizado'!R$5,'B. Despesa'!$K$5:$K$1048576,'01 Base Realizado'!$B73) -> 0 | T73: -253300.75 | V73: 0.01 | Y73: No mês de Mar/2026 não houve geração da conta pois devido ao aumento no consumo foi para análise;
B74: Energia Elétrica | C74: 5.4.1.03.00020 | D74: =SUMIFS('B. Despesa'!$H:$H,'B. Despesa'!$I:$I,'01 Base Realizado'!D$5,'B. Despesa'!$K:$K,'01 Base Realizado'!$B74) -> -2476.09 | E74: =-D74/D$38 -> 0.011726511 | F74: =SUMIFS('B. Despesa'!$H$5:$H$1048576,'B. Despesa'!$I$5:$I$1048576,'01 Base Realizado'!F$5,'B. Despesa'!$K$5:$K$1048576,'01 Base Realizado'!$B74) -> -1231 | G74: =-F74/F$38 -> 0.0047462226 | H74: =SUMIFS('B. Despesa'!$H$5:$H$1048576,'B. Despesa'!$I$5:$I$1048576,'01 Base Realizado'!H$5,'B. Despesa'!$K$5:$K$1048576,'01 Base Realizado'!$B74) -> -1327.81 | I74: =-H74/H$38 -> 0.0033246658 | J74: =SUMIFS('B. Despesa'!$H$5:$H$1048576,'B. Despesa'!$I$5:$I$1048576,'01 Base Realizado'!J$5,'B. Despesa'!$K$5:$K$1048576,'01 Base Realizado'!$B74) -> 0 | K74: =SUMIFS('B. Despesa'!$H$5:$H$1048576,'B. Despesa'!$I$5:$I$1048576,'01 Base Realizado'!K$5,'B. Despesa'!$K$5:$K$1048576,'01 Base Realizado'!$B74) -> 0 | L74: =SUMIFS('B. Despesa'!$H$5:$H$1048576,'B. Despesa'!$I$5:$I$1048576,'01 Base Realizado'!L$5,'B. Despesa'!$K$5:$K$1048576,'01 Base Realizado'!$B74) -> 0 | M74: =SUMIFS('B. Despesa'!$H$5:$H$1048576,'B. Despesa'!$I$5:$I$1048576,'01 Base Realizado'!M$5,'B. Despesa'!$K$5:$K$1048576,'01 Base Realizado'!$B74) -> 0 | N74: =SUMIFS('B. Despesa'!$H$5:$H$1048576,'B. Despesa'!$I$5:$I$1048576,'01 Base Realizado'!N$5,'B. Despesa'!$K$5:$K$1048576,'01 Base Realizado'!$B74) -> 0 | O74: =SUMIFS('B. Despesa'!$H$5:$H$1048576,'B. Despesa'!$I$5:$I$1048576,'01 Base Realizado'!O$5,'B. Despesa'!$K$5:$K$1048576,'01 Base Realizado'!$B74) -> 0 | P74: =SUMIFS('B. Despesa'!$H$5:$H$1048576,'B. Despesa'!$I$5:$I$1048576,'01 Base Realizado'!P$5,'B. Despesa'!$K$5:$K$1048576,'01 Base Realizado'!$B74) -> 0 | Q74: =SUMIFS('B. Despesa'!$H$5:$H$1048576,'B. Despesa'!$I$5:$I$1048576,'01 Base Realizado'!Q$5,'B. Despesa'!$K$5:$K$1048576,'01 Base Realizado'!$B74) -> 0 | R74: =SUMIFS('B. Despesa'!$H$5:$H$1048576,'B. Despesa'!$I$5:$I$1048576,'01 Base Realizado'!R$5,'B. Despesa'!$K$5:$K$1048576,'01 Base Realizado'!$B74) -> 0 | T74: -303960.9 | V74: 0.012
B75: Gás Encanado | C75: 5.4.1.03.00021 | D75: =SUMIFS('B. Despesa'!$H:$H,'B. Despesa'!$I:$I,'01 Base Realizado'!D$5,'B. Despesa'!$K:$K,'01 Base Realizado'!$B75) -> 0 | E75: =-D75/D$38 -> 0 | F75: =SUMIFS('B. Despesa'!$H$5:$H$1048576,'B. Despesa'!$I$5:$I$1048576,'01 Base Realizado'!F$5,'B. Despesa'!$K$5:$K$1048576,'01 Base Realizado'!$B75) -> 0 | G75: =-F75/F$38 -> 0 | H75: =SUMIFS('B. Despesa'!$H$5:$H$1048576,'B. Despesa'!$I$5:$I$1048576,'01 Base Realizado'!H$5,'B. Despesa'!$K$5:$K$1048576,'01 Base Realizado'!$B75) -> 0 | I75: =-H75/H$38 -> 0 | J75: =SUMIFS('B. Despesa'!$H$5:$H$1048576,'B. Despesa'!$I$5:$I$1048576,'01 Base Realizado'!J$5,'B. Despesa'!$K$5:$K$1048576,'01 Base Realizado'!$B75) -> 0 | K75: =SUMIFS('B. Despesa'!$H$5:$H$1048576,'B. Despesa'!$I$5:$I$1048576,'01 Base Realizado'!K$5,'B. Despesa'!$K$5:$K$1048576,'01 Base Realizado'!$B75) -> 0 | L75: =SUMIFS('B. Despesa'!$H$5:$H$1048576,'B. Despesa'!$I$5:$I$1048576,'01 Base Realizado'!L$5,'B. Despesa'!$K$5:$K$1048576,'01 Base Realizado'!$B75) -> 0 | M75: =SUMIFS('B. Despesa'!$H$5:$H$1048576,'B. Despesa'!$I$5:$I$1048576,'01 Base Realizado'!M$5,'B. Despesa'!$K$5:$K$1048576,'01 Base Realizado'!$B75) -> 0 | N75: =SUMIFS('B. Despesa'!$H$5:$H$1048576,'B. Despesa'!$I$5:$I$1048576,'01 Base Realizado'!N$5,'B. Despesa'!$K$5:$K$1048576,'01 Base Realizado'!$B75) -> 0 | O75: =SUMIFS('B. Despesa'!$H$5:$H$1048576,'B. Despesa'!$I$5:$I$1048576,'01 Base Realizado'!O$5,'B. Despesa'!$K$5:$K$1048576,'01 Base Realizado'!$B75) -> 0 | P75: =SUMIFS('B. Despesa'!$H$5:$H$1048576,'B. Despesa'!$I$5:$I$1048576,'01 Base Realizado'!P$5,'B. Despesa'!$K$5:$K$1048576,'01 Base Realizado'!$B75) -> 0 | Q75: =SUMIFS('B. Despesa'!$H$5:$H$1048576,'B. Despesa'!$I$5:$I$1048576,'01 Base Realizado'!Q$5,'B. Despesa'!$K$5:$K$1048576,'01 Base Realizado'!$B75) -> 0 | R75: =SUMIFS('B. Despesa'!$H$5:$H$1048576,'B. Despesa'!$I$5:$I$1048576,'01 Base Realizado'!R$5,'B. Despesa'!$K$5:$K$1048576,'01 Base Realizado'!$B75) -> 0 | T75: -126650.38 | V75: 0.005
B76: MANUTENÇÃO | D76: =SUM(D77:D79) -> -934.5 | E76: =-D76/D$38 -> 0.0044256972 | F76: =SUM(F77:F79) -> -4500 | G76: =-F76/F$38 -> 0.017350123 | H76: =SUM(H77:H79) -> -960 | I76: =-H76/H$38 -> 0.0024037167 | J76: =SUM(J80:J83) -> 0 | K76: =SUM(K80:K83) -> 0 | L76: =SUM(L80:L83) -> 0 | M76: =SUM(M80:M83) -> 0 | N76: =SUM(N80:N83) -> 0 | O76: =SUM(O80:O83) -> 0 | P76: =SUM(P80:P83) -> 0 | Q76: =SUM(Q80:Q83) -> 0 | R76: =SUM(R80:R83) -> 0 | T76: -844692.6 | V76: %
B77: Manutenção e Conservação | C77: 5.4.1.03.00023 | D77: =SUMIFS('B. Despesa'!$H:$H,'B. Despesa'!$I:$I,'01 Base Realizado'!D$5,'B. Despesa'!$K:$K,'01 Base Realizado'!$B77) -> -934.5 | E77: =-D77/D$38 -> 0.0044256972 | F77: =SUMIFS('B. Despesa'!$H$5:$H$1048576,'B. Despesa'!$I$5:$I$1048576,'01 Base Realizado'!F$5,'B. Despesa'!$K$5:$K$1048576,'01 Base Realizado'!$B77) -> -3600 | G77: =-F77/F$38 -> 0.013880099 | H77: =SUMIFS('B. Despesa'!$H$5:$H$1048576,'B. Despesa'!$I$5:$I$1048576,'01 Base Realizado'!H$5,'B. Despesa'!$K$5:$K$1048576,'01 Base Realizado'!$B77) -> -960 | I77: =-H77/H$38 -> 0.0024037167 | J77: =SUMIFS('B. Despesa'!$H$5:$H$1048576,'B. Despesa'!$I$5:$I$1048576,'01 Base Realizado'!J$5,'B. Despesa'!$K$5:$K$1048576,'01 Base Realizado'!$B77) -> 0 | K77: =SUMIFS('B. Despesa'!$H$5:$H$1048576,'B. Despesa'!$I$5:$I$1048576,'01 Base Realizado'!K$5,'B. Despesa'!$K$5:$K$1048576,'01 Base Realizado'!$B77) -> 0 | L77: =SUMIFS('B. Despesa'!$H$5:$H$1048576,'B. Despesa'!$I$5:$I$1048576,'01 Base Realizado'!L$5,'B. Despesa'!$K$5:$K$1048576,'01 Base Realizado'!$B77) -> 0 | M77: =SUMIFS('B. Despesa'!$H$5:$H$1048576,'B. Despesa'!$I$5:$I$1048576,'01 Base Realizado'!M$5,'B. Despesa'!$K$5:$K$1048576,'01 Base Realizado'!$B77) -> 0 | N77: =SUMIFS('B. Despesa'!$H$5:$H$1048576,'B. Despesa'!$I$5:$I$1048576,'01 Base Realizado'!N$5,'B. Despesa'!$K$5:$K$1048576,'01 Base Realizado'!$B77) -> 0 | O77: =SUMIFS('B. Despesa'!$H$5:$H$1048576,'B. Despesa'!$I$5:$I$1048576,'01 Base Realizado'!O$5,'B. Despesa'!$K$5:$K$1048576,'01 Base Realizado'!$B77) -> 0 | P77: =SUMIFS('B. Despesa'!$H$5:$H$1048576,'B. Despesa'!$I$5:$I$1048576,'01 Base Realizado'!P$5,'B. Despesa'!$K$5:$K$1048576,'01 Base Realizado'!$B77) -> 0 | Q77: =SUMIFS('B. Despesa'!$H$5:$H$1048576,'B. Despesa'!$I$5:$I$1048576,'01 Base Realizado'!Q$5,'B. Despesa'!$K$5:$K$1048576,'01 Base Realizado'!$B77) -> 0 | R77: =SUMIFS('B. Despesa'!$H$5:$H$1048576,'B. Despesa'!$I$5:$I$1048576,'01 Base Realizado'!R$5,'B. Despesa'!$K$5:$K$1048576,'01 Base Realizado'!$B77) -> 0 | T77: -253300.75 | V77: 0.01 | Y77: Em Janeiro tivemos a manutenão do telhado/ Em Fev/2026 houve a manutenção da masseira da cozinha e geladeira/ Mar/2026 manutenção da geladeira de vinhos brancos
B78: Decoração e Paisagismo | C78: 5.4.1.03.00008 | D78: =SUMIFS('B. Despesa'!$H:$H,'B. Despesa'!$I:$I,'01 Base Realizado'!D$5,'B. Despesa'!$K:$K,'01 Base Realizado'!$B78) -> 0 | E78: =-D78/D$38 -> 0 | F78: =SUMIFS('B. Despesa'!$H$5:$H$1048576,'B. Despesa'!$I$5:$I$1048576,'01 Base Realizado'!F$5,'B. Despesa'!$K$5:$K$1048576,'01 Base Realizado'!$B78) -> 0 | G78: =-F78/F$38 -> 0 | H78: =SUMIFS('B. Despesa'!$H$5:$H$1048576,'B. Despesa'!$I$5:$I$1048576,'01 Base Realizado'!H$5,'B. Despesa'!$K$5:$K$1048576,'01 Base Realizado'!$B78) -> 0 | I78: =-H78/H$38 -> 0 | J78: =SUMIFS('B. Despesa'!$H$5:$H$1048576,'B. Despesa'!$I$5:$I$1048576,'01 Base Realizado'!J$5,'B. Despesa'!$K$5:$K$1048576,'01 Base Realizado'!$B78) -> 0 | K78: =SUMIFS('B. Despesa'!$H$5:$H$1048576,'B. Despesa'!$I$5:$I$1048576,'01 Base Realizado'!K$5,'B. Despesa'!$K$5:$K$1048576,'01 Base Realizado'!$B78) -> 0 | L78: =SUMIFS('B. Despesa'!$H$5:$H$1048576,'B. Despesa'!$I$5:$I$1048576,'01 Base Realizado'!L$5,'B. Despesa'!$K$5:$K$1048576,'01 Base Realizado'!$B78) -> 0 | M78: =SUMIFS('B. Despesa'!$H$5:$H$1048576,'B. Despesa'!$I$5:$I$1048576,'01 Base Realizado'!M$5,'B. Despesa'!$K$5:$K$1048576,'01 Base Realizado'!$B78) -> 0 | N78: =SUMIFS('B. Despesa'!$H$5:$H$1048576,'B. Despesa'!$I$5:$I$1048576,'01 Base Realizado'!N$5,'B. Despesa'!$K$5:$K$1048576,'01 Base Realizado'!$B78) -> 0 | O78: =SUMIFS('B. Despesa'!$H$5:$H$1048576,'B. Despesa'!$I$5:$I$1048576,'01 Base Realizado'!O$5,'B. Despesa'!$K$5:$K$1048576,'01 Base Realizado'!$B78) -> 0 | P78: =SUMIFS('B. Despesa'!$H$5:$H$1048576,'B. Despesa'!$I$5:$I$1048576,'01 Base Realizado'!P$5,'B. Despesa'!$K$5:$K$1048576,'01 Base Realizado'!$B78) -> 0 | Q78: =SUMIFS('B. Despesa'!$H$5:$H$1048576,'B. Despesa'!$I$5:$I$1048576,'01 Base Realizado'!Q$5,'B. Despesa'!$K$5:$K$1048576,'01 Base Realizado'!$B78) -> 0 | R78: =SUMIFS('B. Despesa'!$H$5:$H$1048576,'B. Despesa'!$I$5:$I$1048576,'01 Base Realizado'!R$5,'B. Despesa'!$K$5:$K$1048576,'01 Base Realizado'!$B78) -> 0 | T78: -25330.075 | V78: 0.001
B79: Dedetização | C79: 5.4.1.03.00009 | D79: =SUMIFS('B. Despesa'!$H:$H,'B. Despesa'!$I:$I,'01 Base Realizado'!D$5,'B. Despesa'!$K:$K,'01 Base Realizado'!$B79) -> 0 | E79: =-D79/D$38 -> 0 | F79: =SUMIFS('B. Despesa'!$H$5:$H$1048576,'B. Despesa'!$I$5:$I$1048576,'01 Base Realizado'!F$5,'B. Despesa'!$K$5:$K$1048576,'01 Base Realizado'!$B79) -> -900 | G79: =-F79/F$38 -> 0.0034700247 | H79: =SUMIFS('B. Despesa'!$H$5:$H$1048576,'B. Despesa'!$I$5:$I$1048576,'01 Base Realizado'!H$5,'B. Despesa'!$K$5:$K$1048576,'01 Base Realizado'!$B79) -> 0 | I79: =-H79/H$38 -> 0 | J79: =SUMIFS('B. Despesa'!$H$5:$H$1048576,'B. Despesa'!$I$5:$I$1048576,'01 Base Realizado'!J$5,'B. Despesa'!$K$5:$K$1048576,'01 Base Realizado'!$B79) -> 0 | K79: =SUMIFS('B. Despesa'!$H$5:$H$1048576,'B. Despesa'!$I$5:$I$1048576,'01 Base Realizado'!K$5,'B. Despesa'!$K$5:$K$1048576,'01 Base Realizado'!$B79) -> 0 | L79: =SUMIFS('B. Despesa'!$H$5:$H$1048576,'B. Despesa'!$I$5:$I$1048576,'01 Base Realizado'!L$5,'B. Despesa'!$K$5:$K$1048576,'01 Base Realizado'!$B79) -> 0 | M79: =SUMIFS('B. Despesa'!$H$5:$H$1048576,'B. Despesa'!$I$5:$I$1048576,'01 Base Realizado'!M$5,'B. Despesa'!$K$5:$K$1048576,'01 Base Realizado'!$B79) -> 0 | N79: =SUMIFS('B. Despesa'!$H$5:$H$1048576,'B. Despesa'!$I$5:$I$1048576,'01 Base Realizado'!N$5,'B. Despesa'!$K$5:$K$1048576,'01 Base Realizado'!$B79) -> 0 | O79: =SUMIFS('B. Despesa'!$H$5:$H$1048576,'B. Despesa'!$I$5:$I$1048576,'01 Base Realizado'!O$5,'B. Despesa'!$K$5:$K$1048576,'01 Base Realizado'!$B79) -> 0 | P79: =SUMIFS('B. Despesa'!$H$5:$H$1048576,'B. Despesa'!$I$5:$I$1048576,'01 Base Realizado'!P$5,'B. Despesa'!$K$5:$K$1048576,'01 Base Realizado'!$B79) -> 0 | Q79: =SUMIFS('B. Despesa'!$H$5:$H$1048576,'B. Despesa'!$I$5:$I$1048576,'01 Base Realizado'!Q$5,'B. Despesa'!$K$5:$K$1048576,'01 Base Realizado'!$B79) -> 0 | R79: =SUMIFS('B. Despesa'!$H$5:$H$1048576,'B. Despesa'!$I$5:$I$1048576,'01 Base Realizado'!R$5,'B. Despesa'!$K$5:$K$1048576,'01 Base Realizado'!$B79) -> 0 | T79: -33600 | V79: =-T79/T11 -> 0.0012250102 | Y79: O pagamento é realizado trimestralmente;
B80: OPERAÇÃO | D80: =SUM(D81:D96) -> -52862.23 | E80: =-D80/D$38 -> 0.25035016 | F80: =SUM(F81:F96) -> -66223.54 | G80: =-F80/F$38 -> 0.25533035 | H80: =SUM(H81:H96) -> -83235.31 | I80: =-H80/H$38 -> 0.20841053 | J80: =SUM(J81:J95) -> 0 | K80: =SUM(K81:K95) -> 0 | L80: =SUM(L81:L95) -> 0 | M80: =SUM(M81:M95) -> 0 | N80: =SUM(N81:N95) -> 0 | O80: =SUM(O81:O95) -> 0 | P80: =SUM(P81:P95) -> 0 | Q80: =SUM(Q81:Q95) -> 0 | R80: =SUM(R81:R95) -> 0 | T80: -3116823.6 | V80: %
B81: Aluguel de Maquinas | C81: 5.4.1.03.00002 | D81: =SUMIFS('B. Despesa'!$H:$H,'B. Despesa'!$I:$I,'01 Base Realizado'!D$5,'B. Despesa'!$K:$K,'01 Base Realizado'!$B81) -> -1800 | E81: =-D81/D$38 -> 0.0085246175 | F81: =SUMIFS('B. Despesa'!$H$5:$H$1048576,'B. Despesa'!$I$5:$I$1048576,'01 Base Realizado'!F$5,'B. Despesa'!$K$5:$K$1048576,'01 Base Realizado'!$B81) -> -1800 | G81: =-F81/F$38 -> 0.0069400493 | H81: =SUMIFS('B. Despesa'!$H$5:$H$1048576,'B. Despesa'!$I$5:$I$1048576,'01 Base Realizado'!H$5,'B. Despesa'!$K$5:$K$1048576,'01 Base Realizado'!$B81) -> -1800 | I81: =-H81/H$38 -> 0.0045069689 | J81: =SUMIFS('B. Despesa'!$H$5:$H$1048576,'B. Despesa'!$I$5:$I$1048576,'01 Base Realizado'!J$5,'B. Despesa'!$K$5:$K$1048576,'01 Base Realizado'!$B81) -> 0 | K81: =SUMIFS('B. Despesa'!$H$5:$H$1048576,'B. Despesa'!$I$5:$I$1048576,'01 Base Realizado'!K$5,'B. Despesa'!$K$5:$K$1048576,'01 Base Realizado'!$B81) -> 0 | L81: =SUMIFS('B. Despesa'!$H$5:$H$1048576,'B. Despesa'!$I$5:$I$1048576,'01 Base Realizado'!L$5,'B. Despesa'!$K$5:$K$1048576,'01 Base Realizado'!$B81) -> 0 | M81: =SUMIFS('B. Despesa'!$H$5:$H$1048576,'B. Despesa'!$I$5:$I$1048576,'01 Base Realizado'!M$5,'B. Despesa'!$K$5:$K$1048576,'01 Base Realizado'!$B81) -> 0 | N81: =SUMIFS('B. Despesa'!$H$5:$H$1048576,'B. Despesa'!$I$5:$I$1048576,'01 Base Realizado'!N$5,'B. Despesa'!$K$5:$K$1048576,'01 Base Realizado'!$B81) -> 0 | O81: =SUMIFS('B. Despesa'!$H$5:$H$1048576,'B. Despesa'!$I$5:$I$1048576,'01 Base Realizado'!O$5,'B. Despesa'!$K$5:$K$1048576,'01 Base Realizado'!$B81) -> 0 | P81: =SUMIFS('B. Despesa'!$H$5:$H$1048576,'B. Despesa'!$I$5:$I$1048576,'01 Base Realizado'!P$5,'B. Despesa'!$K$5:$K$1048576,'01 Base Realizado'!$B81) -> 0 | Q81: =SUMIFS('B. Despesa'!$H$5:$H$1048576,'B. Despesa'!$I$5:$I$1048576,'01 Base Realizado'!Q$5,'B. Despesa'!$K$5:$K$1048576,'01 Base Realizado'!$B81) -> 0 | R81: =SUMIFS('B. Despesa'!$H$5:$H$1048576,'B. Despesa'!$I$5:$I$1048576,'01 Base Realizado'!R$5,'B. Despesa'!$K$5:$K$1048576,'01 Base Realizado'!$B81) -> 0 | T81: -300000 | V81: =-T81/T11 -> 0.010937591
B82: Assessoria Nutricional | C82: 5.4.1.03.00003 | D82: =SUMIFS('B. Despesa'!$H:$H,'B. Despesa'!$I:$I,'01 Base Realizado'!D$5,'B. Despesa'!$K:$K,'01 Base Realizado'!$B82) -> -995 | E82: =-D82/D$38 -> 0.0047122191 | F82: =SUMIFS('B. Despesa'!$H$5:$H$1048576,'B. Despesa'!$I$5:$I$1048576,'01 Base Realizado'!F$5,'B. Despesa'!$K$5:$K$1048576,'01 Base Realizado'!$B82) -> -995 | G82: =-F82/F$38 -> 0.0038363051 | H82: =SUMIFS('B. Despesa'!$H$5:$H$1048576,'B. Despesa'!$I$5:$I$1048576,'01 Base Realizado'!H$5,'B. Despesa'!$K$5:$K$1048576,'01 Base Realizado'!$B82) -> -995 | I82: =-H82/H$38 -> 0.0024913523 | J82: =SUMIFS('B. Despesa'!$H$5:$H$1048576,'B. Despesa'!$I$5:$I$1048576,'01 Base Realizado'!J$5,'B. Despesa'!$K$5:$K$1048576,'01 Base Realizado'!$B82) -> 0 | K82: =SUMIFS('B. Despesa'!$H$5:$H$1048576,'B. Despesa'!$I$5:$I$1048576,'01 Base Realizado'!K$5,'B. Despesa'!$K$5:$K$1048576,'01 Base Realizado'!$B82) -> 0 | L82: =SUMIFS('B. Despesa'!$H$5:$H$1048576,'B. Despesa'!$I$5:$I$1048576,'01 Base Realizado'!L$5,'B. Despesa'!$K$5:$K$1048576,'01 Base Realizado'!$B82) -> 0 | M82: =SUMIFS('B. Despesa'!$H$5:$H$1048576,'B. Despesa'!$I$5:$I$1048576,'01 Base Realizado'!M$5,'B. Despesa'!$K$5:$K$1048576,'01 Base Realizado'!$B82) -> 0 | N82: =SUMIFS('B. Despesa'!$H$5:$H$1048576,'B. Despesa'!$I$5:$I$1048576,'01 Base Realizado'!N$5,'B. Despesa'!$K$5:$K$1048576,'01 Base Realizado'!$B82) -> 0 | O82: =SUMIFS('B. Despesa'!$H$5:$H$1048576,'B. Despesa'!$I$5:$I$1048576,'01 Base Realizado'!O$5,'B. Despesa'!$K$5:$K$1048576,'01 Base Realizado'!$B82) -> 0 | P82: =SUMIFS('B. Despesa'!$H$5:$H$1048576,'B. Despesa'!$I$5:$I$1048576,'01 Base Realizado'!P$5,'B. Despesa'!$K$5:$K$1048576,'01 Base Realizado'!$B82) -> 0 | Q82: =SUMIFS('B. Despesa'!$H$5:$H$1048576,'B. Despesa'!$I$5:$I$1048576,'01 Base Realizado'!Q$5,'B. Despesa'!$K$5:$K$1048576,'01 Base Realizado'!$B82) -> 0 | R82: =SUMIFS('B. Despesa'!$H$5:$H$1048576,'B. Despesa'!$I$5:$I$1048576,'01 Base Realizado'!R$5,'B. Despesa'!$K$5:$K$1048576,'01 Base Realizado'!$B82) -> 0 | T82: -4150 | V82: 0.0024
B83: Despesas com Segurança | C83: 5.4.1.03.00016 | D83: =SUMIFS('B. Despesa'!$H:$H,'B. Despesa'!$I:$I,'01 Base Realizado'!D$5,'B. Despesa'!$K:$K,'01 Base Realizado'!$B83) -> -6900 | E83: =-D83/D$38 -> 0.0326777 | F83: =SUMIFS('B. Despesa'!$H$5:$H$1048576,'B. Despesa'!$I$5:$I$1048576,'01 Base Realizado'!F$5,'B. Despesa'!$K$5:$K$1048576,'01 Base Realizado'!$B83) -> -7400 | G83: =-F83/F$38 -> 0.028531314 | H83: =SUMIFS('B. Despesa'!$H$5:$H$1048576,'B. Despesa'!$I$5:$I$1048576,'01 Base Realizado'!H$5,'B. Despesa'!$K$5:$K$1048576,'01 Base Realizado'!$B83) -> -8600 | I83: =-H83/H$38 -> 0.021533296 | J83: =SUMIFS('B. Despesa'!$H$5:$H$1048576,'B. Despesa'!$I$5:$I$1048576,'01 Base Realizado'!J$5,'B. Despesa'!$K$5:$K$1048576,'01 Base Realizado'!$B83) -> 0 | K83: =SUMIFS('B. Despesa'!$H$5:$H$1048576,'B. Despesa'!$I$5:$I$1048576,'01 Base Realizado'!K$5,'B. Despesa'!$K$5:$K$1048576,'01 Base Realizado'!$B83) -> 0 | L83: =SUMIFS('B. Despesa'!$H$5:$H$1048576,'B. Despesa'!$I$5:$I$1048576,'01 Base Realizado'!L$5,'B. Despesa'!$K$5:$K$1048576,'01 Base Realizado'!$B83) -> 0 | M83: =SUMIFS('B. Despesa'!$H$5:$H$1048576,'B. Despesa'!$I$5:$I$1048576,'01 Base Realizado'!M$5,'B. Despesa'!$K$5:$K$1048576,'01 Base Realizado'!$B83) -> 0 | N83: =SUMIFS('B. Despesa'!$H$5:$H$1048576,'B. Despesa'!$I$5:$I$1048576,'01 Base Realizado'!N$5,'B. Despesa'!$K$5:$K$1048576,'01 Base Realizado'!$B83) -> 0 | O83: =SUMIFS('B. Despesa'!$H$5:$H$1048576,'B. Despesa'!$I$5:$I$1048576,'01 Base Realizado'!O$5,'B. Despesa'!$K$5:$K$1048576,'01 Base Realizado'!$B83) -> 0 | P83: =SUMIFS('B. Despesa'!$H$5:$H$1048576,'B. Despesa'!$I$5:$I$1048576,'01 Base Realizado'!P$5,'B. Despesa'!$K$5:$K$1048576,'01 Base Realizado'!$B83) -> 0 | Q83: =SUMIFS('B. Despesa'!$H$5:$H$1048576,'B. Despesa'!$I$5:$I$1048576,'01 Base Realizado'!Q$5,'B. Despesa'!$K$5:$K$1048576,'01 Base Realizado'!$B83) -> 0 | R83: =SUMIFS('B. Despesa'!$H$5:$H$1048576,'B. Despesa'!$I$5:$I$1048576,'01 Base Realizado'!R$5,'B. Despesa'!$K$5:$K$1048576,'01 Base Realizado'!$B83) -> 0 | T83: -356000 | V83: =-T83/T11 -> 0.012979274
B84: Material de Embalagens | C84: 5.4.1.03.00019 | D84: =SUMIFS('B. Despesa'!$H:$H,'B. Despesa'!$I:$I,'01 Base Realizado'!D$5,'B. Despesa'!$K:$K,'01 Base Realizado'!$B84) -> -1784.88 | E84: =-D84/D$38 -> 0.0084530107 | F84: =SUMIFS('B. Despesa'!$H$5:$H$1048576,'B. Despesa'!$I$5:$I$1048576,'01 Base Realizado'!F$5,'B. Despesa'!$K$5:$K$1048576,'01 Base Realizado'!$B84) -> -278.61 | G84: =-F84/F$38 -> 0.001074204 | H84: =SUMIFS('B. Despesa'!$H$5:$H$1048576,'B. Despesa'!$I$5:$I$1048576,'01 Base Realizado'!H$5,'B. Despesa'!$K$5:$K$1048576,'01 Base Realizado'!$B84) -> -2085.56 | I84: =-H84/H$38 -> 0.0052219745 | J84: =SUMIFS('B. Despesa'!$H$5:$H$1048576,'B. Despesa'!$I$5:$I$1048576,'01 Base Realizado'!J$5,'B. Despesa'!$K$5:$K$1048576,'01 Base Realizado'!$B84) -> 0 | K84: =SUMIFS('B. Despesa'!$H$5:$H$1048576,'B. Despesa'!$I$5:$I$1048576,'01 Base Realizado'!K$5,'B. Despesa'!$K$5:$K$1048576,'01 Base Realizado'!$B84) -> 0 | L84: =SUMIFS('B. Despesa'!$H$5:$H$1048576,'B. Despesa'!$I$5:$I$1048576,'01 Base Realizado'!L$5,'B. Despesa'!$K$5:$K$1048576,'01 Base Realizado'!$B84) -> 0 | M84: =SUMIFS('B. Despesa'!$H$5:$H$1048576,'B. Despesa'!$I$5:$I$1048576,'01 Base Realizado'!M$5,'B. Despesa'!$K$5:$K$1048576,'01 Base Realizado'!$B84) -> 0 | N84: =SUMIFS('B. Despesa'!$H$5:$H$1048576,'B. Despesa'!$I$5:$I$1048576,'01 Base Realizado'!N$5,'B. Despesa'!$K$5:$K$1048576,'01 Base Realizado'!$B84) -> 0 | O84: =SUMIFS('B. Despesa'!$H$5:$H$1048576,'B. Despesa'!$I$5:$I$1048576,'01 Base Realizado'!O$5,'B. Despesa'!$K$5:$K$1048576,'01 Base Realizado'!$B84) -> 0 | P84: =SUMIFS('B. Despesa'!$H$5:$H$1048576,'B. Despesa'!$I$5:$I$1048576,'01 Base Realizado'!P$5,'B. Despesa'!$K$5:$K$1048576,'01 Base Realizado'!$B84) -> 0 | Q84: =SUMIFS('B. Despesa'!$H$5:$H$1048576,'B. Despesa'!$I$5:$I$1048576,'01 Base Realizado'!Q$5,'B. Despesa'!$K$5:$K$1048576,'01 Base Realizado'!$B84) -> 0 | R84: =SUMIFS('B. Despesa'!$H$5:$H$1048576,'B. Despesa'!$I$5:$I$1048576,'01 Base Realizado'!R$5,'B. Despesa'!$K$5:$K$1048576,'01 Base Realizado'!$B84) -> 0 | T84: -25330.075 | V84: 0.001
B85: Lavanderia | C85: 5.4.1.03.00022 | D85: =SUMIFS('B. Despesa'!$H:$H,'B. Despesa'!$I:$I,'01 Base Realizado'!D$5,'B. Despesa'!$K:$K,'01 Base Realizado'!$B85) -> -1529 | E85: =-D85/D$38 -> 0.0072411889 | F85: =SUMIFS('B. Despesa'!$H$5:$H$1048576,'B. Despesa'!$I$5:$I$1048576,'01 Base Realizado'!F$5,'B. Despesa'!$K$5:$K$1048576,'01 Base Realizado'!$B85) -> -1375.17 | G85: =-F85/F$38 -> 0.005302082 | H85: =SUMIFS('B. Despesa'!$H$5:$H$1048576,'B. Despesa'!$I$5:$I$1048576,'01 Base Realizado'!H$5,'B. Despesa'!$K$5:$K$1048576,'01 Base Realizado'!$B85) -> -1976.6 | I85: =-H85/H$38 -> 0.0049491526 | J85: =SUMIFS('B. Despesa'!$H$5:$H$1048576,'B. Despesa'!$I$5:$I$1048576,'01 Base Realizado'!J$5,'B. Despesa'!$K$5:$K$1048576,'01 Base Realizado'!$B85) -> 0 | K85: =SUMIFS('B. Despesa'!$H$5:$H$1048576,'B. Despesa'!$I$5:$I$1048576,'01 Base Realizado'!K$5,'B. Despesa'!$K$5:$K$1048576,'01 Base Realizado'!$B85) -> 0 | L85: =SUMIFS('B. Despesa'!$H$5:$H$1048576,'B. Despesa'!$I$5:$I$1048576,'01 Base Realizado'!L$5,'B. Despesa'!$K$5:$K$1048576,'01 Base Realizado'!$B85) -> 0 | M85: =SUMIFS('B. Despesa'!$H$5:$H$1048576,'B. Despesa'!$I$5:$I$1048576,'01 Base Realizado'!M$5,'B. Despesa'!$K$5:$K$1048576,'01 Base Realizado'!$B85) -> 0 | N85: =SUMIFS('B. Despesa'!$H$5:$H$1048576,'B. Despesa'!$I$5:$I$1048576,'01 Base Realizado'!N$5,'B. Despesa'!$K$5:$K$1048576,'01 Base Realizado'!$B85) -> 0 | O85: =SUMIFS('B. Despesa'!$H$5:$H$1048576,'B. Despesa'!$I$5:$I$1048576,'01 Base Realizado'!O$5,'B. Despesa'!$K$5:$K$1048576,'01 Base Realizado'!$B85) -> 0 | P85: =SUMIFS('B. Despesa'!$H$5:$H$1048576,'B. Despesa'!$I$5:$I$1048576,'01 Base Realizado'!P$5,'B. Despesa'!$K$5:$K$1048576,'01 Base Realizado'!$B85) -> 0 | Q85: =SUMIFS('B. Despesa'!$H$5:$H$1048576,'B. Despesa'!$I$5:$I$1048576,'01 Base Realizado'!Q$5,'B. Despesa'!$K$5:$K$1048576,'01 Base Realizado'!$B85) -> 0 | R85: =SUMIFS('B. Despesa'!$H$5:$H$1048576,'B. Despesa'!$I$5:$I$1048576,'01 Base Realizado'!R$5,'B. Despesa'!$K$5:$K$1048576,'01 Base Realizado'!$B85) -> 0 | T85: -27600 | V85: 0.001
B86: Material Limpeza | C86: 5.4.1.03.00026 | D86: =SUMIFS('B. Despesa'!$H:$H,'B. Despesa'!$I:$I,'01 Base Realizado'!D$5,'B. Despesa'!$K:$K,'01 Base Realizado'!$B86) -> -604.86 | E86: =-D86/D$38 -> 0.0028645556 | F86: =SUMIFS('B. Despesa'!$H$5:$H$1048576,'B. Despesa'!$I$5:$I$1048576,'01 Base Realizado'!F$5,'B. Despesa'!$K$5:$K$1048576,'01 Base Realizado'!$B86) -> -738.55 | G86: =-F86/F$38 -> 0.0028475408 | H86: =SUMIFS('B. Despesa'!$H$5:$H$1048576,'B. Despesa'!$I$5:$I$1048576,'01 Base Realizado'!H$5,'B. Despesa'!$K$5:$K$1048576,'01 Base Realizado'!$B86) -> -1758 | I86: =-H86/H$38 -> 0.0044018063 | J86: =SUMIFS('B. Despesa'!$H$5:$H$1048576,'B. Despesa'!$I$5:$I$1048576,'01 Base Realizado'!J$5,'B. Despesa'!$K$5:$K$1048576,'01 Base Realizado'!$B86) -> 0 | K86: =SUMIFS('B. Despesa'!$H$5:$H$1048576,'B. Despesa'!$I$5:$I$1048576,'01 Base Realizado'!K$5,'B. Despesa'!$K$5:$K$1048576,'01 Base Realizado'!$B86) -> 0 | L86: =SUMIFS('B. Despesa'!$H$5:$H$1048576,'B. Despesa'!$I$5:$I$1048576,'01 Base Realizado'!L$5,'B. Despesa'!$K$5:$K$1048576,'01 Base Realizado'!$B86) -> 0 | M86: =SUMIFS('B. Despesa'!$H$5:$H$1048576,'B. Despesa'!$I$5:$I$1048576,'01 Base Realizado'!M$5,'B. Despesa'!$K$5:$K$1048576,'01 Base Realizado'!$B86) -> 0 | N86: =SUMIFS('B. Despesa'!$H$5:$H$1048576,'B. Despesa'!$I$5:$I$1048576,'01 Base Realizado'!N$5,'B. Despesa'!$K$5:$K$1048576,'01 Base Realizado'!$B86) -> 0 | O86: =SUMIFS('B. Despesa'!$H$5:$H$1048576,'B. Despesa'!$I$5:$I$1048576,'01 Base Realizado'!O$5,'B. Despesa'!$K$5:$K$1048576,'01 Base Realizado'!$B86) -> 0 | P86: =SUMIFS('B. Despesa'!$H$5:$H$1048576,'B. Despesa'!$I$5:$I$1048576,'01 Base Realizado'!P$5,'B. Despesa'!$K$5:$K$1048576,'01 Base Realizado'!$B86) -> 0 | Q86: =SUMIFS('B. Despesa'!$H$5:$H$1048576,'B. Despesa'!$I$5:$I$1048576,'01 Base Realizado'!Q$5,'B. Despesa'!$K$5:$K$1048576,'01 Base Realizado'!$B86) -> 0 | R86: =SUMIFS('B. Despesa'!$H$5:$H$1048576,'B. Despesa'!$I$5:$I$1048576,'01 Base Realizado'!R$5,'B. Despesa'!$K$5:$K$1048576,'01 Base Realizado'!$B86) -> 0 | T86: -60792.181 | V86: 0.0024
B87: Material de Higiene/ Descartaveis | D87: =SUMIFS('B. Despesa'!$H:$H,'B. Despesa'!$I:$I,'01 Base Realizado'!D$5,'B. Despesa'!$K:$K,'01 Base Realizado'!$B87) -> -1920.93 | E87: =-D87/D$38 -> 0.0090973297 | F87: =SUMIFS('B. Despesa'!$H$5:$H$1048576,'B. Despesa'!$I$5:$I$1048576,'01 Base Realizado'!F$5,'B. Despesa'!$K$5:$K$1048576,'01 Base Realizado'!$B87) -> -2079.81 | G87: =-F87/F$38 -> 0.00801888 | H87: =SUMIFS('B. Despesa'!$H$5:$H$1048576,'B. Despesa'!$I$5:$I$1048576,'01 Base Realizado'!H$5,'B. Despesa'!$K$5:$K$1048576,'01 Base Realizado'!$B87) -> -6158.1 | I87: =-H87/H$38 -> 0.015419092 | Y87: Foi efetuado uma compra significativa de material de higiene no mês de Mar/2026
B88: Hostess | D88: =SUMIFS('B. Despesa'!$H:$H,'B. Despesa'!$I:$I,'01 Base Realizado'!D$5,'B. Despesa'!$K:$K,'01 Base Realizado'!$B88) -> -600 | E88: =-D88/D$38 -> 0.0028415392 | F88: =SUMIFS('B. Despesa'!$H$5:$H$1048576,'B. Despesa'!$I$5:$I$1048576,'01 Base Realizado'!F$5,'B. Despesa'!$K$5:$K$1048576,'01 Base Realizado'!$B88) -> -2740 | G88: =-F88/F$38 -> 0.010564297 | H88: =SUMIFS('B. Despesa'!$H$5:$H$1048576,'B. Despesa'!$I$5:$I$1048576,'01 Base Realizado'!H$5,'B. Despesa'!$K$5:$K$1048576,'01 Base Realizado'!$B88) -> -3080 | I88: =-H88/H$38 -> 0.0077119246 | J88: =SUMIFS('B. Despesa'!$H$5:$H$1048576,'B. Despesa'!$I$5:$I$1048576,'01 Base Realizado'!J$5,'B. Despesa'!$K$5:$K$1048576,'01 Base Realizado'!$B88) -> 0 | K88: =SUMIFS('B. Despesa'!$H$5:$H$1048576,'B. Despesa'!$I$5:$I$1048576,'01 Base Realizado'!K$5,'B. Despesa'!$K$5:$K$1048576,'01 Base Realizado'!$B88) -> 0 | L88: =SUMIFS('B. Despesa'!$H$5:$H$1048576,'B. Despesa'!$I$5:$I$1048576,'01 Base Realizado'!L$5,'B. Despesa'!$K$5:$K$1048576,'01 Base Realizado'!$B88) -> 0 | M88: =SUMIFS('B. Despesa'!$H$5:$H$1048576,'B. Despesa'!$I$5:$I$1048576,'01 Base Realizado'!M$5,'B. Despesa'!$K$5:$K$1048576,'01 Base Realizado'!$B88) -> 0 | N88: =SUMIFS('B. Despesa'!$H$5:$H$1048576,'B. Despesa'!$I$5:$I$1048576,'01 Base Realizado'!N$5,'B. Despesa'!$K$5:$K$1048576,'01 Base Realizado'!$B88) -> 0 | O88: =SUMIFS('B. Despesa'!$H$5:$H$1048576,'B. Despesa'!$I$5:$I$1048576,'01 Base Realizado'!O$5,'B. Despesa'!$K$5:$K$1048576,'01 Base Realizado'!$B88) -> 0 | P88: =SUMIFS('B. Despesa'!$H$5:$H$1048576,'B. Despesa'!$I$5:$I$1048576,'01 Base Realizado'!P$5,'B. Despesa'!$K$5:$K$1048576,'01 Base Realizado'!$B88) -> 0 | Q88: =SUMIFS('B. Despesa'!$H$5:$H$1048576,'B. Despesa'!$I$5:$I$1048576,'01 Base Realizado'!Q$5,'B. Despesa'!$K$5:$K$1048576,'01 Base Realizado'!$B88) -> 0 | R88: =SUMIFS('B. Despesa'!$H$5:$H$1048576,'B. Despesa'!$I$5:$I$1048576,'01 Base Realizado'!R$5,'B. Despesa'!$K$5:$K$1048576,'01 Base Realizado'!$B88) -> 0
B89: Limpeza e Conservação | D89: =SUMIFS('B. Despesa'!$H:$H,'B. Despesa'!$I:$I,'01 Base Realizado'!D$5,'B. Despesa'!$K:$K,'01 Base Realizado'!$B89) -> 0 | E89: =-D89/D$38 -> 0 | F89: =SUMIFS('B. Despesa'!$H$5:$H$1048576,'B. Despesa'!$I$5:$I$1048576,'01 Base Realizado'!F$5,'B. Despesa'!$K$5:$K$1048576,'01 Base Realizado'!$B89) -> 0 | G89: =-F89/F$38 -> 0 | I89: =-H89/H$38 -> 0
B90: Sistema e Software OP | D90: =SUMIFS('B. Despesa'!$H:$H,'B. Despesa'!$I:$I,'01 Base Realizado'!D$5,'B. Despesa'!$K:$K,'01 Base Realizado'!$B90) -> -2860.5 | E90: =-D90/D$38 -> 0.013547038 | F90: =SUMIFS('B. Despesa'!$H$5:$H$1048576,'B. Despesa'!$I$5:$I$1048576,'01 Base Realizado'!F$5,'B. Despesa'!$K$5:$K$1048576,'01 Base Realizado'!$B90) -> -2772.5 | G90: =-F90/F$38 -> 0.010689604 | H90: =SUMIFS('B. Despesa'!$H$5:$H$1048576,'B. Despesa'!$I$5:$I$1048576,'01 Base Realizado'!H$5,'B. Despesa'!$K$5:$K$1048576,'01 Base Realizado'!$B90) -> -2772.5 | I90: =-H90/H$38 -> 0.006941984
B91: Consultoria OP | D91: =SUMIFS('B. Despesa'!$H:$H,'B. Despesa'!$I:$I,'01 Base Realizado'!D$5,'B. Despesa'!$K:$K,'01 Base Realizado'!$B91) -> 0 | E91: =-D91/D$38 -> 0 | F91: =SUMIFS('B. Despesa'!$H$5:$H$1048576,'B. Despesa'!$I$5:$I$1048576,'01 Base Realizado'!F$5,'B. Despesa'!$K$5:$K$1048576,'01 Base Realizado'!$B91) -> 0 | G91: =-F91/F$38 -> 0 | I91: =-H91/H$38 -> 0
B92: Ações (Eventos com Funcionários) | D92: =SUMIFS('B. Despesa'!$H:$H,'B. Despesa'!$I:$I,'01 Base Realizado'!D$5,'B. Despesa'!$K:$K,'01 Base Realizado'!$B92) -> 0 | E92: =-D92/D$38 -> 0 | F92: =SUMIFS('B. Despesa'!$H$5:$H$1048576,'B. Despesa'!$I$5:$I$1048576,'01 Base Realizado'!F$5,'B. Despesa'!$K$5:$K$1048576,'01 Base Realizado'!$B92) -> 0 | G92: =-F92/F$38 -> 0 | H92: =SUMIFS('B. Despesa'!$H$5:$H$1048576,'B. Despesa'!$I$5:$I$1048576,'01 Base Realizado'!H$5,'B. Despesa'!$K$5:$K$1048576,'01 Base Realizado'!$B92) -> 0 | I92: =-H92/H$38 -> 0 | J92: =SUMIFS('B. Despesa'!$H$5:$H$1048576,'B. Despesa'!$I$5:$I$1048576,'01 Base Realizado'!J$5,'B. Despesa'!$K$5:$K$1048576,'01 Base Realizado'!$B92) -> 0 | K92: =SUMIFS('B. Despesa'!$H$5:$H$1048576,'B. Despesa'!$I$5:$I$1048576,'01 Base Realizado'!K$5,'B. Despesa'!$K$5:$K$1048576,'01 Base Realizado'!$B92) -> 0 | L92: =SUMIFS('B. Despesa'!$H$5:$H$1048576,'B. Despesa'!$I$5:$I$1048576,'01 Base Realizado'!L$5,'B. Despesa'!$K$5:$K$1048576,'01 Base Realizado'!$B92) -> 0 | M92: =SUMIFS('B. Despesa'!$H$5:$H$1048576,'B. Despesa'!$I$5:$I$1048576,'01 Base Realizado'!M$5,'B. Despesa'!$K$5:$K$1048576,'01 Base Realizado'!$B92) -> 0 | N92: =SUMIFS('B. Despesa'!$H$5:$H$1048576,'B. Despesa'!$I$5:$I$1048576,'01 Base Realizado'!N$5,'B. Despesa'!$K$5:$K$1048576,'01 Base Realizado'!$B92) -> 0 | O92: =SUMIFS('B. Despesa'!$H$5:$H$1048576,'B. Despesa'!$I$5:$I$1048576,'01 Base Realizado'!O$5,'B. Despesa'!$K$5:$K$1048576,'01 Base Realizado'!$B92) -> 0 | P92: =SUMIFS('B. Despesa'!$H$5:$H$1048576,'B. Despesa'!$I$5:$I$1048576,'01 Base Realizado'!P$5,'B. Despesa'!$K$5:$K$1048576,'01 Base Realizado'!$B92) -> 0 | Q92: =SUMIFS('B. Despesa'!$H$5:$H$1048576,'B. Despesa'!$I$5:$I$1048576,'01 Base Realizado'!Q$5,'B. Despesa'!$K$5:$K$1048576,'01 Base Realizado'!$B92) -> 0 | R92: =SUMIFS('B. Despesa'!$H$5:$H$1048576,'B. Despesa'!$I$5:$I$1048576,'01 Base Realizado'!R$5,'B. Despesa'!$K$5:$K$1048576,'01 Base Realizado'!$B92) -> 0 | T92: -25330.075 | V92: 0.001
B93: Utensílios | C93: 5.4.1.03.00028 | D93: =SUMIFS('B. Despesa'!$H:$H,'B. Despesa'!$I:$I,'01 Base Realizado'!D$5,'B. Despesa'!$K:$K,'01 Base Realizado'!$B93) -> 0 | E93: =-D93/D$38 -> 0 | F93: =SUMIFS('B. Despesa'!$H$5:$H$1048576,'B. Despesa'!$I$5:$I$1048576,'01 Base Realizado'!F$5,'B. Despesa'!$K$5:$K$1048576,'01 Base Realizado'!$B93) -> -4042.26 | G93: =-F93/F$38 -> 0.015585269 | H93: =SUMIFS('B. Despesa'!$H$5:$H$1048576,'B. Despesa'!$I$5:$I$1048576,'01 Base Realizado'!H$5,'B. Despesa'!$K$5:$K$1048576,'01 Base Realizado'!$B93) -> -11050.63 | I93: =-H93/H$38 -> 0.027669359 | J93: =SUMIFS('B. Despesa'!$H$5:$H$1048576,'B. Despesa'!$I$5:$I$1048576,'01 Base Realizado'!J$5,'B. Despesa'!$K$5:$K$1048576,'01 Base Realizado'!$B93) -> 0 | K93: =SUMIFS('B. Despesa'!$H$5:$H$1048576,'B. Despesa'!$I$5:$I$1048576,'01 Base Realizado'!K$5,'B. Despesa'!$K$5:$K$1048576,'01 Base Realizado'!$B93) -> 0 | L93: =SUMIFS('B. Despesa'!$H$5:$H$1048576,'B. Despesa'!$I$5:$I$1048576,'01 Base Realizado'!L$5,'B. Despesa'!$K$5:$K$1048576,'01 Base Realizado'!$B93) -> 0 | M93: =SUMIFS('B. Despesa'!$H$5:$H$1048576,'B. Despesa'!$I$5:$I$1048576,'01 Base Realizado'!M$5,'B. Despesa'!$K$5:$K$1048576,'01 Base Realizado'!$B93) -> 0 | N93: =SUMIFS('B. Despesa'!$H$5:$H$1048576,'B. Despesa'!$I$5:$I$1048576,'01 Base Realizado'!N$5,'B. Despesa'!$K$5:$K$1048576,'01 Base Realizado'!$B93) -> 0 | O93: =SUMIFS('B. Despesa'!$H$5:$H$1048576,'B. Despesa'!$I$5:$I$1048576,'01 Base Realizado'!O$5,'B. Despesa'!$K$5:$K$1048576,'01 Base Realizado'!$B93) -> 0 | P93: =SUMIFS('B. Despesa'!$H$5:$H$1048576,'B. Despesa'!$I$5:$I$1048576,'01 Base Realizado'!P$5,'B. Despesa'!$K$5:$K$1048576,'01 Base Realizado'!$B93) -> 0 | Q93: =SUMIFS('B. Despesa'!$H$5:$H$1048576,'B. Despesa'!$I$5:$I$1048576,'01 Base Realizado'!Q$5,'B. Despesa'!$K$5:$K$1048576,'01 Base Realizado'!$B93) -> 0 | R93: =SUMIFS('B. Despesa'!$H$5:$H$1048576,'B. Despesa'!$I$5:$I$1048576,'01 Base Realizado'!R$5,'B. Despesa'!$K$5:$K$1048576,'01 Base Realizado'!$B93) -> 0 | T93: -75990.226 | V93: 0.003 | Y93: Impacto no mês março de 2026 ELLEGANZA 4.8k e Tramontina 5.5k
B94: Despesas de Seguros | C94: 5.4.1.03.00033 | D94: =SUMIFS('B. Despesa'!$H:$H,'B. Despesa'!$I:$I,'01 Base Realizado'!D$5,'B. Despesa'!$K:$K,'01 Base Realizado'!$B94) -> 0 | E94: =-D94/D$38 -> 0 | F94: =SUMIFS('B. Despesa'!$H$5:$H$1048576,'B. Despesa'!$I$5:$I$1048576,'01 Base Realizado'!F$5,'B. Despesa'!$K$5:$K$1048576,'01 Base Realizado'!$B94) -> 0 | G94: =-F94/F$38 -> 0 | H94: =SUMIFS('B. Despesa'!$H$5:$H$1048576,'B. Despesa'!$I$5:$I$1048576,'01 Base Realizado'!H$5,'B. Despesa'!$K$5:$K$1048576,'01 Base Realizado'!$B94) -> 0 | I94: =-H94/H$38 -> 0 | J94: =SUMIFS('B. Despesa'!$H$5:$H$1048576,'B. Despesa'!$I$5:$I$1048576,'01 Base Realizado'!J$5,'B. Despesa'!$K$5:$K$1048576,'01 Base Realizado'!$B94) -> 0 | K94: =SUMIFS('B. Despesa'!$H$5:$H$1048576,'B. Despesa'!$I$5:$I$1048576,'01 Base Realizado'!K$5,'B. Despesa'!$K$5:$K$1048576,'01 Base Realizado'!$B94) -> 0 | L94: =SUMIFS('B. Despesa'!$H$5:$H$1048576,'B. Despesa'!$I$5:$I$1048576,'01 Base Realizado'!L$5,'B. Despesa'!$K$5:$K$1048576,'01 Base Realizado'!$B94) -> 0 | M94: =SUMIFS('B. Despesa'!$H$5:$H$1048576,'B. Despesa'!$I$5:$I$1048576,'01 Base Realizado'!M$5,'B. Despesa'!$K$5:$K$1048576,'01 Base Realizado'!$B94) -> 0 | N94: =SUMIFS('B. Despesa'!$H$5:$H$1048576,'B. Despesa'!$I$5:$I$1048576,'01 Base Realizado'!N$5,'B. Despesa'!$K$5:$K$1048576,'01 Base Realizado'!$B94) -> 0 | O94: =SUMIFS('B. Despesa'!$H$5:$H$1048576,'B. Despesa'!$I$5:$I$1048576,'01 Base Realizado'!O$5,'B. Despesa'!$K$5:$K$1048576,'01 Base Realizado'!$B94) -> 0 | P94: =SUMIFS('B. Despesa'!$H$5:$H$1048576,'B. Despesa'!$I$5:$I$1048576,'01 Base Realizado'!P$5,'B. Despesa'!$K$5:$K$1048576,'01 Base Realizado'!$B94) -> 0 | Q94: =SUMIFS('B. Despesa'!$H$5:$H$1048576,'B. Despesa'!$I$5:$I$1048576,'01 Base Realizado'!Q$5,'B. Despesa'!$K$5:$K$1048576,'01 Base Realizado'!$B94) -> 0 | R94: =SUMIFS('B. Despesa'!$H$5:$H$1048576,'B. Despesa'!$I$5:$I$1048576,'01 Base Realizado'!R$5,'B. Despesa'!$K$5:$K$1048576,'01 Base Realizado'!$B94) -> 0 | T94: -33828 | V94: =-T94/T11 -> 0.0012333227 | Y94: Precisamos dos contratos de Seguro Predial, (Regilene)
B95: Prestação de Serviço Pessoa Jurídica OP | C95: 5.4.1.03.00037 | D95: =SUMIFS('B. Despesa'!$H:$H,'B. Despesa'!$I:$I,'01 Base Realizado'!D$5,'B. Despesa'!$K:$K,'01 Base Realizado'!$B95) -> -33637.46 | E95: =-D95/D$38 -> 0.1593036 | F95: =SUMIFS('B. Despesa'!$H$5:$H$1048576,'B. Despesa'!$I$5:$I$1048576,'01 Base Realizado'!F$5,'B. Despesa'!$K$5:$K$1048576,'01 Base Realizado'!$B95) -> -41772.04 | G95: =-F95/F$38 -> 0.16105557 | H95: =SUMIFS('B. Despesa'!$H$5:$H$1048576,'B. Despesa'!$I$5:$I$1048576,'01 Base Realizado'!H$5,'B. Despesa'!$K$5:$K$1048576,'01 Base Realizado'!$B95) -> -42729.32 | I95: =-H95/H$38 -> 0.10698873 | J95: =SUMIFS('B. Despesa'!$H$5:$H$1048576,'B. Despesa'!$I$5:$I$1048576,'01 Base Realizado'!J$5,'B. Despesa'!$K$5:$K$1048576,'01 Base Realizado'!$B95) -> 0 | K95: =SUMIFS('B. Despesa'!$H$5:$H$1048576,'B. Despesa'!$I$5:$I$1048576,'01 Base Realizado'!K$5,'B. Despesa'!$K$5:$K$1048576,'01 Base Realizado'!$B95) -> 0 | L95: =SUMIFS('B. Despesa'!$H$5:$H$1048576,'B. Despesa'!$I$5:$I$1048576,'01 Base Realizado'!L$5,'B. Despesa'!$K$5:$K$1048576,'01 Base Realizado'!$B95) -> 0 | M95: =SUMIFS('B. Despesa'!$H$5:$H$1048576,'B. Despesa'!$I$5:$I$1048576,'01 Base Realizado'!M$5,'B. Despesa'!$K$5:$K$1048576,'01 Base Realizado'!$B95) -> 0 | N95: =SUMIFS('B. Despesa'!$H$5:$H$1048576,'B. Despesa'!$I$5:$I$1048576,'01 Base Realizado'!N$5,'B. Despesa'!$K$5:$K$1048576,'01 Base Realizado'!$B95) -> 0 | O95: =SUMIFS('B. Despesa'!$H$5:$H$1048576,'B. Despesa'!$I$5:$I$1048576,'01 Base Realizado'!O$5,'B. Despesa'!$K$5:$K$1048576,'01 Base Realizado'!$B95) -> 0 | P95: =SUMIFS('B. Despesa'!$H$5:$H$1048576,'B. Despesa'!$I$5:$I$1048576,'01 Base Realizado'!P$5,'B. Despesa'!$K$5:$K$1048576,'01 Base Realizado'!$B95) -> 0 | Q95: =SUMIFS('B. Despesa'!$H$5:$H$1048576,'B. Despesa'!$I$5:$I$1048576,'01 Base Realizado'!Q$5,'B. Despesa'!$K$5:$K$1048576,'01 Base Realizado'!$B95) -> 0 | R95: =SUMIFS('B. Despesa'!$H$5:$H$1048576,'B. Despesa'!$I$5:$I$1048576,'01 Base Realizado'!R$5,'B. Despesa'!$K$5:$K$1048576,'01 Base Realizado'!$B95) -> 0 | T95: -1161000 | V95: =-T95/T11 -> 0.042328476 | Y95: Fev/26 tivemos entrada do Anderson que teve um recebimento de 5,2k proporcional ao mês e um aumento em Mar/2026 corespondete ao mês para 7,2 outro impacto, se deu por conta da variavel no valor de prestação de serviço do colaborador Amauri que recebe uma variação da Gorjeta do mês
B96: Monitoramento | D96: =SUMIFS('B. Despesa'!$H:$H,'B. Despesa'!$I:$I,'01 Base Realizado'!D$5,'B. Despesa'!$K:$K,'01 Base Realizado'!$B96) -> -229.6 | E96: =-D96/D$38 -> 0.0010873623 | F96: =SUMIFS('B. Despesa'!$H$5:$H$1048576,'B. Despesa'!$I$5:$I$1048576,'01 Base Realizado'!F$5,'B. Despesa'!$K$5:$K$1048576,'01 Base Realizado'!$B96) -> -229.6 | G96: =-F96/F$38 -> 0.00088524185 | H96: =SUMIFS('B. Despesa'!$H$5:$H$1048576,'B. Despesa'!$I$5:$I$1048576,'01 Base Realizado'!H$5,'B. Despesa'!$K$5:$K$1048576,'01 Base Realizado'!$B96) -> -229.6 | I96: =-H96/H$38 -> 0.00057488892
B97: ADMINISTRATIVA | D97: =SUM(D98:D111) -> -15510.2 | E97: =-D97/D$38 -> 0.073454734 | F97: =SUM(F98:F111) -> -15131.34 | G97: =-F97/F$38 -> 0.058340137 | H97: =SUM(H98:H111) -> -15093.36 | I97: =-H97/H$38 -> 0.037791836 | T97: -1831971.4 | V97: %
B98: Prestação de Serviço Pessoa Jurídica ADM | C98: 4.1.1.03.00009 | D98: =SUMIFS('B. Despesa'!$H:$H,'B. Despesa'!$I:$I,'01 Base Realizado'!D$5,'B. Despesa'!$K:$K,'01 Base Realizado'!$B98) -> 0 | E98: =-D98/D$38 -> 0 | F98: =SUMIFS('B. Despesa'!$H$5:$H$1048576,'B. Despesa'!$I$5:$I$1048576,'01 Base Realizado'!F$5,'B. Despesa'!$K$5:$K$1048576,'01 Base Realizado'!$B98) -> 0 | G98: =-F98/F$38 -> 0 | H98: =SUMIFS('B. Despesa'!$H$5:$H$1048576,'B. Despesa'!$I$5:$I$1048576,'01 Base Realizado'!H$5,'B. Despesa'!$K$5:$K$1048576,'01 Base Realizado'!$B98) -> 0 | I98: =-H98/H$38 -> 0 | J98: =SUMIFS('B. Despesa'!$H$5:$H$1048576,'B. Despesa'!$I$5:$I$1048576,'01 Base Realizado'!J$5,'B. Despesa'!$K$5:$K$1048576,'01 Base Realizado'!$B98) -> 0 | K98: =SUMIFS('B. Despesa'!$H$5:$H$1048576,'B. Despesa'!$I$5:$I$1048576,'01 Base Realizado'!K$5,'B. Despesa'!$K$5:$K$1048576,'01 Base Realizado'!$B98) -> 0 | L98: =SUMIFS('B. Despesa'!$H$5:$H$1048576,'B. Despesa'!$I$5:$I$1048576,'01 Base Realizado'!L$5,'B. Despesa'!$K$5:$K$1048576,'01 Base Realizado'!$B98) -> 0 | M98: =SUMIFS('B. Despesa'!$H$5:$H$1048576,'B. Despesa'!$I$5:$I$1048576,'01 Base Realizado'!M$5,'B. Despesa'!$K$5:$K$1048576,'01 Base Realizado'!$B98) -> 0 | N98: =SUMIFS('B. Despesa'!$H$5:$H$1048576,'B. Despesa'!$I$5:$I$1048576,'01 Base Realizado'!N$5,'B. Despesa'!$K$5:$K$1048576,'01 Base Realizado'!$B98) -> 0 | O98: =SUMIFS('B. Despesa'!$H$5:$H$1048576,'B. Despesa'!$I$5:$I$1048576,'01 Base Realizado'!O$5,'B. Despesa'!$K$5:$K$1048576,'01 Base Realizado'!$B98) -> 0 | P98: =SUMIFS('B. Despesa'!$H$5:$H$1048576,'B. Despesa'!$I$5:$I$1048576,'01 Base Realizado'!P$5,'B. Despesa'!$K$5:$K$1048576,'01 Base Realizado'!$B98) -> 0 | Q98: =SUMIFS('B. Despesa'!$H$5:$H$1048576,'B. Despesa'!$I$5:$I$1048576,'01 Base Realizado'!Q$5,'B. Despesa'!$K$5:$K$1048576,'01 Base Realizado'!$B98) -> 0 | R98: =SUMIFS('B. Despesa'!$H$5:$H$1048576,'B. Despesa'!$I$5:$I$1048576,'01 Base Realizado'!R$5,'B. Despesa'!$K$5:$K$1048576,'01 Base Realizado'!$B98) -> 0 | T98: -792000 | V98: =-T98/$T$11 -> 0.02887524
B99: Transporte/Fretes | C99: 5.4.1.03.00022 | D99: =SUMIFS('B. Despesa'!$H:$H,'B. Despesa'!$I:$I,'01 Base Realizado'!D$5,'B. Despesa'!$K:$K,'01 Base Realizado'!$B99) -> 0 | E99: =-D99/D$38 -> 0 | F99: =SUMIFS('B. Despesa'!$H$5:$H$1048576,'B. Despesa'!$I$5:$I$1048576,'01 Base Realizado'!F$5,'B. Despesa'!$K$5:$K$1048576,'01 Base Realizado'!$B99) -> 0 | G99: =-F99/F$38 -> 0 | H99: =SUMIFS('B. Despesa'!$H$5:$H$1048576,'B. Despesa'!$I$5:$I$1048576,'01 Base Realizado'!H$5,'B. Despesa'!$K$5:$K$1048576,'01 Base Realizado'!$B99) -> 0 | I99: =-H99/H$38 -> 0 | J99: =SUMIFS('B. Despesa'!$H$5:$H$1048576,'B. Despesa'!$I$5:$I$1048576,'01 Base Realizado'!J$5,'B. Despesa'!$K$5:$K$1048576,'01 Base Realizado'!$B99) -> 0 | K99: =SUMIFS('B. Despesa'!$H$5:$H$1048576,'B. Despesa'!$I$5:$I$1048576,'01 Base Realizado'!K$5,'B. Despesa'!$K$5:$K$1048576,'01 Base Realizado'!$B99) -> 0 | L99: =SUMIFS('B. Despesa'!$H$5:$H$1048576,'B. Despesa'!$I$5:$I$1048576,'01 Base Realizado'!L$5,'B. Despesa'!$K$5:$K$1048576,'01 Base Realizado'!$B99) -> 0 | M99: =SUMIFS('B. Despesa'!$H$5:$H$1048576,'B. Despesa'!$I$5:$I$1048576,'01 Base Realizado'!M$5,'B. Despesa'!$K$5:$K$1048576,'01 Base Realizado'!$B99) -> 0 | N99: =SUMIFS('B. Despesa'!$H$5:$H$1048576,'B. Despesa'!$I$5:$I$1048576,'01 Base Realizado'!N$5,'B. Despesa'!$K$5:$K$1048576,'01 Base Realizado'!$B99) -> 0 | O99: =SUMIFS('B. Despesa'!$H$5:$H$1048576,'B. Despesa'!$I$5:$I$1048576,'01 Base Realizado'!O$5,'B. Despesa'!$K$5:$K$1048576,'01 Base Realizado'!$B99) -> 0 | P99: =SUMIFS('B. Despesa'!$H$5:$H$1048576,'B. Despesa'!$I$5:$I$1048576,'01 Base Realizado'!P$5,'B. Despesa'!$K$5:$K$1048576,'01 Base Realizado'!$B99) -> 0 | Q99: =SUMIFS('B. Despesa'!$H$5:$H$1048576,'B. Despesa'!$I$5:$I$1048576,'01 Base Realizado'!Q$5,'B. Despesa'!$K$5:$K$1048576,'01 Base Realizado'!$B99) -> 0 | R99: =SUMIFS('B. Despesa'!$H$5:$H$1048576,'B. Despesa'!$I$5:$I$1048576,'01 Base Realizado'!R$5,'B. Despesa'!$K$5:$K$1048576,'01 Base Realizado'!$B99) -> 0 | T99: -12000 | V99: =-T99/$T$11 -> 0.00043750363
B100: Telefone e Internet | C100: 4.1.1.03.00018 | D100: =SUMIFS('B. Despesa'!$H:$H,'B. Despesa'!$I:$I,'01 Base Realizado'!D$5,'B. Despesa'!$K:$K,'01 Base Realizado'!$B100) -> -99 | E100: =-D100/D$38 -> 0.00046885396 | F100: =SUMIFS('B. Despesa'!$H$5:$H$1048576,'B. Despesa'!$I$5:$I$1048576,'01 Base Realizado'!F$5,'B. Despesa'!$K$5:$K$1048576,'01 Base Realizado'!$B100) -> -195.34 | G100: =-F100/F$38 -> 0.00075314958 | H100: =SUMIFS('B. Despesa'!$H$5:$H$1048576,'B. Despesa'!$I$5:$I$1048576,'01 Base Realizado'!H$5,'B. Despesa'!$K$5:$K$1048576,'01 Base Realizado'!$B100) -> -195.34 | I100: =-H100/H$38 -> 0.00048910628 | J100: =SUMIFS('B. Despesa'!$H$5:$H$1048576,'B. Despesa'!$I$5:$I$1048576,'01 Base Realizado'!J$5,'B. Despesa'!$K$5:$K$1048576,'01 Base Realizado'!$B100) -> 0 | K100: =SUMIFS('B. Despesa'!$H$5:$H$1048576,'B. Despesa'!$I$5:$I$1048576,'01 Base Realizado'!K$5,'B. Despesa'!$K$5:$K$1048576,'01 Base Realizado'!$B100) -> 0 | L100: =SUMIFS('B. Despesa'!$H$5:$H$1048576,'B. Despesa'!$I$5:$I$1048576,'01 Base Realizado'!L$5,'B. Despesa'!$K$5:$K$1048576,'01 Base Realizado'!$B100) -> 0 | M100: =SUMIFS('B. Despesa'!$H$5:$H$1048576,'B. Despesa'!$I$5:$I$1048576,'01 Base Realizado'!M$5,'B. Despesa'!$K$5:$K$1048576,'01 Base Realizado'!$B100) -> 0 | N100: =SUMIFS('B. Despesa'!$H$5:$H$1048576,'B. Despesa'!$I$5:$I$1048576,'01 Base Realizado'!N$5,'B. Despesa'!$K$5:$K$1048576,'01 Base Realizado'!$B100) -> 0 | O100: =SUMIFS('B. Despesa'!$H$5:$H$1048576,'B. Despesa'!$I$5:$I$1048576,'01 Base Realizado'!O$5,'B. Despesa'!$K$5:$K$1048576,'01 Base Realizado'!$B100) -> 0 | P100: =SUMIFS('B. Despesa'!$H$5:$H$1048576,'B. Despesa'!$I$5:$I$1048576,'01 Base Realizado'!P$5,'B. Despesa'!$K$5:$K$1048576,'01 Base Realizado'!$B100) -> 0 | Q100: =SUMIFS('B. Despesa'!$H$5:$H$1048576,'B. Despesa'!$I$5:$I$1048576,'01 Base Realizado'!Q$5,'B. Despesa'!$K$5:$K$1048576,'01 Base Realizado'!$B100) -> 0 | R100: =SUMIFS('B. Despesa'!$H$5:$H$1048576,'B. Despesa'!$I$5:$I$1048576,'01 Base Realizado'!R$5,'B. Despesa'!$K$5:$K$1048576,'01 Base Realizado'!$B100) -> 0 | T100: -18600 | V100: =-T100/$T$11 -> 0.00067813063
B101: Serviços TI | D101: =SUMIFS('B. Despesa'!$H:$H,'B. Despesa'!$I:$I,'01 Base Realizado'!D$5,'B. Despesa'!$K:$K,'01 Base Realizado'!$B101) -> -480 | E101: =-D101/D$38 -> 0.0022732313 | F101: =SUMIFS('B. Despesa'!$H$5:$H$1048576,'B. Despesa'!$I$5:$I$1048576,'01 Base Realizado'!F$5,'B. Despesa'!$K$5:$K$1048576,'01 Base Realizado'!$B101) -> 0 | G101: =-F101/F$38 -> 0 | I101: =-H101/H$38 -> 0
B102: Material de Escritório | C102: 4.1.1.03.00024 | D102: =SUMIFS('B. Despesa'!$H:$H,'B. Despesa'!$I:$I,'01 Base Realizado'!D$5,'B. Despesa'!$K:$K,'01 Base Realizado'!$B102) -> 0 | E102: =-D102/D$38 -> 0 | F102: =SUMIFS('B. Despesa'!$H$5:$H$1048576,'B. Despesa'!$I$5:$I$1048576,'01 Base Realizado'!F$5,'B. Despesa'!$K$5:$K$1048576,'01 Base Realizado'!$B102) -> -490 | G102: =-F102/F$38 -> 0.0018892357 | H102: =SUMIFS('B. Despesa'!$H$5:$H$1048576,'B. Despesa'!$I$5:$I$1048576,'01 Base Realizado'!H$5,'B. Despesa'!$K$5:$K$1048576,'01 Base Realizado'!$B102) -> -452.02 | I102: =-H102/H$38 -> 0.0011318 | J102: =SUMIFS('B. Despesa'!$H$5:$H$1048576,'B. Despesa'!$I$5:$I$1048576,'01 Base Realizado'!J$5,'B. Despesa'!$K$5:$K$1048576,'01 Base Realizado'!$B102) -> 0 | K102: =SUMIFS('B. Despesa'!$H$5:$H$1048576,'B. Despesa'!$I$5:$I$1048576,'01 Base Realizado'!K$5,'B. Despesa'!$K$5:$K$1048576,'01 Base Realizado'!$B102) -> 0 | L102: =SUMIFS('B. Despesa'!$H$5:$H$1048576,'B. Despesa'!$I$5:$I$1048576,'01 Base Realizado'!L$5,'B. Despesa'!$K$5:$K$1048576,'01 Base Realizado'!$B102) -> 0 | M102: =SUMIFS('B. Despesa'!$H$5:$H$1048576,'B. Despesa'!$I$5:$I$1048576,'01 Base Realizado'!M$5,'B. Despesa'!$K$5:$K$1048576,'01 Base Realizado'!$B102) -> 0 | N102: =SUMIFS('B. Despesa'!$H$5:$H$1048576,'B. Despesa'!$I$5:$I$1048576,'01 Base Realizado'!N$5,'B. Despesa'!$K$5:$K$1048576,'01 Base Realizado'!$B102) -> 0 | O102: =SUMIFS('B. Despesa'!$H$5:$H$1048576,'B. Despesa'!$I$5:$I$1048576,'01 Base Realizado'!O$5,'B. Despesa'!$K$5:$K$1048576,'01 Base Realizado'!$B102) -> 0 | P102: =SUMIFS('B. Despesa'!$H$5:$H$1048576,'B. Despesa'!$I$5:$I$1048576,'01 Base Realizado'!P$5,'B. Despesa'!$K$5:$K$1048576,'01 Base Realizado'!$B102) -> 0 | Q102: =SUMIFS('B. Despesa'!$H$5:$H$1048576,'B. Despesa'!$I$5:$I$1048576,'01 Base Realizado'!Q$5,'B. Despesa'!$K$5:$K$1048576,'01 Base Realizado'!$B102) -> 0 | R102: =SUMIFS('B. Despesa'!$H$5:$H$1048576,'B. Despesa'!$I$5:$I$1048576,'01 Base Realizado'!R$5,'B. Despesa'!$K$5:$K$1048576,'01 Base Realizado'!$B102) -> 0 | T102: -25330.075 | V102: 0.001 | Y102: Compra de bobinas no mês de Fev/2026;
B103: Material de Copa e Limpeza | C103: 4.1.1.03.00025 | D103: =SUMIFS('B. Despesa'!$H:$H,'B. Despesa'!$I:$I,'01 Base Realizado'!D$5,'B. Despesa'!$K:$K,'01 Base Realizado'!$B103) -> 0 | E103: =-D103/D$38 -> 0 | F103: =SUMIFS('B. Despesa'!$H$5:$H$1048576,'B. Despesa'!$I$5:$I$1048576,'01 Base Realizado'!F$5,'B. Despesa'!$K$5:$K$1048576,'01 Base Realizado'!$B103) -> 0 | G103: =-F103/F$38 -> 0 | H103: =SUMIFS('B. Despesa'!$H$5:$H$1048576,'B. Despesa'!$I$5:$I$1048576,'01 Base Realizado'!H$5,'B. Despesa'!$K$5:$K$1048576,'01 Base Realizado'!$B103) -> 0 | I103: =-H103/H$38 -> 0 | J103: =SUMIFS('B. Despesa'!$H$5:$H$1048576,'B. Despesa'!$I$5:$I$1048576,'01 Base Realizado'!J$5,'B. Despesa'!$K$5:$K$1048576,'01 Base Realizado'!$B103) -> 0 | K103: =SUMIFS('B. Despesa'!$H$5:$H$1048576,'B. Despesa'!$I$5:$I$1048576,'01 Base Realizado'!K$5,'B. Despesa'!$K$5:$K$1048576,'01 Base Realizado'!$B103) -> 0 | L103: =SUMIFS('B. Despesa'!$H$5:$H$1048576,'B. Despesa'!$I$5:$I$1048576,'01 Base Realizado'!L$5,'B. Despesa'!$K$5:$K$1048576,'01 Base Realizado'!$B103) -> 0 | M103: =SUMIFS('B. Despesa'!$H$5:$H$1048576,'B. Despesa'!$I$5:$I$1048576,'01 Base Realizado'!M$5,'B. Despesa'!$K$5:$K$1048576,'01 Base Realizado'!$B103) -> 0 | N103: =SUMIFS('B. Despesa'!$H$5:$H$1048576,'B. Despesa'!$I$5:$I$1048576,'01 Base Realizado'!N$5,'B. Despesa'!$K$5:$K$1048576,'01 Base Realizado'!$B103) -> 0 | O103: =SUMIFS('B. Despesa'!$H$5:$H$1048576,'B. Despesa'!$I$5:$I$1048576,'01 Base Realizado'!O$5,'B. Despesa'!$K$5:$K$1048576,'01 Base Realizado'!$B103) -> 0 | P103: =SUMIFS('B. Despesa'!$H$5:$H$1048576,'B. Despesa'!$I$5:$I$1048576,'01 Base Realizado'!P$5,'B. Despesa'!$K$5:$K$1048576,'01 Base Realizado'!$B103) -> 0 | Q103: =SUMIFS('B. Despesa'!$H$5:$H$1048576,'B. Despesa'!$I$5:$I$1048576,'01 Base Realizado'!Q$5,'B. Despesa'!$K$5:$K$1048576,'01 Base Realizado'!$B103) -> 0 | R103: =SUMIFS('B. Despesa'!$H$5:$H$1048576,'B. Despesa'!$I$5:$I$1048576,'01 Base Realizado'!R$5,'B. Despesa'!$K$5:$K$1048576,'01 Base Realizado'!$B103) -> 0 | T103: -278630.83 | V103: 0.011
B104: Sistema e Software ADM | C104: 4.1.1.03.00030 | D104: =SUMIFS('B. Despesa'!$H:$H,'B. Despesa'!$I:$I,'01 Base Realizado'!D$5,'B. Despesa'!$K:$K,'01 Base Realizado'!$B104) -> 0 | E104: =-D104/D$38 -> 0 | F104: =SUMIFS('B. Despesa'!$H$5:$H$1048576,'B. Despesa'!$I$5:$I$1048576,'01 Base Realizado'!F$5,'B. Despesa'!$K$5:$K$1048576,'01 Base Realizado'!$B104) -> 0 | G104: =-F104/F$38 -> 0 | H104: =SUMIFS('B. Despesa'!$H$5:$H$1048576,'B. Despesa'!$I$5:$I$1048576,'01 Base Realizado'!H$5,'B. Despesa'!$K$5:$K$1048576,'01 Base Realizado'!$B104) -> 0 | I104: =-H104/H$38 -> 0 | J104: =SUMIFS('B. Despesa'!$H$5:$H$1048576,'B. Despesa'!$I$5:$I$1048576,'01 Base Realizado'!J$5,'B. Despesa'!$K$5:$K$1048576,'01 Base Realizado'!$B104) -> 0 | K104: =SUMIFS('B. Despesa'!$H$5:$H$1048576,'B. Despesa'!$I$5:$I$1048576,'01 Base Realizado'!K$5,'B. Despesa'!$K$5:$K$1048576,'01 Base Realizado'!$B104) -> 0 | L104: =SUMIFS('B. Despesa'!$H$5:$H$1048576,'B. Despesa'!$I$5:$I$1048576,'01 Base Realizado'!L$5,'B. Despesa'!$K$5:$K$1048576,'01 Base Realizado'!$B104) -> 0 | M104: =SUMIFS('B. Despesa'!$H$5:$H$1048576,'B. Despesa'!$I$5:$I$1048576,'01 Base Realizado'!M$5,'B. Despesa'!$K$5:$K$1048576,'01 Base Realizado'!$B104) -> 0 | N104: =SUMIFS('B. Despesa'!$H$5:$H$1048576,'B. Despesa'!$I$5:$I$1048576,'01 Base Realizado'!N$5,'B. Despesa'!$K$5:$K$1048576,'01 Base Realizado'!$B104) -> 0 | O104: =SUMIFS('B. Despesa'!$H$5:$H$1048576,'B. Despesa'!$I$5:$I$1048576,'01 Base Realizado'!O$5,'B. Despesa'!$K$5:$K$1048576,'01 Base Realizado'!$B104) -> 0 | P104: =SUMIFS('B. Despesa'!$H$5:$H$1048576,'B. Despesa'!$I$5:$I$1048576,'01 Base Realizado'!P$5,'B. Despesa'!$K$5:$K$1048576,'01 Base Realizado'!$B104) -> 0 | Q104: =SUMIFS('B. Despesa'!$H$5:$H$1048576,'B. Despesa'!$I$5:$I$1048576,'01 Base Realizado'!Q$5,'B. Despesa'!$K$5:$K$1048576,'01 Base Realizado'!$B104) -> 0 | R104: =SUMIFS('B. Despesa'!$H$5:$H$1048576,'B. Despesa'!$I$5:$I$1048576,'01 Base Realizado'!R$5,'B. Despesa'!$K$5:$K$1048576,'01 Base Realizado'!$B104) -> 0 | T104: -28344.52 | V104: =-T104/$T$11 -> 0.0010334025
B105: Contabilidade | C105: 4.1.1.03.00031 | D105: =SUMIFS('B. Despesa'!$H:$H,'B. Despesa'!$I:$I,'01 Base Realizado'!D$5,'B. Despesa'!$K:$K,'01 Base Realizado'!$B105) -> -1410 | E105: =-D105/D$38 -> 0.006677617 | F105: =SUMIFS('B. Despesa'!$H$5:$H$1048576,'B. Despesa'!$I$5:$I$1048576,'01 Base Realizado'!F$5,'B. Despesa'!$K$5:$K$1048576,'01 Base Realizado'!$B105) -> -1410 | G105: =-F105/F$38 -> 0.005436372 | H105: =SUMIFS('B. Despesa'!$H$5:$H$1048576,'B. Despesa'!$I$5:$I$1048576,'01 Base Realizado'!H$5,'B. Despesa'!$K$5:$K$1048576,'01 Base Realizado'!$B105) -> -1410 | I105: =-H105/H$38 -> 0.003530459 | J105: =SUMIFS('B. Despesa'!$H$5:$H$1048576,'B. Despesa'!$I$5:$I$1048576,'01 Base Realizado'!J$5,'B. Despesa'!$K$5:$K$1048576,'01 Base Realizado'!$B105) -> 0 | K105: =SUMIFS('B. Despesa'!$H$5:$H$1048576,'B. Despesa'!$I$5:$I$1048576,'01 Base Realizado'!K$5,'B. Despesa'!$K$5:$K$1048576,'01 Base Realizado'!$B105) -> 0 | L105: =SUMIFS('B. Despesa'!$H$5:$H$1048576,'B. Despesa'!$I$5:$I$1048576,'01 Base Realizado'!L$5,'B. Despesa'!$K$5:$K$1048576,'01 Base Realizado'!$B105) -> 0 | M105: =SUMIFS('B. Despesa'!$H$5:$H$1048576,'B. Despesa'!$I$5:$I$1048576,'01 Base Realizado'!M$5,'B. Despesa'!$K$5:$K$1048576,'01 Base Realizado'!$B105) -> 0 | N105: =SUMIFS('B. Despesa'!$H$5:$H$1048576,'B. Despesa'!$I$5:$I$1048576,'01 Base Realizado'!N$5,'B. Despesa'!$K$5:$K$1048576,'01 Base Realizado'!$B105) -> 0 | O105: =SUMIFS('B. Despesa'!$H$5:$H$1048576,'B. Despesa'!$I$5:$I$1048576,'01 Base Realizado'!O$5,'B. Despesa'!$K$5:$K$1048576,'01 Base Realizado'!$B105) -> 0 | P105: =SUMIFS('B. Despesa'!$H$5:$H$1048576,'B. Despesa'!$I$5:$I$1048576,'01 Base Realizado'!P$5,'B. Despesa'!$K$5:$K$1048576,'01 Base Realizado'!$B105) -> 0 | Q105: =SUMIFS('B. Despesa'!$H$5:$H$1048576,'B. Despesa'!$I$5:$I$1048576,'01 Base Realizado'!Q$5,'B. Despesa'!$K$5:$K$1048576,'01 Base Realizado'!$B105) -> 0 | R105: =SUMIFS('B. Despesa'!$H$5:$H$1048576,'B. Despesa'!$I$5:$I$1048576,'01 Base Realizado'!R$5,'B. Despesa'!$K$5:$K$1048576,'01 Base Realizado'!$B105) -> 0 | T105: -120000 | V105: =-T105/$T$11 -> 0.0043750363
B106: Consultoria ADM | C106: 4.1.1.03.00033 | D106: =SUMIFS('B. Despesa'!$H:$H,'B. Despesa'!$I:$I,'01 Base Realizado'!D$5,'B. Despesa'!$K:$K,'01 Base Realizado'!$B106) -> 0 | E106: =-D106/D$38 -> 0 | F106: =SUMIFS('B. Despesa'!$H$5:$H$1048576,'B. Despesa'!$I$5:$I$1048576,'01 Base Realizado'!F$5,'B. Despesa'!$K$5:$K$1048576,'01 Base Realizado'!$B106) -> 0 | G106: =-F106/F$38 -> 0 | H106: =SUMIFS('B. Despesa'!$H$5:$H$1048576,'B. Despesa'!$I$5:$I$1048576,'01 Base Realizado'!H$5,'B. Despesa'!$K$5:$K$1048576,'01 Base Realizado'!$B106) -> 0 | I106: =-H106/H$38 -> 0 | J106: =SUMIFS('B. Despesa'!$H$5:$H$1048576,'B. Despesa'!$I$5:$I$1048576,'01 Base Realizado'!J$5,'B. Despesa'!$K$5:$K$1048576,'01 Base Realizado'!$B106) -> 0 | K106: =SUMIFS('B. Despesa'!$H$5:$H$1048576,'B. Despesa'!$I$5:$I$1048576,'01 Base Realizado'!K$5,'B. Despesa'!$K$5:$K$1048576,'01 Base Realizado'!$B106) -> 0 | L106: =SUMIFS('B. Despesa'!$H$5:$H$1048576,'B. Despesa'!$I$5:$I$1048576,'01 Base Realizado'!L$5,'B. Despesa'!$K$5:$K$1048576,'01 Base Realizado'!$B106) -> 0 | M106: =SUMIFS('B. Despesa'!$H$5:$H$1048576,'B. Despesa'!$I$5:$I$1048576,'01 Base Realizado'!M$5,'B. Despesa'!$K$5:$K$1048576,'01 Base Realizado'!$B106) -> 0 | N106: =SUMIFS('B. Despesa'!$H$5:$H$1048576,'B. Despesa'!$I$5:$I$1048576,'01 Base Realizado'!N$5,'B. Despesa'!$K$5:$K$1048576,'01 Base Realizado'!$B106) -> 0 | O106: =SUMIFS('B. Despesa'!$H$5:$H$1048576,'B. Despesa'!$I$5:$I$1048576,'01 Base Realizado'!O$5,'B. Despesa'!$K$5:$K$1048576,'01 Base Realizado'!$B106) -> 0 | P106: =SUMIFS('B. Despesa'!$H$5:$H$1048576,'B. Despesa'!$I$5:$I$1048576,'01 Base Realizado'!P$5,'B. Despesa'!$K$5:$K$1048576,'01 Base Realizado'!$B106) -> 0 | Q106: =SUMIFS('B. Despesa'!$H$5:$H$1048576,'B. Despesa'!$I$5:$I$1048576,'01 Base Realizado'!Q$5,'B. Despesa'!$K$5:$K$1048576,'01 Base Realizado'!$B106) -> 0 | R106: =SUMIFS('B. Despesa'!$H$5:$H$1048576,'B. Despesa'!$I$5:$I$1048576,'01 Base Realizado'!R$5,'B. Despesa'!$K$5:$K$1048576,'01 Base Realizado'!$B106) -> 0 | T106: -492000 | V106: =-T106/$T$11 -> 0.017937649
B107: Honorarios Advocaticios | C107: 4.1.1.03.00034 | D107: =SUMIFS('B. Despesa'!$H:$H,'B. Despesa'!$I:$I,'01 Base Realizado'!D$5,'B. Despesa'!$K:$K,'01 Base Realizado'!$B107) -> -3036 | E107: =-D107/D$38 -> 0.014378188 | F107: =SUMIFS('B. Despesa'!$H$5:$H$1048576,'B. Despesa'!$I$5:$I$1048576,'01 Base Realizado'!F$5,'B. Despesa'!$K$5:$K$1048576,'01 Base Realizado'!$B107) -> -3036 | G107: =-F107/F$38 -> 0.01170555 | H107: =SUMIFS('B. Despesa'!$H$5:$H$1048576,'B. Despesa'!$I$5:$I$1048576,'01 Base Realizado'!H$5,'B. Despesa'!$K$5:$K$1048576,'01 Base Realizado'!$B107) -> -3036 | I107: =-H107/H$38 -> 0.0076017542 | J107: =SUMIFS('B. Despesa'!$H$5:$H$1048576,'B. Despesa'!$I$5:$I$1048576,'01 Base Realizado'!J$5,'B. Despesa'!$K$5:$K$1048576,'01 Base Realizado'!$B107) -> 0 | K107: =SUMIFS('B. Despesa'!$H$5:$H$1048576,'B. Despesa'!$I$5:$I$1048576,'01 Base Realizado'!K$5,'B. Despesa'!$K$5:$K$1048576,'01 Base Realizado'!$B107) -> 0 | L107: =SUMIFS('B. Despesa'!$H$5:$H$1048576,'B. Despesa'!$I$5:$I$1048576,'01 Base Realizado'!L$5,'B. Despesa'!$K$5:$K$1048576,'01 Base Realizado'!$B107) -> 0 | M107: =SUMIFS('B. Despesa'!$H$5:$H$1048576,'B. Despesa'!$I$5:$I$1048576,'01 Base Realizado'!M$5,'B. Despesa'!$K$5:$K$1048576,'01 Base Realizado'!$B107) -> 0 | N107: =SUMIFS('B. Despesa'!$H$5:$H$1048576,'B. Despesa'!$I$5:$I$1048576,'01 Base Realizado'!N$5,'B. Despesa'!$K$5:$K$1048576,'01 Base Realizado'!$B107) -> 0 | O107: =SUMIFS('B. Despesa'!$H$5:$H$1048576,'B. Despesa'!$I$5:$I$1048576,'01 Base Realizado'!O$5,'B. Despesa'!$K$5:$K$1048576,'01 Base Realizado'!$B107) -> 0 | P107: =SUMIFS('B. Despesa'!$H$5:$H$1048576,'B. Despesa'!$I$5:$I$1048576,'01 Base Realizado'!P$5,'B. Despesa'!$K$5:$K$1048576,'01 Base Realizado'!$B107) -> 0 | Q107: =SUMIFS('B. Despesa'!$H$5:$H$1048576,'B. Despesa'!$I$5:$I$1048576,'01 Base Realizado'!Q$5,'B. Despesa'!$K$5:$K$1048576,'01 Base Realizado'!$B107) -> 0 | R107: =SUMIFS('B. Despesa'!$H$5:$H$1048576,'B. Despesa'!$I$5:$I$1048576,'01 Base Realizado'!R$5,'B. Despesa'!$K$5:$K$1048576,'01 Base Realizado'!$B107) -> 0 | T107: -60000 | V107: 0.002
B108: Cartório/Protestos | C108: 4.1.1.03.00041 | D108: =SUMIFS('B. Despesa'!$H:$H,'B. Despesa'!$I:$I,'01 Base Realizado'!D$5,'B. Despesa'!$K:$K,'01 Base Realizado'!$B108) -> -109.96 | E108: =-D108/D$38 -> 0.00052075941 | F108: =SUMIFS('B. Despesa'!$H$5:$H$1048576,'B. Despesa'!$I$5:$I$1048576,'01 Base Realizado'!F$5,'B. Despesa'!$K$5:$K$1048576,'01 Base Realizado'!$B108) -> 0 | G108: =-F108/F$38 -> 0 | H108: =SUMIFS('B. Despesa'!$H$5:$H$1048576,'B. Despesa'!$I$5:$I$1048576,'01 Base Realizado'!H$5,'B. Despesa'!$K$5:$K$1048576,'01 Base Realizado'!$B108) -> 0 | I108: =-H108/H$38 -> 0 | J108: =SUMIFS('B. Despesa'!$H$5:$H$1048576,'B. Despesa'!$I$5:$I$1048576,'01 Base Realizado'!J$5,'B. Despesa'!$K$5:$K$1048576,'01 Base Realizado'!$B108) -> 0 | K108: =SUMIFS('B. Despesa'!$H$5:$H$1048576,'B. Despesa'!$I$5:$I$1048576,'01 Base Realizado'!K$5,'B. Despesa'!$K$5:$K$1048576,'01 Base Realizado'!$B108) -> 0 | L108: =SUMIFS('B. Despesa'!$H$5:$H$1048576,'B. Despesa'!$I$5:$I$1048576,'01 Base Realizado'!L$5,'B. Despesa'!$K$5:$K$1048576,'01 Base Realizado'!$B108) -> 0 | M108: =SUMIFS('B. Despesa'!$H$5:$H$1048576,'B. Despesa'!$I$5:$I$1048576,'01 Base Realizado'!M$5,'B. Despesa'!$K$5:$K$1048576,'01 Base Realizado'!$B108) -> 0 | N108: =SUMIFS('B. Despesa'!$H$5:$H$1048576,'B. Despesa'!$I$5:$I$1048576,'01 Base Realizado'!N$5,'B. Despesa'!$K$5:$K$1048576,'01 Base Realizado'!$B108) -> 0 | O108: =SUMIFS('B. Despesa'!$H$5:$H$1048576,'B. Despesa'!$I$5:$I$1048576,'01 Base Realizado'!O$5,'B. Despesa'!$K$5:$K$1048576,'01 Base Realizado'!$B108) -> 0 | P108: =SUMIFS('B. Despesa'!$H$5:$H$1048576,'B. Despesa'!$I$5:$I$1048576,'01 Base Realizado'!P$5,'B. Despesa'!$K$5:$K$1048576,'01 Base Realizado'!$B108) -> 0 | Q108: =SUMIFS('B. Despesa'!$H$5:$H$1048576,'B. Despesa'!$I$5:$I$1048576,'01 Base Realizado'!Q$5,'B. Despesa'!$K$5:$K$1048576,'01 Base Realizado'!$B108) -> 0 | R108: =SUMIFS('B. Despesa'!$H$5:$H$1048576,'B. Despesa'!$I$5:$I$1048576,'01 Base Realizado'!R$5,'B. Despesa'!$K$5:$K$1048576,'01 Base Realizado'!$B108) -> 0 | T108: -5066.0151 | V108: 0.0002
...

Sheet 02 Budget x Real %
B4: INDICADORES DE PERFORMANCE
D7: BD | E7: REAL | J7: BD | K7: REAL | M7: BD | N7: REAL | P7: MEDIA BD | Q7: MEDIA REAL | T7: 2026 X META | X7: GAP 1°TRI | Y7: 1° Trimestre
B8: INDICADORES | D8: BD JAN.26 | E8: REAL JAN.26 | F8: JAN/FEV | J8: BD FEV.26 | K8: REAL FEV.26 | M8: BD MAR.26 | N8: REAL MAR.26 | P8: JAN-MAR | Q8: JAN-MAR | T8: RL x BD_Jan'26 | U8: RL x BD_Fev'26 | V8: RL x BD_Mar'26 | X8: JAN-MAR | Y8: Comentários
B9: CMV | D9: =-'03- BD x RE 2026'!BH27 -> 0.32211038 | E9: =-'03- BD x RE 2026'!BI27 -> 0.20728177 | F9: =E9 -> 0.20728177 | J9: =-'03- BD x RE 2026'!BK27 -> 0.32 | K9: =-'03- BD x RE 2026'!BL27 -> 0.30320637 | M9: =-'03- BD x RE 2026'!BN27 -> 0.32153809 | N9: =-'03- BD x RE 2026'!BO27 -> 0.21433756 | P9: =AVERAGE(D9,J9,M9) -> 0.32121616 | Q9: =AVERAGE(E9,K9,N9) -> 0.24160856 | T9: =E9-D9 -> -0.11482861 | U9: =K9-J9 -> -0.016793632 | V9: =N9-M9 -> -0.10720053 | X9: =Q9-P9 -> -0.079607592 | Y9: Utilizamos as planilhas de excel para efetuar os lançamento no sistema, em Abril será 100% plan Everest
B10: PESSOAL | D10: =-'03- BD x RE 2026'!BH36 -> 0.23731058 | E10: =-'03- BD x RE 2026'!BI36 -> 0.23718877 | F10: =E10 -> 0.23718877 | J10: =-'03- BD x RE 2026'!BK36 -> 0.16373678 | K10: =-'03- BD x RE 2026'!BL36 -> 0.1711698 | M10: =-'03- BD x RE 2026'!BN36 -> 0.15358703 | N10: =-'03- BD x RE 2026'!BO36 -> 0.15419608 | P10: =AVERAGE(D10,J10,M10) -> 0.18487813 | Q10: =AVERAGE(E10,K10,N10) -> 0.18751821 | T10: =E10-D10 -> -0.00012180991 | U10: =K10-J10 -> 0.007433025 | V10: =N10-M10 -> 0.000609049 | X10: =Q10-P10 -> 0.002640088
B11: OCUPAÇÃO | D11: =-'03- BD x RE 2026'!BH41 -> 0.06525512 | E11: =-'03- BD x RE 2026'!BI41 -> 0.11271439 | F11: =E11 -> 0.11271439 | J11: =-'03- BD x RE 2026'!BK41 -> 0.054007469 | K11: =-'03- BD x RE 2026'!BL41 -> 0.091762875 | M11: =-'03- BD x RE 2026'!BN41 -> 0.045181447 | N11: =-'03- BD x RE 2026'!BO41 -> 0.059592144 | P11: =AVERAGE(D11,J11,M11) -> 0.054814679 | Q11: =AVERAGE(E11,K11,N11) -> 0.088023135 | T11: =E11-D11 -> 0.047459267 | U11: =K11-J11 -> 0.037755406 | V11: =N11-M11 -> 0.014410698 | X11: =Q11-P11 -> 0.033208457
B12: UTILIDADES/ CONSUMO | D12: =-'03- BD x RE 2026'!BH42 -> 0.013801076 | E12: =-'03- BD x RE 2026'!BI42 -> 0.016614574 | F12: =E12 -> 0.016614574 | J12: =-'03- BD x RE 2026'!BK42 -> 0.0078454467 | K12: =-'03- BD x RE 2026'!BL42 -> 0.0065966711 | M12: =-'03- BD x RE 2026'!BN42 -> 0.0067959865 | N12: =-'03- BD x RE 2026'!BO42 -> 0.045069689 | P12: =AVERAGE(D12,J12,M12) -> 0.0094808364 | Q12: =AVERAGE(E12,K12,N12) -> 0.022760311 | T12: =E12-D12 -> 0.0028134981 | U12: =K12-J12 -> -0.0012487756 | V12: =N12-M12 -> 0.038273702 | X12: =Q12-P12 -> 0.013279475
B13: OPERAÇÃO | D13: =-'03- BD x RE 2026'!BH43 -> 0.17735999 | E13: =-'03- BD x RE 2026'!BI43 -> 0.25035016 | F13: =E13 -> 0.25035016 | J13: =-'03- BD x RE 2026'!BK43 -> 0.18578319 | K13: =-'03- BD x RE 2026'!BL43 -> 0.25533035 | M13: =-'03- BD x RE 2026'!BN43 -> 0.15883713 | N13: =-'03- BD x RE 2026'!BO43 -> 0.20841053 | P13: =AVERAGE(D13,J13,M13) -> 0.17399344 | Q13: =AVERAGE(E13,K13,N13) -> 0.23803035 | T13: =E13-D13 -> 0.072990174 | U13: =K13-J13 -> 0.069547162 | V13: =N13-M13 -> 0.049573402 | X13: =Q13-P13 -> 0.064036913
B14: MANUTENÇÃO E CONSERVAS | D14: =-'03- BD x RE 2026'!BH44 -> 0.016603129 | E14: =-'03- BD x RE 2026'!BI44 -> 0.0044256972 | F14: =E14 -> 0.0044256972 | J14: =-'03- BD x RE 2026'!BK44 -> 0.013741343 | K14: =-'03- BD x RE 2026'!BL44 -> 0.017350123 | M14: =-'03- BD x RE 2026'!BN44 -> 0.011495701 | N14: =-'03- BD x RE 2026'!BO44 -> 0.0024037167 | P14: =AVERAGE(D14,J14,M14) -> 0.013946724 | Q14: =AVERAGE(E14,K14,N14) -> 0.0080598458 | T14: =E14-D14 -> -0.012177432 | U14: =K14-J14 -> 0.0036087807 | V14: =N14-M14 -> -0.0090919847 | X14: =Q14-P14 -> -0.0058868785
B15: ADMINISTRATIVA | D15: =-'03- BD x RE 2026'!BH49 -> 0.062842986 | E15: =-'03- BD x RE 2026'!BI49 -> 0.073454734 | F15: =E15 -> 0.073454734 | J15: =-'03- BD x RE 2026'!BK49 -> 0.04911807 | K15: =-'03- BD x RE 2026'!BL49 -> 0.058340137 | M15: =-'03- BD x RE 2026'!BN49 -> 0.042302331 | N15: =-'03- BD x RE 2026'!BO49 -> 0.037791836 | P15: =AVERAGE(D15,J15,M15) -> 0.051421129 | Q15: =AVERAGE(E15,K15,N15) -> 0.056528902 | T15: =E15-D15 -> 0.010611748 | U15: =K15-J15 -> 0.0092220673 | V15: =N15-M15 -> -0.0045104955 | X15: =Q15-P15 -> 0.0051077732
B16: MARKETING | D16: =-'03- BD x RE 2026'!BH50 -> 0.046393338 | E16: =-'03- BD x RE 2026'!BI50 -> 0.040255138 | F16: =E16 -> 0.040255138 | J16: =-'03- BD x RE 2026'!BK50 -> 0.030163746 | K16: =-'03- BD x RE 2026'!BL50 -> 0.0057833745 | M16: =-'03- BD x RE 2026'!BN50 -> 0.030281182 | N16: =-'03- BD x RE 2026'!BO50 -> 0.04777387 | P16: =AVERAGE(D16,J16,M16) -> 0.035612755 | Q16: =AVERAGE(E16,K16,N16) -> 0.031270794 | T16: =E16-D16 -> -0.0061381998 | U16: =K16-J16 -> -0.024380372 | V16: =N16-M16 -> 0.017492688 | X16: =Q16-P16 -> -0.0043419611
B17: TX CARTÕES | D17: =-'03- BD x RE 2026'!BH51 -> 0.026379729 | E17: =-'03- BD x RE 2026'!BI51 -> 0.030902449 | F17: =E17 -> 0.030902449 | J17: =-'03- BD x RE 2026'!BK51 -> 0.015710284 | K17: =-'03- BD x RE 2026'!BL51 -> 0.027070703 | M17: =-'03- BD x RE 2026'!BN51 -> 0.015771449 | N17: =-'03- BD x RE 2026'!BO51 -> 0.025284496 | P17: =AVERAGE(D17,J17,M17) -> 0.019287154 | Q17: =AVERAGE(E17,K17,N17) -> 0.027752549 | T17: =E17-D17 -> 0.0045227194 | U17: =K17-J17 -> 0.011360419 | V17: =N17-M17 -> 0.009513047 | X17: =Q17-P17 -> 0.0084653952
B19: EBITDA | D19: ='02-Res M'!D30 -> 0.03194368 | E19: ='02-Res M'!F30 -> 0.026812326 | F19: =E19 -> 0.026812326 | J19: ='02-Res M'!H30 -> 0.15989367 | K19: ='02-Res M'!J30 -> 0.063389594 | M19: ='02-Res M'!L30 -> 0.21420966 | N19: ='02-Res M'!N30 -> 0.20514008 | P19: =AVERAGE(D19,J19,M19) -> 0.135349 | Q19: =AVERAGE(E19,K19,N19) -> 0.098447335 | T19: =E19-D19 -> -0.0051313537 | U19: =K19-J19 -> -0.09650408 | V19: =N19-M19 -> -0.0090695734 | X19: =Q19-P19 -> -0.036901669
B20: RESULTADO LÍQUIDO | D20: ='02-Res M'!D41 -> 0.030937085 | E20: ='02-Res M'!F41 -> 0.026282806 | F20: =E20 -> 0.026282806 | J20: ='02-Res M'!H41 -> 0.15888822 | K20: ='02-Res M'!J41 -> 0.062853244 | M20: ='02-Res M'!L41 -> 0.21320028 | N20: ='02-Res M'!N41 -> 0.20507741 | P20: =AVERAGE(D20,J20,M20) -> 0.13434186 | Q20: =AVERAGE(E20,K20,N20) -> 0.098071154 | T20: =E20-D20 -> -0.0046542796 | U20: =K20-J20 -> -0.096034972 | V20: =N20-M20 -> -0.0081228726 | X20: =Q20-P20 -> -0.036270708
B22: COMPARATIVOS | D22: BUDGET | E22: REAL | J22: BUDGET | K22: REAL | M22: BUDGET | N22: REAL | P22: Total. BD Tri | Q22: Total Real Tri | X22: 1º TRI
B24: ='02-Res M'!B15 -> Receita Líquida | D24: ='03- BD x RE 2026'!D23 -> 288100 | E24: ='03- BD x RE 2026'!E23 -> 211153.17 | J24: ='03- BD x RE 2026'!G23 -> 348100 | K24: ='03- BD x RE 2026'!H23 -> 259364.15 | M24: ='03- BD x RE 2026'!J23 -> 416100 | N24: ='03- BD x RE 2026'!K23 -> 399381.5 | P24: =SUM(D24,J24,M24) -> 1052300 | Q24: =SUM(E24,K24,N24) -> 869898.82 | X24: =Q24-P24 -> -182401.18
B26: Resultado Líquido BD x REAL | D26: ='03- BD x RE 2026'!D64 -> 8912.9742 | E26: ='03- BD x RE 2026'!E64 -> 5549.6977 | J26: ='03- BD x RE 2026'!G64 -> 55308.988 | K26: ='03- BD x RE 2026'!H64 -> 16301.878 | M26: ='03- BD x RE 2026'!J64 -> 88712.638 | N26: ='03- BD x RE 2026'!K64 -> 81904.124 | P26: =SUM(D26,J26,M26) -> 152934.6 | Q26: =SUM(E26,K26,N26) -> 103755.7 | X26: =Q26-P26 -> -49178.9
AQ32: O descolamento percetual do real x budguet é devido o valor do faturamento te defit de 47%, concequentimete o impacto percetualmete aumentou porém em valor nomenal está em linha com o budguet

Sheet 02-Res M
B4: COMPARATIVO REAL VS ORÇAMENTO 2026 | W4: INDICES
D6: BD JAN'26 | F6: REAL JAN'26 | H6: BD FEV'26 | J6: REAL FEV'26 | L6: BD MAR26 | N6: BD MAR26 | P6: VAR REAL X BD | S6: V' RE X BD FEV26 | U6: V' RE X BD MAR/26 | W6: PARTICIPAÇÃO
B8: Clientes | D8: ='03- BD x RE 2026'!D7/1000 -> 0 | F8: ='03- BD x RE 2026'!E7/1000 -> 4.761 | H8: ='[1]03- BD x RE 2026'!G7/1000 -> 7.8601684 | J8: ='[1]03- BD x RE 2026'!H7/1000 -> 4.661 | L8: ='[1]03- BD x RE 2026'!J7/1000 -> 7.9214504 | N8: ='[1]03- BD x RE 2026'!K7/1000 -> 6.592 | P8: =IF(ISERROR($F8/D8-1),"-",($F8/D8-1)) -> - | S8: =IF(ISERROR($J8/J8-1),"-",($H8/J8-1)) -> 0.68636953 | U8: =IF(ISERROR($L8/N8-1),"-",($L8/N8-1)) -> 0.20167633
B9: Ticket Médio FB | D9: =IF(ISERROR(D11/D8),0,(D11/D8)) -> 0 | F9: =IF(ISERROR(F11/F8),0,(F11/F8)) -> 44.447429 | H9: =IF(ISERROR(H11/H8),0,(H11/H8)) -> 44.528308 | J9: =IF(ISERROR(J11/J8),0,(J11/J8)) -> 55.821384 | L9: =IF(ISERROR(L11/L8),0,(L11/L8)) -> 53.020594 | N9: =IF(ISERROR(N11/N8),0,(N11/N8)) -> 60.980869 | P9: =IF(ISERROR($F9/D9-1),"-",($F9/D9-1)) -> - | S9: =IF(ISERROR($H9/J9-1),"-",($H9/J9-1)) -> -0.20230734 | U9: =IF(ISERROR($L9/N9-1),"-",($L9/N9-1)) -> -0.13053726
S10: =IF(ISERROR($H10/J10-1),"-",($H10/J10-1)) -> - | U10: =IF(ISERROR($H10/K10-1),"-",($H10/K10-1)) -> -
B11: Faturamento Bruto | D11: ='03- BD x RE 2026'!D10/1000 -> 290 | F11: ='03- BD x RE 2026'!E10/1000 -> 211.61421 | H11: ='03- BD x RE 2026'!G10/1000 -> 350 | J11: ='03- BD x RE 2026'!H10/1000 -> 260.18347 | L11: ='03- BD x RE 2026'!J10/1000 -> 420 | N11: ='03- BD x RE 2026'!K10/1000 -> 401.98589 | P11: =IF(ISERROR($F11/D11-1),"-",($F11/D11-1)) -> -0.27029583 | S11: =IF(ISERROR($H11/J11-1),"-",($H11/J11-1)) -> 0.3452046 | U11: =IF(ISERROR($L11/N11-1),"-",($L11/N11-1)) -> 0.044812792 | W11: JAN'26 | AD11: FEV'26 | AH11: Mar'26
S12: =IF(ISERROR($H12/J12-1),"-",($H12/J12-1)) -> -
B13: Impostos (ICMS/PIS/COFINS) | D13: ='03- BD x RE 2026'!D18/1000 -> -1.9 | F13: ='03- BD x RE 2026'!E18/1000 -> -0.46104 | H13: ='03- BD x RE 2026'!G18/1000 -> -1.9 | J13: ='03- BD x RE 2026'!H18/1000 -> -0.81932 | L13: ='03- BD x RE 2026'!J18/1000 -> -3.9 | N13: ='03- BD x RE 2026'!K18/1000 -> -2.60439 | P13: =IF(ISERROR($F13/D13-1),"-",($F13/D13-1)) -> -0.75734737 | S13: =IF(ISERROR($H13/J13-1),"-",($H13/J13-1)) -> 1.3189962 | U13: =IF(ISERROR($L13/N13-1),"-",($L13/N13-1)) -> 0.49747158
S14: =IF(ISERROR($H14/J14-1),"-",($H14/J14-1)) -> -
B15: Receita Líquida | D15: =D11+D13 -> 288.1 | F15: =F11+F13 -> 211.15317 | H15: =H11+H13 -> 348.1 | J15: =J11+J13 -> 259.36415 | L15: =L11+L13 -> 416.1 | N15: =N11+N13 -> 399.3815 | P15: =IF(ISERROR($F15/D15-1),"-",($F15/D15-1)) -> -0.26708376 | S15: =IF(ISERROR($H15/J15-1),"-",($H15/J15-1)) -> 0.34212843 | U15: =IF(ISERROR($L15/N15-1),"-",($L15/N15-1)) -> 0.041860978 | W15: PART% BD | Y15: PART% REAL | AD15: PART% BD | AF15: PART% REAL | AH15: PART% BD | AJ15: PART% REAL
S16: =IF(ISERROR($H16/J16-1),"-",($H16/J16-1)) -> -
B17: ='[2]2 DRE '!A27 -> CUSTOS/DESPESAS | D17: =SUM(D18:D23) -> -239.82604 | F17: =SUM(F18:F23) -> -174.95631 | H17: =SUM(H18:H23) -> -259.37426 | J17: =SUM(J18:J23) -> -219.27065 | L17: =SUM(L18:L23) -> -290.20286 | N17: =SUM(N18:N23) -> -273.18083 | P17: =IF(ISERROR($F17/D17-1),"-",($F17/D17-1)) -> -0.27048659 | S17: =IF(ISERROR($H17/J17-1),"-",($H17/J17-1)) -> 0.18289548 | U17: =IF(ISERROR($L17/N17-1),"-",($L17/N17-1)) -> 0.062310508 | W17: =IF(ISERROR($D17/$D$15),"-",($D17/$D$15)) -> -0.83244027 | Y17: =IF(ISERROR(F17/F$15),"-",(F17/F$15)) -> -0.82857535 | AA17: Var | AC17: Impacto | AD17: =IF(ISERROR($H17/$H$15),"-",($H17/$H$15)) -> -0.74511423 | AF17: =IF(ISERROR($J17/$J$15),"-",($J17/$J$15)) -> -0.84541619 | AH17: =IF(ISERROR($L17/$L$15),"-",($L17/$L$15)) -> -0.69743538 | AJ17: =IF(ISERROR($N17/$N$15),"-",($N17/$N$15)) -> -0.68400971
B18: CMV | D18: ='03- BD x RE 2026'!D27/1000 -> -92.8 | F18: ='03- BD x RE 2026'!E27/1000 -> -43.768202 | H18: ='03- BD x RE 2026'!G27/1000 -> -111.392 | J18: ='03- BD x RE 2026'!H27/1000 -> -78.640862 | L18: ='03- BD x RE 2026'!J27/1000 -> -133.792 | N18: ='03- BD x RE 2026'!K27/1000 -> -85.602456 | P18: =IF(ISERROR($F18/D18-1),"-",($F18/D18-1)) -> -0.52835989 | S18: =IF(ISERROR($H18/J18-1),"-",($H18/J18-1)) -> 0.41646464 | U18: =IF(ISERROR($L18/N18-1),"-",($L18/N18-1)) -> 0.56294581 | W18: =IF(ISERROR($D18/$D$15),"-",($D18/$D$15)) -> -0.32211038 | Y18: =IF(ISERROR(F18/F$15),"-",(F18/F$15)) -> -0.20728177 | AA18: =Y18-W18 -> 0.11482861 | AC18: =-Y18*AA18 -> 0.023801877 | AD18: =IF(ISERROR($H18/$H$15),"-",($H18/$H$15)) -> -0.32 | AF18: =IF(ISERROR(J18/J$15),"-",(J18/J$15)) -> -0.30320637 | AH18: =IF(ISERROR($L18/$L$15),"-",($L18/$L$15)) -> -0.32153809 | AJ18: =IF(ISERROR($N18/$N$15),"-",($N18/$N$15)) -> -0.21433756
B19: Pessoal | D19: ='03- BD x RE 2026'!D36/1000 -> -68.369177 | F19: ='03- BD x RE 2026'!E36/1000 -> -50.08316 | H19: ='03- BD x RE 2026'!G36/1000 -> -56.996772 | J19: ='03- BD x RE 2026'!H36/1000 -> -44.39531 | L19: ='03- BD x RE 2026'!J36/1000 -> -63.907562 | N19: ='03- BD x RE 2026'!K36/1000 -> -61.58306 | P19: =IF(ISERROR($F19/D19-1),"-",($F19/D19-1)) -> -0.26745996 | S19: =IF(ISERROR($H19/J19-1),"-",($H19/J19-1)) -> 0.28384669 | U19: =IF(ISERROR($L19/N19-1),"-",($L19/N19-1)) -> 0.037745799 | W19: =IF(ISERROR($D19/$D$15),"-",($D19/$D$15)) -> -0.23731058 | Y19: =IF(ISERROR(F19/F$15),"-",(F19/F$15)) -> -0.23718877 | AA19: =Y19-W19 -> 0.00012180991 | AC19: =-Y19*AA19 -> 2.8891944e-05 | AD19: =IF(ISERROR($H19/$H$15),"-",($H19/$H$15)) -> -0.16373678 | AF19: =IF(ISERROR(J19/J$15),"-",(J19/J$15)) -> -0.1711698 | AH19: =IF(ISERROR($L19/$L$15),"-",($L19/$L$15)) -> -0.15358703 | AJ19: =IF(ISERROR($N19/$N$15),"-",($N19/$N$15)) -> -0.15419608
B20: Ocupação | D20: ='03- BD x RE 2026'!D41/1000 -> -18.8 | F20: ='03- BD x RE 2026'!E41/1000 -> -23.8 | H20: ='03- BD x RE 2026'!G41/1000 -> -18.8 | J20: ='03- BD x RE 2026'!H41/1000 -> -23.8 | L20: ='03- BD x RE 2026'!J41/1000 -> -18.8 | N20: ='03- BD x RE 2026'!K41/1000 -> -23.8 | P20: =IF(ISERROR($F20/D20-1),"-",($F20/D20-1)) -> 0.26595745 | S20: =IF(ISERROR($H20/J20-1),"-",($H20/J20-1)) -> -0.21008403 | U20: =IF(ISERROR($L20/N20-1),"-",($L20/N20-1)) -> -0.21008403 | W20: =IF(ISERROR($D20/$D$15),"-",($D20/$D$15)) -> -0.06525512 | Y20: =IF(ISERROR(F20/F$15),"-",(F20/F$15)) -> -0.11271439 | AA20: =Y20-W20 -> -0.047459267 | AC20: =-Y20*AA20 -> -0.0053493421 | AD20: =IF(ISERROR($H20/$H$15),"-",($H20/$H$15)) -> -0.054007469 | AF20: =IF(ISERROR(J20/J$15),"-",(J20/J$15)) -> -0.091762875 | AH20: =IF(ISERROR($L20/$L$15),"-",($L20/$L$15)) -> -0.045181447 | AJ20: =IF(ISERROR($N20/$N$15),"-",($N20/$N$15)) -> -0.059592144
B21: Utilidades/ Consumo | D21: ='03- BD x RE 2026'!D42/1000 -> -3.97609 | F21: ='03- BD x RE 2026'!E42/1000 -> -3.50822 | H21: ='03- BD x RE 2026'!G42/1000 -> -2.731 | J21: ='03- BD x RE 2026'!H42/1000 -> -1.71094 | L21: ='03- BD x RE 2026'!J42/1000 -> -2.82781 | N21: ='03- BD x RE 2026'!K42/1000 -> -18 | P21: =IF(ISERROR($F21/D21-1),"-",($F21/D21-1)) -> -0.11767088 | S21: =IF(ISERROR($H21/J21-1),"-",($H21/J21-1)) -> 0.59619858 | U21: =IF(ISERROR($L21/N21-1),"-",($L21/N21-1)) -> -0.84289944 | W21: =IF(ISERROR($D21/$D$15),"-",($D21/$D$15)) -> -0.013801076 | Y21: =IF(ISERROR(F21/F$15),"-",(F21/F$15)) -> -0.016614574 | AA21: =Y21-W21 -> -0.0028134981 | AC21: =-Y21*AA21 -> -4.6745073e-05 | AD21: =IF(ISERROR($H21/$H$15),"-",($H21/$H$15)) -> -0.0078454467 | AF21: =IF(ISERROR(J21/J$15),"-",(J21/J$15)) -> -0.0065966711 | AH21: =IF(ISERROR($L21/$L$15),"-",($L21/$L$15)) -> -0.0067959865 | AJ21: =IF(ISERROR($N21/$N$15),"-",($N21/$N$15)) -> -0.045069689
B22: Operação | D22: ='03- BD x RE 2026'!D43/1000 -> -51.097412 | F22: ='03- BD x RE 2026'!E43/1000 -> -52.86223 | H22: ='03- BD x RE 2026'!G43/1000 -> -64.671129 | J22: ='03- BD x RE 2026'!H43/1000 -> -66.22354 | L22: ='03- BD x RE 2026'!J43/1000 -> -66.092129 | N22: ='03- BD x RE 2026'!K43/1000 -> -83.23531 | P22: =IF(ISERROR($F22/D22-1),"-",($F22/D22-1)) -> 0.0345383 | S22: =IF(ISERROR($H22/J22-1),"-",($H22/J22-1)) -> -0.023441986 | U22: =IF(ISERROR($L22/N22-1),"-",($L22/N22-1)) -> -0.20596044 | W22: =IF(ISERROR($D22/$D$15),"-",($D22/$D$15)) -> -0.17735999 | Y22: =IF(ISERROR(F22/F$15),"-",(F22/F$15)) -> -0.25035016 | AA22: =Y22-W22 -> -0.072990174 | AC22: =-Y22*AA22 -> -0.018273102 | AD22: =IF(ISERROR($H22/$H$15),"-",($H22/$H$15)) -> -0.18578319 | AF22: =IF(ISERROR(J22/J$15),"-",(J22/J$15)) -> -0.25533035 | AH22: =IF(ISERROR($L22/$L$15),"-",($L22/$L$15)) -> -0.15883713 | AJ22: =IF(ISERROR($N22/$N$15),"-",($N22/$N$15)) -> -0.20841053
B23: Manutenção e Conservação | D23: ='03- BD x RE 2026'!D44/1000 -> -4.7833614 | F23: ='03- BD x RE 2026'!E44/1000 -> -0.9345 | H23: ='03- BD x RE 2026'!G44/1000 -> -4.7833614 | J23: ='03- BD x RE 2026'!H44/1000 -> -4.5 | L23: ='03- BD x RE 2026'!J44/1000 -> -4.7833614 | N23: ='03- BD x RE 2026'!K44/1000 -> -0.96 | P23: =IF(ISERROR($F23/D23-1),"-",($F23/D23-1)) -> -0.80463529 | S23: =IF(ISERROR($H23/J23-1),"-",($H23/J23-1)) -> 0.062969198 | U23: =IF(ISERROR($L23/N23-1),"-",($L23/N23-1)) -> 3.9826681 | W23: =IF(ISERROR($D23/$D$15),"-",($D23/$D$15)) -> -0.016603129 | Y23: =IF(ISERROR(F23/F$15),"-",(F23/F$15)) -> -0.0044256972 | AA23: =Y23-W23 -> 0.012177432 | AC23: =-Y23*AA23 -> 5.3893625e-05 | AD23: =IF(ISERROR($H23/$H$15),"-",($H23/$H$15)) -> -0.013741343 | AF23: =IF(ISERROR(J23/J$15),"-",(J23/J$15)) -> -0.017350123 | AH23: =IF(ISERROR($L23/$L$15),"-",($L23/$L$15)) -> -0.011495701 | AJ23: =IF(ISERROR($N23/$N$15),"-",($N23/$N$15)) -> -0.0024037167
B24: ='[2]2 DRE '!A52 -> DESPESAS ADMINISTRATIVAS | D24: =SUM(D25:D27) -> -39.070985 | F24: =SUM(F25:F27) -> -30.53535 | H24: =SUM(H25:H27) -> -33.06675 | J24: =SUM(J25:J27) -> -23.65251 | L24: =SUM(L25:L27) -> -36.7645 | N24: =SUM(N25:N27) -> -44.27152 | P24: =IF(ISERROR($F24/D24-1),"-",($F24/D24-1)) -> -0.2184648 | S24: =IF(ISERROR($H24/J24-1),"-",($H24/J24-1)) -> 0.39802287 | U24: =IF(ISERROR($L24/N24-1),"-",($L24/N24-1)) -> -0.1695677 | W24: =IF(ISERROR($D24/$D$15),"-",($D24/$D$15)) -> -0.13561605 | Y24: =IF(ISERROR(F24/F$15),"-",(F24/F$15)) -> -0.14461232 | AA24: =Y24-W24 -> -0.0089962676 | AC24: =AA24-Y24 -> 0.13561605 | AD24: =IF(ISERROR($H24/$H$15),"-",($H24/$H$15)) -> -0.0949921 | AF24: =IF(ISERROR($J24/$J$15),"-",($J24/$J$15)) -> -0.091194215 | AH24: =IF(ISERROR($L24/$L$15),"-",($L24/$L$15)) -> -0.088354963 | AJ24: =IF(ISERROR($N24/$N$15),"-",($N24/$N$15)) -> -0.1108502
B25: Administrativa | D25: ='03- BD x RE 2026'!D49/1000 -> -18.105064 | F25: ='03- BD x RE 2026'!E49/1000 -> -15.5102 | H25: ='03- BD x RE 2026'!G49/1000 -> -17.098 | J25: ='03- BD x RE 2026'!H49/1000 -> -15.13134 | L25: ='03- BD x RE 2026'!J49/1000 -> -17.602 | N25: ='03- BD x RE 2026'!K49/1000 -> -15.09336 | P25: =IF(ISERROR($F25/D25-1),"-",($F25/D25-1)) -> -0.14332257 | S25: =IF(ISERROR($H25/J25-1),"-",($H25/J25-1)) -> 0.12997263 | U25: =IF(ISERROR($L25/N25-1),"-",($L25/N25-1)) -> 0.16620819 | W25: =IF(ISERROR($D25/$D$15),"-",($D25/$D$15)) -> -0.062842986 | Y25: =IF(ISERROR(F25/F$15),"-",(F25/F$15)) -> -0.073454734 | AA25: =Y25-W25 -> -0.010611748 | AC25: =-Y25*AA25 -> -0.00077948313 | AD25: =IF(ISERROR($H25/$H$15),"-",($H25/$H$15)) -> -0.04911807 | AF25: =IF(ISERROR(J25/J$15),"-",(J25/J$15)) -> -0.058340137 | AH25: =IF(ISERROR($L25/$L$15),"-",($L25/$L$15)) -> -0.042302331 | AJ25: =IF(ISERROR($N25/$N$15),"-",($N25/$N$15)) -> -0.037791836
B26: Marketing | D26: ='03- BD x RE 2026'!D50/1000 -> -13.365921 | F26: ='03- BD x RE 2026'!E50/1000 -> -8.5 | H26: ='03- BD x RE 2026'!G50/1000 -> -10.5 | J26: ='03- BD x RE 2026'!H50/1000 -> -1.5 | L26: ='03- BD x RE 2026'!J50/1000 -> -12.6 | N26: ='03- BD x RE 2026'!K50/1000 -> -19.08 | P26: =IF(ISERROR($D26/F26-1),"-",($D26/F26-1)) -> 0.57246125 | S26: =IF(ISERROR($H26/J26-1),"-",($H26/J26-1)) -> 6 | U26: =IF(ISERROR($L26/N26-1),"-",($L26/N26-1)) -> -0.33962264 | W26: =IF(ISERROR($D26/$D$15),"-",($D26/$D$15)) -> -0.046393338 | Y26: =IF(ISERROR(F26/F$15),"-",(F26/F$15)) -> -0.040255138 | AA26: =Y26-W26 -> 0.0061381998 | AC26: =-Y26*AA26 -> 0.00024709408 | AD26: =IF(ISERROR($H26/$H$15),"-",($H26/$H$15)) -> -0.030163746 | AF26: =IF(ISERROR(J26/J$15),"-",(J26/J$15)) -> -0.0057833745 | AH26: =IF(ISERROR($L26/$L$15),"-",($L26/$L$15)) -> -0.030281182 | AJ26: =IF(ISERROR($N26/$N$15),"-",($N26/$N$15)) -> -0.04777387
B27: Taxa Cartão Crédito | D27: ='03- BD x RE 2026'!D51/1000 -> -7.6 | F27: ='03- BD x RE 2026'!E51/1000 -> -6.52515 | H27: ='03- BD x RE 2026'!G51/1000 -> -5.46875 | J27: ='03- BD x RE 2026'!H51/1000 -> -7.02117 | L27: ='03- BD x RE 2026'!J51/1000 -> -6.5625 | N27: ='03- BD x RE 2026'!K51/1000 -> -10.09816 | P27: =IF(ISERROR($F27/D27-1),"-",($F27/D27-1)) -> -0.14142763 | S27: =IF(ISERROR($H27/J27-1),"-",($H27/J27-1)) -> -0.2211056 | U27: =IF(ISERROR($L27/N27-1),"-",($L27/N27-1)) -> -0.35012913 | W27: =IF(ISERROR($D27/$D$15),"-",($D27/$D$15)) -> -0.026379729 | Y27: =IF(ISERROR(F27/F$15),"-",(F27/F$15)) -> -0.030902449 | AA27: =Y27-W27 -> -0.0045227194 | AC27: =-Y27*AA27 -> -0.0001397631 | AD27: =IF(ISERROR($H27/$H$15),"-",($H27/$H$15)) -> -0.015710284 | AF27: =IF(ISERROR(J27/J$15),"-",(J27/J$15)) -> -0.027070703 | AH27: =IF(ISERROR($L27/$L$15),"-",($L27/$L$15)) -> -0.015771449 | AJ27: =IF(ISERROR($N27/$N$15),"-",($N27/$N$15)) -> -0.025284496
S28: =IF(ISERROR($H28/J28-1),"-",($H28/J28-1)) -> - | U28: =IF(ISERROR($L28/N28-1),"-",($L28/N28-1)) -> - | W28: =IF(ISERROR($D28/$D$15),"-",($D28/$D$15)) -> 0 | AA28: =Y28-W28 -> 0 | AC28: =-Y28*AA28 -> 0 | AD28: =IF(ISERROR($H28/$H$15),"-",($H28/$H$15)) -> 0 | AH28: =IF(ISERROR($L28/$L$15),"-",($L28/$L$15)) -> 0 | AJ28: =IF(ISERROR($N28/$N$15),"-",($N28/$N$15)) -> 0
B29: LAJIDA | D29: =D15+D17+D24 -> 9.2029742 | F29: =F15+F17+F24 -> 5.6615077 | H29: =H15+H17+H24 -> 55.658988 | J29: =J15+J17+J24 -> 16.440988 | L29: =L15+L17+L24 -> 89.132638 | N29: =N15+N17+N24 -> 81.929154 | P29: =IF(ISERROR($F29/D29-1),"-",($F29/D29-1)) -> -0.38481761 | S29: =IF(ISERROR($H29/J29-1),"-",($H29/J29-1)) -> 2.3853797 | U29: =IF(ISERROR($L29/N29-1),"-",($L29/N29-1)) -> 0.087923329 | W29: =IF(ISERROR($D29/$D$15),"-",($D29/$D$15)) -> 0.03194368 | Y29: =IF(ISERROR(F29/F$15),"-",(F29/F$15)) -> 0.026812326 | AA29: =Y29-W29 -> -0.0051313537 | AC29: =AA29-Y29 -> -0.03194368 | AD29: =IF(ISERROR($H29/$H$15),"-",($H29/$H$15)) -> 0.15989367 | AF29: =IF(ISERROR($J29/$J$15),"-",($J29/$J$15)) -> 0.063389594 | AH29: =IF(ISERROR($L29/$L$15),"-",($L29/$L$15)) -> 0.21420966 | AJ29: =IF(ISERROR($N29/$N$15),"-",($N29/$N$15)) -> 0.20514008
B30: MARGEM EBITDA | D30: =IF(ISERROR(D29/D15),0,(D29/D15)) -> 0.03194368 | F30: =IF(ISERROR(F29/F15),0,(F29/F15)) -> 0.026812326 | H30: =IF(ISERROR(H29/H15),0,(H29/H15)) -> 0.15989367 | J30: =IF(ISERROR(J29/J15),0,(J29/J15)) -> 0.063389594 | L30: =IF(ISERROR(L29/L15),0,(L29/L15)) -> 0.21420966 | N30: =IF(ISERROR(N29/N15),0,(N29/N15)) -> 0.20514008 | P30: =IF(ISERROR($F30/D30-1),"-",($F30/D30-1)) -> -0.16063753 | S30: =IF(ISERROR($H30/J30-1),"-",($H30/J30-1)) -> 1.5223962 | U30: =IF(ISERROR($L30/N30-1),"-",($L30/N30-1)) -> 0.04421161 | W30: =IF(ISERROR($D30/$D$15),"-",($D30/$D$15)) -> 0.00011087706 | Y30: =IF(ISERROR($F30/$F$15),"-",($F30/$F$15)) -> 0.00012698046 | AA30: =Y30-W30 -> 1.6103402e-05 | AC30: =-Y30*AA30 -> -2.0448173e-09 | AD30: =IF(ISERROR($H30/$H$15),"-",($H30/$H$15)) -> 0.00045933259 | AF30: =IF(ISERROR(J30/J$15),"-",(J30/J$15)) -> 0.00024440384 | AH30: =IF(ISERROR($L30/$L$15),"-",($L30/$L$15)) -> 0.00051480331 | AJ30: =IF(ISERROR($N30/$N$15),"-",($N30/$N$15)) -> 0.00051364443
S31: =IF(ISERROR($H31/J31-1),"-",($H31/J31-1)) -> - | U31: =IF(ISERROR($H31/K31-1),"-",($H31/K31-1)) -> - | W31: =IF(ISERROR($D31/$D$15),"-",($D31/$D$15)) -> 0 | AA31: =Y31-W31 -> 0 | AC31: =-Y31*AA31 -> 0 | AD31: =IF(ISERROR($H31/$H$15),"-",($H31/$H$15)) -> 0 | AH31: =IF(ISERROR($L31/$L$15),"-",($L31/$L$15)) -> 0 | AJ31: =IF(ISERROR($N31/$N$15),"-",($N31/$N$15)) -> 0
B32: Depreciação & Amortização | P32: =IF(ISERROR($F32/D32-1),"-",($F32/D32-1)) -> - | S32: =IF(ISERROR($H32/J32-1),"-",($H32/J32-1)) -> - | U32: =IF(ISERROR($H32/K32-1),"-",($H32/K32-1)) -> - | AF32: =IF(ISERROR(O32/O$15),"-",(O32/O$15)) -> - | AH32: =IF(ISERROR($L32/$L$15),"-",($L32/$L$15)) -> 0 | AJ32: =IF(ISERROR($N32/$N$15),"-",($N32/$N$15)) -> 0
S33: =IF(ISERROR($H33/J33-1),"-",($H33/J33-1)) -> - | U33: =IF(ISERROR($H33/K33-1),"-",($H33/K33-1)) -> - | W33: =IF(ISERROR($D33/$D$15),"-",($D33/$D$15)) -> 0 | AA33: =Y33-W33 -> 0 | AC33: =-Y33*AA33 -> 0 | AD33: =IF(ISERROR($H33/$H$15),"-",($H33/$H$15)) -> 0 | AH33: =IF(ISERROR($L33/$L$15),"-",($L33/$L$15)) -> 0 | AJ33: =IF(ISERROR($N33/$N$15),"-",($N33/$N$15)) -> 0
B34: LAIR | D34: =D29+D32 -> 9.2029742 | F34: =F29+F32 -> 5.6615077 | H34: =H29+H32 -> 55.658988 | J34: =J29+J32 -> 16.440988 | L34: =L29+L32 -> 89.132638 | N34: =N29+N32 -> 81.929154 | P34: =IF(ISERROR($F34/D34-1),"-",($F34/D34-1)) -> -0.38481761 | S34: =IF(ISERROR($H34/J34-1),"-",($H34/J34-1)) -> 2.3853797 | U34: =IF(ISERROR($L34/N34-1),"-",($L34/N34-1)) -> 0.087923329 | W34: =IF(ISERROR($D34/$D$15),"-",($D34/$D$15)) -> 0.03194368 | Y34: =IF(ISERROR(F34/F$15),"-",(F34/F$15)) -> 0.026812326 | AA34: =Y34-W34 -> -0.0051313537 | AC34: =AA34-Y34 -> -0.03194368 | AD34: =IF(ISERROR($H34/$H$15),"-",($H34/$H$15)) -> 0.15989367 | AF34: =IF(ISERROR($J34/$J$15),"-",($J34/$J$15)) -> 0.063389594 | AH34: =IF(ISERROR($L34/$L$15),"-",($L34/$L$15)) -> 0.21420966 | AJ34: =IF(ISERROR($N34/$N$15),"-",($N34/$N$15)) -> 0.20514008
B35: MARGEM EBIT | D35: =IF(ISERROR(D34/D15),0,(D34/D15)) -> 0.03194368 | F35: =IF(ISERROR(F34/F15),0,(F34/F15)) -> 0.026812326 | H35: =IF(ISERROR(H34/H15),0,(H34/H15)) -> 0.15989367 | J35: =IF(ISERROR(J34/J15),0,(J34/J15)) -> 0.063389594 | L35: =IF(ISERROR(L34/L15),0,(L34/L15)) -> 0.21420966 | N35: =IF(ISERROR(N34/N15),0,(N34/N15)) -> 0.20514008 | P35: =IF(ISERROR($F35/D35-1),"-",($F35/D35-1)) -> -0.16063753 | S35: =IF(ISERROR($H35/J35-1),"-",($H35/J35-1)) -> 1.5223962 | U35: =IF(ISERROR($L35/N35-1),"-",($L35/N35-1)) -> 0.04421161 | W35: =IF(ISERROR($D35/$D$15),"-",($D35/$D$15)) -> 0.00011087706 | Y35: =IF(ISERROR($F35/$F$15),"-",($F35/$F$15)) -> 0.00012698046 | AA35: =Y35-W35 -> 1.6103402e-05 | AC35: =-Y35*AA35 -> -2.0448173e-09 | AD35: =IF(ISERROR($H35/$H$15),"-",($H35/$H$15)) -> 0.00045933259 | AF35: =IF(ISERROR(J35/J$15),"-",(J35/J$15)) -> 0.00024440384 | AH35: =IF(ISERROR($L35/$L$15),"-",($L35/$L$15)) -> 0.00051480331 | AJ35: =IF(ISERROR($N35/$N$15),"-",($N35/$N$15)) -> 0.00051364443
B36: Despesas Financeiras | D36: ='03- BD x RE 2026'!D61/1000 -> -0.29 | F36: ='03- BD x RE 2026'!E61/1000 -> -0.11181 | H36: ='03- BD x RE 2026'!G61/1000 -> -0.35 | J36: ='03- BD x RE 2026'!H61/1000 -> -0.13911 | L36: ='03- BD x RE 2026'!J61/1000 -> -0.42 | N36: ='03- BD x RE 2026'!K61/1000 -> -0.02503 | P36: =IF(ISERROR($F36/D36-1),"-",($F36/D36-1)) -> -0.61444828 | S36: =IF(ISERROR($H36/J36-1),"-",($H36/J36-1)) -> 1.5159945 | U36: =IF(ISERROR($L36/N36-1),"-",($L36/N36-1)) -> 15.779864 | W36: =IF(ISERROR($D36/$D$15),"-",($D36/$D$15)) -> -0.0010065949 | Y36: =IF(ISERROR(F36/F$15),"-",(F36/F$15)) -> -0.00052952082 | AA36: =Y36-W36 -> 0.00047707411 | AC36: =-Y36*AA36 -> 2.5262068e-07 | AD36: =IF(ISERROR($H36/$H$15),"-",($H36/$H$15)) -> -0.0010054582 | AF36: =IF(ISERROR(J36/J$15),"-",(J36/J$15)) -> -0.00053635015 | AH36: =IF(ISERROR($L36/$L$15),"-",($L36/$L$15)) -> -0.0010093727 | AJ36: =IF(ISERROR($N36/$N$15),"-",($N36/$N$15)) -> -6.2671906e-05
B37: Despesas Pré-Operacionais | D37: ='[2]8 1 BD24'!N64/1000 -> 0 | F37: ='[2]9 1 DRE R23'!N68/1000 -> 0 | P37: =IF(ISERROR(#REF!/D37-1),"-",(#REF!/D37-1)) -> - | S37: =IF(ISERROR($H37/J37-1),"-",($H37/J37-1)) -> - | U37: =IF(ISERROR($H37/K37-1),"-",($H37/K37-1)) -> - | W37: =IF(ISERROR($D37/$D$15),"-",($D37/$D$15)) -> 0 | Y37: =IF(ISERROR(F37/F$15),"-",(F37/F$15)) -> 0 | AA37: =Y37-W37 -> 0 | AC37: =-Y37*AA37 -> 0 | AD37: =IF(ISERROR($H37/$H$15),"-",($H37/$H$15)) -> 0 | AF37: =IF(ISERROR(O37/O$15),"-",(O37/O$15)) -> - | AH37: =IF(ISERROR($L37/$L$15),"-",($L37/$L$15)) -> 0 | AJ37: =IF(ISERROR($N37/$N$15),"-",($N37/$N$15)) -> 0
B38: IRPJ/CSLL | P38: =IF(ISERROR($F38/D38-1),"-",($F38/D38-1)) -> - | S38: =IF(ISERROR($H38/J38-1),"-",($H38/J38-1)) -> - | U38: =IF(ISERROR($H38/K38-1),"-",($H38/K38-1)) -> - | W38: =IF(ISERROR($D38/$D$15),"-",($D38/$D$15)) -> 0 | Y38: =IF(ISERROR(F38/F$15),"-",(F38/F$15)) -> 0 | AA38: =Y38-W38 -> 0 | AC38: =-Y38*AA38 -> 0 | AD38: =IF(ISERROR($H38/$H$15),"-",($H38/$H$15)) -> 0 | AF38: =IF(ISERROR(J38/J$15),"-",(J38/J$15)) -> 0 | AH38: =IF(ISERROR($L38/$L$15),"-",($L38/$L$15)) -> 0 | AJ38: =IF(ISERROR($N38/$N$15),"-",($N38/$N$15)) -> 0
S39: =IF(ISERROR($H39/J39-1),"-",($H39/J39-1)) -> - | U39: =IF(ISERROR($H39/K39-1),"-",($H39/K39-1)) -> - | AA39: =Y39-W39 -> 0
B40: RESULTADO OPERACIONAL | D40: =D34+D36+D37+D38 -> 8.9129742 | F40: =F34+F36+F37+F38 -> 5.5496977 | H40: =H34+H36+H37+H38 -> 55.308988 | J40: =J34+J36+J37+J38 -> 16.301878 | L40: =L34+L36+L37+L38 -> 88.712638 | N40: =N34+N36+N37+N38 -> 81.904124 | P40: =IF(ISERROR($F40/D40-1),"-",($F40/D40-1)) -> -0.37734615 | S40: =IF(ISERROR($H40/J40-1),"-",($H40/J40-1)) -> 2.3927985 | U40: =IF(ISERROR($H40/K40-1),"-",($H40/K40-1)) -> - | W40: =IF(ISERROR($D40/$D$15),"-",($D40/$D$15)) -> 0.030937085 | Y40: =IF(ISERROR(F40/F$15),"-",(F40/F$15)) -> 0.026282806 | AA40: =Y40-W40 -> -0.0046542796 | AC40: =-Y40*AA40 -> 0.00012232753 | AD40: =IF(ISERROR($H40/$H$15),"-",($H40/$H$15)) -> 0.15888822 | AF40: =IF(ISERROR($J40/$J$15),"-",($J40/$J$15)) -> 0.062853244 | AH40: =IF(ISERROR($L40/$L$15),"-",($L40/$L$15)) -> 0.21320028 | AJ40: =IF(ISERROR($N40/$N$15),"-",($N40/$N$15)) -> 0.20507741
B41: ='[2]2 DRE '!A70 -> Margem líquida | D41: =IF(ISERROR(D40/D15),0,(D40/D15)) -> 0.030937085 | F41: =IF(ISERROR(F40/F15),0,(F40/F15)) -> 0.026282806 | H41: =IF(ISERROR(H40/H15),0,(H40/H15)) -> 0.15888822 | J41: =IF(ISERROR(J40/J15),0,(J40/J15)) -> 0.062853244 | L41: =IF(ISERROR(L40/L15),0,(L40/L15)) -> 0.21320028 | N41: =IF(ISERROR(N40/N15),0,(N40/N15)) -> 0.20507741

Sheet 03- BD x RE 2026
A1: BD(2026)
C5: 2026 | D5: JAN | G5: FEV | J5: MAR | M5: ABR | P5: MAI | S5: JUN | V5: JUL | Y5: AGO | AB5: SET | AE5: OUT | AH5: NOV | AK5: DEZ | AN5: 2026 ACUM. | AQ5: 2026 MÉDIA ANUAL | AT5: 2026 PART% | AV5: JAN | AW5: FEV | AX5: MAR | AY5: ABR | AZ5: MAI | BA5: JUN | BB5: JUL | BC5: AGO | BD5: SET | BE5: OUT | BF5: NOV | BG5: DEZ
D6: PROJETADO | E6: REALIZADO | G6: PROJETADO | H6: REALIZADO | J6: PROJETADO | K6: REALIZADO | M6: PROJETADO | N6: REALIZADO | P6: PROJETADO | Q6: REALIZADO | S6: PROJETADO | T6: REALIZADO | V6: PROJETADO | W6: REALIZADO | Y6: PROJETADO | Z6: REALIZADO | AB6: PROJETADO | AC6: REALIZADO | AE6: PROJETADO | AF6: REALIZADO | AH6: PROJETADO | AI6: REALIZADO | AK6: PROJETADO | AL6: REALIZADO | AN6: PROJETADO | AO6: REALIZADO | AQ6: PROJETADO | AR6: REALIZADO
A7: CLIENTES | C7: =SUM(D7,G7,J7,M7,P7,S7,V7,Y7,AB7,AE7,AH7,AK7) -> 0 | D7: ='04 -Base Orçado 2026'!E7 -> 0 | E7: ='01 Base Realizado'!D7 -> 4761 | G7: ='04 -Base Orçado 2026'!F7 -> 0 | J7: ='04 -Base Orçado 2026'!G7 -> 0 | M7: ='04 -Base Orçado 2026'!H7 -> 0 | P7: ='04 -Base Orçado 2026'!I7 -> 0 | S7: ='04 -Base Orçado 2026'!J7 -> 0 | V7: ='04 -Base Orçado 2026'!K7 -> 0 | Y7: ='04 -Base Orçado 2026'!L7 -> 0 | AB7: ='04 -Base Orçado 2026'!M7 -> 0 | AE7: ='04 -Base Orçado 2026'!N7 -> 0 | AH7: ='04 -Base Orçado 2026'!O7 -> 0 | AK7: ='03- BD x RE 2026'!P7 -> 0 | AN7: =SUM(D7,G7,J7,M7,P7,S7,V7,Y7,AB7,AE7,AH7,AK7) -> 0 | AO7: =SUM(E7,H7,K7,N7,Q7,T7,W7,Z7,AC7,AF7,AI7,AL7) -> 4761 | AQ7: =AN7/12 -> 0
A8: Ticket Médio - R$M | C8: =SUM(D8,G8,J8,M8,P8,S8,V8,Y8,AB8,AE8,AH8,AK8) -> 0 | D8: ='04 -Base Orçado 2026'!E8 -> 0 | E8: ='01 Base Realizado'!D8 -> 292 | G8: ='04 -Base Orçado 2026'!F8 -> 0 | J8: ='04 -Base Orçado 2026'!G8 -> 0 | M8: ='04 -Base Orçado 2026'!H8 -> 0 | P8: ='04 -Base Orçado 2026'!I8 -> 0 | S8: ='04 -Base Orçado 2026'!J8 -> 0 | V8: ='04 -Base Orçado 2026'!K8 -> 0 | Y8: ='04 -Base Orçado 2026'!L8 -> 0 | AB8: ='04 -Base Orçado 2026'!M8 -> 0 | AE8: ='04 -Base Orçado 2026'!N8 -> 0 | AH8: ='04 -Base Orçado 2026'!O8 -> 0 | AK8: ='04 -Base Orçado 2026'!P8 -> 0 | AN8: =IF(ISERROR(AN10/AN7),"0",(AN10/AN7)) -> 0 | AO8: =IF(ISERROR(AO10/AO7),"0",(AO10/AO7)) -> 183.52942 | AQ8: =IF(ISERROR(AQ10/AQ7),"0",(AQ10/AQ7)) -> 0
A10: Faturamento Bruto | C10: =SUM(D10,G10,J10,M10,P10,S10,V10,Y10,AB10,AE10,AH10,AK10) -> 5727226.9 | D10: =SUM(D11:D16)-D11 -> 290000 | E10: =SUM(E11:E16)-E11 -> 211614.21 | G10: =SUM(G11:G16) -> 350000 | H10: =SUM(H11:H16)-H11 -> 260183.47 | J10: =SUM(J11:J16) -> 420000 | K10: =SUM(K11:K16)-K11 -> 401985.89 | M10: =SUM(M11:M16) -> 462000 | P10: =SUM(P11:P16) -> 508200 | S10: =SUM(S11:S16) -> 523446 | V10: =SUM(V11:V16) -> 481570.32 | Y10: =SUM(Y11:Y16) -> 505648.84 | AB10: =SUM(AB11:AB16) -> 530931.28 | AE10: =SUM(AE11:AE16) -> 557477.84 | AH10: =SUM(AH11:AH16) -> 563052.62 | AK10: =SUM(AK11:AK16) -> 534899.99 | AN10: =SUM(D10,G10,J10,M10,P10,S10,V10,Y10,AB10,AE10,AH10,AK10) -> 5727226.9 | AO10: =SUM(E10,H10,K10,N10,Q10,T10,W10,Z10,AC10,AF10,AI10,AL10) -> 873783.57 | AQ10: =AN10/12 -> 477268.91 | AR10: =AQ10/$AT$12 -> 159089.64
A11: Gorjetas Recebidas | C11: =SUM(D11,G11,J11,M11,P11,S11,V11,Y11,AB11,AE11,AH11,AK11) -> 0 | D11: ='04 -Base Orçado 2026'!E13 -> 0 | E11: ='01 Base Realizado'!D12 -> 24239 | G11: ='04 -Base Orçado 2026'!F13 -> 0 | H11: ='01 Base Realizado'!F12 -> 29204.66 | J11: ='04 -Base Orçado 2026'!H13 -> 0 | K11: ='01 Base Realizado'!H12 -> 46878.24 | M11: ='04 -Base Orçado 2026'!H13 -> 0 | P11: ='04 -Base Orçado 2026'!I13 -> 0 | S11: ='04 -Base Orçado 2026'!J13 -> 0 | V11: ='04 -Base Orçado 2026'!K13 -> 0 | Y11: ='04 -Base Orçado 2026'!L13 -> 0 | AB11: ='04 -Base Orçado 2026'!M13 -> 0 | AE11: ='04 -Base Orçado 2026'!N13 -> 0 | AH11: ='04 -Base Orçado 2026'!O13 -> 0 | AK11: ='04 -Base Orçado 2026'!P13 -> 0
A12: Dinheiro/Pix | C12: =SUM(D12,G12,J12,M12,P12,S12,V12,Y12,AB12,AE12,AH12,AK12) -> 875584.03 | D12: ='04 -Base Orçado 2026'!E14 -> 60000 | E12: ='01 Base Realizado'!D13 -> 6593.74 | G12: ='04 -Base Orçado 2026'!F14 -> 52500 | H12: ='01 Base Realizado'!F13 -> 16527.59 | J12: ='04 -Base Orçado 2026'!G14 -> 63000 | K12: ='01 Base Realizado'!H13 -> 23177.13 | M12: ='04 -Base Orçado 2026'!H14 -> 69300 | P12: ='04 -Base Orçado 2026'!I14 -> 76230 | S12: ='04 -Base Orçado 2026'!J14 -> 78516.9 | V12: ='04 -Base Orçado 2026'!K14 -> 72235.548 | Y12: ='04 -Base Orçado 2026'!L14 -> 75847.325 | AB12: ='04 -Base Orçado 2026'!M14 -> 79639.692 | AE12: ='04 -Base Orçado 2026'!N14 -> 83621.676 | AH12: ='04 -Base Orçado 2026'!O14 -> 84457.893 | AK12: ='04 -Base Orçado 2026'!P14 -> 80234.998 | AN12: =SUM(D12,G12,J12,M12,P12,S12,V12,Y12,AB12,AE12,AH12,AK12) -> 875584.03 | AO12: =SUM(E12,H12,K12,N12,Q12,T12,W12,Z12,AC12,AF12,AI12,AL12) -> 46298.46 | AQ12: =AN12/12 -> 72965.336 | AR12: =AO12/AT12 -> 15432.82 | AT12: =COUNTA(E12,H12,K12,N12,Q12,T12,W12,Z12,AC12,AF12,AI12,AL12) -> 3
A13: Cartão de Débito/ Crédito | C13: =SUM(D13,G13,J13,M13,P13,S13,V13,Y13,AB13,AE13,AH13,AK13) -> 4267920.2 | D13: ='04 -Base Orçado 2026'!E15 -> 190000 | E13: ='01 Base Realizado'!D14 -> 205020.47 | G13: ='04 -Base Orçado 2026'!F15 -> 262500 | H13: ='01 Base Realizado'!F14 -> 243655.88 | J13: ='04 -Base Orçado 2026'!G15 -> 315000 | K13: ='01 Base Realizado'!H14 -> 378808.76 | M13: ='04 -Base Orçado 2026'!H15 -> 346500 | P13: ='04 -Base Orçado 2026'!I15 -> 381150 | S13: ='04 -Base Orçado 2026'!J15 -> 392584.5 | V13: ='04 -Base Orçado 2026'!K15 -> 361177.74 | Y13: ='04 -Base Orçado 2026'!L15 -> 379236.63 | AB13: ='04 -Base Orçado 2026'!M15 -> 398198.46 | AE13: ='04 -Base Orçado 2026'!N15 -> 418108.38 | AH13: ='04 -Base Orçado 2026'!O15 -> 422289.47 | AK13: ='04 -Base Orçado 2026'!P15 -> 401174.99 | AN13: =SUM(D13,G13,J13,M13,P13,S13,V13,Y13,AB13,AE13,AH13,AK13) -> 4267920.2 | AO13: =SUM(E13,H13,K13,N13,Q13,T13,W13,Z13,AC13,AF13,AI13,AL13) -> 827485.11 | AQ13: =AN13/12 -> 355660.01 | AR13: =AO13/AT13 -> 275828.37 | AT13: =COUNTA(E13,H13,K13,N13,Q13,T13,W13,Z13,AC13,AF13,AI13,AL13) -> 3
A14: Evento Faturado | C14: =SUM(D14,G14,J14,M14,P14,S14,V14,Y14,AB14,AE14,AH14,AK14) -> 40000 | D14: ='04 -Base Orçado 2026'!E17 -> 40000 | E14: ='01 Base Realizado'!D15 -> 0 | G14: ='04 -Base Orçado 2026'!F16 -> 0 | J14: ='04 -Base Orçado 2026'!G16 -> 0 | M14: ='04 -Base Orçado 2026'!H16 -> 0 | P14: ='04 -Base Orçado 2026'!I16 -> 0 | S14: ='04 -Base Orçado 2026'!J16 -> 0 | V14: ='04 -Base Orçado 2026'!K16 -> 0 | Y14: ='04 -Base Orçado 2026'!L16 -> 0 | AB14: ='04 -Base Orçado 2026'!M16 -> 0 | AE14: ='04 -Base Orçado 2026'!N16 -> 0 | AH14: ='04 -Base Orçado 2026'!O16 -> 0 | AK14: ='04 -Base Orçado 2026'!P16 -> 0 | AN14: =SUM(D14,G14,J14,M14,P14,S14,V14,Y14,AB14,AE14,AH14,AK14) -> 40000 | AO14: =SUM(E14,H14,K14,N14,Q14,T14,W14,Z14,AC14,AF14,AI14,AL14) -> 0 | AQ14: =AN14/12 -> 3333.3333 | AR14: =AO14/AT14 -> 0 | AT14: =COUNTA(E14,H14,K14,N14,Q14,T14,W14,Z14,AC14,AF14,AI14,AL14) -> 1
A15: Delivery | C15: =SUM(D15,G15,J15,M15,P15,S15,V15,Y15,AB15,AE15,AH15,AK15) -> 543722.69 | D15: 0 | E15: ='01 Base Realizado'!D15 -> 0 | G15: ='04 -Base Orçado 2026'!F17 -> 35000 | J15: ='04 -Base Orçado 2026'!G17 -> 42000 | M15: ='04 -Base Orçado 2026'!H17 -> 46200 | P15: ='04 -Base Orçado 2026'!I17 -> 50820 | S15: ='04 -Base Orçado 2026'!J17 -> 52344.6 | V15: ='04 -Base Orçado 2026'!K17 -> 48157.032 | Y15: ='04 -Base Orçado 2026'!L17 -> 50564.884 | AB15: ='04 -Base Orçado 2026'!M17 -> 53093.128 | AE15: ='04 -Base Orçado 2026'!N17 -> 55747.784 | AH15: ='04 -Base Orçado 2026'!O17 -> 56305.262 | AK15: ='04 -Base Orçado 2026'!P17 -> 53489.999 | AN15: =SUM(D15,G15,J15,M15,P15,S15,V15,Y15,AB15,AE15,AH15,AK15) -> 543722.69 | AO15: =SUM(E15,H15,K15,N15,Q15,T15,W15,Z15,AC15,AF15,AI15,AL15) -> 0 | AQ15: =AN15/12 -> 45310.224 | AR15: =AO15/AT15 -> 0 | AT15: =COUNTA(E15,H15,K15,N15,Q15,T15,W15,Z15,AC15,AF15,AI15,AL15) -> 1
A16: Voucher | C16: =SUM(D16,G16,J16,M16,P16,S16,V16,Y16,AB16,AE16,AH16,AK16) -> 0 | D16: ='04 -Base Orçado 2026'!E18 -> 0 | G16: ='04 -Base Orçado 2026'!F18 -> 0 | J16: ='04 -Base Orçado 2026'!G18 -> 0 | M16: ='04 -Base Orçado 2026'!H18 -> 0 | P16: ='04 -Base Orçado 2026'!I18 -> 0 | S16: ='04 -Base Orçado 2026'!J18 -> 0 | V16: ='04 -Base Orçado 2026'!K18 -> 0 | Y16: ='04 -Base Orçado 2026'!L18 -> 0 | AB16: ='04 -Base Orçado 2026'!M18 -> 0 | AE16: ='04 -Base Orçado 2026'!N18 -> 0 | AH16: ='04 -Base Orçado 2026'!O18 -> 0 | AK16: ='04 -Base Orçado 2026'!P18 -> 0 | AN16: =SUM(D16,G16,J16,M16,P16,S16,V16,Y16,AB16,AE16,AH16,AK16) -> 0 | AO16: =SUM(E16,H16,K16,N16,Q16,T16,W16,Z16,AC16,AF16,AI16,AL16) -> 0 | AQ16: =AN16/12 -> 0 | AR16: =IFERROR(AO16/AT16,"") | AT16: =COUNTA(E16,H16,K16,N16,Q16,T16,W16,Z16,AC16,AF16,AI16,AL16) -> 0
A18: Impostos sobre Vendas | C18: =SUM(D18,G18,J18,M18,P18,S18,V18,Y18,AB18,AE18,AH18,AK18) -> -28800 | D18: =SUM(D19:D22) -> -1900 | E18: =SUM(E19:E22) -> -461.04 | G18: =SUM(G19:G22) -> -1900 | H18: =SUM(H19:H22) -> -819.32 | J18: =SUM(J19:J22) -> -3900 | K18: =SUM(K19:K22) -> -2604.39 | M18: =SUM(M19:M22) -> -1900 | P18: =SUM(P19:P22) -> -1900 | S18: =SUM(S19:S22) -> -1900 | V18: =SUM(V19:V22) -> -3900 | Y18: =SUM(Y19:Y22) -> -1900 | AB18: =SUM(AB19:AB22) -> -1900 | AE18: =SUM(AE19:AE22) -> -1900 | AH18: =SUM(AH19:AH22) -> -3900 | AK18: =SUM(AK19:AK22) -> -1900 | AN18: =SUM(D18,G18,J18,M18,P18,S18,V18,Y18,AB18,AE18,AH18,AK18) -> -28800 | AO18: =SUM(E18,H18,K18,N18,Q18,T18,W18,Z18,AC18,AF18,AI18,AL18) -> -3884.75 | AQ18: =AN18/12 -> -2400 | AR18: =AO18/12 -> -323.72917 | AT18: =SUM(AT19:AT22) -> -0.0050540264 | AV18: =SUM(AV19:AV22) -> -0.0065949323 | AW18: =SUM(AW19:AW22) -> -0.0054582017 | AX18: =SUM(AX19:AX22) -> -0.0093727469 | AY18: =SUM(AY19:AY22) -> -0.0041295371 | AZ18: =SUM(AZ19:AZ22) -> -0.0037527158 | BA18: =SUM(BA19:BA22) -> -0.0036430152 | BB18: =SUM(BB19:BB22) -> -0.008164627 | BC18: =SUM(BC19:BC22) -> -0.0037717209 | ... BG18: =SUM(BG19:BG22) -> -0.003564728
A19: ICMS | C19: =SUM(D19,G19,J19,M19,P19,S19,V19,Y19,AB19,AE19,AH19,AK19) -> -12000 | D19: ='04 -Base Orçado 2026'!E22 -> -1000 | E19: ='01 Base Realizado'!D20 -> -461.04 | G19: ='04 -Base Orçado 2026'!F22 -> -1000 | H19: ='01 Base Realizado'!F20 -> 0 | J19: ='04 -Base Orçado 2026'!G22 -> -1000 | K19: ='01 Base Realizado'!H20 -> 0 | M19: ='04 -Base Orçado 2026'!H22 -> -1000 | P19: ='04 -Base Orçado 2026'!I22 -> -1000 | S19: ='04 -Base Orçado 2026'!J22 -> -1000 | V19: ='04 -Base Orçado 2026'!K22 -> -1000 | Y19: ='04 -Base Orçado 2026'!L22 -> -1000 | AB19: ='04 -Base Orçado 2026'!M22 -> -1000 | AE19: ='04 -Base Orçado 2026'!N22 -> -1000 | AH19: ='04 -Base Orçado 2026'!O22 -> -1000 | AK19: ='04 -Base Orçado 2026'!P22 -> -1000 | AN19: =SUM(D19,G19,J19,M19,P19,S19,V19,Y19,AB19,AE19,AH19,AK19) -> -12000 | AO19: =SUM(E19,H19,K19,N19,Q19,T19,W19,Z19,AC19,AF19,AI19,AL19) -> -461.04 | AQ19: =AN19/12 -> -1000 | AT19: =IF(ISERROR(C19/C$23),0,(C19/C$23)) -> -0.0021058443 | AV19: =IF(ISERROR(D19/D$23),0,(D19/D$23)) -> -0.003471017 | AW19: =IF(ISERROR(G19/G$23),0,(G19/G$23)) -> -0.0028727377 | AX19: =IF(ISERROR(J19/J$23),0,(J19/J$23)) -> -0.0024032684 | AY19: =IF(ISERROR(M19/M$23),0,(M19/M$23)) -> -0.0021734406 | AZ19: =IF(ISERROR(P19/P$23),0,(P19/P$23)) -> -0.0019751136 | BA19: =IF(ISERROR(S19/S$23),0,(S19/S$23)) -> -0.0019173764 | BB19: =IF(ISERROR(V19/V$23),0,(V19/V$23)) -> -0.0020934941 | BC19: =IF(ISERROR(Y19/Y$23),0,(Y19/Y$23)) -> -0.0019851162 | BD19: =IF(ISERROR(AB19/AB$23),0,(AB19/AB$23)) -> -0.0018902474 | BE19: =IF(ISERROR(AE19/AE$23),0,(AE19/AE$23)) -> -0.0017999278 | BF19: =IF(ISERROR(AH19/AH$23),0,(AH19/AH$23)) -> -0.0017884205 | BG19: =IF(ISERROR(AK19/AK$23),0,(AK19/AK$23)) -> -0.0018761726
A20: PIS/COFINS | C20: =SUM(D20,G20,J20,M20,P20,S20,V20,Y20,AB20,AE20,AH20,AK20) -> -10800 | D20: ='04 -Base Orçado 2026'!E23 -> -900 | E20: ='01 Base Realizado'!D21 -> 0 | G20: ='04 -Base Orçado 2026'!F23 -> -900 | H20: ='01 Base Realizado'!F21 -> -819.32 | J20: ='04 -Base Orçado 2026'!G23 -> -900 | K20: ='01 Base Realizado'!H21 -> -929.52 | M20: ='04 -Base Orçado 2026'!H23 -> -900 | P20: ='04 -Base Orçado 2026'!I23 -> -900 | S20: ='04 -Base Orçado 2026'!J23 -> -900 | V20: ='04 -Base Orçado 2026'!K23 -> -900 | Y20: ='04 -Base Orçado 2026'!L23 -> -900 | AB20: ='04 -Base Orçado 2026'!M23 -> -900 | AE20: ='04 -Base Orçado 2026'!N23 -> -900 | AH20: ='04 -Base Orçado 2026'!O23 -> -900 | AK20: ='04 -Base Orçado 2026'!P23 -> -900 | AN20: =SUM(D20,G20,J20,M20,P20,S20,V20,Y20,AB20,AE20,AH20,AK20) -> -10800 | AO20: =SUM(E20,H20,K20,N20,Q20,T20,W20,Z20,AC20,AF20,AI20,AL20) -> -1748.84 | AQ20: =AN20/12 -> -900 | AT20: =IF(ISERROR(C20/C$23),0,(C20/C$23)) -> -0.0018952599 | AV20: =IF(ISERROR(D20/D$23),0,(D20/D$23)) -> -0.0031239153 | AW20: =IF(ISERROR(G20/G$23),0,(G20/G$23)) -> -0.0025854639 | AX20: =IF(ISERROR(J20/J$23),0,(J20/J$23)) -> -0.0021629416 | AY20: =IF(ISERROR(M20/M$23),0,(M20/M$23)) -> -0.0019560965 | AZ20: =IF(ISERROR(P20/P$23),0,(P20/P$23)) -> -0.0017776022 | BA20: =IF(ISERROR(S20/S$23),0,(S20/S$23)) -> -0.0017256388 | BB20: =IF(ISERROR(V20/V$23),0,(V20/V$23)) -> -0.0018841447 | BC20: =IF(ISERROR(Y20/Y$23),0,(Y20/Y$23)) -> -0.0017866046 | BD20: =IF(ISERROR(AB20/AB$23),0,(AB20/AB$23)) -> -0.0017012227 | BE20: =IF(ISERROR(AE20/AE$23),0,(AE20/AE$23)) -> -0.001619935 | BF20: =IF(ISERROR(AH20/AH$23),0,(AH20/AH$23)) -> -0.0016095784 | BG20: =IF(ISERROR(AK20/AK$23),0,(AK20/AK$23)) -> -0.0016885554
A21: IRPJ/CSLL | C21: =SUM(D21,G21,J21,M21,P21,S21,V21,Y21,AB21,AE21,AH21,AK21) -> -6000 | D21: ='04 -Base Orçado 2026'!E24 -> 0 | E21: ='01 Base Realizado'!D22 -> 0 | G21: 0 | J21: ='04 -Base Orçado 2026'!G28 -> -2000 | K21: ='01 Base Realizado'!H24 -> -1674.87 | M21: ='04 -Base Orçado 2026'!H24 -> 0 | P21: ='04 -Base Orçado 2026'!I24 -> 0 | S21: ='04 -Base Orçado 2026'!J24 -> 0 | V21: ='04 -Base Orçado 2026'!K28 -> -2000 | Y21: ='04 -Base Orçado 2026'!L24 -> 0 | AB21: ='04 -Base Orçado 2026'!M24 -> 0 | AE21: ='04 -Base Orçado 2026'!N24 -> 0 | AH21: ='04 -Base Orçado 2026'!O28 -> -2000 | AK21: ='04 -Base Orçado 2026'!P24 -> 0 | AN21: =SUM(D21,G21,J21,M21,P21,S21,V21,Y21,AB21,AE21,AH21,AK21) -> -6000 | AO21: =SUM(E21,H21,K21,N21,Q21,T21,W21,Z21,AC21,AF21,AI21,AL21) -> -1674.87 | AQ21: =AN21/12 -> -500 | AT21: =IF(ISERROR(C21/C$23),0,(C21/C$23)) -> -0.0010529222 | AV21: =IF(ISERROR(D21/D$23),0,(D21/D$23)) -> 0 | AW21: =IF(ISERROR(G21/G$23),0,(G21/G$23)) -> 0 | AX21: =IF(ISERROR(J21/J$23),0,(J21/J$23)) -> -0.0048065369 | AY21: =IF(ISERROR(M21/M$23),0,(M21/M$23)) -> 0 | AZ21: =IF(ISERROR(P21/P$23),0,(P21/P$23)) -> 0 | BA21: =IF(ISERROR(S21/S$23),0,(S21/S$23)) -> 0 | BB21: =IF(ISERROR(V21/V$23),0,(V21/V$23)) -> -0.0041869882 | BC21: =IF(ISERROR(Y21/Y$23),0,(Y21/Y$23)) -> 0 | BD21: =IF(ISERROR(AB21/AB$23),0,(AB21/AB$23)) -> 0 | BE21: =IF(ISERROR(AE21/AE$23),0,(AE21/AE$23)) -> 0 | BF21: =IF(ISERROR(AH21/AH$23),0,(AH21/AH$23)) -> -0.003576841 | BG21: =IF(ISERROR(AK21/AK$23),0,(AK21/AK$23)) -> 0
C22: =SUM(D22,G22,J22,M22,P22,S22,V22,Y22,AB22,AE22,AH22,AK22) -> 0
A23: Receita Líquida | C23: =SUM(D23,G23,J23,M23,P23,S23,V23,Y23,AB23,AE23,AH23,AK23) -> 5698426.9 | D23: =D10+D18 -> 288100 | E23: =E10+E18 -> 211153.17 | G23: =G10+G18 -> 348100 | H23: =H10+H18 -> 259364.15 | J23: =J10+J18 -> 416100 | K23: =K10+K18 -> 399381.5 | M23: =M10+M18 -> 460100 | P23: =P10+P18 -> 506300 | S23: =S10+S18 -> 521546 | V23: =V10+V18 -> 477670.32 | Y23: =Y10+Y18 -> 503748.84 | AB23: =AB10+AB18 -> 529031.28 | AE23: =AE10+AE18 -> 555577.84 | AH23: =AH10+AH18 -> 559152.62 | AK23: =AK10+AK18 -> 532999.99 | AN23: =SUM(D23,G23,J23,M23,P23,S23,V23,Y23,AB23,AE23,AH23,AK23) -> 5698426.9 | AO23: =SUM(E23,H23,K23,N23,Q23,T23,W23,Z23,AC23,AF23,AI23,AL23) -> 869898.82 | AQ23: =AN23/12 -> 474868.91 | AR23: =AO23/12 -> 72491.568 | AT23: =C23/C10 -> 0.99497139
C24: =SUM(D24,G24,J24,M24,P24,S24,V24,Y24,AB24,AE24,AH24,AK24) -> 0 | AN24: =SUM(D24:AK24) -> 0 | AQ24: =AN24/12 -> 0
A25: CUSTOS/DESPESAS | C25: =SUM(D25,G25,J25,M25,P25,S25,V25,Y25,AB25,AE25,AH25,AK25) -> -2262049.1 | D25: =SUM(,D27,D36,D41,D42,D43,D44) -> -239826.04 | E25: =SUM(,E27,E36,E41,E42,E43,E44) -> -174956.31 | G25: =SUM(,G27,G36,G41,G42,G43,G44) -> -259374.26 | H25: =SUM(,H27,H36,H41,H42,H43,H44) -> -219270.65 | J25: =SUM(,J27,J36,J41,J42,J43,J44) -> -290202.86 | K25: =SUM(,K27,K36,K41,K42,K43,K44) -> -273180.83 | M25: =SUM(M33:M44) -> -157386.47 | P25: =SUM(P33:P44) -> -162482.33 | S25: =SUM(S33:S44) -> -164163.97 | V25: =SUM(V33:V44) -> -159545.08 | Y25: =SUM(Y33:Y44) -> -162200.94 | AB25: =SUM(AB33:AB44) -> -164989.59 | AE25: =SUM(AE33:AE44) -> -167917.68 | AH25: =SUM(AH33:AH44) -> -168532.58 | AK25: =SUM(AK33:AK44) -> -165427.34 | AN25: =SUM(D25,G25,J25,M25,P25,S25,V25,Y25,AB25,AE25,AH25,AK25) -> -2262049.1 | AO25: =SUM(E25,H25,K25,N25,Q25,T25,W25,Z25,AC25,AF25,AI25,AL25) -> -667407.79 | AQ25: =AN25/12 -> -188504.09 | AR25: =AO25/$AT$12 -> -222469.26 | AT25: =SUM(AT27,AT36,AT41,AT42,AT43,AT44) -> -0.33764847 | AV25: =SUM(AV33:AV43) -> -0.47992568 | AW25: =SUM(AW33:AW43) -> -0.40352744 | AX25: =SUM(AX33:AX43) -> -0.3576056 | AY25: =SUM(AY33:AY43) -> -0.32363206 | AZ25: =SUM(AZ33:AZ43) -> -0.30416546 | BA25: =SUM(BA33:BA43) -> -0.29849832 | BB25: =SUM(BB33:BB43) -> -0.31624681 | BC25: =SUM(BC33:BC43) -> -0.30514726 | ... BG25: =SUM(BG33:BG43) -> -0.294454 | BH25: BD | BI25: REAL Jan | BK25: BD | BL25: REAL Fev | BN25: BD | BO25: REAL Mar
C26: =SUM(D26,G26,J26,M26,P26,S26,V26,Y26,AB26,AE26,AH26,AK26) -> 0 | AN26: =SUM(D26:AK26) -> 0 | AQ26: =AN26/12 -> 0
A27: CMV | C27: =SUM(D27,G27,J27,M27,P27,S27,V27,Y27,AB27,AE27,AH27,AK27) -> 1150056.6 | D27: ='04 -Base Orçado 2026'!E40 -> -92800 | E27: =-SUM(E28:E34) -> -43768.202 | G27: ='04 -Base Orçado 2026'!F40 -> -111392 | H27: =-SUM(H28:H34) -> -78640.862 | J27: ='04 -Base Orçado 2026'!G40 -> -133792 | K27: =-SUM(K28:K34) -> -85602.456 | M27: =-'04 -Base Orçado 2026'!H40 -> 147232 | P27: =-'04 -Base Orçado 2026'!I40 -> 162016 | S27: =-'04 -Base Orçado 2026'!J40 -> 166894.72 | V27: =-'04 -Base Orçado 2026'!K40 -> 153494.5 | Y27: =-'04 -Base Orçado 2026'!L40 -> 161199.63 | AB27: =-'04 -Base Orçado 2026'!M40 -> 169290.01 | AE27: =-'04 -Base Orçado 2026'!N40 -> 177784.91 | AH27: =-'04 -Base Orçado 2026'!O40 -> 179568.84 | AK27: =-'04 -Base Orçado 2026'!P40 -> 170560 | AN27: =SUM(D27,G27,J27,M27,P27,S27,V27,Y27,AB27,AE27,AH27,AK27) -> 1150056.6 | AO27: =SUM(E27,H27,K27,N27,Q27,T27,W27,Z27,AC27,AF27,AI27,AL27) -> -208011.52 | AQ27: =AN27/12 -> 95838.05 | AR27: =AO27/$AT$12 -> -69337.173 | AT27: =SUM(AT33:AT34) -> 0 | AV27: =SUM(AV33:AV34) -> 0 | AW27: =SUM(AW33:AW34) -> 0 | AX27: =SUM(AX33:AX34) -> 0 | AY27: =SUM(AY33:AY34) -> 0 | AZ27: =SUM(AZ33:AZ34) -> 0 | BA27: =SUM(BA33:BA34) -> 0 | BB27: =SUM(BB33:BB34) -> 0 | BC27: =SUM(BC33:BC34) -> 0 | ... BG27: =SUM(BG33:BG34) -> 0 | BH27: =D27/$D$23 -> -0.32211038 | BI27: =E27/$E$23 -> -0.20728177 | BK27: =G27/$G$23 -> -0.32 | BL27: =H27/$H$23 -> -0.30320637 | BN27: =J27/$J$23 -> -0.32153809 | BO27: =K27/$K$23 -> -0.21433756
A28: Estoque Inicial | D28: ='04 -Base Orçado 2026'!E31 -> 0 | E28: ='01 Base Realizado'!D29 -> 141723.27 | H28: ='01 Base Realizado'!F29 -> 127034.79 | K28: ='01 Base Realizado'!H29 -> 122710.94 | BN28: =J28/$J$23 -> 0 | BO28: =K28/$K$23 -> 0.30725245
A29: Compra Mês | D29: ='04 -Base Orçado 2026'!E32 -> 0 | E29: ='01 Base Realizado'!D30 -> 27342.98 | H29: ='01 Base Realizado'!F30 -> 61684.24 | K29: ='01 Base Realizado'!H30 -> 91589.48 | BN29: =J29/$J$23 -> 0 | BO29: =K29/$K$23 -> 0.2293283
A30: Estoque Final | D30: ='04 -Base Orçado 2026'!E33 -> 0 | E30: ='01 Base Realizado'!D33 -> -127034.79 | H30: ='01 Base Realizado'!F31 -> 8902.82 | K30: ='01 Base Realizado'!H31 -> 9675.06 | BN30: =J30/$J$23 -> 0 | BO30: =K30/$K$23 -> 0.024225108
A31: Transferência de Estoque Entrada | D31: ='04 -Base Orçado 2026'!E34 -> 0 | E31: 0 | H31: ='01 Base Realizado'!F32 -> -1110.51 | K31: ='01 Base Realizado'!H32 -> -98.85 | BN31: =J31/$J$23 -> 0 | BO31: =K31/$K$23 -> -0.00024750771
A32: Transferência de Estoque Saída | E32: 0 | H32: ='01 Base Realizado'!F33 -> -122710.94 | K32: ='01 Base Realizado'!H33 -> -142103.99 | BN32: =J32/$J$23 -> 0 | BO32: =K32/$K$23 -> -0.35581014
A33: Bonificações | C33: =SUM(D33,G33,J33,M33,P33,S33,V33,Y33,AB33,AE33,AH33,AK33) -> 0 | D33: ='04 -Base Orçado 2026'!E35 -> 0 | E33: ='01 Base Realizado'!D34 -> 0 | H33: ='01 Base Realizado'!F34 -> 0 | K33: ='01 Base Realizado'!H34 -> 0 | AN33: =SUM(D33:AK33) -> 0 | AQ33: =AN33/12 -> 0 | AR33: =AO33/$AT$12 -> 0 | AT33: =IF(ISERROR(C33/C$23),0,(C33/C$23)) -> 0 | AV33: =IF(ISERROR(D33/D$23),0,(D33/D$23)) -> 0 | AW33: =IF(ISERROR(G33/G$23),0,(G33/G$23)) -> 0 | AX33: =IF(ISERROR(J33/J$23),0,(J33/J$23)) -> 0 | AY33: =IF(ISERROR(M33/M$23),0,(M33/M$23)) -> 0 | AZ33: =IF(ISERROR(P33/P$23),0,(P33/P$23)) -> 0 | BA33: =IF(ISERROR(S33/S$23),0,(S33/S$23)) -> 0 | BB33: =IF(ISERROR(V33/V$23),0,(V33/V$23)) -> 0 | BC33: =IF(ISERROR(Y33/Y$23),0,(Y33/Y$23)) -> 0 | BD33: =IF(ISERROR(AB33/AB$23),0,(AB33/AB$23)) -> 0 | BE33: =IF(ISERROR(AE33/AE$23),0,(AE33/AE$23)) -> 0 | BF33: =IF(ISERROR(AH33/AH$23),0,(AH33/AH$23)) -> 0 | BG33: =IF(ISERROR(AK33/AK$23),0,(AK33/AK$23)) -> 0 | BH33: =D33/$D$23 -> 0 | BK33: =F33/$G$23 -> 0 | BN33: =J33/$J$23 -> 0 | BO33: =K33/$K$23 -> 0
A34: (-) Reclassificação CMV | C34: =SUM(D34,G34,J34,M34,P34,S34,V34,Y34,AB34,AE34,AH34,AK34) -> 0 | D34: ='04 -Base Orçado 2026'!E36 -> 0 | E34: ='01 Base Realizado'!D35 -> 1736.74 | H34: ='01 Base Realizado'!F35 -> 4840.47 | K34: ='01 Base Realizado'!H35 -> 3829.81 | AN34: =SUM(D34:AK34) -> 10407.02 | AQ34: =AN34/12 -> 867.25167 | AR34: =AO34/$AT$12 -> 0 | AT34: =IF(ISERROR(C34/C$23),0,(C34/C$23)) -> 0 | AV34: =IF(ISERROR(D34/D$23),0,(D34/D$23)) -> 0 | AW34: =IF(ISERROR(G34/G$23),0,(G34/G$23)) -> 0 | AX34: =IF(ISERROR(J34/J$23),0,(J34/J$23)) -> 0 | AY34: =IF(ISERROR(M34/M$23),0,(M34/M$23)) -> 0 | AZ34: =IF(ISERROR(P34/P$23),0,(P34/P$23)) -> 0 | BA34: =IF(ISERROR(S34/S$23),0,(S34/S$23)) -> 0 | BB34: =IF(ISERROR(V34/V$23),0,(V34/V$23)) -> 0 | BC34: =IF(ISERROR(Y34/Y$23),0,(Y34/Y$23)) -> 0 | BD34: =IF(ISERROR(AB34/AB$23),0,(AB34/AB$23)) -> 0 | BE34: =IF(ISERROR(AE34/AE$23),0,(AE34/AE$23)) -> 0 | BF34: =IF(ISERROR(AH34/AH$23),0,(AH34/AH$23)) -> 0 | BG34: =IF(ISERROR(AK34/AK$23),0,(AK34/AK$23)) -> 0 | BH34: =D34/$D$23 -> 0 | BK34: =F34/$G$23 -> 0 | BN34: =J34/$J$23 -> 0 | BO34: =K34/$K$23 -> 0.0095893525
C35: =SUM(D35,G35,J35,M35,P35,S35,V35,Y35,AB35,AE35,AH35,AK35) -> 0 | AN35: =SUM(D35:AK35) -> 0 | AO35: =SUM(E35,H35,K35,N35,Q35,T35,W35,Z35,AC35,AF35,AI35,AL35) -> 0 | AQ35: =AN35/12 -> 0 | AR35: =AO35/$AT$12 -> 0
A36: Pessoal | C36: =SUM(D36,G36,J36,M36,P36,S36,V36,Y36,AB36,AE36,AH36,AK36) -> -803529.37 | D36: =SUM(D37:D39) -> -68369.177 | E36: =SUM(E37:E39) -> -50083.16 | G36: ='04 -Base Orçado 2026'!F42 -> -56996.772 | H36: =SUM(H37:H39) -> -44395.31 | J36: ='04 -Base Orçado 2026'!G42 -> -63907.562 | K36: =SUM(K37:K39) -> -61583.06 | M36: ='04 -Base Orçado 2026'!H42 -> -63158.382 | P36: ='04 -Base Orçado 2026'!I42 -> -67316.382 | S36: ='04 -Base Orçado 2026'!J42 -> -68688.522 | V36: ='04 -Base Orçado 2026'!K42 -> -64919.711 | Y36: ='04 -Base Orçado 2026'!L42 -> -67086.777 | AB36: ='04 -Base Orçado 2026'!M42 -> -69362.197 | AE36: ='04 -Base Orçado 2026'!N42 -> -71751.388 | AH36: ='04 -Base Orçado 2026'!O42 -> -72253.118 | AK36: ='04 -Base Orçado 2026'!P42 -> -69719.381 | AN36: =SUM(D36,G36,J36,M36,P36,S36,V36,Y36,AB36,AE36,AH36,AK36) -> -803529.37 | AO36: =SUM(E36,H36,K36,N36,Q36,T36,W36,Z36,AC36,AF36,AI36,AL36) -> -156061.53 | AQ36: =AN36/12 -> -66960.781 | AR36: =AO36/$AT$12 -> -52020.51 | AT36: =IF(ISERROR(C36/C$23),0,(C36/C$23)) -> -0.14100898 | AV36: =IF(ISERROR(D36/D$23),0,(D36/D$23)) -> -0.23731058 | AW36: =IF(ISERROR(G36/G$23),0,(G36/G$23)) -> -0.16373678 | AX36: =IF(ISERROR(J36/J$23),0,(J36/J$23)) -> -0.15358703 | AY36: =IF(ISERROR(M36/M$23),0,(M36/M$23)) -> -0.13727099 | AZ36: =IF(ISERROR(P36/P$23),0,(P36/P$23)) -> -0.1329575 | BA36: =IF(ISERROR(S36/S$23),0,(S36/S$23)) -> -0.13170175 | BB36: =IF(ISERROR(V36/V$23),0,(V36/V$23)) -> -0.13590903 | BC36: =IF(ISERROR(Y36/Y$23),0,(Y36/Y$23)) -> -0.13317505 | BD36: =IF(ISERROR(AB36/AB$23),0,(AB36/AB$23)) -> -0.13111171 | BE36: =IF(ISERROR(AE36/AE$23),0,(AE36/AE$23)) -> -0.12914732 | BF36: =IF(ISERROR(AH36/AH$23),0,(AH36/AH$23)) -> -0.12921896 | BG36: =IF(ISERROR(AK36/AK$23),0,(AK36/AK$23)) -> -0.1308056 | BH36: =D36/$D$23 -> -0.23731058 | BI36: =E36/$E$23 -> -0.23718877 | BK36: =G36/$G$23 -> -0.16373678 | BL36: =H36/$H$23 -> -0.1711698 | BN36: =J36/$J$23 -> -0.15358703 | BO36: =K36/$K$23 -> -0.15419608
A37: Salários e Encargos | C37: =SUM(D37,G37,J37,M37,P37,S37,V37,Y37,AB37,AE37,AH37,AK37) -> -123365.95 | D37: =SUM('04 -Base Orçado 2026'!E43:E58) -> -68369.177 | E37: =SUM('01 Base Realizado'!D42:D58) -> -50083.16 | G37: =SUM('04 -Base Orçado 2026'!F43:F58) -> -54996.772 | H37: ='01 Base Realizado'!F41 -> -44395.31 | K37: ='01 Base Realizado'!H41 -> -61583.06 | AR37: =AO37/$AT$12 -> 0 | BH37: =D37/$D$23 -> -0.23731058 | BK37: =G37/$G$23 -> -0.1579913 | BL37: =H37/$H$23 -> -0.1711698 | BN37: =J37/$J$23 -> 0 | BO37: =K37/$K$23 -> -0.15419608
A38: Gorjetas Recebidas | C38: =SUM(D38,G38,J38,M38,P38,S38,V38,Y38,AB38,AE38,AH38,AK38) -> 0 | D38: ='04 -Base Orçado 2026'!E59 -> 0 | E38: ='01 Base Realizado'!D59 -> 0 | AR38: =AO38/$AT$12 -> 0 | BH38: =D38/$D$23 -> 0 | BK38: =G38/$G$23 -> 0 | BL38: =H38/$H$23 -> 0 | BN38: =J38/$J$23 -> 0 | BO38: =K38/$K$23 -> 0
A39: Gorjetas Pagas | C39: =SUM(D39,G39,J39,M39,P39,S39,V39,Y39,AB39,AE39,AH39,AK39) -> 0 | D39: ='04 -Base Orçado 2026'!E60 -> 0 | E39: ='01 Base Realizado'!D60 -> 0 | AR39: =AO39/$AT$12 -> 0 | BH39: =D39/$D$23 -> 0 | BK39: =G39/$G$23 -> 0 | BL39: =H39/$H$23 -> 0 | BN39: =J39/$J$23 -> 0 | BO39: =K39/$K$23 -> 0
C40: =SUM(D40,G40,J40,M40,P40,S40,V40,Y40,AB40,AE40,AH40,AK40) -> 0 | E40: ='01 Base Realizado'!D61 -> 0 | H40: ='01 Base Realizado'!J61 -> 0 | K40: ='01 Base Realizado'!M61 -> 0 | AR40: =AO40/$AT$12 -> 0
A41: Ocupação | C41: =SUM(D41,G41,J41,M41,P41,S41,V41,Y41,AB41,AE41,AH41,AK41) -> -225600 | D41: ='04 -Base Orçado 2026'!E67 -> -18800 | E41: ='01 Base Realizado'!D67 -> -23800 | G41: ='04 -Base Orçado 2026'!F67 -> -18800 | H41: ='01 Base Realizado'!F67 -> -23800 | J41: ='04 -Base Orçado 2026'!G67 -> -18800 | K41: ='01 Base Realizado'!H67 -> -23800 | M41: ='04 -Base Orçado 2026'!H67 -> -18800 | P41: ='04 -Base Orçado 2026'!I67 -> -18800 | S41: ='04 -Base Orçado 2026'!J67 -> -18800 | V41: ='04 -Base Orçado 2026'!K67 -> -18800 | Y41: ='04 -Base Orçado 2026'!L67 -> -18800 | AB41: ='04 -Base Orçado 2026'!M67 -> -18800 | AE41: ='04 -Base Orçado 2026'!N67 -> -18800 | AH41: ='04 -Base Orçado 2026'!O67 -> -18800 | AK41: ='04 -Base Orçado 2026'!P67 -> -18800 | AN41: =SUM(D41,G41,J41,M41,P41,S41,V41,Y41,AB41,AE41,AH41,AK41) -> -225600 | AO41: =SUM(E41,H41,K41,N41,Q41,T41,W41,Z41,AC41,AF41,AI41,AL41) -> -71400 | AQ41: =AN41/12 -> -18800 | AR41: =AO41/$AT$12 -> -23800 | AT41: =IF(ISERROR(C41/C$23),0,(C41/C$23)) -> -0.039589874 | AV41: =IF(ISERROR(D41/D$23),0,(D41/D$23)) -> -0.06525512 | AW41: =IF(ISERROR(G41/G$23),0,(G41/G$23)) -> -0.054007469 | AX41: =IF(ISERROR(J41/J$23),0,(J41/J$23)) -> -0.045181447 | AY41: =IF(ISERROR(M41/M$23),0,(M41/M$23)) -> -0.040860682 | AZ41: =IF(ISERROR(P41/P$23),0,(P41/P$23)) -> -0.037132135 | BA41: =IF(ISERROR(S41/S$23),0,(S41/S$23)) -> -0.036046677 | BB41: =IF(ISERROR(V41/V$23),0,(V41/V$23)) -> -0.039357689 | BC41: =IF(ISERROR(Y41/Y$23),0,(Y41/Y$23)) -> -0.037320185 | BD41: =IF(ISERROR(AB41/AB$23),0,(AB41/AB$23)) -> -0.035536651 | BE41: =IF(ISERROR(AE41/AE$23),0,(AE41/AE$23)) -> -0.033838643 | BF41: =IF(ISERROR(AH41/AH$23),0,(AH41/AH$23)) -> -0.033622305 | BG41: =IF(ISERROR(AK41/AK$23),0,(AK41/AK$23)) -> -0.035272046 | BH41: =D41/$D$23 -> -0.06525512 | BI41: =E41/$E$23 -> -0.11271439 | BK41: =G41/$G$23 -> -0.054007469 | BL41: =H41/$H$23 -> -0.091762875 | BN41: =J41/$J$23 -> -0.045181447 | BO41: =K41/$K$23 -> -0.059592144
A42: Utilidades/ Consumo | C42: =SUM(D42,G42,J42,M42,P42,S42,V42,Y42,AB42,AE42,AH42,AK42) -> -42834.9 | D42: ='04 -Base Orçado 2026'!E71 -> -3976.09 | E42: ='01 Base Realizado'!D72 -> -3508.22 | G42: ='04 -Base Orçado 2026'!F71 -> -2731 | H42: ='01 Base Realizado'!F72 -> -1710.94 | J42: ='04 -Base Orçado 2026'!G71 -> -2827.81 | K42: ='01 Base Realizado'!H68 -> -18000 | M42: ='04 -Base Orçado 2026'!H71 -> -3700 | P42: ='04 -Base Orçado 2026'!I71 -> -3700 | S42: ='04 -Base Orçado 2026'!J71 -> -3700 | V42: ='04 -Base Orçado 2026'!K71 -> -3700 | Y42: ='04 -Base Orçado 2026'!L71 -> -3700 | AB42: ='04 -Base Orçado 2026'!M71 -> -3700 | AE42: ='04 -Base Orçado 2026'!N71 -> -3700 | AH42: ='04 -Base Orçado 2026'!O71 -> -3700 | AK42: ='04 -Base Orçado 2026'!P71 -> -3700 | AN42: =SUM(D42,G42,J42,M42,P42,S42,V42,Y42,AB42,AE42,AH42,AK42) -> -42834.9 | AO42: =SUM(E42,H42,K42,N42,Q42,T42,W42,Z42,AC42,AF42,AI42,AL42) -> -23219.16 | AQ42: =AN42/12 -> -3569.575 | AR42: =AO42/$AT$12 -> -7739.72 | AT42: =IF(ISERROR(C42/C$23),0,(C42/C$23)) -> -0.0075169693 | BH42: =D42/$D$23 -> -0.013801076 | BI42: =E42/$E$23 -> -0.016614574 | BK42: =G42/$G$23 -> -0.0078454467 | BL42: =H42/$H$23 -> -0.0065966711 | BN42: =J42/$J$23 -> -0.0067959865 | BO42: =K42/$K$23 -> -0.045069689
A43: Operação | C43: =SUM(D43,G43,J43,M43,P43,S43,V43,Y43,AB43,AE43,AH43,AK43) -> -794700.53 | D43: ='04 -Base Orçado 2026'!E79 -> -51097.412 | E43: ='01 Base Realizado'!D80 -> -52862.23 | G43: ='04 -Base Orçado 2026'!F79 -> -64671.129 | H43: ='01 Base Realizado'!F80 -> -66223.54 | J43: ='04 -Base Orçado 2026'!G79 -> -66092.129 | K43: ='01 Base Realizado'!H80 -> -83235.31 | M43: ='04 -Base Orçado 2026'!H79 -> -66944.729 | P43: ='04 -Base Orçado 2026'!I79 -> -67882.589 | S43: ='04 -Base Orçado 2026'!J79 -> -68192.083 | V43: ='04 -Base Orçado 2026'!K79 -> -67342.006 | Y43: ='04 -Base Orçado 2026'!L79 -> -67830.8 | AB43: ='04 -Base Orçado 2026'!M79 -> -68344.034 | AE43: ='04 -Base Orçado 2026'!N79 -> -68882.929 | AH43: ='04 -Base Orçado 2026'!O79 -> -68996.097 | AK43: ='04 -Base Orçado 2026'!P79 -> -68424.599 | AN43: =SUM(D43,G43,J43,M43,P43,S43,V43,Y43,AB43,AE43,AH43,AK43) -> -794700.53 | AO43: =SUM(E43,H43,K43,N43,Q43,T43,W43,Z43,AC43,AF43,AI43,AL43) -> -202321.08 | AQ43: =AN43/12 -> -66225.045 | AR43: =AO43/$AT$12 -> -67440.36 | AT43: =IF(ISERROR(C43/C$23),0,(C43/C$23)) -> -0.13945964 | AV43: =IF(ISERROR(D43/D$23),0,(D43/D$23)) -> -0.17735999 | AW43: =IF(ISERROR(G43/G$23),0,(G43/G$23)) -> -0.18578319 | AX43: =IF(ISERROR(J43/J$23),0,(J43/J$23)) -> -0.15883713 | AY43: =IF(ISERROR(M43/M$23),0,(M43/M$23)) -> -0.14550039 | AZ43: =IF(ISERROR(P43/P$23),0,(P43/P$23)) -> -0.13407582 | BA43: =IF(ISERROR(S43/S$23),0,(S43/S$23)) -> -0.13074989 | BB43: =IF(ISERROR(V43/V$23),0,(V43/V$23)) -> -0.14098009 | BC43: =IF(ISERROR(Y43/Y$23),0,(Y43/Y$23)) -> -0.13465202 | BD43: =IF(ISERROR(AB43/AB$23),0,(AB43/AB$23)) -> -0.12918713 | BE43: =IF(ISERROR(AE43/AE$23),0,(AE43/AE$23)) -> -0.1239843 | BF43: =IF(ISERROR(AH43/AH$23),0,(AH43/AH$23)) -> -0.12339403 | BG43: =IF(ISERROR(AK43/AK$23),0,(AK43/AK$23)) -> -0.12837636 | BH43: =D43/$D$23 -> -0.17735999 | BI43: =E43/$E$23 -> -0.25035016 | BK43: =G43/$G$23 -> -0.18578319 | BL43: =H43/$H$23 -> -0.25533035 | BN43: =J43/$J$23 -> -0.15883713 | BO43: =K43/$K$23 -> -0.20841053
A44: Manutenção e Conservação | C44: =SUM(D44,G44,J44,M44,P44,S44,V44,Y44,AB44,AE44,AH44,AK44) -> -57400.337 | D44: ='04 -Base Orçado 2026'!E76 -> -4783.3614 | E44: ='01 Base Realizado'!D77 -> -934.5 | G44: ='04 -Base Orçado 2026'!F76 -> -4783.3614 | H44: ='01 Base Realizado'!F76 -> -4500 | J44: ='04 -Base Orçado 2026'!G76 -> -4783.3614 | K44: ='01 Base Realizado'!H76 -> -960 | M44: ='04 -Base Orçado 2026'!H76 -> -4783.3614 | P44: ='04 -Base Orçado 2026'!I76 -> -4783.3614 | S44: ='04 -Base Orçado 2026'!J76 -> -4783.3614 | V44: ='04 -Base Orçado 2026'!K76 -> -4783.3614 | Y44: ='04 -Base Orçado 2026'!L76 -> -4783.3614 | AB44: ='04 -Base Orçado 2026'!M76 -> -4783.3614 | AE44: ='04 -Base Orçado 2026'!N76 -> -4783.3614 | AH44: ='04 -Base Orçado 2026'!O76 -> -4783.3614 | AK44: ='04 -Base Orçado 2026'!P76 -> -4783.3614 | AN44: =SUM(D44:AK44) -> -63794.837 | AO44: =SUM(E44,H44,K44,N44,Q44,T44,W44,Z44,AC44,AF44,AI44,AL44) -> -6394.5 | AQ44: =AN44/12 -> -5316.2364 | AR44: =AO44/$AT$12 -> -2131.5 | AT44: =IF(ISERROR(C44/C$23),0,(C44/C$23)) -> -0.010073015 | AV44: =IF(ISERROR(D44/D$23),0,(D44/D$23)) -> -0.016603129 | AW44: =IF(ISERROR(G44/G$23),0,(G44/G$23)) -> -0.013741343 | AX44: =IF(ISERROR(J44/J$23),0,(J44/J$23)) -> -0.011495701 | AY44: =IF(ISERROR(M44/M$23),0,(M44/M$23)) -> -0.010396352 | AZ44: =IF(ISERROR(P44/P$23),0,(P44/P$23)) -> -0.009447682 | BA44: =IF(ISERROR(S44/S$23),0,(S44/S$23)) -> -0.0091715043 | BB44: =IF(ISERROR(V44/V$23),0,(V44/V$23)) -> -0.010013939 | BC44: =IF(ISERROR(Y44/Y$23),0,(Y44/Y$23)) -> -0.0094955284 | BD44: =IF(ISERROR(AB44/AB$23),0,(AB44/AB$23)) -> -0.0090417365 | BE44: =IF(ISERROR(AE44/AE$23),0,(AE44/AE$23)) -> -0.0086097051 | BF44: =IF(ISERROR(AH44/AH$23),0,(AH44/AH$23)) -> -0.0085546615 | BG44: =IF(ISERROR(AK44/AK$23),0,(AK44/AK$23)) -> -0.0089744118 | BH44: =D44/$D$23 -> -0.016603129 | BI44: =E44/$E$23 -> -0.0044256972 | BK44: =G44/$G$23 -> -0.013741343 | BL44: =H44/$H$23 -> -0.017350123 | BN44: =J44/$J$23 -> -0.011495701 | BO44: =K44/$K$23 -> -0.0024037167
A45: Lucro Bruto | C45: =SUM(D45,G45,J45,M45,P45,S45,V45,Y45,AB45,AE45,AH45,AK45) -> 3436377.7 | D45: =D23+D25 -> 48273.959 | E45: =E23+E25 -> 36196.858 | G45: =G23+G25 -> 88725.738 | H45: =H23+H25 -> 40093.498 | J45: =J23+J25 -> 125897.14 | K45: =K23+K25 -> 126200.67 | M45: =M23+M25 -> 302713.53 | P45: =P23+P25 -> 343817.67 | S45: =S23+S25 -> 357382.03 | V45: =V23+V25 -> 318125.24 | Y45: =Y23+Y25 -> 341547.9 | AB45: =AB23+AB25 -> 364041.69 | AE45: =AE23+AE25 -> 387660.16 | AH45: =AH23+AH25 -> 390620.04 | AK45: =AK23+AK25 -> 367572.65 | AN45: =SUM(D45,G45,J45,M45,P45,S45,V45,Y45,AB45,AE45,AH45,AK45) -> 3436377.7 | AO45: =SUM(E45,H45,K45,N45,Q45,T45,W45,Z45,AC45,AF45,AI45,AL45) -> 202491.03 | AQ45: =AN45/12 -> 286364.81 | AR45: =AO45/$AT$12 -> 67497.01 | AT45: =IF(ISERROR(C45/C$23),0,(C45/C$23)) -> 0.60303972 | AV45: =IF(ISERROR(D45/D$23),0,(D45/D$23)) -> 0.16755973 | AW45: =IF(ISERROR(G45/G$23),0,(G45/G$23)) -> 0.25488577 | AX45: =IF(ISERROR(J45/J$23),0,(J45/J$23)) -> 0.30256462 | AY45: =IF(ISERROR(M45/M$23),0,(M45/M$23)) -> 0.65792986 | AZ45: =IF(ISERROR(P45/P$23),0,(P45/P$23)) -> 0.67907894 | BA45: =IF(ISERROR(S45/S$23),0,(S45/S$23)) -> 0.68523588 | BB45: =IF(ISERROR(V45/V$23),0,(V45/V$23)) -> 0.66599332 | BC45: =IF(ISERROR(Y45/Y$23),0,(Y45/Y$23)) -> 0.67801228 | BD45: =IF(ISERROR(AB45/AB$23),0,(AB45/AB$23)) -> 0.68812885 | BE45: =IF(ISERROR(AE45/AE$23),0,(AE45/AE$23)) -> 0.6977603 | BF45: =IF(ISERROR(AH45/AH$23),0,(AH45/AH$23)) -> 0.69859289 | BG45: =IF(ISERROR(AK45/AK$23),0,(AK45/AK$23)) -> 0.68962975
C46: =SUM(D46,G46,J46,M46,P46,S46,V46,Y46,AB46,AE46,AH46,AK46) -> 6.8653722 | D46: =IF(ISERROR(D45/D23),"-",(D45/D23)) -> 0.16755973 | E46: =IF(ISERROR(E45/E23),"-",(E45/E23)) -> 0.17142465 | G46: =IF(ISERROR(G45/G23),"-",(G45/G23)) -> 0.25488577 | H46: =IF(ISERROR(H45/H23),"-",(H45/H23)) -> 0.15458381 | J46: =IF(ISERROR(J45/J23),"-",(J45/J23)) -> 0.30256462 | K46: =IF(ISERROR(K45/K23),"-",(K45/K23)) -> 0.31599029 | M46: =IF(ISERROR(M45/M23),"-",(M45/M23)) -> 0.65792986 | P46: =IF(ISERROR(P45/P23),"-",(P45/P23)) -> 0.67907894 | S46: =IF(ISERROR(S45/S23),"-",(S45/S23)) -> 0.68523588 | V46: =IF(ISERROR(V45/V23),"-",(V45/V23)) -> 0.66599332 | Y46: =IF(ISERROR(Y45/Y23),"-",(Y45/Y23)) -> 0.67801228 | AB46: =IF(ISERROR(AB45/AB23),"-",(AB45/AB23)) -> 0.68812885 | AE46: =IF(ISERROR(AE45/AE23),"-",(AE45/AE23)) -> 0.6977603 | AH46: =IF(ISERROR(AH45/AH23),"-",(AH45/AH23)) -> 0.69859289 | AK46: =IF(ISERROR(AK45/AK23),"-",(AK45/AK23)) -> 0.68962975 | AN46: =IF(ISERROR(AN45/AN23),"-",(AN45/AN23)) -> 0.60303972 | AO46: =IF(ISERROR(AO45/AO23),"-",(AO45/AO23)) -> 0.23277538 | AQ46: =IF(ISERROR(AQ45/AQ23),"-",(AQ45/AQ23)) -> 0.60303972 | AR46: =AO46/$AT$12 -> 0.077591794
